Workbook

Sheet %Cost vs Budget
A1: Partner | B1: Used of Budget
A2: GOT | B2: 20.498143
A3: MNU | B3: 29.334355
A4: SCA | B4: 22.228008
A5: FOC | B5: 23.329146
A6: CLTV | B6: 15.344396
A7: MAI | B7: 10.421054
A8: BIN | B8: 7.6098034
A9: IOC | B9: 6.7956784
A10: HIE | B10: 22.468177
A11: BAL | B11: 45.780785
A12: MEERI | B12: 23.913983
A13: MCN | B13: 11.289715
A14: CKR | B14: 33.117715

Sheet WP Cost vs Budget
B23: Task/WP | C23: TOTAL COST | D23: TOTAL BUDGET
B24: WP1 | C24: =SUM('Direct &Indirect Personnal Cost'!C7) -> 104301.99 | D24: =SUM('Direct &Indirect Personnal Cost'!E7) -> 226991.17
B25: T1.1 | C25: =SUM('Direct &Indirect Personnal Cost'!C8) -> 41306.53 | D25: =SUM('Direct &Indirect Personnal Cost'!E8) -> 88440.74
B26: T1.2 | C26: =SUM('Direct &Indirect Personnal Cost'!C9) -> 29037.419 | D26: =SUM('Direct &Indirect Personnal Cost'!E9) -> 53116.01
B27: T1.3 | C27: =SUM('Direct &Indirect Personnal Cost'!C10) -> 30982.771 | D27: =SUM('Direct &Indirect Personnal Cost'!E10) -> 85434.42
B38: Task/WP | C38: TOTAL COST | D38: TOTAL BUDGET
B39: WP2 | C39: =SUM('Direct &Indirect Personnal Cost'!C11) -> 67811.891 | D39: =SUM('Direct &Indirect Personnal Cost'!E11) -> 153493.81
B40: T2.1 | C40: =SUM('Direct &Indirect Personnal Cost'!C12) -> 19605.459 | D40: =SUM('Direct &Indirect Personnal Cost'!E12) -> 67887.51
B41: T2.2 | C41: =SUM('Direct &Indirect Personnal Cost'!C13) -> 5204.3416 | D41: =SUM('Direct &Indirect Personnal Cost'!E13) -> 3343.75
B42: T2.3 | C42: =SUM('Direct &Indirect Personnal Cost'!C14) -> 10794.029 | D42: =SUM('Direct &Indirect Personnal Cost'!E14) -> 12525
B43: T2.4 | C43: =SUM('Direct &Indirect Personnal Cost'!C15) -> 32291.647 | D43: =SUM('Direct &Indirect Personnal Cost'!E15) -> 69737.55
B53: Task/WP | C53: TOTAL COST | D53: TOTAL BUDGET
B54: WP3 | C54: =SUM('Direct &Indirect Personnal Cost'!C16) -> 84177.462 | D54: =SUM('Direct &Indirect Personnal Cost'!E16) -> 3434125.1
B55: T3.1 | C55: =SUM('Direct &Indirect Personnal Cost'!C17) -> 47109.12 | D55: =SUM('Direct &Indirect Personnal Cost'!E17) -> 68475.03
B56: T3.2 | C56: =SUM('Direct &Indirect Personnal Cost'!C18) -> 14557.76 | D56: =SUM('Direct &Indirect Personnal Cost'!E18) -> 18562.5
B57: T3.3 | C57: =SUM('Direct &Indirect Personnal Cost'!C19) -> 15885.025 | D57: =SUM('Direct &Indirect Personnal Cost'!E19) -> 121637.57
B58: T3.4 | C58: =SUM('Direct &Indirect Personnal Cost'!C20) -> 0 | D58: =SUM('Direct &Indirect Personnal Cost'!E20) -> 26750
B59: T3.5 | C59: =SUM('Direct &Indirect Personnal Cost'!C21) -> 0 | D59: =SUM('Direct &Indirect Personnal Cost'!E21) -> 3026750
B60: T3.6 | C60: =SUM('Direct &Indirect Personnal Cost'!C22) -> 6187.5 | D60: =SUM('Direct &Indirect Personnal Cost'!E22) -> 171950.02
B68: Task/WP | C68: TOTAL COST | D68: TOTAL BUDGET
B69: WP4 | C69: =SUM('Direct &Indirect Personnal Cost'!C23) -> 21789.228 | D69: =SUM('Direct &Indirect Personnal Cost'!E23) -> 701740.32
B70: T4.1 | C70: =SUM('Direct &Indirect Personnal Cost'!C24) -> 8330.8886 | D70: =SUM('Direct &Indirect Personnal Cost'!E24) -> 24218.75
B71: T4.2 | C71: =SUM('Direct &Indirect Personnal Cost'!C25) -> 5322.8375 | D71: =SUM('Direct &Indirect Personnal Cost'!E25) -> 170550.08
B72: T4.3 | C72: =SUM('Direct &Indirect Personnal Cost'!C26) -> 261.4 | D72: =SUM('Direct &Indirect Personnal Cost'!E26) -> 113875.05
B73: T4.4 | C73: =SUM('Direct &Indirect Personnal Cost'!C27) -> 0 | D73: =SUM('Direct &Indirect Personnal Cost'!E27) -> 70268.81
B74: T4.5 | C74: =SUM('Direct &Indirect Personnal Cost'!C28) -> 359.90748 | D74: =SUM('Direct &Indirect Personnal Cost'!E28) -> 114196.76
B75: T4.6 | C75: =SUM('Direct &Indirect Personnal Cost'!C29) -> 230.555 | D75: =SUM('Direct &Indirect Personnal Cost'!E29) -> 6925
B76: T4.7 | C76: =SUM('Direct &Indirect Personnal Cost'!C30) -> 798.075 | D76: =SUM('Direct &Indirect Personnal Cost'!E30) -> 54018.33
B77: T4.8 | C77: =SUM('Direct &Indirect Personnal Cost'!C31) -> 595.19468 | D77: =SUM('Direct &Indirect Personnal Cost'!E31) -> 53087.47
B78: T4.9 | C78: =SUM('Direct &Indirect Personnal Cost'!C32) -> 5748.05 | D78: =SUM('Direct &Indirect Personnal Cost'!E32) -> 94600.07
B83: Task/WP | C83: TOTAL COST | D83: TOTAL BUDGET
B84: WP5 | C84: =SUM('Direct &Indirect Personnal Cost'!C33) -> 42546.324 | D84: =SUM('Direct &Indirect Personnal Cost'!E33) -> 148095.23
B85: T5.1 | C85: =SUM('Direct &Indirect Personnal Cost'!C34) -> 40961.187 | D85: =SUM('Direct &Indirect Personnal Cost'!E34) -> 55221.35
B86: T5.2 | C86: =SUM('Direct &Indirect Personnal Cost'!C35) -> 771.5 | D86: =SUM('Direct &Indirect Personnal Cost'!E35) -> 55221.35
B87: T5.3 | C87: =SUM('Direct &Indirect Personnal Cost'!C36) -> 796.20625 | D87: =SUM('Direct &Indirect Personnal Cost'!E36) -> 37652.53
B98: Task/WP | C98: TOTAL COST | D98: TOTAL BUDGET
B99: WP6 | C99: =SUM('Direct &Indirect Personnal Cost'!C37) -> 56406.84 | D99: =SUM('Direct &Indirect Personnal Cost'!E37) -> 231218.95
B100: T6.1 | C100: =SUM('Direct &Indirect Personnal Cost'!C38) -> 39381.405 | D100: =SUM('Direct &Indirect Personnal Cost'!E38) -> 55825.06
B101: T6.2 | C101: =SUM('Direct &Indirect Personnal Cost'!C39) -> 10860.063 | D101: =SUM('Direct &Indirect Personnal Cost'!E39) -> 108168.84
B102: T6.3 | C102: =SUM('Direct &Indirect Personnal Cost'!C40) -> 1066.5956 | D102: =SUM('Direct &Indirect Personnal Cost'!E40) -> 67225.05
B113: Task/WP | C113: TOTAL COST | D113: TOTAL BUDGET
B114: WP7 | C114: =SUM('Direct &Indirect Personnal Cost'!C41) -> 115933.43 | D114: =SUM('Direct &Indirect Personnal Cost'!E41) -> 214000
B115: T7.1 | C115: =SUM('Direct &Indirect Personnal Cost'!C42) -> 42675.264 | D115: =SUM('Direct &Indirect Personnal Cost'!E42) -> 147125
B116: T7.2 | C116: =SUM('Direct &Indirect Personnal Cost'!C43) -> 50402.562 | D116: =SUM('Direct &Indirect Personnal Cost'!E43) -> 46812.5
B117: T7.3 | C117: =SUM('Direct &Indirect Personnal Cost'!C44) -> 22782.089 | D117: =SUM('Direct &Indirect Personnal Cost'!E44) -> 20062.5

Sheet PM Efforth per Task
G1: B1 | H1: B2 | I1: B3 | J1: B4 | K1: B5 | L1: B6 | M1: B7 | N1: B8 | O1: B9 | P1: B10 | Q1: B11 | R1: B12
B2: No | C2: Work Packages (WP) & Tasks (T) | D2: Lead | E2: Start | F2: End | G2: MNU | H2: FOC | I2: CTLV | J2: CKR | K2: MAI | L2: BIN | M2: IOC | N2: HIE | O2: MCN | P2: MEERI | Q2: SCA | R2: BAL | S2: TOTAL PMs | T2: =T3+T7+T12+T19+T29+T33+T37 -> 1
B3: WP1 | C3: Assessment of potential new value chains and selection of Topics for Call of Proposals | D3: MEERI | E3: 1 | F3: 6 | G3: =SUM( G4:G6) -> 1.5 | H3: =SUM(H4:H6) -> 2.25 | I3: =SUM(I4:I6) -> 2.25 | J3: =SUM(J4:J6) -> 3.25 | K3: =SUM(K4:K6) -> 3.25 | L3: =SUM(L4:L6) -> 3.25 | M3: =SUM(M4:M6) -> 1.5 | N3: =SUM(N4:N6) -> 2.25 | O3: =SUM(O4:O6) -> 1.5 | ... R3: =SUM(R4:R6) -> 1 | S3: =SUM(G3:R3) -> 26.75 | T3: =S3/ S$41 -> 0.12022472
B4: T1.1 | C4: Sustainable challenges, needs and trends of four industrial offshore sectors | D4: HIE | E4: 1 | F4: 3 | G4: 1 | H4: 1 | I4: 0.25 | J4: 0.25 | K4: 0.25 | L4: 0.25 | M4: 1 | N4: 1.75 | O4: 1 | P4: 0 | Q4: 0.5 | R4: 0.5 | S4: =SUM(G4:R4) -> 7.75
B5: T1.2 | C5: Assessment of emerging technology trends and solutions | D5: MEERI | E5: 1 | F5: 4 | G5: 0.25 | H5: 0.25 | I5: 1 | J5: 1 | K5: 1 | L5: 1 | M5: 0.25 | N5: 0.25 | O5: 0.25 | P5: 1.75 | Q5: 0.25 | R5: 0.25 | S5: =SUM(G5:R5) -> 7.5
B6: T1.3 | C6: Potential new value chains and selection of Call Topics | D6: MEERI | E6: 3 | F6: 6 | G6: 0.25 | H6: 1 | I6: 1 | J6: 2 | K6: 2 | L6: 2 | M6: 0.25 | N6: 0.25 | O6: 0.25 | P6: 2 | Q6: 0.25 | R6: 0.25 | S6: =SUM(G6:R6) -> 11.5
B7: WP2 | C7: Methodologies and tools for cross-sectoral/-border collaboration and technology transfer | D7: HIE | E7: 1 | F7: 36 | G7: =SUM(G8:G11) -> 0.5 | H7: =SUM(H8:H11) -> 2.5 | I7: =SUM(I8:I11) -> 2.5 | J7: =SUM(J8:J11) -> 2 | K7: =SUM(K8:K11) -> 0.5 | L7: =SUM(L8:L11) -> 0.5 | M7: =SUM(M8:M11) -> 0.5 | N7: =SUM(N8:N11) -> 3.5 | ... S7: =SUM(S8:S11) -> 17.75 | T7: =S7/ S$41 -> 0.079775281
B8: T2.1 | C8: Methologies and tools for cross-sectoral/-border collaboration and technology transfer | D8: HIE | E8: 1 | F8: 36 | G8: 0.25 | H8: 1.25 | I8: 1.25 | J8: 0.75 | K8: 0.25 | L8: 0.25 | M8: 0.25 | N8: 3.25 | O8: 0.25 | P8: 0.25 | Q8: 0.25 | R8: 0 | S8: =SUM(G8:R8) -> 8.25
B9: T2.2 | C9: Establishment of a Collaborative Virtual Environment | D9: MNU | E9: 1 | F9: 36 | G9: 0.25 | H9: 0 | I9: 0 | J9: 0 | K9: 0 | L9: 0 | M9: 0 | N9: 0 | O9: 0 | P9: 0 | Q9: 0 | R9: 0 | S9: =SUM(G9:R9) -> 0.25
B10: T2.3 | C10: Establishment of a Survey tool | D10: CKR | E10: 1 | F10: 36 | G10: 0 | H10: 1 | I10: 1 | J10: 1 | K10: 0 | L10: 0 | M10: 0 | N10: 0 | O10: 0 | P10: 0 | Q10: 0 | R10: 0 | S10: =SUM(G10:R10) -> 3
B11: T2.4 | C11: Establishment of the GreenOffshoreTech Cluster Collaboration Platform | D11: BAL | E11: 1 | F11: 36 | G11: 0 | H11: 0.25 | I11: 0.25 | J11: 0.25 | K11: 0.25 | L11: 0.25 | M11: 0.25 | N11: 0.25 | O11: 0.25 | P11: 0.25 | Q11: 0.25 | R11: 3.75 | S11: =SUM(G11:R11) -> 6.25
B12: WP3 | C12: Direct financial support to SMEs through a competitive Call for Proposals | D12: CKR | E12: 1 | F12: 36 | G12: =SUM(G13:G18) -> 7 | H12: =SUM(H13:H18) -> 2.5 | I12: =SUM(I13:I18) -> 3.5 | J12: =SUM(J13:J18) -> 6 | K12: =SUM(K13:K18) -> 3.5 | L12: =SUM(L13:L18) -> 3.5 | M12: =SUM(M13:M18) -> 2.5 | N12: =SUM(N13:N18) -> 2.5 | ... S12: =SUM(S13:S18) -> 45.5 | T12: =S12/ S$41 -> 0.20449438
B13: T3.1 | C13: Preparation of the Call for Proposals | D13: CKR | E13: 1 | F13: 7 | G13: 0.5 | H13: 0.5 | I13: 0.5 | J13: 3 | K13: 0.5 | L13: 0.5 | M13: 0.5 | N13: 0.5 | O13: 0.5 | P13: 0.5 | Q13: 0.5 | R13: 0.5 | S13: =SUM(G13:R13) -> 8.5
B14: T3.2 | C14: Publication of the Call for Proposals and Proposal reception. | D14: BAL | E14: 8 | F14: 18 | G14: 0.5 | H14: 0 | I14: 0 | J14: 0 | K14: 0 | L14: 0 | M14: 0 | N14: 0 | O14: 0 | P14: 0 | Q14: 0 | R14: 1 | S14: =SUM(G14:R14) -> 1.5
B15: T3.3 | C15: Evaluation and Selection of SMEs Proposals | D15: BAL | E15: 11 | F15: 20 | G15: 1 | H15: 1 | I15: 1 | J15: 1 | K15: 1 | L15: 1 | M15: 1 | N15: 1 | O15: 1 | P15: 1 | Q15: 1 | R15: 1.5 | S15: =SUM(G15:R15) -> 12.5
B16: T3.4 | C16: Contracting with winner SMEs Projects | D16: MNU | E16: 13 | F16: 22 | G16: 2 | H16: 0 | I16: 0 | J16: 0 | K16: 0 | L16: 0 | M16: 0 | N16: 0 | O16: 0 | P16: 0 | Q16: 0 | R16: 0 | S16: =SUM(G16:R16) -> 2
B17: T3.5 | C17: Payments and financial monitoring of winner SMEs Projects | D17: MNU | E17: 13 | F17: 36 | G17: 2 | H17: 0 | I17: 0 | J17: 0 | K17: 0 | L17: 0 | M17: 0 | N17: 0 | O17: 0 | P17: 0 | Q17: 0 | R17: 0 | S17: =SUM(G17:R17) -> 2
B18: T3.6 | C18: Technical monitoring of winner SMEs Projects | D18: SCA | E18: 13 | F18: 36 | G18: 1 | H18: 1 | I18: 2 | J18: 2 | K18: 2 | L18: 2 | M18: 1 | N18: 1 | O18: 1 | P18: 2 | Q18: 3 | R18: 1 | S18: =SUM(G18:R18) -> 19
B19: WP4 | C19: Business Support Services to winner SMEs | D19: MAI | E19: 1 | F19: 36 | G19: =SUM(G20:G28) -> 5.5 | H19: =SUM(H20:H28) -> 8.5 | I19: =SUM(I20:I28) -> 7 | J19: =SUM(J20:J28) -> 3 | K19: =SUM(K20:K28) -> 8 | L19: =SUM(L20:L28) -> 9 | M19: =SUM(M20:M28) -> 3 | N19: =SUM(N20:N28) -> 7 | ... S19: =SUM(S20:S28) -> 74.75 | T19: =S19/ S$41 -> 0.33595506
B20: T4.1 | C20: Programme of Business Support Services to winner SMEs | D20: MAI | E20: 1 | F20: 36 | G20: 0 | H20: 0 | I20: 0 | J20: 0 | K20: 2.5 | L20: 0 | M20: 0 | N20: 0 | O20: 0 | P20: 0 | Q20: 0 | R20: 0 | S20: =SUM(G20:R20) -> 2.5
B21: T4.2 | C21: Business Support Service #1 Business & Tech Academy | D21: MAI | E21: 1 | F21: 24 | G21: 1 | H21: 1 | I21: 1 | J21: 1 | K21: 3 | L21: 3.5 | M21: 1 | N21: 1 | O21: 1 | P21: 1.5 | Q21: 1 | R21: 1.5 | S21: =SUM(G21:R21) -> 17.5
B22: T4.3 | C22: Business Support Service #2 Brokerage & B2B matchmaking events | D22: CMAB | E22: 1 | F22: 24 | G22: 0.5 | H22: 4 | I22: 0.5 | J22: 0.5 | K22: 1 | L22: 4 | M22: 0.5 | N22: 0.5 | O22: 0.5 | P22: 0.5 | Q22: 0.5 | R22: 0.5 | S22: =SUM(G22:R22) -> 13.5
B23: T4.4 | C23: Business Support Service #3 Access to Finance | D23: HIE | E23: 1 | F23: 24 | G23: 0.5 | H23: 0.5 | I23: 0.5 | J23: 0.5 | K23: 0.5 | L23: 0.5 | M23: 0.5 | N23: 3 | O23: 0.5 | P23: 0 | Q23: 0 | R23: 0 | S23: =SUM(G23:R23) -> 7
B24: T4.5 | C24: Business Support Service #4 One-to-One Mentoring and Coaching | D24: SCA | E24: 1 | F24: 32 | G24: 0 | H24: 0 | I24: 0 | J24: 0 | K24: 0 | L24: 0 | M24: 0 | N24: 0 | O24: 0 | P24: 0 | Q24: 9.75 | R24: 0 | S24: =SUM(G24:R24) -> 9.75
B25: T4.6 | C25: Business Support Service #5 Branding | D25: FOC | E25: 1 | F25: 32 | G25: 0 | H25: 2 | I25: 0 | J25: 0 | K25: 0 | L25: 0 | M25: 0 | N25: 0 | O25: 0 | P25: 0 | Q25: 0 | R25: 0 | S25: =SUM(G25:R25) -> 2
B26: T4.7 | C26: Business Support Service #6 Internationalisation | D26: MCN | E26: 1 | F26: 32 | G26: 0.5 | H26: 0.5 | I26: 0.5 | J26: 0.5 | K26: 0.5 | L26: 0.5 | M26: 0.5 | N26: 0.5 | O26: 2 | P26: 0 | Q26: 0 | R26: 0 | S26: =SUM(G26:R26) -> 6
B27: T4.8 | C27: Business Support Service #7 Investor pitching | D27: CTLV | E27: 1 | F27: 32 | G27: 0.5 | H27: 0 | I27: 4 | J27: 0 | K27: 0 | L27: 0 | M27: 0 | N27: 1.5 | O27: 0 | P27: 0 | Q27: 1 | R27: 0 | S27: =SUM(G27:R27) -> 7
B28: T4.9 | C28: Business Support Service #8 Investor rounds | D28: MNU | E28: 1 | F28: 32 | G28: 2.5 | H28: 0.5 | I28: 0.5 | J28: 0.5 | K28: 0.5 | L28: 0.5 | M28: 0.5 | N28: 0.5 | O28: 2 | P28: 0.5 | Q28: 0.5 | R28: 0.5 | S28: =SUM(G28:R28) -> 9.5
B29: WP5 | C29: Large-scale Demonstrator (LSD) setup, validation, and impact assessment | D29: SCA | E29: 1 | F29: 36 | G29: =SUM(G30:G32) -> 0.75 | H29: =SUM(H30:H32) -> 0.75 | I29: =SUM(I30:I32) -> 0.75 | J29: =SUM(J30:J32) -> 0.75 | K29: =SUM(K30:K32) -> 0.75 | L29: =SUM(L30:L32) -> 0.75 | M29: =SUM(M30:M32) -> 0.75 | N29: =SUM(N30:N32) -> 0.75 | ... S29: =SUM(S30:S32) -> 14.25 | T29: =S29/ S$41 -> 0.064044944
B30: T5.1 | C30: Set-up of the GreenOffshoreTech LSD in GreenOffshoreTech regions | D30: SCA | E30: 1 | F30: 36 | G30: 0.25 | H30: 0.25 | I30: 0.25 | J30: 0.25 | K30: 0.25 | L30: 0.25 | M30: 0.25 | N30: 0.25 | O30: 0.25 | P30: 0.25 | Q30: 2.5 | R30: 0.25 | S30: =SUM(G30:R30) -> 5.25
B31: T5.2 | C31: Validation & Impact assessment of GreenOffshoreTech LSD | D31: SCA | E31: 1 | F31: 36 | G31: 0.25 | H31: 0.25 | I31: 0.25 | J31: 0.25 | K31: 0.25 | L31: 0.25 | M31: 0.25 | N31: 0.25 | O31: 0.25 | P31: 0.25 | Q31: 2.5 | R31: 0.25 | S31: =SUM(G31:R31) -> 5.25
B32: T5.3 | C32: Guidelines of Best Practice to foster cross-sector/-border collaboration and technology transfer through Clusters | D32: SCA | E32: 35 | F32: 36 | G32: 0.25 | H32: 0.25 | I32: 0.25 | J32: 0.25 | K32: 0.25 | L32: 0.25 | M32: 0.25 | N32: 0.25 | O32: 0.25 | P32: 0.25 | Q32: 1 | R32: 0.25 | S32: =SUM(G32:R32) -> 3.75
B33: WP6 | C33: Communication, Dissemination, Exploitation & Sustainability | D33: FOC | E33: 1 | F33: 36 | G33: =SUM(G34:G36) -> 2 | H33: =SUM(H34:H36) -> 7.5 | I33: =SUM(I34:I36) -> 2 | J33: =SUM(J34:J36) -> 2 | K33: =SUM(K34:K36) -> 3 | L33: =SUM(L34:L36) -> 2 | M33: =SUM(M34:M36) -> 2 | N33: =SUM(N34:N36) -> 2 | ... S33: =SUM(S34:S36) -> 27.5 | T33: =S33/ S$41 -> 0.12359551
B34: T6.1 | C34: Communication plan and Communication activities | D34: FOC | E34: 1 | F34: 36 | G34: 0.5 | H34: 4 | I34: 0.5 | J34: 0.5 | K34: 0.5 | L34: 0.5 | M34: 0.5 | N34: 0.5 | O34: 0.5 | P34: 0 | Q34: 0 | R34: 0 | S34: =SUM(G34:R34) -> 8
B35: T6.2 | C35: Dissemination strategy and Dissemination activities | D35: FOC | E35: 1 | F35: 36 | G35: 1 | H35: 3 | I35: 1 | J35: 1 | K35: 1 | L35: 1 | M35: 1 | N35: 1 | O35: 1 | P35: 0.5 | Q35: 0.5 | R35: 0.5 | S35: =SUM(G35:R35) -> 12.5
B36: T6.3 | C36: Exploitation strategy, IPR and Sustainability | D36: MAI | E36: 1 | F36: 36 | G36: 0.5 | H36: 0.5 | I36: 0.5 | J36: 0.5 | K36: 1.5 | L36: 0.5 | M36: 0.5 | N36: 0.5 | O36: 0.5 | P36: 0.5 | Q36: 0.5 | R36: 0.5 | S36: =SUM(G36:R36) -> 7
B37: WP7 | C37: Project Management and Coordination | D37: MNU | E37: 1 | F37: 36 | G37: =SUM(G38:G40) -> 16 | H37: =SUM(H38:H40) -> 0 | I37: =SUM(I38:I40) -> 0 | J37: =SUM(J38:J40) -> 0 | K37: =SUM(K38:K40) -> 0 | L37: =SUM(L38:L40) -> 0 | M37: =SUM(M38:M40) -> 0 | N37: =SUM(N38:N40) -> 0 | ... S37: =SUM(S38:S40) -> 16 | T37: =S37/ S$41 -> 0.071910112
B38: T7.1 | C38: Project coordination | D38: MNU | E38: 1 | F38: 36 | G38: 11 | H38: 0 | I38: 0 | J38: 0 | K38: 0 | L38: 0 | M38: 0 | N38: 0 | O38: 0 | P38: 0 | Q38: 0 | R38: 0 | S38: =SUM(G38:R38) -> 11
B39: T7.2 | C39: Project administration & Financial Management | D39: MNU | E39: 1 | F39: 36 | G39: 3.5 | H39: 0 | I39: 0 | J39: 0 | K39: 0 | L39: 0 | M39: 0 | N39: 0 | O39: 0 | P39: 0 | Q39: 0 | R39: 0 | S39: =SUM(G39:R39) -> 3.5
B40: T7.3 | C40: Quality Assurance | D40: MNU | E40: 1 | F40: 36 | G40: 1.5 | H40: 0 | I40: 0 | J40: 0 | K40: 0 | L40: 0 | M40: 0 | N40: 0 | O40: 0 | P40: 0 | Q40: 0 | R40: 0 | S40: =SUM(G40:R40) -> 1.5
D41: Lead | E41: Start | F41: End | G41: =G3+G7+G12+G19+G29+G33+G37 -> 33.25 | H41: =H3+H7+H12+H19+H29+H33+H37 -> 24 | I41: =I3+I7+I12+I19+I29+I33+I37 -> 18 | J41: =J3+J7+J12+J19+J29+J33+J37 -> 17 | K41: =K3+K7+K12+K19+K29+K33+K37 -> 19 | L41: =L3+L7+L12+L19+L29+L33+L37 -> 19 | M41: =M3+M7+M12+M19+M29+M33+M37 -> 10.25 | N41: =N3+N7+N12+N19+N29+N33+N37 -> 18 | ... R41: =R3+R7+R12+R19+R29+R33+R37 -> 13 | S41: =SUM(G41:R41) -> 222.5
F43: No | G43: =G$1 -> B1 | H43: =H$1 -> B2 | I43: =I$1 -> B3 | J43: =J$1 -> B4 | K43: =K$1 -> B5 | L43: =L$1 -> B6 | M43: =M$1 -> B7 | N43: =N$1 -> B8 | ... R43: =R$1 -> B12
F44: Partner | G44: =G$2 -> MNU | H44: =H$2 -> FOC | I44: =I$2 -> CTLV | J44: =J$2 -> CKR | K44: =K$2 -> MAI | L44: =L$2 -> BIN | M44: =M$2 -> IOC | N44: =N$2 -> HIE | ... R44: =R$2 -> BAL | S44: TOTAL
F45: =B3 -> WP1 | G45: =G3 -> 1.5 | H45: =H3 -> 2.25 | I45: =I3 -> 2.25 | J45: =J3 -> 3.25 | K45: =K3 -> 3.25 | L45: =L3 -> 3.25 | M45: =M3 -> 1.5 | N45: =N3 -> 2.25 | ... S45: =S3 -> 26.75 | T45: =S45/ S$52 -> 0.12022472
F46: =B7 -> WP2 | G46: =G7 -> 0.5 | H46: =H7 -> 2.5 | I46: =I7 -> 2.5 | J46: =J7 -> 2 | K46: =K7 -> 0.5 | L46: =L7 -> 0.5 | M46: =M7 -> 0.5 | N46: =N7 -> 3.5 | ... S46: =S7 -> 17.75 | T46: =S46/ S$52 -> 0.079775281
F47: =B12 -> WP3 | G47: =G12 -> 7 | H47: =H12 -> 2.5 | I47: =I12 -> 3.5 | J47: =J12 -> 6 | K47: =K12 -> 3.5 | L47: =L12 -> 3.5 | M47: =M12 -> 2.5 | N47: =N12 -> 2.5 | ... S47: =S12 -> 45.5 | T47: =S47/ S$52 -> 0.20449438
F48: =B19 -> WP4 | G48: =G19 -> 5.5 | H48: =H19 -> 8.5 | I48: =I19 -> 7 | J48: =J19 -> 3 | K48: =K19 -> 8 | L48: =L19 -> 9 | M48: =M19 -> 3 | N48: =N19 -> 7 | ... S48: =S19 -> 74.75 | T48: =S48/ S$52 -> 0.33595506
F49: =B29 -> WP5 | G49: =G29 -> 0.75 | H49: =H29 -> 0.75 | I49: =I29 -> 0.75 | J49: =J29 -> 0.75 | K49: =K29 -> 0.75 | L49: =L29 -> 0.75 | M49: =M29 -> 0.75 | N49: =N29 -> 0.75 | ... S49: =S29 -> 14.25 | T49: =S49/ S$52 -> 0.064044944
F50: =B33 -> WP6 | G50: =G33 -> 2 | H50: =H33 -> 7.5 | I50: =I33 -> 2 | J50: =J33 -> 2 | K50: =K33 -> 3 | L50: =L33 -> 2 | M50: =M33 -> 2 | N50: =N33 -> 2 | ... S50: =S33 -> 27.5 | T50: =S50/ S$52 -> 0.12359551
F51: =B37 -> WP7 | G51: =G37 -> 16 | H51: =H37 -> 0 | I51: =I37 -> 0 | J51: =J37 -> 0 | K51: =K37 -> 0 | L51: =L37 -> 0 | M51: =M37 -> 0 | N51: =N37 -> 0 | ... S51: =S37 -> 16 | T51: =S51/ S$52 -> 0.071910112
F52: SUM | G52: =G41 -> 33.25 | H52: =H41 -> 24 | I52: =I41 -> 18 | J52: =J41 -> 17 | K52: =K41 -> 19 | L52: =L41 -> 19 | M52: =M41 -> 10.25 | N52: =N41 -> 18 | ... S52: =S41 -> 222.5 | T52: =SUM(T45:T51) -> 1

Sheet Efforth per task PM
F1: B1 | G1: B2 | H1: B3 | I1: B4 | J1: B5 | K1: B6 | L1: B7 | M1: B8 | N1: B9 | O1: B10 | P1: B11 | Q1: B12
A2: No | B2: Work Packages (WP) & Tasks (T) | C2: Lead | D2: Start | E2: End | F2: MNU | G2: FOC | H2: CTLV | I2: CKR | J2: MAI | K2: BIN | L2: IOC | M2: HIE | N2: MCN | O2: MEERI | P2: SCA | Q2: BAL | R2: TOTAL PMs | S2: =S3+S7+S12+S19+S29+S33+S37 -> 1
A3: WP1 | B3: Assessment of potential new value chains and selection of Topics for Call of Proposals | C3: MEERI | D3: 1 | E3: 6 | F3: =SUM( F4:F6) -> 1.5 | G3: =SUM(G4:G6) -> 2.25 | H3: =SUM(H4:H6) -> 2.25 | I3: =SUM(I4:I6) -> 3.25 | J3: =SUM(J4:J6) -> 3.25 | K3: =SUM(K4:K6) -> 3.25 | L3: =SUM(L4:L6) -> 1.5 | M3: =SUM(M4:M6) -> 2.25 | N3: =SUM(N4:N6) -> 1.5 | ... Q3: =SUM(Q4:Q6) -> 1 | R3: =SUM(F3:Q3) -> 26.75 | S3: =R3/ R$41 -> 0.12022472
A4: T1.1 | B4: Sustainable challenges, needs and trends of four industrial offshore sectors | C4: HIE | D4: 1 | E4: 3 | F4: 1 | G4: 1 | H4: 0.25 | I4: 0.25 | J4: 0.25 | K4: 0.25 | L4: 1 | M4: 1.75 | N4: 1 | O4: 0 | P4: 0.5 | Q4: 0.5 | R4: =SUM(F4:Q4) -> 7.75
A5: T1.2 | B5: Assessment of emerging technology trends and solutions | C5: MEERI | D5: 1 | E5: 4 | F5: 0.25 | G5: 0.25 | H5: 1 | I5: 1 | J5: 1 | K5: 1 | L5: 0.25 | M5: 0.25 | N5: 0.25 | O5: 1.75 | P5: 0.25 | Q5: 0.25 | R5: =SUM(F5:Q5) -> 7.5
A6: T1.3 | B6: Potential new value chains and selection of Call Topics | C6: MEERI | D6: 3 | E6: 6 | F6: 0.25 | G6: 1 | H6: 1 | I6: 2 | J6: 2 | K6: 2 | L6: 0.25 | M6: 0.25 | N6: 0.25 | O6: 2 | P6: 0.25 | Q6: 0.25 | R6: =SUM(F6:Q6) -> 11.5
A7: WP2 | B7: Methodologies and tools for cross-sectoral/-border collaboration and technology transfer | C7: HIE | D7: 1 | E7: 36 | F7: =SUM(F8:F11) -> 0.5 | G7: =SUM(G8:G11) -> 2.5 | H7: =SUM(H8:H11) -> 2.5 | I7: =SUM(I8:I11) -> 2 | J7: =SUM(J8:J11) -> 0.5 | K7: =SUM(K8:K11) -> 0.5 | L7: =SUM(L8:L11) -> 0.5 | M7: =SUM(M8:M11) -> 3.5 | ... R7: =SUM(R8:R11) -> 17.75 | S7: =R7/ R$41 -> 0.079775281
A8: T2.1 | B8: Methologies and tools for cross-sectoral/-border collaboration and technology transfer | C8: HIE | D8: 1 | E8: 36 | F8: 0.25 | G8: 1.25 | H8: 1.25 | I8: 0.75 | J8: 0.25 | K8: 0.25 | L8: 0.25 | M8: 3.25 | N8: 0.25 | O8: 0.25 | P8: 0.25 | Q8: 0 | R8: =SUM(F8:Q8) -> 8.25
A9: T2.2 | B9: Establishment of a Collaborative Virtual Environment | C9: MNU | D9: 1 | E9: 36 | F9: 0.25 | G9: 0 | H9: 0 | I9: 0 | J9: 0 | K9: 0 | L9: 0 | M9: 0 | N9: 0 | O9: 0 | P9: 0 | Q9: 0 | R9: =SUM(F9:Q9) -> 0.25
A10: T2.3 | B10: Establishment of a Survey tool | C10: CKR | D10: 1 | E10: 36 | F10: 0 | G10: 1 | H10: 1 | I10: 1 | J10: 0 | K10: 0 | L10: 0 | M10: 0 | N10: 0 | O10: 0 | P10: 0 | Q10: 0 | R10: =SUM(F10:Q10) -> 3
A11: T2.4 | B11: Establishment of the GreenOffshoreTech Cluster Collaboration Platform | C11: BAL | D11: 1 | E11: 36 | F11: 0 | G11: 0.25 | H11: 0.25 | I11: 0.25 | J11: 0.25 | K11: 0.25 | L11: 0.25 | M11: 0.25 | N11: 0.25 | O11: 0.25 | P11: 0.25 | Q11: 3.75 | R11: =SUM(F11:Q11) -> 6.25
A12: WP3 | B12: Direct financial support to SMEs through a competitive Call for Proposals | C12: CKR | D12: 1 | E12: 36 | F12: =SUM(F13:F18) -> 7 | G12: =SUM(G13:G18) -> 2.5 | H12: =SUM(H13:H18) -> 3.5 | I12: =SUM(I13:I18) -> 6 | J12: =SUM(J13:J18) -> 3.5 | K12: =SUM(K13:K18) -> 3.5 | L12: =SUM(L13:L18) -> 2.5 | M12: =SUM(M13:M18) -> 2.5 | ... R12: =SUM(R13:R18) -> 45.5 | S12: =R12/ R$41 -> 0.20449438
A13: T3.1 | B13: Preparation of the Call for Proposals | C13: CKR | D13: 1 | E13: 7 | F13: 0.5 | G13: 0.5 | H13: 0.5 | I13: 3 | J13: 0.5 | K13: 0.5 | L13: 0.5 | M13: 0.5 | N13: 0.5 | O13: 0.5 | P13: 0.5 | Q13: 0.5 | R13: =SUM(F13:Q13) -> 8.5
A14: T3.2 | B14: Publication of the Call for Proposals and Proposal reception. | C14: BAL | D14: 8 | E14: 18 | F14: 0.5 | G14: 0 | H14: 0 | I14: 0 | J14: 0 | K14: 0 | L14: 0 | M14: 0 | N14: 0 | O14: 0 | P14: 0 | Q14: 1 | R14: =SUM(F14:Q14) -> 1.5
A15: T3.3 | B15: Evaluation and Selection of SMEs Proposals | C15: BAL | D15: 11 | E15: 20 | F15: 1 | G15: 1 | H15: 1 | I15: 1 | J15: 1 | K15: 1 | L15: 1 | M15: 1 | N15: 1 | O15: 1 | P15: 1 | Q15: 1.5 | R15: =SUM(F15:Q15) -> 12.5
A16: T3.4 | B16: Contracting with winner SMEs Projects | C16: MNU | D16: 13 | E16: 22 | F16: 2 | G16: 0 | H16: 0 | I16: 0 | J16: 0 | K16: 0 | L16: 0 | M16: 0 | N16: 0 | O16: 0 | P16: 0 | Q16: 0 | R16: =SUM(F16:Q16) -> 2
A17: T3.5 | B17: Payments and financial monitoring of winner SMEs Projects | C17: MNU | D17: 13 | E17: 36 | F17: 2 | G17: 0 | H17: 0 | I17: 0 | J17: 0 | K17: 0 | L17: 0 | M17: 0 | N17: 0 | O17: 0 | P17: 0 | Q17: 0 | R17: =SUM(F17:Q17) -> 2
A18: T3.6 | B18: Technical monitoring of winner SMEs Projects | C18: SCA | D18: 13 | E18: 36 | F18: 1 | G18: 1 | H18: 2 | I18: 2 | J18: 2 | K18: 2 | L18: 1 | M18: 1 | N18: 1 | O18: 2 | P18: 3 | Q18: 1 | R18: =SUM(F18:Q18) -> 19
A19: WP4 | B19: Business Support Services to winner SMEs | C19: MAI | D19: 1 | E19: 36 | F19: =SUM(F20:F28) -> 5.5 | G19: =SUM(G20:G28) -> 8.5 | H19: =SUM(H20:H28) -> 7 | I19: =SUM(I20:I28) -> 3 | J19: =SUM(J20:J28) -> 8 | K19: =SUM(K20:K28) -> 9 | L19: =SUM(L20:L28) -> 3 | M19: =SUM(M20:M28) -> 7 | ... R19: =SUM(R20:R28) -> 74.75 | S19: =R19/ R$41 -> 0.33595506
A20: T4.1 | B20: Programme of Business Support Services to winner SMEs | C20: MAI | D20: 1 | E20: 36 | F20: 0 | G20: 0 | H20: 0 | I20: 0 | J20: 2.5 | K20: 0 | L20: 0 | M20: 0 | N20: 0 | O20: 0 | P20: 0 | Q20: 0 | R20: =SUM(F20:Q20) -> 2.5
A21: T4.2 | B21: Business Support Service #1 Business & Tech Academy | C21: MAI | D21: 1 | E21: 24 | F21: 1 | G21: 1 | H21: 1 | I21: 1 | J21: 3 | K21: 3.5 | L21: 1 | M21: 1 | N21: 1 | O21: 1.5 | P21: 1 | Q21: 1.5 | R21: =SUM(F21:Q21) -> 17.5
A22: T4.3 | B22: Business Support Service #2 Brokerage & B2B matchmaking events | C22: CMAB | D22: 1 | E22: 24 | F22: 0.5 | G22: 4 | H22: 0.5 | I22: 0.5 | J22: 1 | K22: 4 | L22: 0.5 | M22: 0.5 | N22: 0.5 | O22: 0.5 | P22: 0.5 | Q22: 0.5 | R22: =SUM(F22:Q22) -> 13.5
A23: T4.4 | B23: Business Support Service #3 Access to Finance | C23: HIE | D23: 1 | E23: 24 | F23: 0.5 | G23: 0.5 | H23: 0.5 | I23: 0.5 | J23: 0.5 | K23: 0.5 | L23: 0.5 | M23: 3 | N23: 0.5 | O23: 0 | P23: 0 | Q23: 0 | R23: =SUM(F23:Q23) -> 7
A24: T4.5 | B24: Business Support Service #4 One-to-One Mentoring and Coaching | C24: SCA | D24: 1 | E24: 32 | F24: 0 | G24: 0 | H24: 0 | I24: 0 | J24: 0 | K24: 0 | L24: 0 | M24: 0 | N24: 0 | O24: 0 | P24: 9.75 | Q24: 0 | R24: =SUM(F24:Q24) -> 9.75
A25: T4.6 | B25: Business Support Service #5 Branding | C25: FOC | D25: 1 | E25: 32 | F25: 0 | G25: 2 | H25: 0 | I25: 0 | J25: 0 | K25: 0 | L25: 0 | M25: 0 | N25: 0 | O25: 0 | P25: 0 | Q25: 0 | R25: =SUM(F25:Q25) -> 2
A26: T4.7 | B26: Business Support Service #6 Internationalisation | C26: MCN | D26: 1 | E26: 32 | F26: 0.5 | G26: 0.5 | H26: 0.5 | I26: 0.5 | J26: 0.5 | K26: 0.5 | L26: 0.5 | M26: 0.5 | N26: 2 | O26: 0 | P26: 0 | Q26: 0 | R26: =SUM(F26:Q26) -> 6
A27: T4.8 | B27: Business Support Service #7 Investor pitching | C27: CTLV | D27: 1 | E27: 32 | F27: 0.5 | G27: 0 | H27: 4 | I27: 0 | J27: 0 | K27: 0 | L27: 0 | M27: 1.5 | N27: 0 | O27: 0 | P27: 1 | Q27: 0 | R27: =SUM(F27:Q27) -> 7
A28: T4.9 | B28: Business Support Service #8 Investor rounds | C28: MNU | D28: 1 | E28: 32 | F28: 2.5 | G28: 0.5 | H28: 0.5 | I28: 0.5 | J28: 0.5 | K28: 0.5 | L28: 0.5 | M28: 0.5 | N28: 2 | O28: 0.5 | P28: 0.5 | Q28: 0.5 | R28: =SUM(F28:Q28) -> 9.5
A29: WP5 | B29: Large-scale Demonstrator (LSD) setup, validation, and impact assessment | C29: SCA | D29: 1 | E29: 36 | F29: =SUM(F30:F32) -> 0.75 | G29: =SUM(G30:G32) -> 0.75 | H29: =SUM(H30:H32) -> 0.75 | I29: =SUM(I30:I32) -> 0.75 | J29: =SUM(J30:J32) -> 0.75 | K29: =SUM(K30:K32) -> 0.75 | L29: =SUM(L30:L32) -> 0.75 | M29: =SUM(M30:M32) -> 0.75 | ... R29: =SUM(R30:R32) -> 14.25 | S29: =R29/ R$41 -> 0.064044944
A30: T5.1 | B30: Set-up of the GreenOffshoreTech LSD in GreenOffshoreTech regions | C30: SCA | D30: 1 | E30: 36 | F30: 0.25 | G30: 0.25 | H30: 0.25 | I30: 0.25 | J30: 0.25 | K30: 0.25 | L30: 0.25 | M30: 0.25 | N30: 0.25 | O30: 0.25 | P30: 2.5 | Q30: 0.25 | R30: =SUM(F30:Q30) -> 5.25
A31: T5.2 | B31: Validation & Impact assessment of GreenOffshoreTech LSD | C31: SCA | D31: 1 | E31: 36 | F31: 0.25 | G31: 0.25 | H31: 0.25 | I31: 0.25 | J31: 0.25 | K31: 0.25 | L31: 0.25 | M31: 0.25 | N31: 0.25 | O31: 0.25 | P31: 2.5 | Q31: 0.25 | R31: =SUM(F31:Q31) -> 5.25
A32: T5.3 | B32: Guidelines of Best Practice to foster cross-sector/-border collaboration and technology transfer through Clusters | C32: SCA | D32: 35 | E32: 36 | F32: 0.25 | G32: 0.25 | H32: 0.25 | I32: 0.25 | J32: 0.25 | K32: 0.25 | L32: 0.25 | M32: 0.25 | N32: 0.25 | O32: 0.25 | P32: 1 | Q32: 0.25 | R32: =SUM(F32:Q32) -> 3.75
A33: WP6 | B33: Communication, Dissemination, Exploitation & Sustainability | C33: FOC | D33: 1 | E33: 36 | F33: =SUM(F34:F36) -> 2 | G33: =SUM(G34:G36) -> 7.5 | H33: =SUM(H34:H36) -> 2 | I33: =SUM(I34:I36) -> 2 | J33: =SUM(J34:J36) -> 3 | K33: =SUM(K34:K36) -> 2 | L33: =SUM(L34:L36) -> 2 | M33: =SUM(M34:M36) -> 2 | ... R33: =SUM(R34:R36) -> 27.5 | S33: =R33/ R$41 -> 0.12359551
A34: T6.1 | B34: Communication plan and Communication activities | C34: FOC | D34: 1 | E34: 36 | F34: 0.5 | G34: 4 | H34: 0.5 | I34: 0.5 | J34: 0.5 | K34: 0.5 | L34: 0.5 | M34: 0.5 | N34: 0.5 | O34: 0 | P34: 0 | Q34: 0 | R34: =SUM(F34:Q34) -> 8
A35: T6.2 | B35: Dissemination strategy and Dissemination activities | C35: FOC | D35: 1 | E35: 36 | F35: 1 | G35: 3 | H35: 1 | I35: 1 | J35: 1 | K35: 1 | L35: 1 | M35: 1 | N35: 1 | O35: 0.5 | P35: 0.5 | Q35: 0.5 | R35: =SUM(F35:Q35) -> 12.5
A36: T6.3 | B36: Exploitation strategy, IPR and Sustainability | C36: MAI | D36: 1 | E36: 36 | F36: 0.5 | G36: 0.5 | H36: 0.5 | I36: 0.5 | J36: 1.5 | K36: 0.5 | L36: 0.5 | M36: 0.5 | N36: 0.5 | O36: 0.5 | P36: 0.5 | Q36: 0.5 | R36: =SUM(F36:Q36) -> 7
A37: WP7 | B37: Project Management and Coordination | C37: MNU | D37: 1 | E37: 36 | F37: =SUM(F38:F40) -> 16 | G37: =SUM(G38:G40) -> 0 | H37: =SUM(H38:H40) -> 0 | I37: =SUM(I38:I40) -> 0 | J37: =SUM(J38:J40) -> 0 | K37: =SUM(K38:K40) -> 0 | L37: =SUM(L38:L40) -> 0 | M37: =SUM(M38:M40) -> 0 | ... R37: =SUM(R38:R40) -> 16 | S37: =R37/ R$41 -> 0.071910112
A38: T7.1 | B38: Project coordination | C38: MNU | D38: 1 | E38: 36 | F38: 11 | G38: 0 | H38: 0 | I38: 0 | J38: 0 | K38: 0 | L38: 0 | M38: 0 | N38: 0 | O38: 0 | P38: 0 | Q38: 0 | R38: =SUM(F38:Q38) -> 11
A39: T7.2 | B39: Project administration & Financial Management | C39: MNU | D39: 1 | E39: 36 | F39: 3.5 | G39: 0 | H39: 0 | I39: 0 | J39: 0 | K39: 0 | L39: 0 | M39: 0 | N39: 0 | O39: 0 | P39: 0 | Q39: 0 | R39: =SUM(F39:Q39) -> 3.5
A40: T7.3 | B40: Quality Assurance | C40: MNU | D40: 1 | E40: 36 | F40: 1.5 | G40: 0 | H40: 0 | I40: 0 | J40: 0 | K40: 0 | L40: 0 | M40: 0 | N40: 0 | O40: 0 | P40: 0 | Q40: 0 | R40: =SUM(F40:Q40) -> 1.5
C41: Lead | D41: Start | E41: End | F41: =F3+F7+F12+F19+F29+F33+F37 -> 33.25 | G41: =G3+G7+G12+G19+G29+G33+G37 -> 24 | H41: =H3+H7+H12+H19+H29+H33+H37 -> 18 | I41: =I3+I7+I12+I19+I29+I33+I37 -> 17 | J41: =J3+J7+J12+J19+J29+J33+J37 -> 19 | K41: =K3+K7+K12+K19+K29+K33+K37 -> 19 | L41: =L3+L7+L12+L19+L29+L33+L37 -> 10.25 | M41: =M3+M7+M12+M19+M29+M33+M37 -> 18 | ... Q41: =Q3+Q7+Q12+Q19+Q29+Q33+Q37 -> 13 | R41: =SUM(F41:Q41) -> 222.5
E43: No | F43: =F$1 -> B1 | G43: =G$1 -> B2 | H43: =H$1 -> B3 | I43: =I$1 -> B4 | J43: =J$1 -> B5 | K43: =K$1 -> B6 | L43: =L$1 -> B7 | M43: =M$1 -> B8 | ... Q43: =Q$1 -> B12
E44: Partner | F44: =F$2 -> MNU | G44: =G$2 -> FOC | H44: =H$2 -> CTLV | I44: =I$2 -> CKR | J44: =J$2 -> MAI | K44: =K$2 -> BIN | L44: =L$2 -> IOC | M44: =M$2 -> HIE | ... Q44: =Q$2 -> BAL | R44: TOTAL
E45: =A3 -> WP1 | F45: =F3 -> 1.5 | G45: =G3 -> 2.25 | H45: =H3 -> 2.25 | I45: =I3 -> 3.25 | J45: =J3 -> 3.25 | K45: =K3 -> 3.25 | L45: =L3 -> 1.5 | M45: =M3 -> 2.25 | ... R45: =R3 -> 26.75 | S45: =R45/ R$52 -> 0.12022472
E46: =A7 -> WP2 | F46: =F7 -> 0.5 | G46: =G7 -> 2.5 | H46: =H7 -> 2.5 | I46: =I7 -> 2 | J46: =J7 -> 0.5 | K46: =K7 -> 0.5 | L46: =L7 -> 0.5 | M46: =M7 -> 3.5 | ... R46: =R7 -> 17.75 | S46: =R46/ R$52 -> 0.079775281
E47: =A12 -> WP3 | F47: =F12 -> 7 | G47: =G12 -> 2.5 | H47: =H12 -> 3.5 | I47: =I12 -> 6 | J47: =J12 -> 3.5 | K47: =K12 -> 3.5 | L47: =L12 -> 2.5 | M47: =M12 -> 2.5 | ... R47: =R12 -> 45.5 | S47: =R47/ R$52 -> 0.20449438
E48: =A19 -> WP4 | F48: =F19 -> 5.5 | G48: =G19 -> 8.5 | H48: =H19 -> 7 | I48: =I19 -> 3 | J48: =J19 -> 8 | K48: =K19 -> 9 | L48: =L19 -> 3 | M48: =M19 -> 7 | ... R48: =R19 -> 74.75 | S48: =R48/ R$52 -> 0.33595506
E49: =A29 -> WP5 | F49: =F29 -> 0.75 | G49: =G29 -> 0.75 | H49: =H29 -> 0.75 | I49: =I29 -> 0.75 | J49: =J29 -> 0.75 | K49: =K29 -> 0.75 | L49: =L29 -> 0.75 | M49: =M29 -> 0.75 | ... R49: =R29 -> 14.25 | S49: =R49/ R$52 -> 0.064044944
E50: =A33 -> WP6 | F50: =F33 -> 2 | G50: =G33 -> 7.5 | H50: =H33 -> 2 | I50: =I33 -> 2 | J50: =J33 -> 3 | K50: =K33 -> 2 | L50: =L33 -> 2 | M50: =M33 -> 2 | ... R50: =R33 -> 27.5 | S50: =R50/ R$52 -> 0.12359551
E51: =A37 -> WP7 | F51: =F37 -> 16 | G51: =G37 -> 0 | H51: =H37 -> 0 | I51: =I37 -> 0 | J51: =J37 -> 0 | K51: =K37 -> 0 | L51: =L37 -> 0 | M51: =M37 -> 0 | ... R51: =R37 -> 16 | S51: =R51/ R$52 -> 0.071910112
E52: SUM | F52: =F41 -> 33.25 | G52: =G41 -> 24 | H52: =H41 -> 18 | I52: =I41 -> 17 | J52: =J41 -> 19 | K52: =K41 -> 19 | L52: =L41 -> 10.25 | M52: =M41 -> 18 | ... R52: =R41 -> 222.5 | S52: =SUM(S45:S51) -> 1

Sheet MONITORING TABLE 75%
A2: INNOSUP 1: Monitoring Table 75% requirement
A3: version 23/03/2018
A4: Project: GreenOffshoreTech - GA 101005541
A5: Period covered: from project start date (01/09/2021) to 31/05/2022 - M1-M9 | B5: Deliverable D7.5
A7: ***Please read the instructions in Sheet 2 and look at the example in Sheet 3 before completing the table*** | J7: automatic filling
A9: Section 1 - Direct financial support to SMEs to support innovation | B9: Related WP task | C9: N° of beneficiary SMEs for country 1: (specify country) for period covered | D9: N° of beneficiary SMEs for country 2: (specify country) for period covered | E9: N° of beneficiary SMEs for country 3: (specify country) for period covered | F9: N° of beneficiary SMEs for country 4: (specify country) for period covered | G9: N° of beneficiary SMEs for country 5: (specify country) for period covered | H9: TOTAL n° of beneficiary SMEs for period covered | I9: TOTAL n° of beneficiary SMEs for whole project duration (target) | J9: (Average) cost per individual service (in €) | K9: Total costs for all beneficiary SMEs for period covered | L9: Total budget for all beneficiary SMEs for whole project duration (target) | M9: Beneficiaries: country distribution (for period covered) | N9: Partners involved (in period covered) | O9: Additional information
A10: CALL - cutoff 1: | B10: --- | H10: --- | I10: --- | J10: --- | K10: --- | L10: --- | M10: --- | N10: --- | O10: ---
A11: Direct funding (lump sums) - PHASE 1 | B11: T3.5 | H11: 0 | I11: 50 | J11: 5000 | K11: 0 | L11: =I11*J11 -> 250000 | M11: xx SMEs: 10x NO, 8x PL, 6x UK, etc | N11: MNU | O11: Payments done to SMEs.
A12: Direct funding (lump sums) - PHASE 2 | B12: T3.5 | H12: 0 | I12: 25 | J12: 45000 | K12: 0 | L12: =I12*J12 -> 1125000 | M12: xx SMEs: 5x NO, 4x PL, 3x UK, etc | N12: MNU | O12: Payments done to SMEs.
A13: Direct funding (lump sums) - PHASE 3 | B13: T3.5 | H13: 0 | I13: 12 | J13: 10000 | K13: 0 | L13: =I13*J13 -> 120000 | M13: xx SMEs: 1x NO, 1x PL, 1x UK, etc | N13: MNU | O13: Payments done to SMEs.
A14: CALL - cutoff 2: | B14: --- | H14: --- | I14: --- | J14: --- | K14: --- | L14: --- | M14: --- | N14: --- | O14: ---
A15: Direct funding (lump sums) - PHASE 1 | B15: T3.5 | H15: 0 | I15: 50 | J15: 5000 | K15: 0 | L15: =I15*J15 -> 250000 | M15: xx SMEs: 8x NO, 6x PL, 4x UK, etc | N15: MNU | O15: Payments done to SMEs.
A16: Direct funding (lump sums) - PHASE 2 | B16: T3.5 | H16: 0 | I16: 25 | J16: 45000 | K16: 0 | L16: =I16*J16 -> 1125000 | M16: xx SMEs: 4x NO, 3x PL, 2x UK, etc | N16: MNU | O16: Payments done to SMEs.
A17: Direct funding (lump sums) - PHASE 3 | B17: T3.5 | H17: 0 | I17: 13 | J17: 10000 | K17: 0 | L17: =I17*J17 -> 130000 | M17: xx SMEs: 1x NO, 1x PL, 1x UK, etc | N17: MNU | O17: Payments done to SMEs.
A18: Total amounts - section 1 | H18: =SUM(H10:H17) -> 0 | I18: =I11+I15 -> 100 | K18: =SUM(K10:K17) -> 0 | L18: =SUM(L10:L17) -> 3000000
A20: Total of unique SMEs directly assisted (section 1) | H20: =H11+H15 -> 0 | I20: =I11+I15 -> 100 | M20: xx SMEs: 18x NO, 14x PL, 10x UK, etc.
A22: Section 2 - Direct innovation support (non financial) to individual SMEs | B22: Related WP task | C22: N° of beneficiary SMEs for country 1: (specify country) for period covered | D22: N° of beneficiary SMEs for country 2: (specify country) for period covered | E22: N° of beneficiary SMEs for country 3: (specify country) for period covered | F22: N° of beneficiary SMEs for country 4: (specify country) for period covered | G22: N° of beneficiary SMEs for country 5: (specify country) for period covered | H22: TOTAL n° of beneficiary SMEs for period covered | I22: TOTAL n° of beneficiary SMEs for whole project duration (target) | J22: (Average) cost per individual service (in €) | K22: Total costs for all beneficiary SMEs for period covered | L22: Total budget for all beneficiary SMEs for whole project duration (target) | M22: Beneficiaries: country distribution (for period covered) | N22: Partners involved (in period covered) | O22: Additional information
A23: CALL - cutoff 1+2: | B23: --- | H23: --- | I23: --- | J23: --- | K23: --- | L23: --- | M23: --- | N23: --- | O23: ---
A24: Delivery of Business Support Service #1 Business & Tech Academy | B24: T4.2 | H24: 0 | I24: 100 | K24: 0 | L24: 104189 | M24: xx SMEs: 18x NO, 14x PL, 10x UK, etc. | N24: MAI (lead), MNU, FOC, CTLV, CKR, CMAB, IOC, HIE, MCN, MEERI, SCA, BAL | O24: Staff costs (direct + indirect)
A25: Delivery of Business Support Service #2 Brokerage & B2B matchmaking events | B25: T4.3 | H25: 0 | I25: 100 | K25: 0 | L25: 81036 | M25: xx SMEs: 18x NO, 14x PL, 10x UK, etc. | N25: CMAB (lead), MNU, FOC, CTLV, CKR, CMAB, IOC, HIE, MCN, MEERI, SCA, BAL | O25: Staff costs (direct + indirect)
A26: Delivery of Business Support Service #3 Access to Finance | B26: T4.4 | H26: 0 | I26: 100 | K26: 0 | L26: 43412 | M26: xx SMEs: 18x NO, 14x PL, 10x UK, etc. | N26: HIE (lead), MNU, FOC, CTLV, CKR, MAI, CMAB, IOC, HIE, MCN | O26: Staff costs (direct + indirect)
A27: Delivery of Business Support Service #4 One-to-One Mentoring and Coaching | B27: T4.5 | H27: 0 | I27: 50 | K27: 0 | L27: 59330 | M27: xx SMEs: 9x NO, 7x PL, 5x UK, etc. | N27: SCA (lead) | O27: Staff costs (direct + indirect)
A28: Delivery of Business Support Service #5 Branding | B28: T4.6 | H28: 0 | I28: 50 | K28: 0 | L28: 14471 | M28: xx SMEs: 9x NO, 7x PL, 5x UK, etc. | N28: FOC (lead) | O28: Staff costs (direct + indirect)
A29: Delivery of Business Support Service #6 Internationalisation | B29: T4.7 | H29: 0 | I29: 50 | K29: 0 | L29: 34730 | M29: xx SMEs: 9x NO, 7x PL, 5x UK, etc. | N29: MCN (lead), MNU, FOC, CTLV, CKR, MAI, CMAB, IOC, HIE | O29: Staff costs (direct + indirect)
A30: Delivery of Business Support Service #7 Investor pitching | B30: T4.8 | H30: 0 | I30: 50 | K30: 0 | L30: 40518 | M30: xx SMEs: 9x NO, 7x PL, 5x UK, etc. | N30: CTLV (lead), MNU, HIE, SCA | O30: Staff costs (direct + indirect)
A31: Delivery of Business Support Service #8 Investor rounds | B31: T4.9 | H31: 0 | I31: 50 | K31: 0 | L31: 54989 | M31: xx SMEs: 9x NO, 7x PL, 5x UK, etc. | N31: MNU (lead), FOC, CTLV, CKR, MAI, CMAB, IOC, HIE, MCN, MEERI, SCA, BAL | O31: Staff costs (direct + indirect)
A32: Total amounts - section 2 | H32: =SUM(H23:H31) -> 0 | I32: =I24 -> 100 | K32: =SUM(K23:K31) -> 0 | L32: =SUM(L23:L31) -> 432675
A34: Total of unique SMEs directly assisted (section 2) | H34: =H24 -> 0 | I34: =I24 -> 100 | M34: xx SMEs: 18x NO, 14x PL, 10x UK, etc.
A36: Total of unique SMEs directly assisted (sections 1 + 2) | H36: =H20 -> 0 | I36: =I20 -> 100 | M36: xx SMEs: 18x NO, 14x PL, 10x UK, etc.
A38: Section 3 - other innovation services provided to SMEs | B38: Related WP task | H38: TOTAL n° of SMEs for period covered | I38: TOTAL n° of SMEs for whole project duration (target) | K38: Total costs for period covered | L38: Total budget for whole project duration (target) | M38: Number of services (for period covered) | N38: Partners involved (in period covered) | O38: Additional information
A39: Virtual Brockerage Event (?) | B39: T6.2 | H39: 0 | I39: 100 | J39: --- | K39: 0 | L39: 0 | M39: 1x virtual brockerage event | N39: FOC (lead), MNU, CTLV, CKR, MAI, CMAB, IOC, HIE, MCN, MEERI, SCA, BAL | O39: ---
A40: --- | B40: --- | H40: --- | I40: --- | J40: --- | K40: --- | L40: --- | M40: --- | N40: --- | O40: ---
A41: --- | B41: --- | H41: --- | I41: --- | J41: --- | K41: --- | L41: --- | M41: --- | N41: --- | O41: ---
A43: Total amounts - section 3 | H43: =SUM(H37:H42) -> 0 | I43: =SUM(I37:I42) -> 100 | K43: =SUM(K37:K42) -> 0 | L43: =SUM(L37:L42) -> 0
A45: Section 4 - costs for preparation / management / monitoring of services in other sections | B45: Related WP task | H45: --- | I45: --- | J45: --- | K45: Total costs for period covered | L45: Total budget for whole project duration (target) | M45: --- | N45: Partners involved (in period covered) | O45: Additional information
A46: Costs for preparation/ management/ monitoring of services in Section 1+2: | B46: --- | H46: --- | I46: --- | J46: --- | K46: --- | L46: --- | M46: --- | N46: --- | O46: ---
A47: Costs for preparation of the Topics for the Call for Proposals | B47: T1.1, T1.2, T1.3 | H47: --- | I47: --- | J47: --- | K47: 110616 | L47: 213716 | M47: --- | N47: MEERI (lead), HIE (lead), MNU, FOC, CTLV, CKR, MAI, CMAB, IOC, MCN, SCA, BAL | O47: Staff costs (direct + indirect)
A48: Cost for preparation of the Cluster Collaboration Platform for managing the open Call, the development of the new Virtual Matchmaking tool, and the estbalishment of a Virtual Collaboration Environment | B48: T2.1, T2.2, T2.3, T2.4 | H48: --- | I48: --- | J48: --- | K48: 67975 | L48: 145038 | M48: --- | N48: HIE (lead), BAL (lead), CKR (lead), MNU, FOC, CTLV, MAI, CMAB, IOC, MCN, SCA | O48: Staff costs (direct + indirect)
A49: Costs for preparation, evaluation and monitoring of the Call for Proposals and the winner SMEs Projects | B49: T3.1, T3.2, T3.3, T3.4, T3.5, T3.6 | H49: --- | I49: --- | J49: --- | K49: 87880 | L49: 423719 | M49: --- | N49: CKR (lead), BAL (lead), MNU (lead), SCA (lead), FOC, CTLV, MAI, CMAB, ICO, HIE, MCN, MEERI | O49: Staff costs (direct + indirect)
A50: Costs for preparation and monitoring of the Business Support Services | B50: T4.1, T4.2, T4.3, T4.4, T4.5, T4.6, T4.7, T4.8, T4.9 | H50: --- | I50: --- | J50: --- | K50: 21953 | L50: 332827 | M50: --- | N50: MAI (lead), MNU (lead), FOC (lead), CTLV(lead), CMAB (lead), HIE (lead), MCN (lead), SCA (lead), IOC, CKR, MEERI, BAL | O50: Staff costs (direct + indirect)
A51: Costs for preparation and monitoring of the Large-scale Demonstrator | B51: T5.1, T5.2, T5.3 | H51: --- | I51: --- | J51: --- | K51: 42546 | L51: 136613 | M51: --- | N51: SCA (lead), MNU, FOC, CTLV, CKR, MAI, CMAB, IOC, HIE, MCN, MEERI, BAL | O51: Staff costs (direct + indirect)
A56: Total amounts - section 4 | K56: =SUM(K46:K55) -> 330970 | L56: =SUM(L46:L55) -> 1251913
A58: Section 5 - costs of SME partners in the consortium not declared in sections 1,2, 3 and 4 | B58: Related WP task | H58: --- | I58: --- | J58: --- | K58: Total costs for period covered | L58: Total budget for whole project duration (target) | M58: --- | N58: Partners involved (in period covered) | O58: Additional information
A59: Partner 7 - IOC | B59: T6.1 | H59: --- | I59: --- | J59: --- | K59: 4821 | L59: 4685 | M59: Reviews, workshop support. | N59: FOC, IOC
A60: Partner 11 - SCA | B60: T7.1, T7.2,T7.3, T6.1 | H60: --- | I60: --- | J60: --- | K60: 6548 | L60: 0 | M60: Reviews, workshop support. | N60: FOC, SCA, MNU | O60: No Allocated budget for T6.1, T7.1, T7.2 and T7.3 (spending of 6548 Euro without prior clarification from WP owners).
A61: Partner 12 - BAL | B61: --- | H61: --- | I61: --- | J61: --- | K61: 0 | L61: 0 | M61: --- | N61: --- | O61: ---
A64: Total amounts - section 5 | K64: =SUM(K58:K63) -> 11369 | L64: =SUM(L58:L63) -> 4685
A66: GRAND TOTAL | K66: Total innovation support costs for period covered | L66: Total innovation support budget for whole project duration (target) | O66: Additional information
A67: sections 1 to 5 | K67: =K64+K56+K43+K32+K18 -> 342339 | L67: =L64+L56+L43+L32+L18 -> 4689273
A70: Total budget of the project (in €): | B70: 5253231.2
A71: Total budget of the project to be allocated to support innovation in SMEs (in €): | B71: =L67 -> 4689273 | D71: € | H71: imported from GRAND TOTAL
A72: % of costs to be allocated to support innovation in SMEs vs total costs: | B72: =B71/B70 -> 0.89264546 | D72: =D71/#REF! -> #VALUE! | H72: minimum 75% of total budget
A73: % of costs allocated to support innovation in SMEs in the period covered vs total budget: | B73: =K67/B70 -> 0.06516732 | H73: Total innovation support costs for period covered from GRAND TOTAL divided by total budget of the project
D74: =K65/#REF! -> #REF!

Sheet Direct &Indirect Personnal Cost
A2: ALL DIRECT & INDIRECT COST CALCULATIONS PER PARTNER | AA2: 7266
A3: TOTAL BUDGET IS NOT EQUAL TO EC CONTRIBUTION DUE TO THE SME PARTNERS
A4: 70%. Delivered Hourly cost estimate and Budget allocation.
A5: GreenOfshoreTech TOTAL (Period M1 to M9) | B5: Task/ WP | C5: TOTAL COST | D5: Other Dir. Cost Budget | E5: TOTAL BUDGET | F5: % spend | G5: MNU COST | H5: Other Dir. Cost Budget | J5: % spend | K5: SCA COST | L5: Other Dir. Cost Budget | M5: SCA BUDGET | N5: % spend | O5: FOC COST | P5: Other Dir. Cost Budget | Q5: FOC BUDGET | R5: % spend | S5: CTLV COST | T5: Other Dir. Cost Budget | U5: CTLV BUDGET | V5: % spend | W5: MAI COST | X5: Other Dir. Cost | Y5: Revised MAI BUDGET | Z5: MAI BUDGET | AA5: % spend | AB5: BIN COST | AC5: Other Dir. Cost | AD5: BIN BUDGET | AE5: % spend | AF5: IOC COST | AG5: Other Dir. Cost | AH5: IOC BUDGET | AI5: % spend | AJ5: HIE COST | AK5: Other Dir. Cost | AL5: HIE BUDGET | AM5: % spend | AN5: BAL COST | AO5: Other Dir. Cost | AP5: BAL BUDGET | AQ5: % spend | AR5: MEERI COST | AS5: Other Dir. Cost | AT5: MEERI BUDGET | AU5: % spend | AV5: MCN COST | AW5: Other Dir. Cost | AX5: MCN BUDGET | AY5: % spend | AZ5: CKR COST | BA5: Other Dir. Cost | BB5: CKR BUDGET | BC5: % spend
A6: Otherdirect Cost ( travel, equipment & Other goods and services)(ODC) | B6: ODC | C6: =SUM(G6+K6+O6+S6+W6+AB6+AF6+AJ6+AN6+AR6+AV6+AZ6) -> 5763.75 | E6: =SUM(I6+M6+Q6+U6+Z6+AD6+AH6+AL6+AP6+AT6+AX6+BB6) -> 343929 | F6: =100/E6*C6 -> 1.6758546 | G6: 0 | I6: 39500 | J6: =100/I6*G6 -> 0 | K6: 0 | M6: 20750 | N6: =100/M6*K6 -> 0 | O6: 0 | Q6: 42500 | R6: =100/Q6*O6 -> 0 | S6: 0 | U6: 20750 | V6: =100/U6*S6 -> 0 | W6: 0 | Y6: 20750 | Z6: 20750 | AA6: =100/Z6*W6 -> 0 | AB6: 0 | AD6: 56429 | AE6: =100/AD6*AB6 -> 0 | AF6: =SUM(IOC!K9) -> 0 | AH6: 20750 | AI6: =100/AH6*AF6 -> 0 | AJ6: =SUM(HIE!L9) -> 5763.75 | AL6: 20750 | AM6: =100/AL6*AJ6 -> 27.777108 | AN6: 0 | AP6: 20750 | AQ6: =100/AP6*AN6 -> 0 | AR6: 0 | AT6: =SUM(MEERI!M1*MEERI!$O$1) -> 20750 | AU6: =100/AT6*AR6 -> 0 | AV6: 0 | AX6: =SUM(MCN!V1*MCN!$T$1) -> 39500 | AY6: =100/AX6*AV6 -> 0 | AZ6: 0 | BB6: 20750 | BC6: =100/BB6*AZ6 -> 0
A7: Assessment of potential new value chains and selection of Topics for Call of Proposals | B7: WP1 | C7: =SUM(G7+K7+O7+S7+W7+AB7+AF7+AJ7+AN7+AR7+AV7+AZ7) -> 104301.99 | D7: =SUM(H7+L7+P7+T7+X7+AC7+AG7+AK7+AO7+AS7+AW7+BA7) -> 31600 | E7: =SUM(I7+M7+Q7+U7+Z7+AD7+AH7+AH7+AL7+AP7+AT7+AX7+BB7) -> 226991.17 | F7: =100/E7*C7 -> 45.949802 | G7: {=MNU!C7:C45} -> 8024.875 | H7: =SUM(H8:H10) -> 31600 | I7: =SUM(I8:I10) -> 20062.5 | J7: =100/I7*G7 -> 39.999377 | K7: =SUM(SCA!W12) -> 13497.165 | L7: =SUM(L8:L10) -> 0 | M7: =SUM(M8:M10) -> 11712.46 | N7: =100/M7*K7 -> 115.23766 | O7: {=FOC!D8:D46} -> 1875.625 | P7: =SUM(P8:P10) -> 0 | Q7: =SUM(Q8:Q10) -> 7790.62 | R7: =100/Q7*O7 -> 24.075427 | S7: {=CLTV!AQ8:AQ46} -> 6823.4177 | T7: =SUM(T8:T10) -> 0 | U7: =SUM(U8:U10) -> 10546.88 | V7: =100/U7*S7 -> 64.696078 | W7: =SUM(MAI!X10) -> 12627.337 | X7: =SUM(X8:X10) -> 0 | Y7: =SUM(Y8:Y10) -> 31484.38 | Z7: =SUM(Z8:Z10) -> 31484.38 | AA7: =100/Z7*W7 -> 40.106674 | AB7: {=BIN!S8:S46} -> 13000.737 | AC7: =SUM(AC8:AC10) -> 0 | AD7: =SUM(AD8:AD10) -> 36562.5 | AE7: =100/AD7*AB7 -> 35.557573 | AF7: =SUM(IOC!K10) -> 2402.5312 | AG7: =SUM(AG8:AG10) -> 0 | AH7: =SUM(AH8:AH10) -> 17306.54 | AI7: =100/AH7*AF7 -> 13.882216 | AJ7: =SUM(HIE!L10) -> 12255.246 | AK7: =SUM(AK8:AK10) -> 0 | AL7: =SUM(AL8:AL10) -> 23906.25 | AM7: =100/AL7*AJ7 -> 51.263774 | AN7: {=BAL!V9:V47} -> 13402.888 | AO7: =SUM(AO8:AO10) -> 0 | AP7: =SUM(AP8:AP10) -> 12375 | AQ7: =100/AP7*AN7 -> 108.30616 | AR7: {=MEERI!G10:G48} -> 8319.05 | AS7: =SUM(AS8:AS10) -> 0 | AT7: =SUM(AT8:AT10) -> 13406.25 | AU7: =100/AT7*AR7 -> 62.05352 | AV7: {=MCN!C7:C45} -> 7696.99 | AW7: =SUM(AW8:AW10) -> 0 | AX7: =SUM(AX8:AX10) -> 10312.5 | AY7: =100/AX7*AV7 -> 74.637479 | AZ7: ='CKR '!C6 -> 4376.13 | BA7: =SUM(BA8:BA10) -> 0 | BB7: =SUM(BB8:BB10) -> 14218.75 | BC7: =100/BB7*AZ7 -> 30.777178
A8: Sustainable challenges, needs and trends of four industrial offshore sectors | B8: T1.1 | C8: =SUM(G8+K8+O8+S8+W8+AB8+AF8+AJ8+AN8+AR8+AV8+AZ8) -> 41306.53 | D8: =SUM(H8+L8+P8+T8+X8+AC8+AG8+AK8+AO8+AS8+AW8+BA8) -> 31600 | E8: =SUM(I8+M8+Q8+U8+Z8+AD8+AH8+AH8+AL8+AP8+AT8+AX8+BB8) -> 88440.74 | F8: =100/E8*C8 -> 46.705319 | G8: 3265.9375 | H8: 31600 | I8: 13375 | J8: =100/I8*G8 -> 24.418224 | K8: =SUM(SCA!W13) -> 6648.4552 | M8: 5856.22 | N8: =100/M8*K8 -> 113.5281 | O8: 780.13 | Q8: 3462.5 | R8: =100/Q8*O8 -> 22.53083 | S8: 508.68068 | U8: 4687.5 | V8: =100/U8*S8 -> 10.851855 | W8: =SUM(MAI!X11) -> 0 | Y8: 2421.88 | Z8: 2421.88 | AA8: =100/Z8*W8 -> 0 | AB8: 2578.095 | AD8: 2812.5 | AE8: =100/AD8*AB8 -> 91.6656 | AF8: =SUM(IOC!K11) -> 310.53125 | AH8: 11537.57 | AI8: =100/AH8*AF8 -> 2.6914788 | AJ8: =SUM(HIE!L11) -> 11586.268 | AL8: 18593.75 | AM8: =100/AL8*AJ8 -> 62.312701 | AN8: 7215.3875 | AP8: 6187.5 | AQ8: =100/AP8*AN8 -> 116.61232 | AR8: 307.44 | AT8: 0 | AU8: =100/AT8*AR8 -> #DIV/0! | AV8: 6508.745 | AX8: 6875 | AY8: =100/AX8*AV8 -> 94.672655 | AZ8: ='CKR '!C7 -> 1596.86 | BB8: 1093.75 | BC8: =100/BB8*AZ8 -> 145.99863
A9: Assessment of emerging technology trends and solutions | B9: T1.2 | C9: =SUM(G9+K9+O9+S9+W9+AB9+AF9+AJ9+AN9+AR9+AV9+AZ9) -> 29037.419 | D9: =SUM(H9+L9+P9+T9+X9+AC9+AG9+AK9+AO9+AS9+AW9+BA9) -> 0 | E9: =SUM(I9+M9+Q9+U9+Z9+AD9+AH9+AH9+AL9+AP9+AT9+AX9+BB9) -> 53116.01 | F9: =100/E9*C9 -> 54.667922 | G9: 1399.6875 | I9: 3343.75 | J9: =100/I9*G9 -> 41.859813 | K9: =SUM(SCA!W14) -> 3484.4313 | M9: 2928.12 | N9: =100/M9*K9 -> 118.99893 | O9: 194.2 | Q9: 865.62 | R9: =100/Q9*O9 -> 22.434787 | S9: 2541.4263 | U9: 1171.88 | V9: =100/U9*S9 -> 216.86745 | W9: =SUM(MAI!X12) -> 5070.8375 | Y9: 9687.5 | Z9: 9687.5 | AA9: =100/Z9*W9 -> 52.344129 | AB9: 5960.02 | AD9: 11250 | AE9: =100/AD9*AB9 -> 52.977956 | AF9: =SUM(IOC!K12) -> 1470.9375 | AH9: 2884.57 | AI9: =100/AH9*AF9 -> 50.993302 | AJ9: =SUM(HIE!L12) -> 411.67883 | AL9: 2656.25 | AM9: =100/AL9*AJ9 -> 15.498497 | AN9: 3093.75 | AP9: 3093.75 | AQ9: =100/AP9*AN9 -> 100 | AR9: 4060.45 | AT9: 6256.25 | AU9: =100/AT9*AR9 -> 64.902298 | AV9: 0 | AX9: 1718.75 | AY9: =100/AX9*AV9 -> 0 | AZ9: ='CKR '!C8 -> 1350 | BB9: 4375 | BC9: =100/BB9*AZ9 -> 30.857143
A10: Potential new value chains and selection of Call Topics | B10: T1.3 | C10: =SUM(G10+K10+O10+S10+W10+AB10+AF10+AJ10+AN10+AR10+AV10+AZ10) -> 30982.771 | D10: =SUM(H10+L10+P10+T10+X10+AC10+AG10+AK10+AO10+AS10+AW10+BA10) -> 0 | E10: =SUM(I9+M10+Q10+U10+Z10+AD10+AH10+AH10+AL10+AP10+AT10+AX10+BB10) -> 85434.42 | F10: =100/E10*C10 -> 36.264975 | G10: 3359.25 | I10: 3343.75 | J10: =100/I10*G10 -> 100.46355 | K10: =SUM(SCA!W15) -> 3364.2785 | M10: 2928.12 | N10: =100/M10*K10 -> 114.89551 | O10: 526.17 | Q10: 3462.5 | R10: =100/Q10*O10 -> 15.196245 | S10: 3773.3108 | U10: 4687.5 | V10: =100/U10*S10 -> 80.497296 | W10: =SUM(MAI!X13) -> 7556.5 | Y10: 19375 | Z10: 19375 | AA10: =100/Z10*W10 -> 39.00129 | AB10: 1862.475 | AD10: 22500 | AE10: =100/AD10*AB10 -> 8.2776667 | AF10: =SUM(IOC!K13) -> 621.0625 | AH10: 2884.4 | AI10: =100/AH10*AF10 -> 21.531774 | AJ10: =SUM(HIE!L13) -> 257.29927 | AL10: 2656.25 | AM10: =100/AL10*AJ10 -> 9.6865606 | AN10: 3093.75 | AP10: 3093.75 | AQ10: =100/AP10*AN10 -> 100 | AR10: 3951.16 | AT10: 7150 | AU10: =100/AT10*AR10 -> 55.260979 | AV10: 1188.245 | AX10: 1718.75 | AY10: =100/AX10*AV10 -> 69.134255 | AZ10: ='CKR '!C9 -> 1429.27 | BB10: 8750 | BC10: =100/BB10*AZ10 -> 16.334514
A11: Methodologies and tools for cross-sectoral/-border collaboration and technology transfer | B11: WP2 | C11: =SUM(G11+K11+O11+S11+W11+AB11+AF11+AJ11+AN11+AR11+AV11+AZ11) -> 67811.891 | D11: =SUM(H11+L11+P11+T11+X11+AC11+AG11+AK11+AO11+AS11+AW11+BA11) -> 0 | E11: =SUM(I11+M11+Q11+U11+Z11+AD11+AH11+AH11+AL11+AP11+AT11+AX11+BB11) -> 153493.81 | F11: =100/E11*C11 -> 44.178909 | G11: 5346.8063 | H11: =SUM(H12:H15) -> 0 | I11: =SUM(I12:I15) -> 6687.5 | J11: =100/I11*G11 -> 79.952243 | K11: =SUM(SCA!W16) -> 3123.9729 | L11: =SUM(L12:L15) -> 0 | M11: =SUM(M12:M15) -> 5856.22 | N11: =100/M11*K11 -> 53.344528 | O11: 174.2875 | P11: =SUM(P12:P15) -> 0 | Q11: =SUM(Q12:Q15) -> 8656.24 | R11: =100/Q11*O11 -> 2.0134319 | S11: 3711.9305 | T11: =SUM(T12:T15) -> 0 | U11: =SUM(U12:U15) -> 11718.76 | V11: =100/U11*S11 -> 31.675113 | W11: =SUM(MAI!X14) -> 0 | X11: =SUM(X12:X15) -> 0 | Y11: =SUM(Y12:Y15) -> 4843.76 | Z11: =SUM(Z12:Z15) -> 4843.76 | AA11: =100/Z11*W11 -> 0 | AB11: 653.5 | AC11: =SUM(AC12:AC15) -> 0 | AD11: =SUM(AD12:AD15) -> 5625 | AE11: =100/AD11*AB11 -> 11.617778 | AF11: =SUM(IOC!K14) -> 555.6875 | AG11: =SUM(AG12:AG15) -> 0 | AH11: =SUM(AH12:AH15) -> 5768.79 | AI11: =100/AH11*AF11 -> 9.6326526 | AJ11: =SUM(HIE!L14) -> 15281.059 | AK11: =SUM(AK12:AK15) -> 0 | AL11: =SUM(AL12:AL15) -> 37187.5 | AM11: =100/AL11*AJ11 -> 41.091923 | AN11: 30049.188 | AO11: =SUM(AO12:AO15) -> 0 | AP11: =SUM(AP12:AP15) -> 47406.25 | AQ11: =100/AP11*AN11 -> 63.386552 | AR11: 1776.61 | AS11: =SUM(AS12:AS15) -> 0 | AT11: =SUM(AT12:AT15) -> 1787.5 | AU11: =100/AT11*AR11 -> 99.390769 | AV11: 565.24 | AW11: =SUM(AW12:AW15) -> 0 | AX11: =SUM(AX12:AX15) -> 3437.5 | AY11: =100/AX11*AV11 -> 16.443345 | AZ11: ='CKR '!C10 -> 6573.6097 | BA11: =SUM(BA12:BA15) -> 0 | BB11: =SUM(BB12:BB15) -> 8750 | BC11: =100/BB11*AZ11 -> 75.126968
A12: Methologies and tools for cross-sectoral/-border collaboration and technology transfer | B12: T2.1 | C12: =SUM(G12+K12+O12+S12+W12+AB12+AF12+AJ12+AN12+AR12+AV12+AZ12) -> 19605.459 | D12: =SUM(H12+L12+P12+T12+X12+AC12+AG12+AK12+AO12+AS12+AW12+BA12) -> 0 | E12: =SUM(I12+M12+Q12+U12+Z12+AD12+AH12+AH12+AL12+AP12+AT12+AX12+BB12) -> 67887.51 | F12: =100/E12*C12 -> 28.879331 | G12: 1306.375 | I12: 3343.75 | J12: =100/I12*G12 -> 39.069159 | K12: =SUM(SCA!W17) -> 40.050935 | M12: 2928.1 | N12: =100/M12*K12 -> 1.3678131 | O12: 0 | Q12: 4328.12 | R12: =100/Q12*O12 -> 0 | S12: 1816.2619 | U12: 5859.38 | V12: =100/U12*S12 -> 30.997511 | W12: =SUM(MAI!X15) -> 0 | Y12: 2421.88 | Z12: 2421.88 | AA12: =100/Z12*W12 -> 0 | AB12: 130.7 | AD12: 2812.5 | AE12: =100/AD12*AB12 -> 4.6471111 | AF12: =SUM(IOC!K15) -> 0 | AH12: 2884.39 | AI12: =100/AH12*AF13 -> 0 | AJ12: =SUM(HIE!L15) -> 14637.811 | AL12: 34531.25 | AM12: =100/AL12*AJ12 -> 42.390041 | AN12: 0 | AP12: 0 | AQ12: =100/AP12*AN12 -> #DIV/0! | AR12: 1115.02 | AT12: 893.75 | AU12: =100/AT12*AR12 -> 124.75748 | AV12: 559.24 | AX12: 1718.75 | AY12: =100/AX12*AV12 -> 32.5376 | AZ12: ='CKR '!C11 -> 0 | BB12: 3281.25 | BC12: =100/BB12*AZ12 -> 0
A13: Establishment of a Collaborative Virtual Environment | B13: T2.2 | C13: =SUM(G13+K13+O13+S13+W13+AB13+AF13+AJ13+AN13+AR13+AV13+AZ13) -> 5204.3416 | D13: =SUM(H13+L13+P13+T13+X13+AC13+AG13+AK13+AO13+AS13+AW13+BA13) -> 0 | E13: =SUM(I13+M13+Q13+U13+Z13+AD13+AH13+AH13+AL13+AP13+AT13+AX13+BB13) -> 3343.75 | F13: =100/E13*C13 -> 155.64386 | G13: 4040.4313 | I13: 3343.75 | J13: =100/I13*G13 -> 120.83533 | K13: =SUM(SCA!W18) -> 520.66216 | M13: 0 | N13: =100/M13*K13 -> #DIV/0! | O13: 0 | Q13: 0 | R13: =100/Q13*O13 -> #DIV/0! | S13: 0 | U13: 0 | V13: =100/U13*S13 -> #DIV/0! | W13: =SUM(MAI!X16) -> 0 | Y13: 0 | Z13: 0 | AA13: =100/Z13*W13 -> #DIV/0! | AB13: 0 | AD13: 0 | AE13: =100/AD13*AB13 -> #DIV/0! | AF13: =SUM(IOC!K16) -> 0 | AH13: 0 | AI13: =100/AH13*#REF! -> #DIV/0! | AJ13: =SUM(HIE!L16) -> 643.24817 | AL13: 0 | AM13: =100/AL13*AJ13 -> #DIV/0! | AN13: 0 | AP13: 0 | AQ13: =100/AP13*AN13 -> #DIV/0! | AR13: 0 | AT13: 0 | AU13: =100/AT13*AR13 -> #DIV/0! | AV13: 0 | AX13: 0 | AY13: =100/AX13*AV13 -> #DIV/0! | AZ13: ='CKR '!C12 -> 0 | BB13: 0 | BC13: =100/BB13*AZ13 -> #DIV/0!
A14: Establishment of a Survey tool | B14: T2.3 | C14: =SUM(G14+K14+O14+S14+W14+AB14+AF14+AJ14+AN14+AR14+AV14+AZ14) -> 10794.029 | D14: =SUM(H14+L14+P14+T14+X14+AC14+AG14+AK14+AO14+AS14+AW14+BA14) -> 0 | E14: =SUM(I14+M14+Q14+U14+Z14+AD14+AH14+AH14+AL14+AP14+AT14+AX14+BB14) -> 12525 | F14: =100/E14*C14 -> 86.179876 | G14: 0 | I14: 0 | J14: =100/I14*G14 -> #DIV/0! | K14: =SUM(SCA!W19) -> 1321.6809 | M14: 0 | N14: =100/M14*K14 -> #DIV/0! | O14: 139.43 | Q14: 3462.5 | R14: =100/Q14*O14 -> 4.0268592 | S14: 1895.6686 | U14: 4687.5 | V14: =100/U14*S14 -> 40.440929 | W14: =SUM(MAI!X17) -> 0 | Y14: 0 | Z14: 0 | AA14: =100/Z14*W14 -> #DIV/0! | AB14: 196.05 | AD14: 0 | AE14: =100/AD14*AB14 -> #DIV/0! | AF14: =SUM(IOC!K17) -> 0 | AH14: 0 | AI14: =100/AH14*AF14 -> #DIV/0! | AJ14: =SUM(HIE!L17) -> 0 | AL14: 0 | AM14: =100/AL14*AJ14 -> #DIV/0! | AN14: 0 | AP14: 0 | AQ14: =100/AP14*AN14 -> #DIV/0! | AR14: 661.59 | AT14: 0 | AU14: =100/AT14*AR14 -> #DIV/0! | AV14: 6 | AX14: 0 | AY14: =100/AX14*AV14 -> #DIV/0! | AZ14: ='CKR '!C13 -> 6573.61 | BB14: 4375 | BC14: =100/BB14*AZ14 -> 150.25394
A15: Establishment of the GreenOffshoreTech Cluster Collaboration Platform | B15: T2.4 | C15: =SUM(G15+K15+O15+S15+W15+AB15+AF15+AJ15+AN15+AR15+AV15+AZ15) -> 32291.647 | D15: =SUM(H15+L15+P15+T15+X15+AC15+AG15+AK15+AO15+AS15+AW15+BA15) -> 0 | E15: =SUM(I15+M15+Q15+U15+Z15+AD15+AH15+AH15+AL15+AP15+AT15+AX15+BB15) -> 69737.55 | F15: =100/E15*C15 -> 46.304533 | G15: 0 | I15: 0 | J15: =100/I15*G15 -> #DIV/0! | K15: =SUM(SCA!W20) -> 1241.579 | M15: 2928.12 | N15: =100/M15*K15 -> 42.401916 | O15: 0 | Q15: 865.62 | R15: =100/Q15*O15 -> 0 | S15: 249.14268 | U15: 1171.88 | V15: =100/U15*S15 -> 21.260085 | W15: =SUM(MAI!X18) -> 0 | Y15: 2421.88 | Z15: 2421.88 | AA15: =100/Z15*W15 -> 0 | AB15: 196.05 | AD15: 2812.5 | AE15: =100/AD15*AB15 -> 6.9706667 | AF15: =SUM(IOC!K18) -> 555.6875 | AH15: 2884.4 | AI15: =100/AH15*AF15 -> 19.265272 | AJ15: =SUM(HIE!L18) -> 0 | AL15: 2656.25 | AM15: =100/AL15*AJ15 -> 0 | AN15: 30049.188 | AP15: 47406.25 | AQ15: =100/AP15*AN15 -> 63.386552 | AR15: 0 | AT15: 893.75 | AU15: =100/AT15*AR15 -> 0 | AV15: 0 | AX15: 1718.75 | AY15: =100/AX15*AV15 -> 0 | AZ15: ='CKR '!C14 -> 0 | BB15: 1093.75 | BC15: =100/BB15*AZ15 -> 0
A16: Direct financial support to SMEs through a competitive Call for Proposals | B16: WP3 | C16: =SUM(G16+K16+O16+S16+W16+AB16+AF16+AJ16+AN16+AR16+AV16+AZ16) -> 84177.462 | D16: =SUM(H16+L16+P16+T16+X16+AC16+AG16+AK16+AO16+AS16+AW16+BA16) -> 91428.57 | E16: =SUM(I16+M16+Q16+U16+Z16+AD16+AH16+AH16+AL16+AP16+AT16+AX16+BB16) -> 3434125.1 | F16: =100/E16*C16 -> 2.4512054 | G16: 1306.375 | H16: =SUM(H17:H22) -> 0 | I16: =SUM(I17:I22) -> 3094375 | J16: =100/I16*G16 -> 0.042217734 | K16: =SUM(SCA!W21) -> 11374.466 | L16: =SUM(L17:L22) -> 8000 | M16: =SUM(M17:M22) -> 52706.11 | N16: =100/M16*K16 -> 21.580924 | O16: 2002.375 | P16: =SUM(P17:P22) -> 8000 | Q16: =SUM(Q17:Q22) -> 8656.25 | R16: =100/Q16*O16 -> 23.13213 | S16: 962.41046 | T16: =SUM(T17:T22) -> 8000 | U16: =SUM(U17:U22) -> 16406.25 | V16: =100/U16*S16 -> 5.8661209 | W16: =SUM(MAI!X19) -> 0 | X16: =SUM(X17:X22) -> 8000 | Y16: =SUM(Y17:Y22) -> 33906.25 | Z16: =SUM(Z17:Z22) -> 33906.25 | AA16: =100/Z16*W16 -> 0 | AB16: 1364.2125 | AC16: =SUM(AC17:AC22) -> 11428.57 | AD16: =SUM(AD17:AD22) -> 39375 | AE16: =100/AD16*AB16 -> 3.4646667 | AF16: =SUM(IOC!K19) -> 1307.5 | AG16: =SUM(AG17:AG22) -> 8000 | AH16: =SUM(AH17:AH22) -> 28843.88 | AI16: =100/AH16*AF16 -> 4.533024 | AJ16: =SUM(HIE!L19) -> 6539.2514 | AK16: =SUM(AK17:AK22) -> 8000 | AL16: =SUM(AL17:AL22) -> 26562.5 | AM16: =100/AL16*AJ16 -> 24.618358 | AN16: 34570.488 | AO16: =SUM(AO17:AO22) -> 8000 | AP16: =SUM(AP17:AP22) -> 48500 | AQ16: =100/AP16*AN16 -> 71.279356 | AR16: 2131.5 | AS16: =SUM(AS17:AS22) -> 8000 | AT16: =SUM(AT17:AT22) -> 12512.5 | AU16: =100/AT16*AR16 -> 17.034965 | AV16: 2898.055 | AW16: =SUM(AW17:AW22) -> 8000 | AX16: =SUM(AX17:AX22) -> 17187.5 | AY16: =100/AX16*AV16 -> 16.861411 | AZ16: ='CKR '!C15 -> 19720.829 | BA16: =SUM(BA17:BA22) -> 8000 | BB16: =SUM(BB17:BB22) -> 26250 | BC16: =100/BB16*AZ16 -> 75.126968
A17: Preparation of the Call for Proposals | B17: T3.1 | C17: =SUM(G17+K17+O17+S17+W17+AB17+AF17+AJ17+AN17+AR17+AV17+AZ17) -> 47109.12 | D17: =SUM(H17+L17+P17+T17+X17+AC17+AG17+AK17+AO17+AS17+AW17+BA17) -> 19000 | E17: =SUM(I17+M17+Q17+U17+Z17+AD17+AH17+AH17+AL17+AP17+AT17+AX17+BB17) -> 68475.03 | F17: =100/E17*C17 -> 68.797516 | G17: 559.875 | H17: 0 | I17: 6687.5 | J17: =100/I17*G17 -> 8.3719626 | K17: =SUM(SCA!W22) -> 10613.498 | L17: 1000 | M17: 5856.22 | N17: =100/M17*K17 -> 181.23462 | O17: 1601.9 | P17: 2000 | Q17: 1731.25 | R17: =100/Q17*O17 -> 92.52852 | S17: 962.41046 | T17: 1000 | U17: 2343.75 | V17: =100/U17*S17 -> 41.062846 | W17: =SUM(MAI!X20) -> 0 | X17: 1000 | Y17: 4843.75 | Z17: 4843.75 | AA17: =100/Z17*W17 -> 0 | AB17: 653.5 | AC17: 2000 | AD17: 5625 | AE17: =100/AD17*AB17 -> 11.617778 | AF17: =SUM(IOC!K20) -> 1046 | AG17: 2000 | AH17: 5768.78 | AI17: =100/AH17*AF17 -> 18.132083 | AJ17: =SUM(HIE!L20) -> 1628.0514 | AK17: 2000 | AL17: 5312.5 | AM17: =100/AL17*AJ17 -> 30.645674 | AN17: 6187.5 | AO17: 1000 | AP17: 6187.5 | AQ17: =100/AP17*AN17 -> 100 | AR17: 2131.5 | AS17: 2000 | AT17: 1787.5 | AU17: =100/AT17*AR17 -> 119.24476 | AV17: 2004.055 | AW17: 2000 | AX17: 3437.5 | AY17: =100/AX17*AV17 -> 58.299782 | AZ17: ='CKR '!C16 -> 19720.83 | BA17: 3000 | BB17: 13125 | BC17: =100/BB17*AZ17 -> 150.25394
A18: Publication of the Call for Proposals and Proposal reception. | B18: T3.2 | C18: =SUM(G18+K18+O18+S18+W18+AB18+AF18+AJ18+AN18+AR18+AV18+AZ18) -> 14557.76 | D18: =SUM(H18+L18+P18+T18+X18+AC18+AG18+AK18+AO18+AS18+AW18+BA18) -> 2000 | E18: =SUM(I18+M18+Q18+U18+Z18+AD18+AH18+AH18+AL18+AP18+AT18+AX18+BB18) -> 18562.5 | F18: =100/E18*C18 -> 78.425645 | G18: 466.5625 | H18: 0 | I18: 6687.5 | J18: =100/I18*G18 -> 6.9766355 | K18: =SUM(SCA!W23) -> 760.96777 | M18: 0 | N18: =100/M18*K18 -> #DIV/0! | O18: 0 | Q18: 0 | R18: =100/Q18*O18 -> #DIV/0! | S18: 0 | U18: 0 | V18: =100/U18*S18 -> #DIV/0! | W18: =SUM(MAI!X21) -> 0 | Y18: 0 | Z18: 0 | AA18: =100/Z18*W18 -> #DIV/0! | AB18: 673.13 | AD18: 0 | AE18: =100/AD18*AB18 -> #DIV/0! | AF18: =SUM(IOC!K21) -> 261.5 | AH18: 0 | AI18: =100/AH18*AF18 -> #DIV/0! | AJ18: =SUM(HIE!L21) -> 4911.2 | AL18: 0 | AM18: =100/AL18*AJ18 -> #DIV/0! | AN18: 7484.4 | AO18: 2000 | AP18: 11875 | AQ18: =100/AP18*AN18 -> 63.026526 | AR18: 0 | AT18: 0 | AU18: =100/AT18*AR18 -> #DIV/0! | AV18: 0 | AX18: 0 | AY18: =100/AX18*AV18 -> #DIV/0! | AZ18: ='CKR '!C17 -> 0 | BB18: 0 | BC18: =100/BB18*AZ18 -> #DIV/0!
A19: Evaluation and Selection of SMEs Proposals | B19: T3.3 | C19: =SUM(G19+K19+O19+S19+W19+AB19+AF19+AJ19+AN19+AR19+AV19+AZ19) -> 15885.025 | D19: =SUM(H19+L19+P19+T19+X19+AC19+AG19+AK19+AO19+AS19+AW19+BA19) -> 33000 | E19: =SUM(I19+M19+Q19+U19+Z19+AD19+AH19+AH19+AL19+AP19+AT19+AX19+BB19) -> 121637.57 | F19: =100/E19*C19 -> 13.059308 | G19: 279.9375 | H19: 0 | I19: 13750 | J19: =100/I19*G19 -> 2.0359091 | K19: =SUM(SCA!W24) -> 0 | L19: 2000 | M19: 11712.47 | N19: =100/M19*K19 -> 0 | O19: 0 | P19: 3000 | Q19: 3462.5 | R19: =100/Q19*O19 -> 0 | S19: 0 | T19: 3000 | U19: 4687.5 | V19: =100/U19*S19 -> 0 | W19: =SUM(MAI!X22) -> 0 | X19: 3000 | Y19: 9687.5 | Z19: 9687.5 | AA19: =100/Z19*W19 -> 0 | AB19: 0 | AC19: 5000 | AD19: 11250 | AE19: =100/AD19*AB19 -> 0 | AF19: =SUM(IOC!K22) -> 0 | AG19: 3000 | AH19: 11537.55 | AI19: =100/AH19*AF19 -> 0 | AJ19: =SUM(HIE!L22) -> 0 | AK19: 3000 | AL19: 10625 | AM19: =100/AL19*AJ19 -> 0 | AN19: 14711.088 | AO19: 3000 | AP19: 18562.5 | AQ19: =100/AP19*AN19 -> 79.25165 | AR19: 0 | AS19: 3000 | AT19: 3575 | AU19: =100/AT19*AR19 -> 0 | AV19: 894 | AW19: 3000 | AX19: 6875 | AY19: =100/AX19*AV19 -> 13.003636 | AZ19: ='CKR '!C18 -> 0 | BA19: 2000 | BB19: 4375 | BC19: =100/BB19*AZ19 -> 0
A20: Contracting with winner SMEs Projects | B20: T3.4 | C20: =SUM(G20+K20+O20+S20+W20+AB20+AF20+AJ20+AN20+AR20+AV20+AZ20) -> 0 | D20: =SUM(H20+L20+P20+T20+X20+AC20+AG20+AK20+AO20+AS20+AW20+BA20) -> 0 | E20: =SUM(I20+M20+Q20+U20+Z20+AD20+AH20+AH20+AL20+AP20+AT20+AX20+BB20) -> 26750 | F20: =100/E20*C20 -> 0 | G20: 0 | H20: 0 | I20: 26750 | J20: =100/I20*G20 -> 0 | K20: =SUM(SCA!W25) -> 0 | M20: 0 | N20: =100/M20*K20 -> #DIV/0! | O20: 0 | Q20: 0 | R20: =100/Q20*O20 -> #DIV/0! | S20: 0 | U20: 0 | V20: =100/U20*S20 -> #DIV/0! | W20: =SUM(MAI!X23) -> 0 | Y20: 0 | Z20: 0 | AA20: =100/Z20*W20 -> #DIV/0! | AB20: 0 | AD20: 0 | AE20: =100/AD20*AB20 -> #DIV/0! | AF20: =SUM(IOC!K23) -> 0 | AH20: 0 | AI20: =100/AH20*AF20 -> #DIV/0! | AJ20: =SUM(HIE!L23) -> 0 | AL20: 0 | AM20: =100/AL20*AJ20 -> #DIV/0! | AN20: 0 | AP20: 0 | AQ20: =100/AP20*AN20 -> #DIV/0! | AR20: 0 | AT20: 0 | AU20: =100/AT20*AR20 -> #DIV/0! | AV20: 0 | AX20: 0 | AY20: =100/AX20*AV20 -> #DIV/0! | AZ20: ='CKR '!C19 -> 0 | BB20: 0 | BC20: =100/BB20*AZ20 -> #DIV/0!
A21: Payments and financial monitoring of winner SMEs Projects | B21: T3.5 | C21: =SUM(G21+K21+O21+S21+W21+AB21+AF21+AJ21+AN21+AR21+AV21+AZ21) -> 0 | D21: =SUM(H21+L21+P21+T21+X21+AC21+AG21+AK21+AO21+AS21+AW21+BA21) -> 0 | E21: =SUM(I21+M21+Q21+U21+Z21+AD21+AH21+AH21+AL21+AP21+AT21+AX21+BB21) -> 3026750 | F21: =100/E21*C21 -> 0 | G21: 0 | H21: 0 | I21: 3026750 | J21: =100/I21*G21 -> 0 | K21: =SUM(SCA!W26) -> 0 | M21: 0 | N21: =100/M21*K21 -> #DIV/0! | O21: 0 | Q21: 0 | R21: =100/Q21*O21 -> #DIV/0! | S21: 0 | U21: 0 | V21: =100/U21*S21 -> #DIV/0! | W21: =SUM(MAI!X24) -> 0 | Y21: 0 | Z21: 0 | AA21: =100/Z21*W21 -> #DIV/0! | AB21: 0 | AC21: 0 | AD21: 0 | AE21: =100/AD21*AB21 -> #DIV/0! | AF21: =SUM(IOC!K24) -> 0 | AH21: 0 | AI21: =100/AH21*AF21 -> #DIV/0! | AJ21: =SUM(HIE!L24) -> 0 | AL21: 0 | AM21: =100/AL21*AJ21 -> #DIV/0! | AN21: 0 | AP21: 0 | AQ21: =100/AP21*AN21 -> #DIV/0! | AR21: 0 | AT21: 0 | AU21: =100/AT21*AR21 -> #DIV/0! | AV21: 0 | AX21: 0 | AY21: =100/AX21*AV21 -> #DIV/0! | AZ21: ='CKR '!C20 -> 0 | BB21: 0 | BC21: =100/BB21*AZ21 -> #DIV/0!
A22: Technical monitoring of winner SMEs Projects | B22: T3.6 | C22: =SUM(G22+K22+O22+S22+W22+AB22+AF22+AJ22+AN22+AR22+AV22+AZ22) -> 6187.5 | D22: =SUM(H22+L22+P22+T22+X22+AC22+AG22+AK22+AO22+AS22+AW22+BA22) -> 37428.57 | E22: =SUM(I22+M22+Q22+U22+Z22+AD22+AH22+AH22+AL22+AP22+AT22+AX22+BB22) -> 171950.02 | F22: =100/E22*C22 -> 3.5984294 | G22: 0 | H22: 0 | I22: 13750 | J22: =100/I22*G22 -> 0 | K22: =SUM(SCA!W27) -> 0 | L22: 5000 | M22: 35137.42 | N22: =100/M22*K22 -> 0 | O22: 0 | P22: 3000 | Q22: 3462.5 | R22: =100/Q22*O22 -> 0 | S22: 0 | T22: 4000 | U22: 9375 | V22: =100/U22*S22 -> 0 | W22: =SUM(MAI!X25) -> 0 | X22: 4000 | Y22: 19375 | Z22: 19375 | AA22: =100/Z22*W22 -> 0 | AB22: 0 | AC22: 4428.57 | AD22: 22500 | AE22: =100/AD22*AB22 -> 0 | AF22: =SUM(IOC!K25) -> 0 | AG22: 3000 | AH22: 11537.55 | AI22: =100/AH22*AF22 -> 0 | AJ22: =SUM(HIE!L25) -> 0 | AK22: 3000 | AL22: 10625 | AM22: =100/AL22*AJ22 -> 0 | AN22: 6187.5 | AO22: 2000 | AP22: 11875 | AQ22: =100/AP22*AN22 -> 52.105263 | AR22: 0 | AS22: 3000 | AT22: 7150 | AU22: =100/AT22*AR22 -> 0 | AV22: 0 | AW22: 3000 | AX22: 6875 | AY22: =100/AX22*AV22 -> 0 | AZ22: ='CKR '!C21 -> 0 | BA22: 3000 | BB22: 8750 | BC22: =100/BB22*AZ22 -> 0
A23: Business Support Services to winner SMEs (preparation) | B23: WP4 | C23: =SUM(G23+K23+O23+S23+W23+AB23+AF23+AJ23+AN23+AR23+AV23+AZ23) -> 21789.228 | D23: =SUM(H23+L23+P23+T23+X23+AC23+AG23+AK23+AO23+AS23+AW23+BA23) -> 151514.29 | E23: =SUM(I23+M23+Q23+U23+Z23+AD23+AH23+AH23+AL23+AP23+AT23+AX23+BB23) -> 701740.32 | F23: =100/E23*C23 -> 3.1050273 | G23: 6681.175 | H23: =SUM(H24:H32) -> 0 | I23: =SUM(I24:I32) -> 73562.5 | J23: =100/I23*G23 -> 9.082311 | K23: =SUM(SCA!W28) -> 2723.4636 | L23: =SUM(L24:L32) -> 8000 | M23: =SUM(M24:M32) -> 149334.17 | N23: =100/M23*K23 -> 1.8237377 | O23: 58.1 | P23: =SUM(P24:P32) -> 26000 | Q23: =SUM(Q24:Q32) -> 29431.25 | R23: =100/Q23*O23 -> 0.19740922 | S23: 595.19468 | T23: =SUM(T24:T32) -> 8600 | U23: =SUM(U24:U32) -> 32812.5 | V23: =100/U23*S23 -> 1.8139266 | W23: =SUM(MAI!X26) -> 4120.2875 | X23: =SUM(X24:X32) -> 8600 | Y23: =SUM(Y24:Y32) -> 77500 | Z23: =SUM(Z24:Z32) -> 77500 | AA23: =100/Z23*W23 -> 5.3165 | AB23: 653.5 | AC23: =SUM(AC24:AC32) -> 33714.29 | AD23: =SUM(AD24:AD32) -> 101250 | AE23: =100/AD23*AB23 -> 0.6454321 | AF23: =SUM(IOC!K26) -> 0 | AG23: =SUM(AG24:AG32) -> 8600 | AH23: =SUM(AH24:AH32) -> 34612.7 | AI23: =100/AH23*AF23 -> 0 | AJ23: =SUM(HIE!L26) -> 0 | AK23: =SUM(AK24:AK32) -> 8600 | AL23: =SUM(AL24:AL32) -> 74374.5 | AM23: =100/AL23*AJ23 -> 0 | AN23: 5126.7875 | AO23: =SUM(AO24:AO32) -> 8600 | AP23: =SUM(AP24:AP32) -> 30937.5 | AQ23: =100/AP23*AN23 -> 16.571434 | AR23: 661.59 | AS23: =SUM(AS24:AS32) -> 8600 | AT23: =SUM(AT24:AT32) -> 8937.5 | AU23: =100/AT23*AR23 -> 7.4024056 | AV23: 1169.13 | AW23: =SUM(AW24:AW32) -> 23600 | AX23: =SUM(AX24:AX32) -> 41250 | AY23: =100/AX23*AV23 -> 2.8342545 | AZ23: ='CKR '!C22 -> 0 | BA23: =SUM(BA24:BA32) -> 8600 | BB23: =SUM(BB24:BB32) -> 13125 | BC23: =100/BB23*AZ23 -> 0
A24: Programme of Business Support Services to winner SMEs | B24: T4.1 | C24: =SUM(G24+K24+O24+S24+W24+AB24+AF24+AJ24+AN24+AR24+AV24+AZ24) -> 8330.8886 | D24: =SUM(H24+L24+P24+T24+X24+AC24+AG24+AK24+AO24+AS24+AW24+BA24) -> 1000 | E24: =SUM(I24+M24+Q24+U24+Z24+AD24+AH24+AH24+AL24+AP24+AT24+AX24+BB24) -> 24218.75 | F24: =100/E24*C24 -> 34.398508 | G24: 933.125 | H24: 0 | I24: 0 | J24: =100/I24*G24 -> #DIV/0! | K24: =SUM(SCA!W29) -> 2403.0561 | M24: 0 | N24: =100/M24*K24 -> #DIV/0! | O24: 46.48 | Q24: 0 | R24: =100/Q24*O24 -> #DIV/0! | S24: 0 | U24: 0 | V24: =100/U24*S24 -> #DIV/0! | W24: =SUM(MAI!X27) -> 4120.2875 | X24: 1000 | Y24: 24218.75 | Z24: 24218.75 | AA24: =100/Z24*W24 -> 17.0128 | AB24: 65.35 | AD24: 0 | AE24: =100/AD24*AB24 -> #DIV/0! | AF24: =SUM(IOC!K27) -> 0 | AH24: 0 | AI24: =100/AH24*AF24 -> #DIV/0! | AJ24: =SUM(HIE!L27) -> 0 | AL24: 0 | AM24: =100/AL24*AJ24 -> #DIV/0! | AN24: 0 | AP24: 0 | AQ24: =100/AP24*AN24 -> #DIV/0! | AR24: 661.59 | AT24: 0 | AU24: =100/AT24*AR24 -> #DIV/0! | AV24: 101 | AX24: 0 | AY24: =100/AX24*AV24 -> #DIV/0! | AZ24: ='CKR '!C23 -> 0 | BB24: 0 | BC24: =100/BB24*AZ24 -> #DIV/0!
A25: Business Support Service #1 Business & Tech Academy | B25: T4.2 | C25: =SUM(G25+K25+O25+S25+W25+AB25+AF25+AJ25+AN25+AR25+AV25+AZ25) -> 5322.8375 | D25: =SUM(H25+L25+P25+T25+X25+AC25+AG25+AK25+AO25+AS25+AW25+BA25) -> 44600 | E25: =SUM(I25+M25+Q25+U25+Z25+AD25+AH25+AH25+AL25+AP25+AT25+AX25+BB25) -> 170550.08 | F25: =100/E25*C25 -> 3.1209821 | G25: 0 | H25: 0 | I25: 13375 | J25: =100/I25*G25 -> 0 | K25: =SUM(SCA!W30) -> 0 | L25: 1000 | M25: 11712.46 | N25: =100/M25*K25 -> 0 | O25: 0 | P25: 5000 | Q25: 3462.5 | R25: =100/Q25*O25 -> 0 | S25: 0 | T25: 2000 | U25: 4687.5 | V25: =100/U25*S25 -> 0 | W25: =SUM(MAI!X28) -> 0 | X25: 5000 | Y25: 29062.5 | Z25: 29062.5 | AA25: =100/Z25*W25 -> 0 | AB25: 196.05 | AC25: 10000 | AD25: 39375 | AE25: =100/AD25*AB25 -> 0.49790476 | AF25: =SUM(IOC!K28) -> 0 | AG25: 3000 | AH25: 11537.56 | AI25: =100/AH25*AF25 -> 0 | AJ25: =SUM(HIE!L28) -> 0 | AK25: 1000 | AL25: 10625 | AM25: =100/AL25*AJ25 -> 0 | AN25: 5126.7875 | AO25: 4600 | AP25: 18562.5 | AQ25: =100/AP25*AN25 -> 27.619057 | AR25: 0 | AS25: 6000 | AT25: 5362.5 | AU25: =100/AT25*AR25 -> 0 | AV25: 0 | AW25: 5000 | AX25: 6875 | AY25: =100/AX25*AV25 -> 0 | AZ25: ='CKR '!C24 -> 0 | BA25: 2000 | BB25: 4375 | BC25: =100/BB25*AZ25 -> 0
A26: Business Support Service #2 Brokerage & B2B matchmaking events | B26: T4.3 | C26: =SUM(G26+K26+O26+S26+W26+AB26+AF26+AJ26+AN26+AR26+AV26+AZ26) -> 261.4 | D26: =SUM(H26+L26+P26+T26+X26+AC26+AG26+AK26+AO26+AS26+AW26+BA26) -> 34100 | E26: =SUM(I26+M26+Q26+U26+Z26+AD26+AH26+AH26+AL26+AP26+AT26+AX26+BB26) -> 113875.05 | F26: =100/E26*C26 -> 0.22954984 | G26: 0 | H26: 0 | I26: 6687.5 | J26: =100/I26*G26 -> 0 | K26: =SUM(SCA!W31) -> 0 | L26: 1000 | M26: 5856.24 | N26: =100/M26*K26 -> 0 | O26: 0 | P26: 10000 | Q26: 13850 | R26: =100/Q26*O26 -> 0 | S26: 0 | T26: 2000 | U26: 2343.75 | V26: =100/U26*S26 -> 0 | W26: =SUM(MAI!X29) -> 0 | X26: 500 | Y26: 9687.5 | Z26: 9687.5 | AA26: =100/Z26*W26 -> 0 | AB26: 261.4 | AC26: 10000 | AD26: 45000 | AE26: =100/AD26*AB26 -> 0.58088889 | AF26: =SUM(IOC!K29) -> 0 | AG26: 1500 | AH26: 5768.78 | AI26: =100/AH26*AF26 -> 0 | AJ26: =SUM(HIE!L29) -> 0 | AK26: 1000 | AL26: 5312.5 | AM26: =100/AL26*AJ26 -> 0 | AN26: 0 | AO26: 2000 | AP26: 6187.5 | AQ26: =100/AP26*AN26 -> 0 | AR26: 0 | AS26: 1600 | AT26: 1787.5 | AU26: =100/AT26*AR26 -> 0 | AV26: 0 | AW26: 2500 | AX26: 3437.5 | AY26: =100/AX26*AV26 -> 0 | AZ26: ='CKR '!C25 -> 0 | BA26: 2000 | BB26: 2187.5 | BC26: =100/BB26*AZ26 -> 0
A27: Business Support Service #3 Access to Finance | B27: T4.4 | C27: =SUM(G27+K27+O27+S27+W27+AB27+AF27+AJ27+AN27+AR27+AV27+AZ27) -> 0 | D27: =SUM(H27+L27+P27+T27+X27+AC27+AG27+AK27+AO27+AS27+AW27+BA27) -> 10700 | E27: =SUM(I27+M27+Q27+U27+Z27+AD27+AH27+AH27+AL27+AP27+AT27+AX27+BB27) -> 70268.81 | F27: =100/E27*C27 -> 0 | G27: 0 | H27: 0 | I27: 6687.5 | J27: =100/I27*G27 -> 0 | K27: =SUM(SCA!W32) -> 0 | M27: 0 | N27: =100/M27*K27 -> #DIV/0! | O27: 0 | Q27: 1731.25 | R27: =100/Q27*O27 -> 0 | S27: 0 | U27: 2343.75 | V27: =100/U27*S27 -> 0 | W27: =SUM(MAI!X30) -> 0 | X27: 100 | Y27: 4843.75 | Z27: 4843.75 | AA27: =100/Z27*W27 -> 0 | AB27: 0 | AC27: 4000 | AD27: 5625 | AE27: =100/AD27*AB27 -> 0 | AF27: =SUM(IOC!K30) -> 0 | AG27: 1500 | AH27: 5768.78 | AI27: =100/AH27*AF27 -> 0 | AJ27: =SUM(HIE!L30) -> 0 | AK27: 2600 | AL27: 31875 | AM27: =100/AL27*AJ27 -> 0 | AN27: 0 | AP27: 0 | AQ27: =100/AP27*AN27 -> #DIV/0! | AR27: 0 | AT27: 0 | AU27: =100/AT27*AR27 -> #DIV/0! | AV27: 0 | AW27: 2500 | AX27: 3437.5 | AY27: =100/AX27*AV27 -> 0 | AZ27: ='CKR '!C26 -> 0 | BB27: 2187.5 | BC27: =100/BB27*AZ27 -> 0
A28: Business Support Service #4 One-to-One Mentoring and Coaching | B28: T4.5 | C28: =SUM(G28+K28+O28+S28+W28+AB28+AF28+AJ28+AN28+AR28+AV28+AZ28) -> 359.90748 | D28: =SUM(H28+L28+P28+T28+X28+AC28+AG28+AK28+AO28+AS28+AW28+BA28) -> 6000 | E28: =SUM(I28+M28+Q28+U28+Z28+AD28+AH28+AH28+AL28+AP28+AT28+AX28+BB28) -> 114196.76 | F28: =100/E28*C28 -> 0.31516435 | G28: 0 | H28: 0 | I28: 0 | J28: =100/I28*G28 -> #DIV/0! | K28: =SUM(SCA!W33) -> 320.40748 | L28: 6000 | M28: 114196.76 | N28: =100/M28*K28 -> 0.28057493 | O28: 0 | P28: 0 | Q28: 0 | R28: =100/Q28*O28 -> #DIV/0! | S28: 0 | T28: 0 | U28: 0 | V28: =100/U28*S28 -> #DIV/0! | W28: =SUM(MAI!X31) -> 0 | X28: 0 | Y28: 0 | Z28: 0 | AA28: =100/Z28*W28 -> #DIV/0! | AB28: 0 | AC28: 0 | AD28: 0 | AE28: =100/AD28*AB28 -> #DIV/0! | AF28: =SUM(IOC!K31) -> 0 | AG28: 0 | AH28: 0 | AI28: =100/AH28*AF28 -> #DIV/0! | AJ28: =SUM(HIE!L31) -> 0 | AK28: 0 | AL28: 0 | AM28: =100/AL28*AJ28 -> #DIV/0! | AN28: 0 | AO28: 0 | AP28: 0 | AQ28: =100/AP28*AN28 -> #DIV/0! | AR28: 0 | AS28: 0 | AT28: 0 | AU28: =100/AT28*AR28 -> #DIV/0! | AV28: 39.5 | AW28: 0 | AX28: 0 | AY28: =100/AX28*AV28 -> #DIV/0! | AZ28: ='CKR '!C27 -> 0 | BA28: 0 | BB28: 0 | BC28: =100/BB28*AZ28 -> #DIV/0!
A29: Business Support Service #5 Branding | B29: T4.6 | C29: =SUM(G29+K29+O29+S29+W29+AB29+AF29+AJ29+AN29+AR29+AV29+AZ29) -> 230.555 | D29: =SUM(H29+L29+P29+T29+X29+AC29+AG29+AK29+AO29+AS29+AW29+BA29) -> 4000 | E29: =SUM(I29+M29+Q29+U29+Z29+AD29+AH29+AH29+AL29+AP29+AT29+AX29+BB29) -> 6925 | F29: =100/E29*C29 -> 3.3293141 | G29: 0 | H29: 0 | I29: 0 | J29: =100/I29*G29 -> #DIV/0! | K29: =SUM(SCA!W34) -> 0 | M29: 0 | N29: =100/M29*K29 -> #DIV/0! | O29: 0 | P29: 4000 | Q29: 6925 | R29: =100/Q29*O29 -> 0 | S29: 0 | U29: 0 | V29: =100/U29*S29 -> #DIV/0! | W29: =SUM(MAI!X32) -> 0 | Y29: 0 | Z29: 0 | AA29: =100/Z29*W29 -> #DIV/0! | AB29: 0 | AD29: 0 | AE29: =100/AD29*AB29 -> #DIV/0! | AF29: =SUM(IOC!K32) -> 0 | AH29: 0 | AI29: =100/AH29*AF29 -> #DIV/0! | AJ29: =SUM(HIE!L32) -> 0 | AL29: 0 | AM29: =100/AL29*AJ29 -> #DIV/0! | AN29: 0 | AP29: 0 | AQ29: =100/AP29*AN29 -> #DIV/0! | AR29: 0 | AT29: 0 | AU29: =100/AT29*AR29 -> #DIV/0! | AV29: 230.555 | AX29: 0 | AY29: =100/AX29*AV29 -> #DIV/0! | AZ29: ='CKR '!C28 -> 0 | BB29: 0 | BC29: =100/BB29*AZ29 -> #DIV/0!
A30: Business Support Service #6 Internationalisation | B30: T4.7 | C30: =SUM(G30+K30+O30+S30+W30+AB30+AF30+AJ30+AN30+AR30+AV30+AZ30) -> 798.075 | D30: =SUM(H30+L30+P30+T30+X30+AC30+AG30+AK30+AO30+AS30+AW30+BA30) -> 19800 | E30: =SUM(I30+M30+Q30+U30+Z30+AD30+AH30+AH30+AL30+AP30+AT30+AX30+BB30) -> 54018.33 | F30: =100/E30*C30 -> 1.4774152 | G30: 0 | H30: 0 | I30: 6687.5 | J30: =100/I30*G30 -> 0 | K30: =SUM(SCA!W35) -> 0 | M30: 0 | N30: =100/M30*K30 -> #DIV/0! | O30: 0 | P30: 3000 | Q30: 1731.25 | R30: =100/Q30*O30 -> 0 | S30: 0 | T30: 1000 | U30: 2343.75 | V30: =100/U30*S30 -> 0 | W30: =SUM(MAI!X33) -> 0 | X30: 1000 | Y30: 4843.75 | Z30: 4843.75 | AA30: =100/Z30*W30 -> 0 | AB30: 0 | AC30: 4000 | AD30: 5625 | AE30: =100/AD30*AB30 -> 0 | AF30: =SUM(IOC!K33) -> 0 | AG30: 1800 | AH30: 5768.79 | AI30: =100/AH30*AF30 -> 0 | AJ30: =SUM(HIE!L33) -> 0 | AK30: 1000 | AL30: 5312 | AM30: =100/AL30*AJ30 -> 0 | AN30: 0 | AP30: 0 | AQ30: =100/AP30*AN30 -> #DIV/0! | AR30: 0 | AT30: 0 | AU30: =100/AT30*AR30 -> #DIV/0! | AV30: 798.075 | AW30: 6000 | AX30: 13750 | AY30: =100/AX30*AV30 -> 5.8041818 | AZ30: ='CKR '!C29 -> 0 | BA30: 2000 | BB30: 2187.5 | BC30: =100/BB30*AZ30 -> 0
A31: Business Support Service #7 Investor pitching | B31: T4.8 | C31: =SUM(G31+K31+O31+S31+W31+AB31+AF31+AJ31+AN31+AR31+AV31+AZ31) -> 595.19468 | D31: =SUM(H31+L31+P31+T31+X31+AC31+AG31+AK31+AO31+AS31+AW31+BA31) -> 5000 | E31: =SUM(I31+M31+Q31+U31+Z31+AD31+AH31+AH31+AL31+AP31+AT31+AX31+BB31) -> 53087.47 | F31: =100/E31*C31 -> 1.1211585 | G31: 0 | H31: 0 | I31: 6687.5 | J31: =100/I31*G31 -> 0 | K31: =SUM(SCA!W36) -> 0 | M31: 11712.47 | N31: =100/M31*K31 -> 0 | O31: 0 | Q31: 0 | R31: =100/Q31*O31 -> #DIV/0! | S31: 595.19468 | T31: 3000 | U31: 18750 | V31: =100/U31*S31 -> 3.1743716 | W31: =SUM(MAI!X34) -> 0 | Y31: 0 | Z31: 0 | AA31: =100/Z31*W31 -> #DIV/0! | AB31: 0 | AD31: 0 | AE31: =100/AD31*AB31 -> #DIV/0! | AF31: =SUM(IOC!K34) -> 0 | AH31: 0 | AI31: =100/AH31*AF31 -> #DIV/0! | AJ31: =SUM(HIE!L34) -> 0 | AK31: 2000 | AL31: 15937.5 | AM31: =100/AL31*AJ31 -> 0 | AN31: 0 | AP31: 0 | AQ31: =100/AP31*AN31 -> #DIV/0! | AR31: 0 | AT31: 0 | AU31: =100/AT31*AR31 -> #DIV/0! | AV31: 0 | AX31: 0 | AY31: =100/AX31*AV31 -> #DIV/0! | AZ31: ='CKR '!C30 -> 0 | BB31: 0 | BC31: =100/BB31*AZ31 -> #DIV/0!
A32: Business Support Service #8 Investor rounds | B32: T4.9 | C32: =SUM(G32+K32+O32+S32+W32+AB32+AF32+AJ32+AN32+AR32+AV32+AZ32) -> 5748.05 | D32: =SUM(H32+L32+P32+T32+X32+AC32+AG32+AK32+AO32+AS32+AW32+BA32) -> 26314.29 | E32: =SUM(I32+M32+Q32+U32+Z32+AD32+AH32+AH32+AL32+AP32+AT32+AX32+BB32) -> 94600.07 | F32: =100/E32*C32 -> 6.0761583 | G32: 5748.05 | H32: 0 | I32: 33437.5 | J32: =100/I32*G32 -> 17.19043 | K32: =SUM(SCA!W37) -> 0 | M32: 5856.24 | N32: =100/M32*K32 -> 0 | O32: 0 | P32: 4000 | Q32: 1731.25 | R32: =100/Q32*O32 -> 0 | S32: 0 | T32: 600 | U32: 2343.75 | V32: =100/U32*S32 -> 0 | W32: =SUM(MAI!X35) -> 0 | X32: 1000 | Y32: 4843.75 | Z32: 4843.75 | AA32: =100/Z32*W32 -> 0 | AB32: 0 | AC32: 5714.29 | AD32: 5625 | AE32: =100/AD32*AB32 -> 0 | AF32: =SUM(IOC!K35) -> 0 | AG32: 800 | AH32: 5768.79 | AI32: =100/AH32*AF32 -> 0 | AJ32: =SUM(HIE!L35) -> 0 | AK32: 1000 | AL32: 5312.5 | AM32: =100/AL32*AJ32 -> 0 | AN32: 0 | AO32: 2000 | AP32: 6187.5 | AQ32: =100/AP32*AN32 -> 0 | AR32: 0 | AS32: 1000 | AT32: 1787.5 | AU32: =100/AT32*AR32 -> 0 | AV32: 0 | AW32: 7600 | AX32: 13750 | AY32: =100/AX32*AV32 -> 0 | AZ32: ='CKR '!C31 -> 0 | BA32: 2600 | BB32: 2187.5 | BC32: =100/BB32*AZ32 -> 0
A33: Large-scale Demonstrator (LSD) setup, validation, and impact assessment | B33: WP5 | C33: =SUM(G33+K33+O33+S33+W33+AB33+AF33+AJ33+AN33+AR33+AV33+AZ33) -> 42546.324 | D33: =SUM(H33+L33+P33+T33+X33+AC33+AG33+AK33+AO33+AS33+AW33+BA33) -> 0 | E33: =SUM(I33+M33+Q33+U33+Z33+AD33+AH33+AH33+AL33+AP33+AT33+AX33+BB33) -> 148095.23 | F33: =100/E33*C33 -> 28.729031 | G33: 4189.7313 | H33: =SUM(H34:H36) -> 0 | I33: =SUM(I34:I36) -> 10331.25 | J33: =100/I33*G33 -> 40.553962 | K33: =SUM(SCA!W38) -> 33402.48 | L33: =SUM(L34:L36) -> 0 | M33: =SUM(M34:M36) -> 70274.73 | N33: =100/M33*K33 -> 47.531282 | O33: 87.15 | P33: =SUM(P34:P36) -> 0 | Q33: =SUM(Q34:Q36) -> 2596.86 | R33: =100/Q33*O33 -> 3.3559761 | S33: 700.09011 | T33: =SUM(T34:T36) -> 0 | U33: =SUM(U34:U36) -> 3515.64 | V33: =100/U33*S33 -> 19.913589 | W33: =SUM(MAI!X36) -> 0 | X33: =SUM(X34:X36) -> 0 | Y33: =SUM(Y34:Y36) -> 7265.64 | Z33: =SUM(Z34:Z36) -> 7265.64 | AA33: =100/Z33*W33 -> 0 | AB33: 0 | AC33: =SUM(AC34:AC36) -> 0 | AD33: =SUM(AD34:AD36) -> 8436 | AE33: =100/AD33*AB33 -> 0 | AF33: =SUM(IOC!K36) -> 359.5625 | AG33: =SUM(AG34:AG36) -> 0 | AH33: =SUM(AH34:AH36) -> 8653.18 | AI33: =100/AH33*AF33 -> 4.1552643 | AJ33: =SUM(HIE!L36) -> 0 | AK33: =SUM(AK34:AK36) -> 0 | AL33: =SUM(AL34:AL36) -> 7968.75 | AM33: =100/AL33*AJ33 -> 0 | AN33: 0 | AO33: =SUM(AO34:AO36) -> 0 | AP33: =SUM(AP34:AP36) -> 9281.25 | AQ33: =100/AP33*AN33 -> 0 | AR33: 1742.07 | AS33: =SUM(AS34:AS36) -> 0 | AT33: =SUM(AT34:AT36) -> 2681.25 | AU33: =100/AT33*AR33 -> 64.972308 | AV33: 1627 | AW33: =SUM(AW34:AW36) -> 0 | AX33: =SUM(AX34:AX36) -> 5156.25 | AY33: =100/AX33*AV33 -> 31.553939 | AZ33: ='CKR '!C32 -> 438.24065 | BA33: =SUM(BA34:BA36) -> 0 | BB33: =SUM(BB34:BB36) -> 3281.25 | BC33: =100/BB33*AZ33 -> 13.355905
A34: Set-up of the GreenOffshoreTech LSD in GreenOffshoreTech regions | B34: T5.1 | C34: =SUM(G34+K34+O34+S34+W34+AB34+AF34+AJ34+AN34+AR34+AV34+AZ34) -> 40961.187 | D34: =SUM(H34+L34+P34+T34+X34+AC34+AG34+AK34+AO34+AS34+AW34+BA34) -> 0 | E34: =SUM(I34+M34+Q34+U34+Z34+AD34+AH34+AH34+AL34+AP34+AT34+AX34+BB34) -> 55221.35 | F34: =100/E34*C34 -> 74.17636 | G34: 2874.025 | I34: 3443.75 | J34: =100/I34*G34 -> 83.456261 | K34: =SUM(SCA!W39) -> 33402.48 | M34: 29281.19 | N34: =100/M34*K34 -> 114.07487 | O34: 69.72 | Q34: 865.62 | R34: =100/Q34*O34 -> 8.0543426 | S34: 700.09011 | U34: 1171.88 | V34: =100/U34*S34 -> 59.740768 | W34: =SUM(MAI!X37) -> 0 | Y34: 2421.88 | Z34: 2421.88 | AA34: =100/Z34*W34 -> 0 | AB34: 0 | AD34: 2812 | AE34: =100/AD34*AB34 -> 0 | AF34: =SUM(IOC!K37) -> 359.5625 | AH34: 2884.39 | AI34: =100/AH34*AF34 -> 12.465807 | AJ34: =SUM(HIE!L37) -> 0 | AL34: 2656.25 | AM34: =100/AL34*AJ34 -> 0 | AN34: 0 | AP34: 3093.75 | AQ34: =100/AP34*AN34 -> 0 | AR34: 1742.07 | AT34: 893.75 | AU34: =100/AT34*AR34 -> 194.91692 | AV34: 1375 | AX34: 1718.75 | AY34: =100/AX34*AV34 -> 80 | AZ34: ='CKR '!C33 -> 438.24 | BB34: 1093.75 | BC34: =100/BB34*AZ34 -> 40.067657
A35: Validation & Impact assessment of GreenOffshoreTech LSD (data collection) | B35: T5.2 | C35: =SUM(G35+K35+O35+S35+W35+AB35+AF35+AJ35+AN35+AR35+AV35+AZ35) -> 771.5 | D35: =SUM(H35+L35+P35+T35+X35+AC35+AG35+AK35+AO35+AS35+AW35+BA35) -> 0 | E35: =SUM(I35+M35+Q35+U35+Z35+AD35+AH35+AH35+AL35+AP35+AT35+AX35+BB35) -> 55221.35 | F35: =100/E35*C35 -> 1.3971046 | G35: 746.5 | I35: 3443.75 | J35: =100/I35*G35 -> 21.676951 | K35: =SUM(SCA!W40) -> 0 | M35: 29281.19 | N35: =100/M35*K35 -> 0 | O35: 0 | Q35: 865.62 | R35: =100/Q35*O35 -> 0 | S35: 0 | U35: 1171.88 | V35: =100/U35*S35 -> 0 | W35: =SUM(MAI!X38) -> 0 | Y35: 2421.88 | Z35: 2421.88 | AA35: =100/Z35*W35 -> 0 | AB35: 0 | AD35: 2812 | AE35: =100/AD35*AB35 -> 0 | AF35: =SUM(IOC!K38) -> 0 | AH35: 2884.39 | AI35: =100/AH35*AF35 -> 0 | AJ35: =SUM(HIE!L38) -> 0 | AL35: 2656.25 | AM35: =100/AL35*AJ35 -> 0 | AN35: 0 | AP35: 3093.75 | AQ35: =100/AP35*AN35 -> 0 | AR35: 0 | AT35: 893.75 | AU35: =100/AT35*AR35 -> 0 | AV35: 25 | AX35: 1718.75 | AY35: =100/AX35*AV35 -> 1.4545455 | AZ35: ='CKR '!C34 -> 0 | BB35: 1093.75 | BC35: =100/BB35*AZ35 -> 0
A36: Guidelines of Best Practice to foster cross-sector/-border collaboration and technology transfer through Clusters | B36: T5.3 | C36: =SUM(G36+K36+O36+S36+W36+AB36+AF36+AJ36+AN36+AR36+AV36+AZ36) -> 796.20625 | D36: =SUM(H36+L36+P36+T36+X36+AC36+AG36+AK36+AO36+AS36+AW36+BA36) -> 0 | E36: =SUM(I36+M36+Q36+U36+Z36+AD36+AH36+AH36+AL36+AP36+AT36+AX36+BB36) -> 37652.53 | F36: =100/E36*C36 -> 2.1146155 | G36: 569.20625 | I36: 3443.75 | J36: =100/I36*G36 -> 16.528675 | K36: =SUM(SCA!W41) -> 0 | M36: 11712.35 | N36: =100/M36*K36 -> 0 | O36: 0 | Q36: 865.62 | R36: =100/Q36*O36 -> 0 | S36: 0 | U36: 1171.88 | V36: =100/U36*S36 -> 0 | W36: =SUM(MAI!X39) -> 0 | Y36: 2421.88 | Z36: 2421.88 | AA36: =100/Z36*W36 -> 0 | AB36: 0 | AD36: 2812 | AE36: =100/AD36*AB36 -> 0 | AF36: =SUM(IOC!K39) -> 0 | AH36: 2884.4 | AI36: =100/AH36*AF36 -> 0 | AJ36: =SUM(HIE!L39) -> 0 | AL36: 2656.25 | AM36: =100/AL36*AJ36 -> 0 | AN36: 0 | AP36: 3093.75 | AQ36: =100/AP36*AN36 -> 0 | AR36: 0 | AT36: 893.75 | AU36: =100/AT36*AR36 -> 0 | AV36: 227 | AX36: 1718.75 | AY36: =100/AX36*AV36 -> 13.207273 | AZ36: ='CKR '!C35 -> 0 | BB36: 1093.75 | BC36: =100/BB36*AZ36 -> 0
A37: Communication, Dissemination, Exploitation & Sustainability | B37: WP6 | C37: =SUM(G37+K37+O37+S37+W37+AB37+AF37+AJ37+AN37+AR37+AV37+AZ37) -> 56406.84 | D37: =SUM(H37+L37+P37+T37+X37+AC37+AG37+AK37+AO37+AS37+AW37+BA37) -> 0 | E37: =SUM(I37+M37+Q37+U37+Z37+AD37+AH37+AH37+AL37+AP37+AT37+AX37+BB37) -> 231218.95 | F37: =100/E37*C37 -> 24.395423 | G37: 8425.1856 | H37: =SUM(H38:H40) -> 0 | I37: =SUM(I38:I40) -> 26750 | J37: =100/I37*G37 -> 31.496021 | K37: =SUM(SCA!W42) -> 5847.4365 | L37: =SUM(L38:L40) -> 0 | M37: =SUM(M38:M40) -> 11712.44 | N37: =100/M37*K37 -> 49.925007 | O37: 25103.862 | P37: =SUM(P38:P40) -> 0 | Q37: =SUM(Q38:Q40) -> 25968.75 | R37: =100/Q37*O37 -> 96.669507 | S37: 3337.7579 | T37: =SUM(T38:T40) -> 0 | U37: =SUM(U38:U40) -> 9375 | V37: =100/U37*S37 -> 35.602751 | W37: =SUM(MAI!X40) -> 4596 | X37: =SUM(X38:X40) -> 0 | Y37: =SUM(Y38:Y40) -> 29062.5 | Z37: =SUM(Z38:Z40) -> 29062.5 | AA37: =100/Z37*W37 -> 15.814194 | AB37: 408.4375 | AC37: =SUM(AC38:AC40) -> 0 | AD37: =SUM(AD38:AD40) -> 22500 | AE37: =100/AD37*AB37 -> 1.8152778 | AF37: =SUM(IOC!K40) -> 4821.4062 | AG37: =SUM(AG38:AG40) -> 0 | AH37: =SUM(AH38:AH40) -> 23075.13 | AI37: =100/AH37*AF37 -> 20.894384 | AJ37: =SUM(HIE!L40) -> 2261.1825 | AK37: =SUM(AK38:AK40) -> 0 | AL37: =SUM(AL38:AL40) -> 21250 | AM37: =100/AL37*AJ37 -> 10.640859 | AN37: 0 | AO37: =SUM(AO38:AO40) -> 0 | AP37: =SUM(AP38:AP40) -> 12375 | AQ37: =100/AP37*AN37 -> 0 | AR37: 590.43 | AS37: =SUM(AS38:AS40) -> 0 | AT37: =SUM(AT38:AT40) -> 3575 | AU37: =100/AT37*AR37 -> 16.515524 | AV37: 620.725 | AW37: =SUM(AW38:AW40) -> 0 | AX37: =SUM(AX38:AX40) -> 13750 | AY37: =100/AX37*AV37 -> 4.5143636 | AZ37: ='CKR '!C36 -> 394.41658 | BA37: =SUM(BA38:BA40) -> 0 | BB37: =SUM(BB38:BB40) -> 8750 | BC37: =100/BB37*AZ37 -> 4.5076181
A38: Communication plan and Communication activities | B38: T6.1 | C38: =SUM(G38+K38+O38+S38+W38+AB38+AF38+AJ38+AN38+AR38+AV38+AZ38) -> 39381.405 | D38: =SUM(H38+L38+P38+T38+X38+AC38+AG38+AK38+AO38+AS38+AW38+BA38) -> 0 | E38: =SUM(I38+M38+Q38+U38+Z38+AD38+AH38+AH38+AL38+AP38+AT38+AX38+BB38) -> 55825.06 | F38: =100/E38*C38 -> 70.544313 | G38: 6531.875 | I38: 6687.5 | J38: =100/I38*G38 -> 97.672897 | K38: =SUM(SCA!W43) -> 4886.2141 | M38: 0 | N38: =100/M38*K38 -> #DIV/0! | O38: 16847.5 | Q38: 13850 | R38: =100/Q38*O38 -> 121.6426 | S38: 459.24468 | U38: 2343.75 | V38: =100/U38*S38 -> 19.59444 | W38: =SUM(MAI!X41) -> 4596 | Y38: 4843.75 | Z38: 4843.75 | AA38: =100/Z38*W38 -> 94.885161 | AB38: 326.75 | AD38: 5625 | AE38: =100/AD38*AB38 -> 5.8088889 | AF38: =SUM(IOC!K41) -> 4821.4062 | AH38: 5768.78 | AI38: =100/AH38*AF38 -> 83.577572 | AJ38: =SUM(HIE!L41) -> 0 | AL38: 5312.5 | AM38: =100/AL38*AJ38 -> 0 | AN38: 0 | AP38: =SUM(BAL!AF33*BAL!$AH$1) -> 0 | AQ38: =100/AP38*AN38 -> #DIV/0! | AR38: 0 | AT38: 0 | AU38: =100/AT38*AR38 -> #DIV/0! | AV38: 514.315 | AX38: 3437.5 | AY38: =100/AX38*AV38 -> 14.961891 | AZ38: ='CKR '!C37 -> 398.1 | BB38: 2187.5 | BC38: =100/BB38*AZ38 -> 18.198857
A39: Dissemination strategy and Dissemination activities | B39: T6.2 | C39: =SUM(G39+K39+O39+S39+W39+AB39+AF39+AJ39+AN39+AR39+AV39+AZ39) -> 10860.063 | D39: =SUM(H39+L39+P39+T39+X39+AC39+AG39+AK39+AO39+AS39+AW39+BA39) -> 0 | E39: =SUM(I39+M39+Q39+U39+Z39+AD39+AH39+AH39+AL39+AP39+AT39+AX39+BB39) -> 108168.84 | F39: =100/E39*C39 -> 10.039918 | G39: 933.125 | I39: 13375 | J39: =100/I39*G39 -> 6.9766355 | K39: =SUM(SCA!W44) -> 961.22244 | M39: 5856.22 | N39: =100/M39*K39 -> 16.413701 | O39: 3235.59 | Q39: 10387.5 | R39: =100/Q39*O39 -> 31.148881 | S39: 2878.5132 | U39: 4687.5 | V39: =100/U39*S39 -> 61.408281 | W39: =SUM(MAI!X42) -> 0 | Y39: 9687.5 | Z39: 9687.5 | AA39: =100/Z39*W39 -> 0 | AB39: 0 | AD39: 11250 | AE39: =100/AD39*AB39 -> 0 | AF39: =SUM(IOC!K42) -> 0 | AH39: 11537.56 | AI39: =100/AH39*AF39 -> 0 | AJ39: =SUM(HIE!L42) -> 2261.1825 | AL39: 10625 | AM39: =100/AL39*AJ39 -> 21.281718 | AN39: 0 | AP39: =SUM(BAL!AF34*BAL!$AH$1) -> 6187.5 | AQ39: =100/AP39*AN39 -> 0 | AR39: 590.43 | AT39: 1787.5 | AU39: =100/AT39*AR39 -> 33.031049 | AV39: 0 | AX39: 6875 | AY39: =100/AX39*AV39 -> 0 | AZ39: ='CKR '!C38 -> 0 | BB39: 4375 | BC39: =100/BB39*AZ39 -> 0
A40: Exploitation strategy, IPR and Sustainability | B40: T6.3 | C40: =SUM(G40+K40+O40+S40+W40+AB40+AF40+AJ40+AN40+AR40+AV40+AZ40) -> 1066.5956 | D40: =SUM(H40+L40+P40+T40+X40+AC40+AG40+AK40+AO40+AS40+AW40+BA40) -> 0 | E40: =SUM(I40+M40+Q40+U40+Z40+AD40+AH40+AH40+AL40+AP40+AT40+AX40+BB40) -> 67225.05 | F40: =100/E40*C40 -> 1.5866044 | G40: 960.18563 | I40: 6687.5 | J40: =100/I40*G40 -> 14.357916 | K40: =SUM(SCA!W45) -> 0 | M40: 5856.22 | N40: =100/M40*K40 -> 0 | O40: 0 | Q40: 1731.25 | R40: =100/Q40*O40 -> 0 | S40: 0 | U40: 2343.75 | V40: =100/U40*S40 -> 0 | W40: =SUM(MAI!X43) -> 0 | Y40: 14531.25 | Z40: 14531.25 | AA40: =100/Z40*W40 -> 0 | AB40: 0 | AD40: 5625 | AE40: =100/AD40*AB40 -> 0 | AF40: =SUM(IOC!K43) -> 0 | AH40: 5768.79 | AI40: =100/AH40*AF40 -> 0 | AJ40: =SUM(HIE!L43) -> 0 | AL40: 5312.5 | AM40: =100/AL40*AJ40 -> 0 | AN40: 0 | AP40: =SUM(BAL!AF35*BAL!$AH$1) -> 6187.5 | AQ40: =100/AP40*AN40 -> 0 | AR40: 0 | AT40: 1787.5 | AU40: =100/AT40*AR40 -> 0 | AV40: 106.41 | AX40: 3437.5 | AY40: =100/AX40*AV40 -> 3.0955636 | AZ40: ='CKR '!C39 -> 0 | BB40: 2187.5 | BC40: =100/BB40*AZ40 -> 0
A41: Project Management and Coordination | B41: WP7 | C41: =SUM(G41+K41+O41+S41+W41+AB41+AF41+AJ41+AN41+AR41+AV41+AZ41) -> 115933.43 | D41: =SUM(H41+L41+P41+T41+X41+AC41+AG41+AK41+AO41+AS41+AW41+BA41) -> 0 | E41: =SUM(I41+M41+Q41+U41+Z41+AD41+AH41+AH41+AL41+AP41+AT41+AX41+BB41) -> 214000 | F41: =100/E41*C41 -> 54.174501 | G41: 108068.01 | H41: =SUM(H42:H44) -> 0 | I41: =SUM(I42:I44) -> 214000 | J41: =100/I41*G41 -> 50.499068 | K41: =SUM(SCA!W46) -> 1682.1393 | L41: =SUM(L42:L44) -> 0 | M41: =SUM(M42:M44) -> 0 | N41: =100/M41*K41 -> #DIV/0! | O41: 0 | P41: =SUM(P42:P44) -> 0 | Q41: =SUM(Q42:Q44) -> 0 | R41: =100/Q41*O41 -> #DIV/0! | S41: 0 | T41: =SUM(T42:T44) -> 0 | U41: =SUM(U42:U44) -> 0 | V41: =100/U41*S41 -> #DIV/0! | W41: =SUM(MAI!X44) -> 0 | X41: =SUM(X42:X44) -> 0 | Y41: =SUM(Y42:Y44) -> 0 | Z41: =SUM(Z42:Z44) -> 0 | AA41: =100/Z41*W41 -> #DIV/0! | AB41: 367.59375 | AC41: =SUM(AC42:AC44) -> 0 | AD41: =SUM(AD42:AD44) -> 0 | AE41: =100/AD41*AB41 -> #DIV/0! | AF41: =SUM(IOC!K44) -> 0 | AG41: =SUM(AG42:AG44) -> 0 | AH41: =SUM(AH42:AH44) -> 0 | AI41: =100/AH41*AF41 -> #DIV/0! | AJ41: =SUM(HIE!L44) -> 5531.9342 | AK41: =SUM(AK42:AK44) -> 0 | AL41: =SUM(AL42:AL44) -> 0 | AM41: =100/AL41*AJ41 -> #DIV/0! | AN41: 0 | AO41: =SUM(AO42:AO44) -> 0 | AP41: =SUM(AP42:AP44) -> 0 | AQ41: =100/AP41*AN41 -> #DIV/0! | AR41: 0 | AS41: =SUM(AS42:AS44) -> 0 | AT41: =SUM(AT42:AT44) -> 0 | AU41: =100/AT41*AR41 -> #DIV/0! | AV41: 283.76 | AW41: =SUM(AW42:AW44) -> 0 | AX41: =SUM(AX42:AX44) -> 0 | AY41: =100/AX41*AV41 -> #DIV/0! | AZ41: ='CKR '!C40 -> 0 | BA41: =SUM(BA42:BA44) -> 0 | BB41: =SUM(BB42:BB44) -> 0 | BC41: =100/BB41*AZ41 -> #DIV/0!
A42: Project coordination | B42: T7.1 | C42: =SUM(G42+K42+O42+S42+W42+AB42+AF42+AJ42+AN42+AR42+AV42+AZ42) -> 42675.264 | D42: =SUM(H42+L42+P42+T42+X42+AC42+AG42+AK42+AO42+AS42+AW42+BA42) -> 0 | E42: =SUM(I42+M42+Q42+U42+Z42+AD42+AH42+AH42+AL42+AP42+AT42+AX42+BB42) -> 147125 | F42: =100/E42*C42 -> 29.006127 | G42: 37674.922 | I42: 147125 | J42: =100/I42*G42 -> 25.607424 | K42: =SUM(SCA!W47) -> 240.30561 | M42: 0 | N42: =100/M42*K42 -> #DIV/0! | O42: 0 | Q42: 0 | R42: =100/Q42*O42 -> #DIV/0! | S42: 0 | U42: 0 | V42: =100/U42*S42 -> #DIV/0! | W42: =SUM(MAI!X45) -> 0 | Y42: 0 | Z42: 0 | AA42: =100/Z42*W42 -> #DIV/0! | AB42: 0 | AD42: 0 | AE42: =100/AD42*AB42 -> #DIV/0! | AF42: =SUM(IOC!K45) -> 0 | AH42: 0 | AI42: =100/AH42*AF42 -> #DIV/0! | AJ42: =SUM(HIE!L45) -> 4760.0364 | AL42: 0 | AM42: =100/AL42*AJ42 -> #DIV/0! | AN42: 0 | AP42: 0 | AQ42: =100/AP42*AN42 -> #DIV/0! | AR42: 0 | AT42: 0 | AU42: =100/AT42*AR42 -> #DIV/0! | AV42: 0 | AX42: 0 | AY42: =100/AX42*AV42 -> #DIV/0! | AZ42: ='CKR '!C41 -> 0 | BB42: 0 | BC42: =100/BB42*AZ42 -> #DIV/0!
A43: Project administration & Financial Management | B43: T7.2 | C43: =SUM(G43+K43+O43+S43+W43+AB43+AF43+AJ43+AN43+AR43+AV43+AZ43) -> 50402.562 | D43: =SUM(H43+L43+P43+T43+X43+AC43+AG43+AK43+AO43+AS43+AW43+BA43) -> 0 | E43: =SUM(I43+M43+Q43+U43+Z43+AD43+AH43+AH43+AL43+AP43+AT43+AX43+BB43) -> 46812.5 | F43: =100/E43*C43 -> 107.66902 | G43: 48909.747 | I43: 46812.5 | J43: =100/I43*G43 -> 104.4801 | K43: =SUM(SCA!W48) -> 720.91683 | M43: 0 | N43: =100/M43*K43 -> #DIV/0! | O43: 0 | Q43: 0 | R43: =100/Q43*O43 -> #DIV/0! | S43: 0 | U43: 0 | V43: =100/U43*S43 -> #DIV/0! | W43: =SUM(MAI!X46) -> 0 | Y43: 0 | Z43: 0 | AA43: =100/Z43*W43 -> #DIV/0! | AB43: 0 | AD43: 0 | AE43: =100/AD43*AB43 -> #DIV/0! | AF43: =SUM(IOC!K46) -> 0 | AH43: 0 | AI43: =100/AH43*AF43 -> #DIV/0! | AJ43: =SUM(HIE!L46) -> 771.8978 | AL43: 0 | AM43: =100/AL43*AJ43 -> #DIV/0! | AN43: 0 | AP43: 0 | AQ43: =100/AP43*AN43 -> #DIV/0! | AR43: 0 | AT43: 0 | AU43: =100/AT43*AR43 -> #DIV/0! | AV43: 0 | AX43: 0 | AY43: =100/AX43*AV43 -> #DIV/0! | AZ43: ='CKR '!C42 -> 0 | BB43: 0 | BC43: =100/BB43*AZ43 -> #DIV/0!
A44: Quality Assurance | B44: T7.3 | C44: =SUM(G44+K44+O44+S44+W44+AB44+AF44+AJ44+AN44+AR44+AV44+AZ44) -> 22782.089 | D44: =SUM(H44+L44+P44+T44+X44+AC44+AG44+AK44+AO44+AS44+AW44+BA44) -> 0 | E44: =SUM(I44+M44+Q44+U44+Z44+AD44+AH44+AH44+AL44+AP44+AT44+AX44+BB44) -> 20062.5 | F44: =100/E44*C44 -> 113.55558 | G44: 21483.337 | I44: 20062.5 | J44: =100/I44*G44 -> 107.08205 | K44: =SUM(SCA!W49) -> 720.91683 | M44: 0 | N44: =100/M44*K44 -> #DIV/0! | O44: 0 | Q44: 0 | R44: =100/Q44*O44 -> #DIV/0! | S44: 0 | U44: 0 | V44: =100/U44*S44 -> #DIV/0! | W44: =SUM(MAI!X47) -> 0 | Y44: 0 | Z44: 0 | AA44: =100/Z44*W44 -> #DIV/0! | AB44: 294.075 | AD44: 0 | AE44: =100/AD44*AB44 -> #DIV/0! | AF44: =SUM(IOC!K47) -> 0 | AH44: 0 | AI44: =100/AH44*AF44 -> #DIV/0! | AJ44: =SUM(HIE!L47) -> 0 | AL44: 0 | AM44: =100/AL44*AJ44 -> #DIV/0! | AN44: 0 | AP44: 0 | AQ44: =100/AP44*AN44 -> #DIV/0! | AR44: 0 | AT44: 0 | AU44: =100/AT44*AR44 -> #DIV/0! | AV44: 283.76 | AX44: 0 | AY44: =100/AX44*AV44 -> #DIV/0! | AZ44: ='CKR '!C43 -> 0 | BB44: 0 | BC44: =100/BB44*AZ44 -> #DIV/0!
A45: TOTAL | C45: =SUM(G45+K45+O45+S45+W45+AB45+AF45+AJ45+AN45+AR45+AV45+AZ45) -> 498613.68 | D45: =SUM(H45+L45+P45+T45+X45+AC45+AG45+AK45+AO45+AS45+AW45+BA45) -> 274542.86 | E45: =SUM(E6+E7+E11+E16+E23+E33+E37+E41) -> 5453593.6 | F45: =100/E45*C45 -> 9.1428463 | G45: 142042.15 | H45: =SUM(H7+H11+H16+H23+H33+H37+H41) -> 31600 | I45: =SUM(I6+I7+I11+I16+I23+I33+I37+I41) -> 3485268.8 | J45: =100/I45*G45 -> 4.0755007 | K45: =SUM(SCA!W50) -> 71651.123 | L45: =SUM(L7+L11+L16+L23+L33+L37+L41) -> 16000 | M45: =SUM(M6+M7+M11+M16+M23+M33+M37+M41) -> 322346.13 | N45: =100/M45*K45 -> 22.228008 | O45: 29301.4 | P45: =SUM(P7+P11+P16+P23+P33+P37+P41) -> 34000 | Q45: =SUM(Q6+Q7+Q11+Q16+Q23+Q33+Q37+Q41) -> 125599.97 | R45: =100/Q45*O45 -> 23.329146 | S45: 16130.801 | T45: =SUM(T7+T11+T16+T23+T33+T37+T41) -> 16600 | U45: =SUM(U6+U7+U11+U16+U23+U33+U37+U41) -> 105125.03 | V45: =100/U45*S45 -> 15.344396 | W45: =SUM(MAI!X48) -> 21343.625 | X45: =SUM(X7+X11+X16+X23+X33+X37+X41) -> 16600 | Y45: =SUM(Y6+Y7+Y11+Y16+Y23+Y33+Y37+Y41) -> 204812.53 | Z45: =SUM(Z6+Z7+Z11+Z16+Z23+Z33+Z37+Z41) -> 204812.53 | AA45: =100/Z45*W45 -> 10.421054 | AB45: 16447.981 | AC45: =SUM(AC7+AC11+AC16+AC23+AC33+AC37+AC41) -> 45142.86 | AD45: =SUM(AD41+AD37+AD33+AD23+AD16+AD11+AD7+AD6) -> 270177.5 | AE45: =100/AD45*AB45 -> 6.0878427 | AF45: =SUM(IOC!K48) -> 9446.6875 | AG45: =SUM(AG7+AG11+AG16+AG23+AG33+AG37+AG41) -> 16600 | AH45: =SUM(AH6+AH7+AH11+AH16+AH23+AH33+AH37+AH41) -> 139010.22 | AI45: =100/AH45*AF45 -> 6.7956784 | AJ45: =SUM(HIE!L48) -> 47632.423 | AK45: =SUM(AK7+AK11+AK16+AK23+AK33+AK37+AK41) -> 16600 | AL45: =SUM(AL6+AL7+AL11+AL16+AL23+AL33+AL37+AL41) -> 211999.5 | AM45: =100/AL45*AJ45 -> 22.468177 | AN45: 83149.35 | AO45: =SUM(AO7+AO11+AO16+AO23+AO33+AO37+AO41) -> 16600 | AP45: =SUM(AP6+AP7+AP11+AP16+AP23+AP33+AP37+AP41) -> 181625 | AQ45: =100/AP45*AN45 -> 45.780785 | AR45: 15221.25 | AS45: =SUM(AS7+AS11+AS16+AS23+AS33+AS37+AS41) -> 16600 | AT45: =SUM(AT6+AT7+AT11+AT16+AT23+AT33+AT37+AT41) -> 63650 | AU45: =100/AT45*AR45 -> 23.913983 | AV45: 14743.662 | AW45: =SUM(AW7+AW11+AW16+AW23+AW33+AW37+AW41) -> 31600 | AX45: =SUM(AX6+AX7+AX11+AX16+AX23+AX33+AX37+AX41) -> 130593.75 | AY45: =100/AX45*AV45 -> 11.289715 | AZ45: ='CKR '!C44 -> 31503.226 | BA45: =SUM(BA7+BA11+BA16+BA23+BA33+BA37+BA41) -> 16600 | BB45: =SUM(BB6+BB7+BB11+BB16+BB23+BB33+BB37+BB41) -> 95125 | BC45: =100/BB45*AZ45 -> 33.117715
A46: Total budget of the project | E46: 5253231
A47: Budget WP1-5 | E47: =SUM(E7+E11+E16+E23+E33) -> 4664445.7 | F47: Without travel cost
A49: % Cost Allocated to the SMEs | C49: =SUM(E47/E46) -> 0.88791939

Sheet MNU
C1: TOTAL COSTS
C2: Dir & Indir (EUR) | AA2: 81 | AB2: 101
C3: ACTUAL | AA3: AMD2 | AB3: AMD2
A4: GreenOfshoreTech MNU (Period M1 to M10) | B4: Task/ | C4: M1-M10 | AA4: For BUDGET | AB4: For 75% RULE
B5: WP | V5: ORG = | W5: ORG = | AA5: Direct monthly rate | AB5: Direct monthly rate
A6: Otherdirect Cost ( travel, equipment & Other goods and services)(ODC) | V6: AMD1 | W6: AMD1 | X6: AMD2 | Y6: AMD2 | Z6: AMD2 | AA6: 11610 | AB6: 11610 | AC6: Confirmed rate | AE6: 81 Euro per hour
A7: Assessment of potential new value chains and selection of Topics for Call of Proposals | B7: WP1 | C7: =SUM(C8:C10) -> 8024.875 | V7: BUDGET | W7: BUDGET | X7: REVISION | Y7: REVISION | AA7: REVISION | AB7: REVISION
A8: Sustainable challenges, needs and trends of four industrial offshore sectors | B8: T1.1 | C8: =G14*1.25 -> 3265.9375 | U8: Task/ | X8: TOTAL | Y8: TOTAL | Z8: COMMENT | AA8: Personnel costs (DIRECT only) | AB8: Personnel costs (DIRECT & INDIRECT)
A9: Assessment of emerging technology trends and solutions | B9: T1.2 | C9: =G15*1.25 -> 1399.6875 | F9: Budget rate | H9: Actual | K9: 1PM iequals to | M9: 143.333 | U9: WP | V9: PM | W9: hours | X9: PMs | Y9: Hours | AA9: EUR | AB9: EUR
A10: Potential new value chains and selection of Call Topics | B10: T1.3 | C10: =G16*1.25 -> 3359.25 | F10: Project manager | H10: Project manager | T10: Assessment of potential new value chains and selection of Topics for Call of Proposals | U10: WP1 | V10: =SUM( V11:V13) -> 1.5 | W10: =SUM(W11:W13) -> 215 | X10: =SUM(X11:X13) -> 0.7 | Y10: =X10*(1720/12) -> 100.33333 | Z10: minus 0.8 PM | AA10: =SUM(AA11:AA13) -> 8025 | AB10: =SUM(AB11:AB13) -> 10031.25
A11: Methodologies and tools for cross-sectoral/-border collaboration and technology transfer | B11: WP2 | C11: =SUM(C12:C15) -> 5346.8063 | F11: hrs | G11: Salery rate | H11: hrs | I11: Salery rate | T11: Sustainable challenges, needs and trends of four industrial offshore sectors | U11: T1.1 | V11: 1 | W11: =V11*1720/12 -> 143.33333 | X11: 0.29 | Y11: =X11*(1720/12) -> 41.566667 | Z11: minus 0.71 PM | AA11: 3266 | AB11: =AA11*1.25 -> 4082.5
A12: Methologies and tools for cross-sectoral/-border collaboration and technology transfer | B12: T2.1 | C12: =G18*1.25 -> 1306.375 | G12: 74.65 | I12: 82 | T12: Assessment of emerging technology trends and solutions | U12: T1.2 | V12: 0.25 | W12: =V12*1720/12 -> 35.833333 | X12: 0.12 | Y12: =X12*(1720/12) -> 17.2 | Z12: minus 0.13 PM | AA12: 1400 | AB12: =AA12*1.25 -> 1750
A13: Establishment of a Collaborative Virtual Environment | B13: T2.2 | C13: =G19*1.25 -> 4040.4313 | F13: =SUM(F14:F16) -> 86 | G13: =F13*G$12*(1+I$9) -> 6419.9 | H13: =SUM(H14:H16) -> 0 | I13: =H13*I$12*(1+I$9) -> 0 | J13: PM | K13: 0.6 | T13: Potential new value chains and selection of Call Topics | U13: T1.3 | V13: 0.25 | W13: =V13*1720/12 -> 35.833333 | X13: 0.29 | Y13: =X13*(1720/12) -> 41.566667 | Z13: plus 0.04 PM | AA13: 3359 | AB13: =AA13*1.25 -> 4198.75
A14: Establishment of a Survey tool | B14: T2.3 | C14: =G20*1.25 -> 0 | F14: 35 | G14: =F14*G$12*(1+I$9) -> 2612.75 | H14: 0 | I14: =H14*I$12*(1+I$9) -> 0 | T14: Methodologies and tools for cross-sectoral/-border collaboration and technology transfer | U14: WP2 | V14: =SUM(V15:V18) -> 0.5 | W14: =SUM(W15:W18) -> 71.666667 | X14: =SUM( X15:X18) -> 0.46 | Y14: =X14*(1720/12) -> 65.933333 | Z14: minus 0.04 PM | AA14: =SUM(AA15:AA18) -> 5346 | AB14: =SUM(AB15:AB18) -> 6682.5
A15: Establishment of the GreenOffshoreTech Cluster Collaboration Platform | B15: T2.4 | C15: =G21*1.25 -> 0 | F15: 15 | G15: =F15*G$12*(1+I$9) -> 1119.75 | H15: 0 | I15: =H15*I$12*(1+I$9) -> 0 | T15: Methologies and tools for cross-sectoral/-border collaboration and technology transfer | U15: T2.1 | V15: 0.25 | W15: =V15*1720/12 -> 35.833333 | X15: 0.11 | Y15: =X15*(1720/12) -> 15.766667 | Z15: minus 0.14 PM | AA15: 1306 | AB15: =AA15*1.25 -> 1632.5
A16: Direct financial support to SMEs through a competitive Call for Proposals | B16: WP3 | C16: =SUM(C17:C22) -> 1306.375 | F16: 36 | G16: =F16*G$12*(1+I$9) -> 2687.4 | H16: 0 | I16: =H16*I$12*(1+I$9) -> 0 | T16: Establishment of a Collaborative Virtual Environment | U16: T2.2 | V16: 0.25 | W16: =V16*1720/12 -> 35.833333 | X16: 0.35 | Y16: =X16*(1720/12) -> 50.166667 | Z16: plus 0.1 0PM | AA16: 4040 | AB16: =AA16*1.25 -> 5050
A17: Preparation of the Call for Proposals | B17: T3.1 | C17: =G23*1.25 -> 559.875 | F17: =SUM(F18:F21) -> 57.3 | G17: =F17*G$12*(1+I$9) -> 4277.445 | I17: =H17*I$12*(1+I$9) -> 0 | J17: PM | K17: 0.4 | T17: Establishment of a Survey tool | U17: T2.3 | V17: 0 | W17: =V17*1720/12 -> 0 | X17: 0 | Y17: =X17*(1720/12) -> 0 | Z17: OK | AA17: 0 | AB17: =AA17*1.25 -> 0
A18: Publication of the Call for Proposals and Proposal reception. | B18: T3.2 | C18: =G24*1.25 -> 466.5625 | F18: 14 | G18: =F18*G$12*(1+I$9) -> 1045.1 | H18: 0 | I18: =H18*I$12*(1+I$9) -> 0 | T18: Establishment of the GreenOffshoreTech Cluster Collaboration Platform | U18: T2.4 | V18: 0 | W18: =V18*1720/12 -> 0 | X18: 0 | Y18: =X18*(1720/12) -> 0 | Z18: OK | AA18: 0 | AB18: =AA18*1.25 -> 0
A19: Evaluation and Selection of SMEs Proposals | B19: T3.3 | C19: =G25*1.25 -> 279.9375 | F19: 43.3 | G19: =F19*G$12*(1+I$9) -> 3232.345 | H19: 0 | I19: =H19*I$12*(1+I$9) -> 0 | T19: Direct financial support to SMEs through a competitive Call for Proposals | U19: WP3 | V19: =SUM(V20:V25) -> 7 | W19: =SUM(W20:W25) -> 1003.3333 | X19: =SUM(X20:X25) -> 7 | Y19: =X19*(1720/12) -> 1003.3333 | AA19: =SUM(AA20:AA25) -> 94376 | AB19: =SUM(AB20:AB25) -> 117970
A20: Contracting with winner SMEs Projects | B20: T3.4 | C20: =G26*1.25 -> 0 | F20: 0 | G20: =F20*G$12*(1+I$9) -> 0 | H20: 0 | I20: =H20*I$12*(1+I$9) -> 0 | T20: Preparation of the Call for Proposals | U20: T3.1 | V20: 0.5 | W20: =V20*1720/12 -> 71.666667 | X20: 0.5 | Y20: =X20*(1720/12) -> 71.666667 | Z20: OK | AA20: 6688 | AB20: =AA20*1.25 -> 8360
A21: Payments and financial monitoring of winner SMEs Projects | B21: T3.5 | C21: 0 | F21: 0 | G21: =F21*G$12*(1+I$9) -> 0 | H21: 0 | I21: =H21*I$12*(1+I$9) -> 0 | T21: Publication of the Call for Proposals and Proposal reception. | U21: T3.2 | V21: 0.5 | W21: =V21*1720/12 -> 71.666667 | X21: 0.5 | Y21: =X21*(1720/12) -> 71.666667 | Z21: OK | AA21: 6688 | AB21: =AA21*1.25 -> 8360
A22: Technical monitoring of winner SMEs Projects | B22: T3.6 | C22: =G28*1.25 -> 0 | F22: =SUM(F23:F28) -> 14 | G22: =F22*G$12*(1+I$9) -> 1045.1 | H22: =SUM(H23:H28) -> 0 | I22: =H22*I$12*(1+I$9) -> 0 | J22: PM | K22: 0.1 | T22: Evaluation and Selection of SMEs Proposals | U22: T3.3 | V22: 1 | W22: =V22*1720/12 -> 143.33333 | X22: 1 | Y22: =X22*(1720/12) -> 143.33333 | Z22: OK | AA22: 13750 | AB22: =AA22*1.25 -> 17187.5
A23: Business Support Services to winner SMEs (preparation) | B23: WP4 | C23: =SUM(C24:C32) -> 6681.175 | F23: 6 | G23: =F23*G$12*(1+I$9) -> 447.9 | H23: 0 | I23: =H23*I$12*(1+I$9) -> 0 | T23: Contracting with winner SMEs Projects | U23: T3.4 | V23: 2 | W23: =V23*1720/12 -> 286.66667 | X23: 2 | Y23: =X23*(1720/12) -> 286.66667 | Z23: Ok. | AA23: 26750 | AB23: =AA23*1.25 -> 33437.5
A24: Programme of Business Support Services to winner SMEs (prep) | B24: T4.1 | C24: =G30*1.25 -> 933.125 | F24: 5 | G24: =F24*G$12*(1+I$9) -> 373.25 | H24: 0 | I24: =H24*I$12*(1+I$9) -> 0 | T24: Payments and financial monitoring of winner SMEs Projects | U24: T3.5 | V24: 2 | W24: =V24*1720/12 -> 286.66667 | X24: 2 | Y24: =X24*(1720/12) -> 286.66667 | Z24: Ok. | AA24: 26750 | AB24: =AA24*1.25 -> 33437.5
A25: Business Support Service #1 Business & Tech Academy | B25: T4.2 | C25: =G31*1.25 -> 0 | F25: 3 | G25: =F25*G$12*(1+I$9) -> 223.95 | H25: 0 | I25: =H25*I$12*(1+I$9) -> 0 | T25: Technical monitoring of winner SMEs Projects | U25: T3.6 | V25: 1 | W25: =V25*1720/12 -> 143.33333 | X25: 1 | Y25: =X25*(1720/12) -> 143.33333 | Z25: Ok | AA25: 13750 | AB25: =AA25*1.25 -> 17187.5
A26: Business Support Service #2 Brokerage & B2B matchmaking events | B26: T4.3 | C26: =G32*1.25 -> 0 | F26: 0 | G26: =F26*G$12*(1+I$9) -> 0 | H26: 0 | I26: =H26*I$12*(1+I$9) -> 0 | T26: Business Support Services to winner SMEs | U26: WP4 | V26: =SUM(V27:V35) -> 5.5 | W26: =SUM(W27:W35) -> 788.33333 | X26: =SUM(X27:X35) -> 4.36 | Y26: =X26*(1720/12) -> 624.93333 | Z26: minus 0.66 PM | AA26: =SUM(AA27:AA35) -> 56059 | AB26: =SUM(AB27:AB35) -> 70073.75
A27: Business Support Service #3 Access to Finance | B27: T4.4 | C27: =G33*1.25 -> 0 | F27: 0 | G27: =F27*G$12*(1+I$9) -> 0 | H27: 0 | I27: =H27*I$12*(1+I$9) -> 0 | T27: Programme of Business Support Services to winner SMEs | U27: T4.1 | V27: 0 | W27: =V27*1720/12 -> 0 | X27: 0.08 | Y27: =X27*(1720/12) -> 11.466667 | Z27: plus 0,08 PM | AA27: 933 | AB27: =AA27*1.25 -> 1166.25
A28: Business Support Service #4 One-to-One Mentoring and Coaching (prep) | B28: T4.5 | C28: =G34*1.25 -> 0 | F28: 0 | G28: =F28*G$12*(1+I$9) -> 0 | H28: 0 | I28: =H28*I$12*(1+I$9) -> 0 | T28: Business Support Service #1 Business & Tech Academy | U28: T4.2 | V28: 1 | W28: =V28*1720/12 -> 143.33333 | X28: 0.17 | Y28: =X28*(1720/12) -> 24.366667 | Z28: minus 0,83 PM | AA28: 2000 | AB28: =AA28*1.25 -> 2500
A29: Business Support Service #5 Branding | B29: T4.6 | C29: =G35*1.25 -> 0 | F29: =SUM(F30:F38) -> 71.6 | G29: =F29*G$12*(1+I$9) -> 5344.94 | I29: =H29*I$12*(1+I$9) -> 0 | J29: PM | K29: 0.5 | T29: Business Support Service #2 Brokerage & B2B matchmaking events | U29: T4.3 | V29: 0.5 | W29: =V29*1720/12 -> 71.666667 | X29: 0.34 | Y29: =X29*(1720/12) -> 48.733333 | Z29: minus 0.16 PM | AA29: 4000 | AB29: =AA29*1.25 -> 5000
A30: Business Support Service #6 Internationalisation | B30: T4.7 | C30: =G36*1.25 -> 0 | F30: 10 | G30: =F30*G$12*(1+I$9) -> 746.5 | H30: 0 | I30: =H30*I$12*(1+I$9) -> 0 | T30: Business Support Service #3 Access to Finance | U30: T4.4 | V30: 0.5 | W30: =V30*1720/12 -> 71.666667 | X30: 0.17 | Y30: =X30*(1720/12) -> 24.366667 | Z30: minus 0.33 PM | AA30: 2000 | AB30: =AA30*1.25 -> 2500
A31: Business Support Service #7 Investor pitching | B31: T4.8 | C31: =G37*1.25 -> 0 | F31: 0 | G31: =F31*G$12*(1+I$9) -> 0 | H31: 0 | I31: =H31*I$12*(1+I$9) -> 0 | T31: Business Support Service #4 One-to-One Mentoring and Coaching (prep + service) | U31: T4.5 | V31: 0 | W31: =V31*1720/12 -> 0 | X31: 0.17 | Y31: =X31*(1720/12) -> 24.366667 | Z31: plus 0.17 PM | AA31: 2000 | AB31: =AA31*1.25 -> 2500
A32: Business Support Service #8 Investor rounds | B32: T4.9 | C32: =G38*1.25 -> 5748.05 | F32: 0 | G32: =F32*G$12*(1+I$9) -> 0 | H32: 0 | I32: =H32*I$12*(1+I$9) -> 0 | T32: Business Support Service #5 Branding | U32: T4.6 | V32: 0 | W32: =V32*1720/12 -> 0 | X32: 0.17 | Y32: =X32*(1720/12) -> 24.366667 | Z32: plus 0.17 PM | AA32: 2000 | AB32: =AA32*1.25 -> 2500
A33: Large-scale Demonstrator (LSD) setup, validation, and impact assessment | B33: WP5 | C33: =SUM(C34:C36) -> 4189.7313 | F33: 0 | G33: =F33*G$12*(1+I$9) -> 0 | H33: 0 | I33: =H33*I$12*(1+I$9) -> 0 | T33: Business Support Service #6 Internationalisation | U33: T4.7 | V33: 0.5 | W33: =V33*1720/12 -> 71.666667 | X33: 0.26 | Y33: =X33*(1720/12) -> 37.266667 | Z33: plus 0.24 PM | AA33: 3000 | AB33: =AA33*1.25 -> 3750
A34: Set-up of the GreenOffshoreTech LSD in GreenOffshoreTech regions | B34: T5.1 | C34: =G40*1.25 -> 2874.025 | F34: 0 | G34: =F34*G$12*(1+I$9) -> 0 | H34: 0 | I34: =H34*I$12*(1+I$9) -> 0 | T34: Business Support Service #7 Investor pitching | U34: T4.8 | V34: 0.5 | W34: =V34*1720/12 -> 71.666667 | X34: 0.5 | Y34: =X34*(1720/12) -> 71.666667 | Z34: OK | AA34: 6688 | AB34: =AA34*1.25 -> 8360
A35: Validation & Impact assessment of GreenOffshoreTech LSD (data collection) | B35: T5.2 | C35: =G41*1.25 -> 746.5 | F35: 0 | G35: =F35*G$12*(1+I$9) -> 0 | H35: 0 | I35: =H35*I$12*(1+I$9) -> 0 | T35: Business Support Service #8 Investor rounds | U35: T4.9 | V35: 2.5 | W35: =V35*1720/12 -> 358.33333 | X35: 2.5 | Y35: =X35*(1720/12) -> 358.33333 | Z35: OK | AA35: 33438 | AB35: =AA35*1.25 -> 41797.5
A36: Guidelines of Best Practice to foster cross-sector/-border collaboration and technology transfer through Clusters | B36: T5.3 | C36: =G42*1.25 -> 569.20625 | F36: 0 | G36: =F36*G$12*(1+I$9) -> 0 | H36: 0 | I36: =H36*I$12*(1+I$9) -> 0 | T36: Large-scale Demonstrator (LSD) setup, validation, and impact assessment | U36: WP5 | V36: =SUM(V37:V39) -> 0.75 | W36: =SUM(W37:W39) -> 107.5 | X36: =SUM(X37:X39) -> 0.3465 | Y36: =X36*(1720/12) -> 49.665 | Z36: minus 0,4 PM | AA36: =SUM(AA37:AA39) -> 4190 | AB36: =SUM(AB37:AB39) -> 5237.5 | AG36: Verify below this line.
A37: Communication, Dissemination, Exploitation & Sustainability | B37: WP6 | C37: =SUM(C38:C40) -> 8425.1856 | F37: 0 | G37: =F37*G$12*(1+I$9) -> 0 | H37: 0 | I37: =H37*I$12*(1+I$9) -> 0 | T37: Set-up of the GreenOffshoreTech LSD in GreenOffshoreTech regions | U37: T5.1 | V37: 0.25 | W37: =V37*1720/12 -> 35.833333 | X37: 0.2475 | Y37: =X37*(1720/12) -> 35.475 | Z37: OK | AA37: 2874 | AB37: =AA37*1.25 -> 3592.5
A38: Communication plan and Communication activities | B38: T6.1 | C38: =G44*1.25 -> 6531.875 | F38: 61.6 | G38: =F38*G$12*(1+I$9) -> 4598.44 | H38: 0 | I38: =H38*I$12*(1+I$9) -> 0 | T38: Validation & Impact assessment of GreenOffshoreTech LSD (data collection & analysis) | U38: T5.2 | V38: 0.25 | W38: =V38*1720/12 -> 35.833333 | X38: 0.05 | Y38: =X38*(1720/12) -> 7.1666667 | Z38: minus 0.20 PM | AA38: 747 | AB38: =AA38*1.25 -> 933.75
A39: Dissemination strategy and Dissemination activities | B39: T6.2 | C39: =G45*1.25 -> 933.125 | F39: =SUM(F40:F42) -> 44.9 | G39: =F39*G$12*(1+I$9) -> 3351.785 | I39: =H39*I$12*(1+I$9) -> 0 | J39: PM | K39: 0.31 | T39: Guidelines of Best Practice to foster cross-sector/-border collaboration and technology transfer through Clusters | U39: T5.3 | V39: 0.25 | W39: =V39*1720/12 -> 35.833333 | X39: 0.049 | Y39: =X39*(1720/12) -> 7.0233333 | Z39: minus 0.20 PM | AA39: 569 | AB39: =AA39*1.25 -> 711.25
A40: Exploitation strategy, IPR and Sustainability | B40: T6.3 | C40: =G46*1.25 -> 960.18563 | F40: 30.8 | G40: =F40*G$12*(1+I$9) -> 2299.22 | H40: 0 | I40: =H40*I$12*(1+I$9) -> 0 | T40: Communication, Dissemination, Exploitation & Sustainability | U40: WP6 | V40: =SUM(V41:V43) -> 2 | W40: =SUM(W41:W43) -> 286.66667 | X40: =SUM(X41:X43) -> 1.506 | Y40: =X40*(1720/12) -> 215.86 | Z40: minus 0,65 PM | AA40: =SUM(AA41:AA43) -> 17492 | AB40: =SUM(AB41:AB43) -> 21865
A41: Project Management and Coordination | B41: WP7 | C41: =SUM(C42:C44) -> 108068.01 | F41: 8 | G41: =F41*G$12*(1+I$9) -> 597.2 | H41: 0 | I41: =H41*I$12*(1+I$9) -> 0 | T41: Communication plan and Communication activities | U41: T6.1 | V41: 0.5 | W41: =V41*1720/12 -> 71.666667 | X41: 0.562 | Y41: =X41*(1720/12) -> 80.553333 | Z41: plus 0,01 PM | AA41: 6532 | AB41: =AA41*1.25 -> 8165
A42: Project coordination | B42: T7.1 | C42: =G48*1.25 -> 37674.922 | F42: 6.1 | G42: =F42*G$12*(1+I$9) -> 455.365 | H42: 0 | I42: =H42*I$12*(1+I$9) -> 0 | T42: Dissemination strategy and Dissemination activities | U42: T6.2 | V42: 1 | W42: =V42*1720/12 -> 143.33333 | X42: 0.8613 | Y42: =X42*(1720/12) -> 123.453 | Z42: minus 0.24 PM | AA42: 10000 | AB42: =AA42*1.25 -> 12500
A43: Project administration & Financial Management | B43: T7.2 | C43: =G49*1.25 -> 48909.747 | F43: =SUM(F44:F46) -> 90.29 | G43: =F43*G$12*(1+I$9) -> 6740.1485 | I43: =H43*I$12*(1+I$9) -> 0 | J43: PM | K43: 0.63 | T43: Exploitation strategy, IPR and Sustainability | U43: T6.3 | V43: 0.5 | W43: =V43*1720/12 -> 71.666667 | X43: 0.0827 | Y43: =X43*(1720/12) -> 11.853667 | Z43: minus 0.42 PM | AA43: 960 | AB43: =AA43*1.25 -> 1200
A44: Quality Assurance | B44: T7.3 | C44: =G50*1.25 -> 21483.337 | F44: 70 | G44: =F44*G$12*(1+I$9) -> 5225.5 | H44: 0 | I44: =H44*I$12*(1+I$9) -> 0 | T44: Project Management and Coordination | U44: WP7 | V44: =SUM(V45:V47) -> 16 | W44: =SUM(W45:W47) -> 2293.3333 | X44: =SUM(X45:X47) -> 17.0624 | Y44: =X44*(1720/12) -> 2445.6107 | Z44: plus 1,06 PM | AA44: =SUM(AA45:AA47) -> 198093 | AB44: =SUM(AB45:AB47) -> 247616.25
A45: TOTAL | C45: =SUM(C7+C11+C16+C23+C33+C37+C41) -> 142042.15 | F45: 10 | G45: =F45*G$12*(1+I$9) -> 746.5 | H45: 0 | I45: =H45*I$12*(1+I$9) -> 0 | T45: Project coordination | U45: T7.1 | V45: 11 | W45: =V45*1720/12 -> 1576.6667 | X45: 10.9992 | Y45: =X45*(1720/12) -> 1576.552 | Z45: OK | AA45: 127700 | AB45: =AA45*1.25 -> 159625
F46: 10.29 | G46: =F46*G$12*(1+I$9) -> 768.1485 | H46: 0 | I46: =H46*I$12*(1+I$9) -> 0 | T46: Project administration & Financial Management | U46: T7.2 | V46: 3.5 | W46: =V46*1720/12 -> 501.66667 | X46: 4.2128 | Y46: =X46*(1720/12) -> 603.83467 | Z46: plus 0,71 PM | AA46: 48910 | AB46: =AA46*1.25 -> 61137.5
F47: =SUM(F48:F50) -> 1158.13 | G47: =F47*G$12*(1+I$9) -> 86454.405 | I47: =H47*I$12*(1+I$9) -> 0 | J47: PM | K47: 8.08 | T47: Quality Assurance | U47: T7.3 | V47: 1.5 | W47: =V47*1720/12 -> 215 | X47: 1.8504 | Y47: =X47*(1720/12) -> 265.224 | Z47: plus 0,35 PM | AA47: 21483 | AB47: =AA47*1.25 -> 26853.75
F48: 403.75 | G48: =F48*G$12*(1+I$9) -> 30139.938 | H48: 0 | I48: =H48*I$12*(1+I$9) -> 0 | T48: NOTE: Key Tasks are marked light green | V48: =V10+V14+V19+V26+V36+V40+V44 -> 33.25 | W48: =W10+W14+W19+W26+W36+W40+W44 -> 4765.8333 | X48: =(X10+X14+X19+X26+X36+X40+X44) -> 31.4349 | Y48: =(Y10+Y14+Y19+Y26+Y36+Y40+Y44) -> 4505.669 | AA48: =(AA10+AA14+AA19+AA26+AA36+AA40+AA44) -> 383581 | AB48: =(AB10+AB14+AB19+AB26+AB36+AB40+AB44) -> 479476.25
F49: 524.15 | G49: =F49*G$12*(1+I$9) -> 39127.798 | H49: 0 | I49: =H49*I$12*(1+I$9) -> 0
F50: 230.23 | G50: =F50*G$12*(1+I$9) -> 17186.669 | H50: 0 | I50: =H50*I$12*(1+I$9) -> 0
F51: =F13+F17+F22+F29+F39+F43+F47 -> 1522.22 | G51: =F51*G$12*(1+I$9) -> 113633.72 | H51: =H13+H17+H22+H29+H39+H43+H47 -> 0 | I51: =H51*I$12*(1+I$9) -> 0 | J51: PM | K51: =K13+K17+K22+K29+K39+K43+K47 -> 10.62

Sheet SCA
B2: {=B2:J2} -> 0 | W2: TOTAL COSTS
I3: Hourly rate 65,37 | J3: Hourly rate 81,71
I4: AMD2 | J4: AMD2
I5: For BUDGET | J5: For 75% RULE
D6: ORG = | E6: ORG = | I6: Direct monthly rate | J6: Direct monthly rate
D7: AMD1 | E7: AMD1 | F7: AMD2 | G7: AMD2 | H7: AMD2 | I7: 9369.9806 | J7: 9369.9806 | W7: TOTAL COSTS
D8: BUDGET | E8: BUDGET | F8: REVISION | G8: REVISION | I8: REVISION | J8: REVISION | W8: Dir & Indir (EUR)
C9: Task/ | F9: TOTAL | G9: TOTAL | H9: COMMENT | I9: Personnel costs (DIRECT only) | J9: Personnel costs (DIRECT & INDIRECT) | W9: ACTUAL
C10: WP | D10: PM | E10: hours | F10: PMs | G10: Hours | I10: EUR | J10: EUR | U10: SCABERIA AS | V10: Task/ | W10: M1-M9
B11: Assessment of potential new value chains and selection of Topics for Call of Proposals | C11: WP1 | D11: =SUM(D12:D14) -> 1 | E11: =SUM(E12:E14) -> 143.33333 | F11: =SUM(F12:F14) -> 1.2 | G11: =F11*(1720/12) -> 172 | H11: plus 0.2 PM | I11: =SUM(I12:I14) -> 11243.976 | J11: =SUM(J12:J14) -> 14054.97 | V11: WP
B12: Sustainable challenges, needs and trends of four industrial offshore sectors | C12: T1.1 | D12: 0.5 | E12: =D12*1720/12 -> 71.666667 | F12: 0.6 | G12: =F12*(1720/12) -> 86 | H12: plus 0.1 PM | I12: =F12*9369.98 -> 5621.988 | J12: =I12*1.25 -> 7027.485 | U12: Assessment of potential new value chains and selection of Topics for Call of Proposals | V12: WP1 | W12: =SUM(W13:W15) -> 13497.165
B13: Assessment of emerging technology trends and solutions | C13: T1.2 | D13: 0.25 | E13: =D13*1720/12 -> 35.833333 | F13: 0.3 | G13: =F13*(1720/12) -> 43 | H13: plus 0.05 PM | I13: =F13*9369.98 -> 2810.994 | J13: =I13*1.25 -> 3513.7425 | U13: Sustainable challenges, needs and trends of four industrial offshore sectors | V13: T1.1 | W13: 6648.4552
B14: Potential new value chains and selection of Call Topics | C14: T1.3 | D14: 0.25 | E14: =D14*1720/12 -> 35.833333 | F14: 0.3 | G14: =F14*(1720/12) -> 43 | H14: plus 0.05 PM | I14: =F14*9369.98 -> 2810.994 | J14: =I14*1.25 -> 3513.7425 | U14: Assessment of emerging technology trends and solutions | V14: T1.2 | W14: 3484.4313
B15: Methodologies and tools for cross-sectoral/-border collaboration and technology transfer | C15: WP2 | D15: =SUM(D16:D19) -> 0.5 | E15: =SUM(E16:E19) -> 71.666667 | F15: =SUM( F16:F19) -> 0.4 | G15: =F15*(1720/12) -> 57.333333 | H15: minus 0.1 PM | I15: =SUM(I16:I19) -> 3747.992 | J15: =SUM(J16:J19) -> 4684.99 | U15: Potential new value chains and selection of Call Topics | V15: T1.3 | W15: 3364.2785
B16: Methologies and tools for cross-sectoral/-border collaboration and technology transfer | C16: T2.1 | D16: 0.25 | E16: =D16*1720/12 -> 35.833333 | F16: 0.1 | G16: =F16*(1720/12) -> 14.333333 | H16: minus 0.15 PM | I16: =F16*9369.98 -> 936.998 | J16: =I16*1.25 -> 1171.2475 | U16: Methodologies and tools for cross-sectoral/-border collaboration and technology transfer | V16: WP2 | W16: =SUM(W17:W20) -> 3123.9729
B17: Establishment of a Collaborative Virtual Environment | C17: T2.2 | D17: 0 | E17: =D17*1720/12 -> 0 | F17: 0.1 | G17: =F17*(1720/12) -> 14.333333 | H17: plus 0.1 PM | I17: =F17*9369.98 -> 936.998 | J17: =I17*1.25 -> 1171.2475 | U17: Methologies and tools for cross-sectoral/-border collaboration and technology transfer | V17: T2.1 | W17: 40.050935
B18: Establishment of a Survey tool | C18: T2.3 | D18: 0 | E18: =D18*1720/12 -> 0 | F18: 0.1 | G18: =F18*(1720/12) -> 14.333333 | H18: plus 0.1 PM | I18: =F18*9369.98 -> 936.998 | J18: =I18*1.25 -> 1171.2475 | U18: Establishment of a Collaborative Virtual Environment | V18: T2.2 | W18: 520.66216
B19: Establishment of the GreenOffshoreTech Cluster Collaboration Platform | C19: T2.4 | D19: 0.25 | E19: =D19*1720/12 -> 35.833333 | F19: 0.1 | G19: =F19*(1720/12) -> 14.333333 | H19: minus 0.15 PM | I19: =F19*9369.98 -> 936.998 | J19: =I19*1.25 -> 1171.2475 | U19: Establishment of a Survey tool | V19: T2.3 | W19: 1321.6809
B20: Direct financial support to SMEs through a competitive Call for Proposals | C20: WP3 | D20: =SUM(D21:D26) -> 4.5 | E20: =SUM(E21:E26) -> 645 | F20: =SUM(F21:F26) -> 4.2 | G20: =F20*(1720/12) -> 602 | H20: minus 0.3 PM | I20: =SUM(I21:I26) -> 39353.916 | J20: =SUM(J21:J26) -> 49192.395 | U20: Establishment of the GreenOffshoreTech Cluster Collaboration Platform | V20: T2.4 | W20: 1241.579
B21: Preparation of the Call for Proposals | C21: T3.1 | D21: 0.5 | E21: =D21*1720/12 -> 71.666667 | F21: 1 | G21: =F21*(1720/12) -> 143.33333 | H21: plus 0.5 PM (support with Call docs) | I21: =F21*9369.98 -> 9369.98 | J21: =I21*1.25 -> 11712.475 | U21: Direct financial support to SMEs through a competitive Call for Proposals | V21: WP3 | W21: =SUM(W22:W27) -> 11374.466
B22: Publication of the Call for Proposals and Proposal reception. | C22: T3.2 | D22: 0 | E22: =D22*1720/12 -> 0 | F22: 0.1 | G22: =F22*(1720/12) -> 14.333333 | H22: plus 0.1 PM (support with Call announcement doc) | I22: =F22*9369.98 -> 936.998 | J22: =I22*1.25 -> 1171.2475 | U22: Preparation of the Call for Proposals | V22: T3.1 | W22: 10613.498
B23: Evaluation and Selection of SMEs Proposals | C23: T3.3 | D23: 1 | E23: =D23*1720/12 -> 143.33333 | F23: 0.1 | G23: =F23*(1720/12) -> 14.333333 | H23: minus 0.9 PM: SCA cannot be evaluator due to conflict of intrest. | I23: =F23*9369.98 -> 936.998 | J23: =I23*1.25 -> 1171.2475 | U23: Publication of the Call for Proposals and Proposal reception. | V23: T3.2 | W23: 760.96777
B24: Contracting with winner SMEs Projects | C24: T3.4 | D24: 0 | E24: =D24*1720/12 -> 0 | F24: 0 | G24: =F24*(1720/12) -> 0 | H24: Ok. | I24: =F24*9369.98 -> 0 | J24: =I24*1.25 -> 0 | U24: Evaluation and Selection of SMEs Proposals | V24: T3.3 | W24: 0
B25: Payments and financial monitoring of winner SMEs Projects | C25: T3.5 | D25: 0 | E25: =D25*1720/12 -> 0 | F25: 0 | G25: =F25*(1720/12) -> 0 | H25: Ok. | I25: =F25*9369.98 -> 0 | J25: =I25*1.25 -> 0 | U25: Contracting with winner SMEs Projects | V25: T3.4 | W25: 0
B26: Technical monitoring of winner SMEs Projects | C26: T3.6 | D26: 3 | E26: =D26*1720/12 -> 430 | F26: 3 | G26: =F26*(1720/12) -> 430 | H26: Ok | I26: =F26*9369.98 -> 28109.94 | J26: =I26*1.25 -> 35137.425 | U26: Payments and financial monitoring of winner SMEs Projects | V26: T3.5 | W26: 0
B27: Business Support Services to winner SMEs | C27: WP4 | D27: =SUM(D28:D36) -> 12.75 | E27: =SUM(E28:E36) -> 1827.5 | F27: =SUM(F28:F36) -> 11.85 | G27: =F27*(1720/12) -> 1698.5 | H27: minus 0.9 PM (shift to WP7) | I27: =SUM(I28:I36) -> 111034.26 | J27: =SUM(J28:J36) -> 138792.83 | U27: Technical monitoring of winner SMEs Projects | V27: T3.6 | W27: 0
B28: Programme of Business Support Services to winner SMEs | C28: T4.1 | D28: 0 | E28: =D28*1720/12 -> 0 | F28: 0.2 | G28: =F28*(1720/12) -> 28.666667 | H28: plus 0.2 PM (input to definition of all BSSs) | I28: =F28*9369.98 -> 1873.996 | J28: =I28*1.25 -> 2342.495 | U28: Business Support Services to winner SMEs (preparation) | V28: WP4 | W28: =SUM(W29:W37) -> 2723.4636
B29: Business Support Service #1 Business & Tech Academy | C29: T4.2 | D29: 1 | E29: =D29*1720/12 -> 143.33333 | F29: 1 | G29: =F29*(1720/12) -> 143.33333 | H29: Ok. | I29: =F29*9369.98 -> 9369.98 | J29: =I29*1.25 -> 11712.475 | U29: Programme of Business Support Services to winner SMEs (prep) | V29: T4.1 | W29: 2403.0561
B30: Business Support Service #2 Brokerage & B2B matchmaking events | C30: T4.3 | D30: 0.5 | E30: =D30*1720/12 -> 71.666667 | F30: 0.1 | G30: =F30*(1720/12) -> 14.333333 | H30: minus 0.4 PM (virtual instead of F2F) | I30: =F30*9369.98 -> 936.998 | J30: =I30*1.25 -> 1171.2475 | U30: Business Support Service #1 Business & Tech Academy | V30: T4.2 | W30: 0
B31: Business Support Service #3 Access to Finance | C31: T4.4 | D31: 0 | E31: =D31*1720/12 -> 0 | F31: 0 | G31: =F31*(1720/12) -> 0 | H31: Ok. | I31: =F31*9369.98 -> 0 | J31: =I31*1.25 -> 0 | U31: Business Support Service #2 Brokerage & B2B matchmaking events | V31: T4.3 | W31: 0
B32: Business Support Service #4 One-to-One Mentoring and Coaching (prep + service) | C32: T4.5 | D32: 9.75 | E32: =D32*1720/12 -> 1397.5 | F32: 9.75 | G32: =F32*(1720/12) -> 1397.5 | H32: Ok. | I32: =F32*9369.98 -> 91357.305 | J32: =I32*1.25 -> 114196.63 | U32: Business Support Service #3 Access to Finance | V32: T4.4 | W32: 0
B33: Business Support Service #5 Branding | C33: T4.6 | D33: 0 | E33: =D33*1720/12 -> 0 | F33: 0 | G33: =F33*(1720/12) -> 0 | H33: Ok. | I33: =F33*9369.98 -> 0 | J33: =I33*1.25 -> 0 | U33: Business Support Service #4 One-to-One Mentoring and Coaching (prep) | V33: T4.5 | W33: 320.40748
B34: Business Support Service #6 Internationalisation | C34: T4.7 | D34: 0 | E34: =D34*1720/12 -> 0 | F34: 0 | G34: =F34*(1720/12) -> 0 | H34: Ok. | I34: =F34*9369.98 -> 0 | J34: =I34*1.25 -> 0 | U34: Business Support Service #5 Branding | V34: T4.6 | W34: 0
B35: Business Support Service #7 Investor pitching | C35: T4.8 | D35: 1 | E35: =D35*1720/12 -> 143.33333 | F35: 0.5 | G35: =F35*(1720/12) -> 71.666667 | H35: minus 0.5 PM | I35: =F35*9369.98 -> 4684.99 | J35: =I35*1.25 -> 5856.2375 | U35: Business Support Service #6 Internationalisation | V35: T4.7 | W35: 0
B36: Business Support Service #8 Investor rounds | C36: T4.9 | D36: 0.5 | E36: =D36*1720/12 -> 71.666667 | F36: 0.3 | G36: =F36*(1720/12) -> 43 | H36: minus 0.2 PM | I36: =F36*9369.98 -> 2810.994 | J36: =I36*1.25 -> 3513.7425 | U36: Business Support Service #7 Investor pitching | V36: T4.8 | W36: 0
B37: Large-scale Demonstrator (LSD) setup, validation, and impact assessment | C37: WP5 | D37: =SUM(D38:D40) -> 6 | E37: =SUM(E38:E40) -> 860 | F37: =SUM(F38:F40) -> 6 | G37: =F37*(1720/12) -> 860 | H37: OK, but internal shift. | I37: =SUM(I38:I40) -> 56219.88 | J37: =SUM(J38:J40) -> 70274.85 | U37: Business Support Service #8 Investor rounds | V37: T4.9 | W37: 0
B38: Set-up of the GreenOffshoreTech LSD in GreenOffshoreTech regions | C38: T5.1 | D38: 2.5 | E38: =D38*1720/12 -> 358.33333 | F38: 3 | G38: =F38*(1720/12) -> 430 | H38: plus 0.5 PM (from T5.3) | I38: =F38*9369.98 -> 28109.94 | J38: =I38*1.25 -> 35137.425 | U38: Large-scale Demonstrator (LSD) setup, validation, and impact assessment | V38: WP5 | W38: =SUM(W39:W41) -> 33402.48
B39: Validation & Impact assessment of GreenOffshoreTech LSD (data collection & analysis) | C39: T5.2 | D39: 2.5 | E39: =D39*1720/12 -> 358.33333 | F39: 2.5 | G39: =F39*(1720/12) -> 358.33333 | I39: =F39*9369.98 -> 23424.95 | J39: =I39*1.25 -> 29281.187 | U39: Set-up of the GreenOffshoreTech LSD in GreenOffshoreTech regions | V39: T5.1 | W39: 33402.48
B40: Guidelines of Best Practice to foster cross-sector/-border collaboration and technology transfer through Clusters | C40: T5.3 | D40: 1 | E40: =D40*1720/12 -> 143.33333 | F40: 0.5 | G40: =F40*(1720/12) -> 71.666667 | H40: minus 0.5 PM (no INNOSUP comparison) | I40: =F40*9369.98 -> 4684.99 | J40: =I40*1.25 -> 5856.2375 | U40: Validation & Impact assessment of GreenOffshoreTech LSD (data collection) | V40: T5.2 | W40: 0
B41: Communication, Dissemination, Exploitation & Sustainability | C41: WP6 | D41: =SUM(D42:D44) -> 1 | E41: =SUM(E42:E44) -> 143.33333 | F41: =SUM(F42:F44) -> 1 | G41: =F41*(1720/12) -> 143.33333 | H41: OK, but internal shift. | I41: =SUM(I42:I44) -> 9369.98 | J41: =SUM(J42:J44) -> 11712.475 | U41: Guidelines of Best Practice to foster cross-sector/-border collaboration and technology transfer through Clusters | V41: T5.3 | W41: 0
B42: Communication plan and Communication activities | C42: T6.1 | D42: 0 | E42: =D42*1720/12 -> 0 | F42: 0.4 | G42: =F42*(1720/12) -> 57.333333 | H42: plus 0.4 PM (support with first com kit) | I42: =F42*9369.98 -> 3747.992 | J42: =I42*1.25 -> 4684.99 | U42: Communication, Dissemination, Exploitation & Sustainability | V42: WP6 | W42: =SUM(W43:W45) -> 5847.4365
B43: Dissemination strategy and Dissemination activities | C43: T6.2 | D43: 0.5 | E43: =D43*1720/12 -> 71.666667 | F43: 0.3 | G43: =F43*(1720/12) -> 43 | H43: minus 0.2 PM (being SME less relevant) | I43: =F43*9369.98 -> 2810.994 | J43: =I43*1.25 -> 3513.7425 | U43: Communication plan and Communication activities | V43: T6.1 | W43: 4886.2141
B44: Exploitation strategy, IPR and Sustainability | C44: T6.3 | D44: 0.5 | E44: =D44*1720/12 -> 71.666667 | F44: 0.3 | G44: =F44*(1720/12) -> 43 | H44: minus 0.2 PM | I44: =F44*9369.98 -> 2810.994 | J44: =I44*1.25 -> 3513.7425 | U44: Dissemination strategy and Dissemination activities | V44: T6.2 | W44: 961.22244
B45: Project Management and Coordination | C45: WP7 | D45: =SUM(D46:D48) -> 0 | E45: =SUM(E46:E48) -> 0 | F45: =SUM(F46:F48) -> 1.1 | G45: =F45*(1720/12) -> 157.66667 | H45: plus 1.1 PM | I45: =SUM(I46:I48) -> 10306.978 | J45: =SUM(J46:J48) -> 12883.722 | U45: Exploitation strategy, IPR and Sustainability | V45: T6.3 | W45: 0
B46: Project coordination | C46: T7.1 | D46: 0 | E46: =D46*1720/12 -> 0 | F46: 0.5 | G46: =F46*(1720/12) -> 71.666667 | H46: plus 0.5 PM (participation GA meets) | I46: =F46*9369.98 -> 4684.99 | J46: =I46*1.25 -> 5856.2375 | U46: Project Management and Coordination | V46: WP7 | W46: =SUM(W47:W49) -> 1682.1393
B47: Project administration & Financial Management | C47: T7.2 | D47: 0 | E47: =D47*1720/12 -> 0 | F47: 0.5 | G47: =F47*(1720/12) -> 71.666667 | H47: plus 0.5 PM (cost statements, 75% prep) | I47: =F47*9369.98 -> 4684.99 | J47: =I47*1.25 -> 5856.2375 | U47: Project coordination | V47: T7.1 | W47: 240.30561
B48: Quality Assurance | C48: T7.3 | D48: 0 | E48: =D48*1720/12 -> 0 | F48: 0.1 | G48: =F48*(1720/12) -> 14.333333 | H48: plus 0.1 (review work) | I48: =F48*9369.98 -> 936.998 | J48: =I48*1.25 -> 1171.2475 | U48: Project administration & Financial Management | V48: T7.2 | W48: 720.91683
B49: NOTE: Key Tasks are marked light green | D49: =D11+D15+D20+D27+D37+D41+D45 -> 25.75 | E49: =E11+E15+E20+E27+E37+E41+E45 -> 3690.8333 | F49: =(F11+F15+F20+F27+F37+F41+F45) -> 25.75 | G49: =(G11+G15+G20+G27+G37+G41+G45) -> 3690.8333 | I49: =(I11+I15+I20+I27+I37+I41+I45) -> 241276.99 | J49: =(J11+J15+J20+J27+J37+J41+J45) -> 301596.23 | U49: Quality Assurance | V49: T7.3 | W49: 720.91683
W50: =SUM(W12+W16+W21+W28+W38+W42+W46) -> 71651.123

Sheet FOC
D2: TOTAL COSTS
D3: Indir & DIR (EUR)
D4: ACTUAL
B5: GreenOffshoreTech - FÓRUM OCEANO | C5: Task/ | D5: M1-M9
C6: WP
B7: Otherdirect Cost ( travel, equipment & Other goods and services)(ODC) | C7: ALL | D7: 0
B8: Assessment of potential new value chains and selection of Topics for Call of Proposals | C8: WP1 | D8: =SUM(D9:D11)*1.25 -> 1875.625
B9: Sustainable challenges, needs and trends of four industrial offshore sectors | C9: T1.1 | D9: 780.13
B10: Assessment of emerging technology trends and solutions | C10: T1.2 | D10: 194.2
B11: Potential new value chains and selection of Call Topics | C11: T1.3 | D11: 526.17
B12: Methodologies and tools for cross-sectoral/-border collaboration and technology transfer | C12: WP2 | D12: =SUM(D13:D16)*1.25 -> 174.2875
B13: Methologies and tools for cross-sectoral/-border collaboration and technology transfer | C13: T2.1 | D13: 0
B14: Establishment of a Collaborative Virtual Environment | C14: T2.2 | D14: 0
B15: Establishment of a Survey tool | C15: T2.3 | D15: 139.43
B16: Establishment of the GreenOffshoreTech Cluster Collaboration Platform | C16: T2.4 | D16: 0
B17: Direct financial support to SMEs through a competitive Call for Proposals | C17: WP3 | D17: =SUM(D18:D23)*1.25 -> 2002.375
B18: Preparation of the Call for Proposals | C18: T3.1 | D18: 1601.9
B19: Publication of the Call for Proposals and Proposal reception. | C19: T3.2 | D19: 0
B20: Evaluation and Selection of SMEs Proposals | C20: T3.3 | D20: 0
B21: Contracting with winner SMEs Projects | C21: T3.4 | D21: 0
B22: Payments and financial monitoring of winner SMEs Projects | C22: T3.5 | D22: 0
B23: Technical monitoring of winner SMEs Projects | C23: T3.6 | D23: 0
B24: Business Support Services to winner SMEs (preparation) | C24: WP4 | D24: =SUM(D25:D33)*1.25 -> 58.1
B25: Programme of Business Support Services to winner SMEs (prep) | C25: T4.1 | D25: 46.48
B26: Business Support Service #1 Business & Tech Academy | C26: T4.2 | D26: 0
B27: Business Support Service #2 Brokerage & B2B matchmaking events | C27: T4.3 | D27: 0
B28: Business Support Service #3 Access to Finance | C28: T4.4 | D28: 0
B29: Business Support Service #4 One-to-One Mentoring and Coaching (prep) | C29: T4.5 | D29: 0
B30: Business Support Service #5 Branding | C30: T4.6 | D30: 0
B31: Business Support Service #6 Internationalisation | C31: T4.7 | D31: 0
B32: Business Support Service #7 Investor pitching | C32: T4.8 | D32: 0
B33: Business Support Service #8 Investor rounds | C33: T4.9 | D33: 0
B34: Large-scale Demonstrator (LSD) setup, validation, and impact assessment | C34: WP5 | D34: =SUM(D35:D37)*1.25 -> 87.15
B35: Set-up of the GreenOffshoreTech LSD in GreenOffshoreTech regions | C35: T5.1 | D35: 69.72
B36: Validation & Impact assessment of GreenOffshoreTech LSD (data collection) | C36: T5.2 | D36: 0
B37: Guidelines of Best Practice to foster cross-sector/-border collaboration and technology transfer through Clusters | C37: T5.3 | D37: 0
B38: Communication, Dissemination, Exploitation & Sustainability | C38: WP6 | D38: =SUM(D39:D41)*1.25 -> 25103.862
B39: Communication plan and Communication activities | C39: T6.1 | D39: =9569.4+7278.1 -> 16847.5
B40: Dissemination strategy and Dissemination activities | C40: T6.2 | D40: =3235.59 -> 3235.59
B41: Exploitation strategy, IPR and Sustainability | C41: T6.3 | D41: 0
B42: Project Management and Coordination | C42: WP7 | D42: =SUM(D43:D45)*1.25 -> 0
B43: Project coordination | C43: T7.1 | D43: 0
B44: Project administration & Financial Management | C44: T7.2 | D44: 0
B45: Quality Assurance | C45: T7.3 | D45: 0
B46: TOTAL | D46: =D8+D12+D17+D24+D34+D38+D42 -> 29301.4
J51: AMD2 | K51: AMD2
J52: For BUDGET | K52: For 75% RULE
D53: ORG = | E53: ORG = | J53: Direct monthly rate | K53: Direct monthly rate
D54: AMD1 | E54: AMD1 | G54: AMD2 | H54: AMD2 | I54: AMD2 | J54: 3020 | K54: 3020 | M54: Confirmed rate
D55: BUDGET | E55: BUDGET | G55: REVISION | H55: REVISION | J55: REVISION | K55: REVISION
C56: Task/ | F56: Execution | G56: TOTAL | H56: TOTAL | I56: COMMENT | J56: Personnel costs (DIRECT only) | K56: Personnel costs (DIRECT & INDIRECT)
C57: WP | D57: PM | E57: hours | G57: PMs | H57: Hours | J57: EUR | K57: EUR
B58: Assessment of potential new value chains and selection of Topics for Call of Proposals | C58: WP1 | D58: 2.25 | E58: 322.5 | F58: 0.3279 | G58: 0.3279 | H58: 46.999 | J58: 990.258 | K58: 1237.8225
B59: Sustainable challenges, needs and trends of four industrial offshore sectors | C59: T1.1 | D59: 1 | E59: 143.33333 | F59: 0.1744 | G59: 0.1744 | H59: 24.997333 | J59: 526.688 | K59: 658.36
B60: Assessment of emerging technology trends and solutions | C60: T1.2 | D60: 0.25 | E60: 35.833333 | F60: 0.0419 | G60: 0.0419 | H60: 6.0056667 | J60: 126.538 | K60: 158.1725
B61: Potential new value chains and selection of Call Topics | C61: T1.3 | D61: 1 | E61: 143.33333 | F61: 0.1116 | G61: 0.1116 | H61: 15.996 | J61: 337.032 | K61: 421.29
B62: Methodologies and tools for cross-sectoral/-border collaboration and technology transfer | C62: WP2 | D62: 2.5 | E62: 358.33333 | F62: 0.0419 | G62: 1.5419 | H62: 221.00567 | J62: 4656.538 | K62: 5820.6725
B63: Methologies and tools for cross-sectoral/-border collaboration and technology transfer | C63: T2.1 | D63: 1.25 | E63: 179.16667 | G63: 1.25 | H63: 179.16667 | J63: 3775 | K63: 4718.75
B64: Establishment of a Collaborative Virtual Environment | C64: T2.2 | D64: 0 | E64: 0 | G64: 0 | H64: 0 | J64: 0 | K64: 0
B65: Establishment of a Survey tool | C65: T2.3 | D65: 1 | E65: 143.33333 | F65: 0.0419 | G65: 0.0419 | H65: 6.0056667 | J65: 126.538 | K65: 158.1725
B66: Establishment of the GreenOffshoreTech Cluster Collaboration Platform | C66: T2.4 | D66: 0.25 | E66: 35.833333 | G66: 0.25 | H66: 35.833333 | J66: 755 | K66: 943.75
B67: Direct financial support to SMEs through a competitive Call for Proposals | C67: WP3 | D67: 2.5 | E67: 358.33333 | F67: 0.5302 | G67: 2.6302 | H67: 376.99533 | J67: 7943.204 | K67: 9929.005
B68: Preparation of the Call for Proposals | C68: T3.1 | D68: 0.5 | E68: 71.666667 | F68: 0.5302 | G68: 0.5302 | H68: 75.995333 | J68: 1601.204 | K68: 2001.505
B69: Publication of the Call for Proposals and Proposal reception. | C69: T3.2 | D69: 0 | E69: 0 | G69: 0 | H69: 0 | J69: 0 | K69: 0
B70: Evaluation and Selection of SMEs Proposals | C70: T3.3 | D70: 1 | E70: 143.33333 | G70: 2 | H70: 286.66667 | J70: 6040 | K70: 7550
B71: Contracting with winner SMEs Projects | C71: T3.4 | D71: 0 | E71: 0 | G71: 0 | H71: 0 | J71: 0 | K71: 0
B72: Payments and financial monitoring of winner SMEs Projects | C72: T3.5 | D72: 0 | E72: 0 | G72: 0 | H72: 0 | J72: 0 | K72: 0
B73: Technical monitoring of winner SMEs Projects | C73: T3.6 | D73: 1 | E73: 143.33333 | G73: 0.1 | H73: 14.333333 | J73: 302 | K73: 377.5
B74: Business Support Services to winner SMEs | C74: WP4 | D74: 8.5 | E74: 1218.3333 | F74: 0.014 | G74: 6.25 | H74: 895.83333 | J74: 18875 | K74: 23593.75
B75: Programme of Business Support Services to winner SMEs | C75: T4.1 | D75: 0 | E75: 0 | F75: 0.014 | G75: 0.014 | H75: 2.0066667 | J75: 42.28 | K75: 52.85
B76: Business Support Service #1 Business & Tech Academy | C76: T4.2 | D76: 1 | E76: 143.33333 | G76: 0.3 | H76: 43 | J76: 906 | K76: 1132.5
B77: Business Support Service #2 Brokerage & B2B matchmaking events | C77: T4.3 | D77: 4 | E77: 573.33333 | G77: 2.236 | H77: 320.49333 | J77: 6752.72 | K77: 8440.9
B78: Business Support Service #3 Access to Finance | C78: T4.4 | D78: 0.5 | E78: 71.666667 | G78: 0.5 | H78: 71.666667 | J78: 1510 | K78: 1887.5
B79: Business Support Service #4 One-to-One Mentoring and Coaching (prep + service) | C79: T4.5 | D79: 0 | E79: 0 | G79: 0.2 | H79: 28.666667 | J79: 604 | K79: 755
B80: Business Support Service #5 Branding | C80: T4.6 | D80: 2 | E80: 286.66667 | G80: 2 | H80: 286.66667 | J80: 6040 | K80: 7550
B81: Business Support Service #6 Internationalisation | C81: T4.7 | D81: 0.5 | E81: 71.666667 | G81: 0.5 | H81: 71.666667 | J81: 1510 | K81: 1887.5
B82: Business Support Service #7 Investor pitching | C82: T4.8 | D82: 0 | E82: 0 | G82: 0 | H82: 0 | J82: 0 | K82: 0
B83: Business Support Service #8 Investor rounds | C83: T4.9 | D83: 0.5 | E83: 71.666667 | G83: 0.5 | H83: 71.666667 | J83: 1510 | K83: 1887.5
B84: Large-scale Demonstrator (LSD) setup, validation, and impact assessment | C84: WP5 | D84: 0.75 | E84: 107.5 | F84: 0.0209 | G84: 0.75 | H84: 107.5 | J84: 2265 | K84: 2831.25
B85: Set-up of the GreenOffshoreTech LSD in GreenOffshoreTech regions | C85: T5.1 | D85: 0.25 | E85: 35.833333 | F85: 0.0209 | G85: 0.25 | H85: 35.833333 | J85: 755 | K85: 943.75
B86: Validation & Impact assessment of GreenOffshoreTech LSD (data collection & analysis) | C86: T5.2 | D86: 0.25 | E86: 35.833333 | G86: 0.25 | H86: 35.833333 | J86: 755 | K86: 943.75
B87: Guidelines of Best Practice to foster cross-sector/-border collaboration and technology transfer through Clusters | C87: T5.3 | D87: 0.25 | E87: 35.833333 | G87: 0.25 | H87: 35.833333 | J87: 755 | K87: 943.75
B88: Communication, Dissemination, Exploitation & Sustainability | C88: WP6 | D88: 7.5 | E88: 1075 | F88: 3.5023 | G88: 10.5 | H88: 1505 | J88: 31710 | K88: 39637.5
B89: Communication plan and Communication activities | C89: T6.1 | D89: 4 | E89: 573.33333 | F89: 2.4837 | G89: 4 | H89: 573.33333 | J89: 12080 | K89: 15100
B90: Dissemination strategy and Dissemination activities | C90: T6.2 | D90: 3 | E90: 430 | F90: 1.0186 | G90: 6 | H90: 860 | J90: 18120 | K90: 22650
B91: Exploitation strategy, IPR and Sustainability | C91: T6.3 | D91: 0.5 | E91: 71.666667 | G91: 0.5 | H91: 71.666667 | J91: 1510 | K91: 1887.5
B92: Project Management and Coordination | C92: WP7 | D92: 0 | E92: 0 | F92: 0 | G92: 2 | H92: 286.66667 | J92: 6040 | K92: 7550
B93: Project coordination | C93: T7.1 | D93: 0 | E93: 0 | G93: 0.5 | H93: 71.666667 | J93: 1510 | K93: 1887.5
B94: Project administration & Financial Management | C94: T7.2 | D94: 0 | E94: 0 | G94: 1.4 | H94: 200.66667 | J94: 4228 | K94: 5285
B95: Quality Assurance | C95: T7.3 | D95: 0 | E95: 0 | G95: 0.1 | H95: 14.333333 | J95: 302 | K95: 377.5
B96: NOTE: Key Tasks are marked light green | D96: 24 | E96: 3440 | F96: 4.4372 | G96: 24 | H96: 3440 | J96: 72480 | K96: 90600

Sheet CLTV
C1: ORG = | D1: ORG = | H1: Direct monthly rate | I1: Direct monthly rate
C2: AMD1 | D2: AMD1 | E2: AMD2 | F2: AMD2 | G2: AMD2 | H2: 3750 | I2: 3750 | K2: Retrieved from budget | AO2: TOTAL COSTS | AQ2: TOTAL COSTS
C3: BUDGET | D3: BUDGET | E3: REVISION | F3: REVISION | H3: REVISION | I3: REVISION | AO3: DIR | AQ3: Indir & DIR
B4: Task/ | E4: TOTAL | F4: TOTAL | G4: COMMENT | H4: Personnel costs (DIRECT only) | I4: Personnel costs (DIRECT & INDIRECT) | AO4: ACTUAL | AQ4: ACTUAL
B5: WP | C5: PM | D5: hours | E5: PMs | F5: Hours | H5: EUR | I5: EUR | AM5: GreenOfshoreTech PARTNER NAME | AN5: Task/ | AO5: M1-M9 | AQ5: M1-M9
A6: Assessment of potential new value chains and selection of Topics for Call of Proposals | B6: WP1 | C6: =SUM(C7:C9) -> 2.25 | D6: =SUM(D7:D9) -> 322.5 | E6: =SUM(E7:E9) -> 1.716319 | F6: =E6*(1720/12) -> 246.00572 | G6: minus 0,53 PM ( shift to WP6) | H6: =SUM(H7:H9) -> 16081.875 | I6: =SUM(I7:I9) -> 20102.343 | AN6: WP
A7: Sustainable challenges, needs and trends of four industrial offshore sectors | B7: T1.1 | C7: 0.25 | D7: =C7*1720/12 -> 35.833333 | E7: =F7/143.33 -> 0.13953813 | F7: 20 | G7: minus 0,11 PM | H7: =E7*9369.98 -> 1307.4695 | I7: =H7*1.25 -> 1634.3368 | AM7: Otherdirect Cost ( travel, equipment & Other goods and services)(ODC) | AN7: ALL | AO7: 0 | AQ7: 0
A8: Assessment of emerging technology trends and solutions | B8: T1.2 | C8: 1 | D8: =C8*1720/12 -> 143.33333 | E8: =F8/143.33 -> 0.57908323 | F8: 83 | G8: pminus 0,42 PM | H8: =E8*9369.98 -> 5425.9983 | I8: =H8*1.25 -> 6782.4979 | AM8: Assessment of potential new value chains and selection of Topics for Call of Proposals | AN8: WP1 | AO8: =SUM(AO9:AO11) -> 5458.7342 | AQ8: =SUM(AQ9:AQ11) -> 6823.4177
A9: Potential new value chains and selection of Call Topics | B9: T1.3 | C9: 1 | D9: =C9*1720/12 -> 143.33333 | E9: =F9/143.33 -> 0.99769762 | F9: 143 | G9: ok | H9: =E9*9369.98 -> 9348.4068 | I9: =H9*1.25 -> 11685.508 | AM9: Sustainable challenges, needs and trends of four industrial offshore sectors | AN9: T1.1 | AO9: 406.94455 | AQ9: =SUM(AO9:AP9)*1.25 -> 508.68068
A10: Methodologies and tools for cross-sectoral/-border collaboration and technology transfer | B10: WP2 | C10: =SUM(C11:C14) -> 2.5 | D10: =SUM(D11:D14) -> 358.33333 | E10: =SUM( E11:E14) -> 2.5 | F10: =E10*(1720/12) -> 358.33333 | G10: ok | H10: =SUM(H11:H14) -> 23424.95 | I10: =SUM(I11:I14) -> 29281.188 | AM10: Assessment of emerging technology trends and solutions | AN10: T1.2 | AO10: 2033.141 | AQ10: =SUM(AO10:AP10)*1.25 -> 2541.4263
A11: Methologies and tools for cross-sectoral/-border collaboration and technology transfer | B11: T2.1 | C11: 1.25 | D11: =C11*1720/12 -> 179.16667 | E11: =C11 -> 1.25 | F11: =E11*(1720/12) -> 179.16667 | H11: =E11*9369.98 -> 11712.475 | I11: =H11*1.25 -> 14640.594 | AM11: Potential new value chains and selection of Call Topics | AN11: T1.3 | AO11: 3018.6486 | AQ11: =SUM(AO11:AP11)*1.25 -> 3773.3108
A12: Establishment of a Collaborative Virtual Environment | B12: T2.2 | C12: 0 | D12: =C12*1720/12 -> 0 | E12: =C12 -> 0 | F12: =E12*(1720/12) -> 0 | H12: =E12*9369.98 -> 0 | I12: =H12*1.25 -> 0 | AM12: Methodologies and tools for cross-sectoral/-border collaboration and technology transfer | AN12: WP2 | AO12: =SUM(AO13:AO15) -> 2969.5444 | AQ12: =SUM(AQ13:AQ15) -> 3711.9305
A13: Establishment of a Survey tool | B13: T2.3 | C13: 1 | D13: =C13*1720/12 -> 143.33333 | E13: =C13 -> 1 | F13: =E13*(1720/12) -> 143.33333 | H13: =E13*9369.98 -> 9369.98 | I13: =H13*1.25 -> 11712.475 | AM13: Methologies and tools for cross-sectoral/-border collaboration and technology transfer | AN13: T2.1 | AO13: 1453.0095 | AQ13: =SUM(AO13)*1.25 -> 1816.2619
A14: Establishment of the GreenOffshoreTech Cluster Collaboration Platform | B14: T2.4 | C14: 0.25 | D14: =C14*1720/12 -> 35.833333 | E14: =C14 -> 0.25 | F14: =E14*(1720/12) -> 35.833333 | H14: =E14*9369.98 -> 2342.495 | I14: =H14*1.25 -> 2928.1187 | AM14: Establishment of a Collaborative Virtual Environment | AN14: T2.2 | AO14: 0 | AQ14: =SUM(AO14)*1.25 -> 0
A15: Direct financial support to SMEs through a competitive Call for Proposals | B15: WP3 | C15: =SUM(C16:C21) -> 3.5 | D15: =SUM(D16:D21) -> 501.66667 | E15: =SUM(E16:E21) -> 3.5 | F15: =E15*(1720/12) -> 501.66667 | G15: ok | H15: =SUM(H16:H21) -> 32794.93 | I15: =SUM(I16:I21) -> 40993.662 | AM15: Establishment of a Survey tool | AN15: T2.3 | AO15: 1516.5348 | AQ15: =SUM(AO15)*1.25 -> 1895.6686
A16: Preparation of the Call for Proposals | B16: T3.1 | C16: 0.5 | D16: =C16*1720/12 -> 71.666667 | E16: =C16 -> 0.5 | F16: =E16*(1720/12) -> 71.666667 | H16: =E16*9369.98 -> 4684.99 | I16: =H16*1.25 -> 5856.2375 | AM16: Establishment of the GreenOffshoreTech Cluster Collaboration Platform | AN16: T2.4 | AO16: 199.31415 | AQ16: =SUM(AO16)*1.25 -> 249.14268
A17: Publication of the Call for Proposals and Proposal reception. | B17: T3.2 | C17: 0 | D17: =C17*1720/12 -> 0 | E17: =C17 -> 0 | F17: =E17*(1720/12) -> 0 | H17: =E17*9369.98 -> 0 | I17: =H17*1.25 -> 0 | AM17: Direct financial support to SMEs through a competitive Call for Proposals | AN17: WP3 | AO17: =SUM(AO18:AO20) -> 769.92837 | AQ17: =SUM(AQ18:AQ20) -> 962.41046
A18: Evaluation and Selection of SMEs Proposals | B18: T3.3 | C18: 1 | D18: =C18*1720/12 -> 143.33333 | E18: =C18 -> 1 | F18: =E18*(1720/12) -> 143.33333 | H18: =E18*9369.98 -> 9369.98 | I18: =H18*1.25 -> 11712.475 | AM18: Preparation of the Call for Proposals | AN18: T3.1 | AO18: 769.92837 | AQ18: =SUM(AO18)*1.25 -> 962.41046
A19: Contracting with winner SMEs Projects | B19: T3.4 | C19: 0 | D19: =C19*1720/12 -> 0 | E19: =C19 -> 0 | F19: =E19*(1720/12) -> 0 | H19: =E19*9369.98 -> 0 | I19: =H19*1.25 -> 0 | AM19: Publication of the Call for Proposals and Proposal reception. | AN19: T3.2 | AO19: 0 | AQ19: =SUM(AO19)*1.25 -> 0
A20: Payments and financial monitoring of winner SMEs Projects | B20: T3.5 | C20: 0 | D20: =C20*1720/12 -> 0 | E20: =C20 -> 0 | F20: =E20*(1720/12) -> 0 | H20: =E20*9369.98 -> 0 | I20: =H20*1.25 -> 0 | AM20: Evaluation and Selection of SMEs Proposals | AN20: T3.3 | AO20: 0 | AQ20: =SUM(AO20)*1.25 -> 0
A21: Technical monitoring of winner SMEs Projects | B21: T3.6 | C21: 2 | D21: =C21*1720/12 -> 286.66667 | E21: =C21 -> 2 | F21: =E21*(1720/12) -> 286.66667 | H21: =E21*9369.98 -> 18739.96 | I21: =H21*1.25 -> 23424.95 | AM21: Contracting with winner SMEs Projects | AN21: T3.4 | AO21: 0 | AQ21: =SUM(AO21)*1.25 -> 0
A22: Business Support Services to winner SMEs | B22: WP4 | C22: =SUM(C23:C31) -> 7 | D22: =SUM(D23:D31) -> 1003.3333 | E22: =SUM(E23:E31) -> 7 | F22: =E22*(1720/12) -> 1003.3333 | G22: ok | H22: =SUM(H23:H31) -> 65589.86 | I22: =SUM(I23:I31) -> 81987.325 | AM22: Payments and financial monitoring of winner SMEs Projects | AN22: T3.5 | AO22: 0 | AQ22: =SUM(AO22)*1.25 -> 0
A23: Programme of Business Support Services to winner SMEs | B23: T4.1 | C23: 0 | D23: =C23*1720/12 -> 0 | E23: =C23 -> 0 | F23: =E23*(1720/12) -> 0 | H23: =E23*9369.98 -> 0 | I23: =H23*1.25 -> 0 | AM23: Technical monitoring of winner SMEs Projects | AN23: T3.6 | AO23: 0 | AQ23: =SUM(AO23)*1.25 -> 0
A24: Business Support Service #1 Business & Tech Academy | B24: T4.2 | C24: 1 | D24: =C24*1720/12 -> 143.33333 | E24: =C24 -> 1 | F24: =E24*(1720/12) -> 143.33333 | H24: =E24*9369.98 -> 9369.98 | I24: =H24*1.25 -> 11712.475 | AM24: Business Support Services to winner SMEs (preparation) | AN24: WP4 | AO24: =SUM(AO25:AO33) -> 476.15575 | AQ24: =SUM(AQ25:AQ33) -> 595.19468
A25: Business Support Service #2 Brokerage & B2B matchmaking events | B25: T4.3 | C25: 0.5 | D25: =C25*1720/12 -> 71.666667 | E25: =C25 -> 0.5 | F25: =E25*(1720/12) -> 71.666667 | H25: =E25*9369.98 -> 4684.99 | I25: =H25*1.25 -> 5856.2375 | AM25: Programme of Business Support Services to winner SMEs (prep) | AN25: T4.1 | AO25: 0 | AQ25: =SUM(AO25)*1.25 -> 0
A26: Business Support Service #3 Access to Finance | B26: T4.4 | C26: 0.5 | D26: =C26*1720/12 -> 71.666667 | E26: =C26 -> 0.5 | F26: =E26*(1720/12) -> 71.666667 | H26: =E26*9369.98 -> 4684.99 | I26: =H26*1.25 -> 5856.2375 | AM26: Business Support Service #1 Business & Tech Academy | AN26: T4.2 | AO26: 0 | AQ26: =SUM(AO26)*1.25 -> 0
A27: Business Support Service #4 One-to-One Mentoring and Coaching (prep + service) | B27: T4.5 | C27: 0 | D27: =C27*1720/12 -> 0 | E27: =C27 -> 0 | F27: =E27*(1720/12) -> 0 | H27: =E27*9369.98 -> 0 | I27: =H27*1.25 -> 0 | AM27: Business Support Service #2 Brokerage & B2B matchmaking events | AN27: T4.3 | AO27: 0 | AQ27: =SUM(AO27)*1.25 -> 0
A28: Business Support Service #5 Branding | B28: T4.6 | C28: 0 | D28: =C28*1720/12 -> 0 | E28: =C28 -> 0 | F28: =E28*(1720/12) -> 0 | H28: =E28*9369.98 -> 0 | I28: =H28*1.25 -> 0 | AM28: Business Support Service #3 Access to Finance | AN28: T4.4 | AO28: 0 | AQ28: =SUM(AO28)*1.25 -> 0
A29: Business Support Service #6 Internationalisation | B29: T4.7 | C29: 0.5 | D29: =C29*1720/12 -> 71.666667 | E29: =C29 -> 0.5 | F29: =E29*(1720/12) -> 71.666667 | H29: =E29*9369.98 -> 4684.99 | I29: =H29*1.25 -> 5856.2375 | AM29: Business Support Service #4 One-to-One Mentoring and Coaching (prep) | AN29: T4.5 | AO29: 0 | AQ29: =SUM(AO29)*1.25 -> 0
A30: Business Support Service #7 Investor pitching | B30: T4.8 | C30: 4 | D30: =C30*1720/12 -> 573.33333 | E30: =C30 -> 4 | F30: =E30*(1720/12) -> 573.33333 | G30: We would like to add 8000 EUR to this (allocate money from our travel budget). Under this Task not only one persone will be working. The main thing is that one part is coordination, planning, but other thing is - planned staff who will be making B2B meeting, making plans to teach and educate SMEs about investor pitching. When we elaborated deliverable and description for this task, we understood that staff who could make quality training, that will be specially aimed to winner SME's, needs more hours for work. Work includes planning, communication with SMEs, B2B meetings, getting to understend SMEs and what they need and what they want. | H30: =E30*9369.98 -> 37479.92 | I30: =H30*1.25 -> 46849.9 | AM30: Business Support Service #5 Branding | AN30: T4.6 | AO30: 0 | AQ30: =SUM(AO30)*1.25 -> 0
A31: Business Support Service #8 Investor rounds | B31: T4.9 | C31: 0.5 | D31: =C31*1720/12 -> 71.666667 | E31: =C31 -> 0.5 | F31: =E31*(1720/12) -> 71.666667 | H31: =E31*9369.98 -> 4684.99 | I31: =H31*1.25 -> 5856.2375 | AM31: Business Support Service #6 Internationalisation | AN31: T4.7 | AO31: 0 | AQ31: =SUM(AO31)*1.25 -> 0
A32: Large-scale Demonstrator (LSD) setup, validation, and impact assessment | B32: WP5 | C32: =SUM(C33:C35) -> 0.75 | D32: =SUM(D33:D35) -> 107.5 | E32: =SUM(E33:E35) -> 0.75 | F32: =E32*(1720/12) -> 107.5 | G32: ok | H32: =SUM(H33:H35) -> 7027.485 | I32: =SUM(I33:I35) -> 8784.3562 | AM32: Business Support Service #7 Investor pitching | AN32: T4.8 | AO32: 476.15575 | AQ32: =SUM(AO32)*1.25 -> 595.19468
A33: Set-up of the GreenOffshoreTech LSD in GreenOffshoreTech regions | B33: T5.1 | C33: 0.25 | D33: =C33*1720/12 -> 35.833333 | E33: =C33 -> 0.25 | F33: =E33*(1720/12) -> 35.833333 | H33: =E33*9369.98 -> 2342.495 | I33: =H33*1.25 -> 2928.1187 | AM33: Business Support Service #8 Investor rounds | AN33: T4.9 | AO33: 0 | AQ33: =SUM(AO33)*1.25 -> 0
A34: Validation & Impact assessment of GreenOffshoreTech LSD (data collection & analysis) | B34: T5.2 | C34: 0.25 | D34: =C34*1720/12 -> 35.833333 | E34: =C34 -> 0.25 | F34: =E34*(1720/12) -> 35.833333 | H34: =E34*9369.98 -> 2342.495 | I34: =H34*1.25 -> 2928.1187 | AM34: Large-scale Demonstrator (LSD) setup, validation, and impact assessment | AN34: WP5 | AO34: =SUM(AO35:AO37) -> 560.07209 | AQ34: =SUM(AQ35:AQ37) -> 700.09011
A35: Guidelines of Best Practice to foster cross-sector/-border collaboration and technology transfer through Clusters | B35: T5.3 | C35: 0.25 | D35: =C35*1720/12 -> 35.833333 | E35: =C35 -> 0.25 | F35: =E35*(1720/12) -> 35.833333 | H35: =E35*9369.98 -> 2342.495 | I35: =H35*1.25 -> 2928.1187 | AM35: Set-up of the GreenOffshoreTech LSD in GreenOffshoreTech regions | AN35: T5.1 | AO35: 560.07209 | AQ35: =SUM(AO35)*1.25 -> 700.09011
A36: Communication, Dissemination, Exploitation & Sustainability | B36: WP6 | C36: =SUM(C37:C39) -> 2 | D36: =SUM(D37:D39) -> 286.66667 | E36: =SUM(E37:E39) -> 2.53 | F36: =E36*(1720/12) -> 362.63333 | G36: Plus 0,53 PM | H36: =SUM(H37:H39) -> 23706.049 | I36: =SUM(I37:I39) -> 29632.562 | AM36: Validation & Impact assessment of GreenOffshoreTech LSD (data collection) | AN36: T5.2 | AO36: 0 | AQ36: =SUM(AO36)*1.25 -> 0
A37: Communication plan and Communication activities | B37: T6.1 | C37: 0.5 | D37: =C37*1720/12 -> 71.666667 | E37: 0.85 | F37: =E37*(1720/12) -> 121.83333 | G37: plus 0.35 PM | H37: =E37*9369.98 -> 7964.483 | I37: =H37*1.25 -> 9955.6037 | AM37: Guidelines of Best Practice to foster cross-sector/-border collaboration and technology transfer through Clusters | AN37: T5.3 | AO37: 0 | AQ37: =SUM(AO37)*1.25 -> 0
A38: Dissemination strategy and Dissemination activities | B38: T6.2 | C38: 1 | D38: =C38*1720/12 -> 143.33333 | E38: 1.18 | F38: =E38*(1720/12) -> 169.13333 | G38: plus 0.18 PM | H38: =E38*9369.98 -> 11056.576 | I38: =H38*1.25 -> 13820.72 | AM38: Communication, Dissemination, Exploitation & Sustainability | AN38: WP6 | AO38: =SUM(AO39:AO41) -> 2670.2063 | AQ38: =SUM(AQ39:AQ41) -> 3337.7579
A39: Exploitation strategy, IPR and Sustainability | B39: T6.3 | C39: 0.5 | D39: =C39*1720/12 -> 71.666667 | E39: 0.5 | F39: =E39*(1720/12) -> 71.666667 | G39: ok | H39: =E39*9369.98 -> 4684.99 | I39: =H39*1.25 -> 5856.2375 | AM39: Communication plan and Communication activities | AN39: T6.1 | AO39: 367.39575 | AQ39: =SUM(AO39)*1.25 -> 459.24468
A40: Project Management and Coordination | B40: WP7 | C40: =SUM(C41:C43) -> 0 | D40: =SUM(D41:D43) -> 0 | E40: =SUM(E41:E43) -> 0 | F40: =E40*(1720/12) -> 0 | G40: ok | H40: =SUM(H41:H43) -> 0 | I40: =SUM(I41:I43) -> 0 | AM40: Dissemination strategy and Dissemination activities | AN40: T6.2 | AO40: 2302.8105 | AQ40: =SUM(AO40)*1.25 -> 2878.5132
A41: Project coordination | B41: T7.1 | C41: 0 | D41: =C41*1720/12 -> 0 | E41: =C41 -> 0 | F41: =E41*(1720/12) -> 0 | H41: =E41*9369.98 -> 0 | I41: =H41*1.25 -> 0 | AM41: Exploitation strategy, IPR and Sustainability | AN41: T6.3 | AO41: 0 | AQ41: =SUM(AO41)*1.25 -> 0
A42: Project administration & Financial Management | B42: T7.2 | C42: 0 | D42: =C42*1720/12 -> 0 | E42: =C42 -> 0 | F42: =E42*(1720/12) -> 0 | H42: =E42*9369.98 -> 0 | I42: =H42*1.25 -> 0 | AM42: Project Management and Coordination | AN42: WP7 | AO42: =SUM(AO43:AO45) -> 0 | AQ42: =SUM(AQ43:AQ45) -> 0
A43: Quality Assurance | B43: T7.3 | C43: 0 | D43: =C43*1720/12 -> 0 | E43: =C43 -> 0 | F43: =E43*(1720/12) -> 0 | H43: =E43*9369.98 -> 0 | I43: =H43*1.25 -> 0 | AM43: Project coordination | AN43: T7.1 | AO43: 0 | AQ43: =SUM(AO43)*1.25 -> 0
A44: NOTE: Key Tasks to be marked light green | C44: =C6+C10+C15+C22+C32+C36+C40 -> 18 | D44: =D6+D10+D15+D22+D32+D36+D40 -> 2580 | E44: =(E6+E10+E15+E22+E32+E36+E40) -> 17.996319 | F44: =(F6+F10+F15+F22+F32+F36+F40) -> 2579.4724 | H44: =(H6+H10+H15+H22+H32+H36+H40) -> 168625.15 | I44: =(I6+I10+I15+I22+I32+I36+I40) -> 210781.44 | AM44: Project administration & Financial Management | AN44: T7.2 | AO44: 0 | AQ44: =SUM(AO44)*1.25 -> 0
AM45: Quality Assurance | AN45: T7.3 | AO45: 0 | AQ45: =SUM(AO45)*1.25 -> 0
AM46: TOTAL | AO46: =SUM(AO8+AO12+AO17+AO24+AO34+AO38+AO42) -> 12904.641 | AQ46: =SUM(AQ8+AQ12+AQ17+AQ24+AQ34+AQ38+AQ42) -> 16130.801

Sheet MAI
R1: TOTAL COSTS
H2: AMD2 | I2: AMD2 | X2: 1.25
H3: For BUDGET | I3: For 75% RULE | W3: INCLDING IND COST
C4: ORG = | D4: ORG = | H4: Direct monthly rate | I4: Direct monthly rate
C5: AMD1 | D5: AMD1 | E5: AMD2 | F5: AMD2 | G5: AMD2 | H5: 8500 | I5: 8500 | K5: Confirmed rate | T5: TOTAL COSTS
C6: BUDGET | D6: BUDGET | E6: REVISION | F6: REVISION | H6: REVISION | I6: REVISION | T6: Dir & Indir (EUR)
B7: Task/ | E7: TOTAL | F7: TOTAL | G7: COMMENT | H7: Personnel costs (DIRECT only) | I7: Personnel costs (DIRECT & INDIRECT) | T7: ACTUAL
B8: WP | C8: PM | D8: hours | E8: PMs | F8: Hours | H8: EUR | I8: EUR | R8: MAI Carbon | S8: Task/ | T8: M1-M8 | V8: DELIVERABLE
A9: Assessment of potential new value chains and selection of Topics for Call of Proposals | B9: WP1 | C9: =SUM(C10:C12) -> 3.25 | D9: =SUM(D10:D12) -> 465.83333 | E9: =SUM(E10:E12) -> 1.2 | F9: =E9*(1720/12) -> 172 | G9: plus 0.2 PM | H9: =SUM(H10:H12) -> 10200 | I9: =SUM(I10:I12) -> 12750 | S9: WP | V9: D7.5
A10: Sustainable challenges, needs and trends of four industrial offshore sectors | B10: T1.1 | C10: 0.25 | D10: =C10*1720/12 -> 35.833333 | E10: 0.1 | F10: =E10*(1720/12) -> 14.333333 | G10: plus 0.1 PM | H10: =E10*$H$5 -> 850 | I10: =H10*1.25 -> 1062.5 | R10: Assessment of potential new value chains and selection of Topics for Call of Proposals | S10: WP1 | T10: =SUM(T11:T13)*1.25 -> 12627.337 | V10: SECTION 4 | X10: =SUM(X11:X13) -> 12627.337
A11: Assessment of emerging technology trends and solutions | B11: T1.2 | C11: 1 | D11: =C11*1720/12 -> 143.33333 | E11: 0.6 | F11: =E11*(1720/12) -> 86 | G11: plus 0.05 PM | H11: =E11*$H$5 -> 5100 | I11: =H11*1.25 -> 6375 | R11: Sustainable challenges, needs and trends of four industrial offshore sectors | S11: T1.1 | T11: 0 | V11: SECTION 4 | X11: =T11*$X$2 -> 0
A12: Potential new value chains and selection of Call Topics | B12: T1.3 | C12: 2 | D12: =C12*1720/12 -> 286.66667 | E12: 0.5 | F12: =E12*(1720/12) -> 71.666667 | G12: plus 0.05 PM | H12: =E12*$H$5 -> 4250 | I12: =H12*1.25 -> 5312.5 | R12: Assessment of emerging technology trends and solutions | S12: T1.2 | T12: =4056.67 -> 4056.67 | V12: SECTION 4 | X12: =T12*$X$2 -> 5070.8375
A13: Methodologies and tools for cross-sectoral/-border collaboration and technology transfer | B13: WP2 | C13: =SUM(C14:C17) -> 0.5 | D13: =SUM(D14:D17) -> 71.666667 | E13: =SUM( E14:E17) -> 0.5 | F13: =E13*(1720/12) -> 71.666667 | G13: minus 0.1 PM | H13: =SUM(H14:H17) -> 4250 | I13: =SUM(I14:I17) -> 5312.5 | R13: Potential new value chains and selection of Call Topics | S13: T1.3 | T13: =6045.2 -> 6045.2 | V13: SECTION 4 | X13: =T13*$X$2 -> 7556.5
A14: Methologies and tools for cross-sectoral/-border collaboration and technology transfer | B14: T2.1 | C14: 0.25 | D14: =C14*1720/12 -> 35.833333 | E14: 0.25 | F14: =E14*(1720/12) -> 35.833333 | G14: no Change | H14: =E14*$H$5 -> 2125 | I14: =H14*1.25 -> 2656.25 | R14: Methodologies and tools for cross-sectoral/-border collaboration and technology transfer | S14: WP2 | T14: 0 | V14: SECTION 4 | X14: =SUM(X15:X18) -> 0
A15: Establishment of a Collaborative Virtual Environment | B15: T2.2 | C15: 0 | D15: =C15*1720/12 -> 0 | E15: 0 | F15: =E15*(1720/12) -> 0 | G15: no Change | H15: =E15*$H$5 -> 0 | I15: =H15*1.25 -> 0 | R15: Methologies and tools for cross-sectoral/-border collaboration and technology transfer | S15: T2.1 | T15: 0 | V15: SECTION 4 | X15: =T15*$X$2 -> 0
A16: Establishment of a Survey tool | B16: T2.3 | C16: 0 | D16: =C16*1720/12 -> 0 | E16: 0 | F16: =E16*(1720/12) -> 0 | G16: no Change | H16: =E16*$H$5 -> 0 | I16: =H16*1.25 -> 0 | R16: Establishment of a Collaborative Virtual Environment | S16: T2.2 | T16: 0 | V16: SECTION 4 | X16: =T16*$X$2 -> 0
A17: Establishment of the GreenOffshoreTech Cluster Collaboration Platform | B17: T2.4 | C17: 0.25 | D17: =C17*1720/12 -> 35.833333 | E17: 0.25 | F17: =E17*(1720/12) -> 35.833333 | G17: no Change | H17: =E17*$H$5 -> 2125 | I17: =H17*1.25 -> 2656.25 | R17: Establishment of a Survey tool | S17: T2.3 | T17: 0 | V17: SECTION 4 | X17: =T17*$X$2 -> 0
A18: Direct financial support to SMEs through a competitive Call for Proposals | B18: WP3 | C18: =SUM(C19:C24) -> 3.5 | D18: =SUM(D19:D24) -> 501.66667 | E18: =SUM(E19:E24) -> 3.5 | F18: =E18*(1720/12) -> 501.66667 | G18: minus 0.3 PM | H18: =SUM(H19:H24) -> 29750 | I18: =SUM(I19:I24) -> 37187.5 | R18: Establishment of the GreenOffshoreTech Cluster Collaboration Platform | S18: T2.4 | T18: 0 | V18: SECTION 4 | X18: =T18*$X$2 -> 0
A19: Preparation of the Call for Proposals | B19: T3.1 | C19: 0.5 | D19: =C19*1720/12 -> 71.666667 | E19: 0.5 | F19: =E19*(1720/12) -> 71.666667 | G19: no Change | H19: =E19*$H$5 -> 4250 | I19: =H19*1.25 -> 5312.5 | R19: Direct financial support to SMEs through a competitive Call for Proposals | S19: WP3 | T19: 0 | V19: SECTION 4 | X19: =SUM(X20:X25) -> 0
A20: Publication of the Call for Proposals and Proposal reception. | B20: T3.2 | C20: 0 | D20: =C20*1720/12 -> 0 | E20: 0 | F20: =E20*(1720/12) -> 0 | G20: no Change | H20: =E20*$H$5 -> 0 | I20: =H20*1.25 -> 0 | R20: Preparation of the Call for Proposals | S20: T3.1 | T20: 0 | V20: SECTION 4 | X20: =T20*$X$2 -> 0
A21: Evaluation and Selection of SMEs Proposals | B21: T3.3 | C21: 1 | D21: =C21*1720/12 -> 143.33333 | E21: 1 | F21: =E21*(1720/12) -> 143.33333 | G21: no Change | H21: =E21*$H$5 -> 8500 | I21: =H21*1.25 -> 10625 | R21: Publication of the Call for Proposals and Proposal reception. | S21: T3.2 | T21: 0 | V21: SECTION 4 | X21: =T21*$X$2 -> 0
A22: Contracting with winner SMEs Projects | B22: T3.4 | C22: 0 | D22: =C22*1720/12 -> 0 | E22: 0 | F22: =E22*(1720/12) -> 0 | G22: no Change | H22: =E22*$H$5 -> 0 | I22: =H22*1.25 -> 0 | R22: Evaluation and Selection of SMEs Proposals | S22: T3.3 | T22: 0 | V22: SECTION 4 | X22: =T22*$X$2 -> 0
A23: Payments and financial monitoring of winner SMEs Projects | B23: T3.5 | C23: 0 | D23: =C23*1720/12 -> 0 | E23: 0 | F23: =E23*(1720/12) -> 0 | G23: no Change | H23: =E23*$H$5 -> 0 | I23: =H23*1.25 -> 0 | R23: Contracting with winner SMEs Projects | S23: T3.4 | T23: 0 | V23: SECTION 4 | X23: =T23*$X$2 -> 0 | AB23: WP1 | AC23: =SUM(T10) -> 12627.337
A24: Technical monitoring of winner SMEs Projects | B24: T3.6 | C24: 2 | D24: =C24*1720/12 -> 286.66667 | E24: 2 | F24: =E24*(1720/12) -> 286.66667 | G24: no Change | H24: =E24*$H$5 -> 17000 | I24: =H24*1.25 -> 21250 | R24: Payments and financial monitoring of winner SMEs Projects | S24: T3.5 | T24: 0 | V24: SECTION 4 | X24: =T24*$X$2 -> 0 | AB24: WP2 | AC24: =SUM(T14) -> 0
A25: Business Support Services to winner SMEs | B25: WP4 | C25: =SUM(C26:C34) -> 8 | D25: =SUM(D26:D34) -> 1146.6667 | E25: =SUM(E26:E34) -> 8 | F25: =E25*(1720/12) -> 1146.6667 | G25: minus 0.9 PM (shift to WP7) | H25: =SUM(H26:H34) -> 68000 | I25: =SUM(I26:I34) -> 85000 | R25: Technical monitoring of winner SMEs Projects | S25: T3.6 | T25: 0 | V25: SECTION 4 | X25: =T25*$X$2 -> 0 | AB25: WP3 | AC25: =SUM(T19) -> 0
A26: Programme of Business Support Services to winner SMEs | B26: T4.1 | C26: 2.5 | D26: =C26*1720/12 -> 358.33333 | E26: 2.5 | F26: =E26*(1720/12) -> 358.33333 | G26: no Change | H26: =E26*$H$5 -> 21250 | I26: =H26*1.25 -> 26562.5 | R26: Business Support Services to winner SMEs (preparation) | S26: WP4 | T26: =SUM(T27:U35)*1.25 -> 4120.2875 | V26: SECTION 4 | X26: =SUM(X27:X35) -> 4120.2875 | AB26: WP4 | AC26: =SUM(T26) -> 4120.2875
A27: Business Support Service #1 Business & Tech Academy | B27: T4.2 | C27: 3 | D27: =C27*1720/12 -> 430 | E27: 3 | F27: =E27*(1720/12) -> 430 | G27: no Change | H27: =E27*$H$5 -> 25500 | I27: =H27*1.25 -> 31875 | R27: Programme of Business Support Services to winner SMEs (prep) | S27: T4.1 | T27: =3296.23 -> 3296.23 | V27: SECTION 4 | X27: =T27*$X$2 -> 4120.2875 | AB27: WP5 | AC27: =SUM(T36) -> 0
A28: Business Support Service #2 Brokerage & B2B matchmaking events | B28: T4.3 | C28: 1 | D28: =C28*1720/12 -> 143.33333 | E28: 1 | F28: =E28*(1720/12) -> 143.33333 | G28: no Change | H28: =E28*$H$5 -> 8500 | I28: =H28*1.25 -> 10625 | R28: Business Support Service #1 Business & Tech Academy | S28: T4.2 | T28: 0 | V28: SECTION 4 | X28: =T28*$X$2 -> 0 | AB28: WP6 | AC28: =SUM(T40) -> 4596
A29: Business Support Service #3 Access to Finance | B29: T4.4 | C29: 0.5 | D29: =C29*1720/12 -> 71.666667 | E29: 0.5 | F29: =E29*(1720/12) -> 71.666667 | G29: no Change | H29: =E29*$H$5 -> 4250 | I29: =H29*1.25 -> 5312.5 | R29: Business Support Service #2 Brokerage & B2B matchmaking events | S29: T4.3 | T29: 0 | V29: SECTION 4 | X29: =T29*$X$2 -> 0 | AB29: WP7 | AC29: =SUM(T44) -> 0
A30: Business Support Service #4 One-to-One Mentoring and Coaching (prep + service) | B30: T4.5 | C30: 0 | D30: =C30*1720/12 -> 0 | E30: 0 | F30: =E30*(1720/12) -> 0 | G30: no Change | H30: =E30*$H$5 -> 0 | I30: =H30*1.25 -> 0 | R30: Business Support Service #3 Access to Finance | S30: T4.4 | T30: 0 | V30: SECTION 4 | X30: =T30*$X$2 -> 0
A31: Business Support Service #5 Branding | B31: T4.6 | C31: 0 | D31: =C31*1720/12 -> 0 | E31: 0 | F31: =E31*(1720/12) -> 0 | G31: no Change | H31: =E31*$H$5 -> 0 | I31: =H31*1.25 -> 0 | R31: Business Support Service #4 One-to-One Mentoring and Coaching (prep) | S31: T4.5 | T31: 0 | V31: SECTION 4 | X31: =T31*$X$2 -> 0
A32: Business Support Service #6 Internationalisation | B32: T4.7 | C32: 0.5 | D32: =C32*1720/12 -> 71.666667 | E32: 0.5 | F32: =E32*(1720/12) -> 71.666667 | G32: no Change | H32: =E32*$H$5 -> 4250 | I32: =H32*1.25 -> 5312.5 | R32: Business Support Service #5 Branding | S32: T4.6 | T32: 0 | V32: SECTION 4 | X32: =T32*$X$2 -> 0
A33: Business Support Service #7 Investor pitching | B33: T4.8 | C33: 0 | D33: =C33*1720/12 -> 0 | E33: 0 | F33: =E33*(1720/12) -> 0 | G33: no Change | H33: =E33*$H$5 -> 0 | I33: =H33*1.25 -> 0 | R33: Business Support Service #6 Internationalisation | S33: T4.7 | T33: 0 | V33: SECTION 4 | X33: =T33*$X$2 -> 0
A34: Business Support Service #8 Investor rounds | B34: T4.9 | C34: 0.5 | D34: =C34*1720/12 -> 71.666667 | E34: 0.5 | F34: =E34*(1720/12) -> 71.666667 | G34: no Change | H34: =E34*$H$5 -> 4250 | I34: =H34*1.25 -> 5312.5 | R34: Business Support Service #7 Investor pitching | S34: T4.8 | T34: 0 | V34: SECTION 4 | X34: =T34*$X$2 -> 0
A35: Large-scale Demonstrator (LSD) setup, validation, and impact assessment | B35: WP5 | C35: =SUM(C36:C38) -> 0.75 | D35: =SUM(D36:D38) -> 107.5 | E35: =SUM(E36:E38) -> 0.75 | F35: =E35*(1720/12) -> 107.5 | G35: OK, but internal shift. | H35: =SUM(H36:H38) -> 6375 | I35: =SUM(I36:I38) -> 7968.75 | R35: Business Support Service #8 Investor rounds | S35: T4.9 | T35: 0 | V35: SECTION 4 | X35: =T35*$X$2 -> 0
A36: Set-up of the GreenOffshoreTech LSD in GreenOffshoreTech regions | B36: T5.1 | C36: 0.25 | D36: =C36*1720/12 -> 35.833333 | E36: 0.25 | F36: =E36*(1720/12) -> 35.833333 | G36: no Change | H36: =E36*$H$5 -> 2125 | I36: =H36*1.25 -> 2656.25 | R36: Large-scale Demonstrator (LSD) setup, validation, and impact assessment | S36: WP5 | T36: 0 | V36: SECTION 4 | X36: =SUM(X37:X39) -> 0
A37: Validation & Impact assessment of GreenOffshoreTech LSD (data collection & analysis) | B37: T5.2 | C37: 0.25 | D37: =C37*1720/12 -> 35.833333 | E37: 0.25 | F37: =E37*(1720/12) -> 35.833333 | G37: no Change | H37: =E37*$H$5 -> 2125 | I37: =H37*1.25 -> 2656.25 | R37: Set-up of the GreenOffshoreTech LSD in GreenOffshoreTech regions | S37: T5.1 | T37: 0 | V37: SECTION 4 | X37: =T37*$X$2 -> 0
A38: Guidelines of Best Practice to foster cross-sector/-border collaboration and technology transfer through Clusters | B38: T5.3 | C38: 0.25 | D38: =C38*1720/12 -> 35.833333 | E38: 0.25 | F38: =E38*(1720/12) -> 35.833333 | G38: no Change | H38: =E38*$H$5 -> 2125 | I38: =H38*1.25 -> 2656.25 | R38: Validation & Impact assessment of GreenOffshoreTech LSD (data collection) | S38: T5.2 | T38: 0 | V38: SECTION 4 | X38: =T38*$X$2 -> 0
A39: Communication, Dissemination, Exploitation & Sustainability | B39: WP6 | C39: =SUM(C40:C42) -> 3 | D39: =SUM(D40:D42) -> 430 | E39: =SUM(E40:E42) -> 3 | F39: =E39*(1720/12) -> 430 | G39: OK, but internal shift. | H39: =SUM(H40:H42) -> 25500 | I39: =SUM(I40:I42) -> 31875 | R39: Guidelines of Best Practice to foster cross-sector/-border collaboration and technology transfer through Clusters | S39: T5.3 | T39: 0 | V39: SECTION 4 | X39: =T39*$X$2 -> 0
A40: Communication plan and Communication activities | B40: T6.1 | C40: 0.5 | D40: =C40*1720/12 -> 71.666667 | E40: 0.5 | F40: =E40*(1720/12) -> 71.666667 | G40: no Change | H40: =E40*$H$5 -> 4250 | I40: =H40*1.25 -> 5312.5 | R40: Communication, Dissemination, Exploitation & Sustainability | S40: WP6 | T40: =SUM(T41:T43)*1.25 -> 4596 | V40: SECTION 5 | X40: =SUM(X41:X43) -> 4596
A41: Dissemination strategy and Dissemination activities | B41: T6.2 | C41: 1 | D41: =C41*1720/12 -> 143.33333 | E41: 1 | F41: =E41*(1720/12) -> 143.33333 | G41: no Change | H41: =E41*$H$5 -> 8500 | I41: =H41*1.25 -> 10625 | R41: Communication plan and Communication activities | S41: T6.1 | T41: =3676.8 -> 3676.8 | V41: SECTION 5 | X41: =T41*$X$2 -> 4596
A42: Exploitation strategy, IPR and Sustainability | B42: T6.3 | C42: 1.5 | D42: =C42*1720/12 -> 215 | E42: 1.5 | F42: =E42*(1720/12) -> 215 | G42: no Change | H42: =E42*$H$5 -> 12750 | I42: =H42*1.25 -> 15937.5 | R42: Dissemination strategy and Dissemination activities | S42: T6.2 | T42: 0 | V42: SECTION 5 | X42: =T42*$X$2 -> 0
A43: Project Management and Coordination | B43: WP7 | C43: =SUM(C44:C46) -> 0 | D43: =SUM(D44:D46) -> 0 | E43: =SUM(E44:E46) -> 2.05 | F43: =E43*(1720/12) -> 293.83333 | G43: plus 1.1 PM | H43: =SUM(H44:H46) -> 17425 | I43: =SUM(I44:I46) -> 21781.25 | R43: Exploitation strategy, IPR and Sustainability | S43: T6.3 | T43: 0 | V43: SECTION 5 | X43: =T43*$X$2 -> 0
A44: Project coordination | B44: T7.1 | C44: 0 | D44: =C44*1720/12 -> 0 | E44: 1.05 | F44: =E44*(1720/12) -> 150.5 | G44: plus 1,05 PM (participation GA meets) | H44: =E44*$H$5 -> 8925 | I44: =H44*1.25 -> 11156.25 | R44: Project Management and Coordination | S44: WP7 | T44: 0 | V44: SECTION 5 | X44: =SUM(X45:X47) -> 0
A45: Project administration & Financial Management | B45: T7.2 | C45: 0 | D45: =C45*1720/12 -> 0 | E45: 1 | F45: =E45*(1720/12) -> 143.33333 | G45: plus 1 PM (cost statements) | H45: =E45*$H$5 -> 8500 | I45: =H45*1.25 -> 10625 | R45: Project coordination | S45: T7.1 | T45: 0 | V45: SECTION 5 | X45: =T45*$X$2 -> 0
A46: Quality Assurance | B46: T7.3 | C46: 0 | D46: =C46*1720/12 -> 0 | E46: 0 | F46: =E46*(1720/12) -> 0 | H46: =E46*$H$5 -> 0 | I46: =H46*1.25 -> 0 | R46: Project administration & Financial Management | S46: T7.2 | T46: 0 | V46: SECTION 5 | X46: =T46*$X$2 -> 0
A47: NOTE: Key Tasks to be marked light green | C47: =C9+C13+C18+C25+C35+C39+C43 -> 19 | D47: =D9+D13+D18+D25+D35+D39+D43 -> 2723.3333 | E47: =(E9+E13+E18+E25+E35+E39+E43) -> 19 | F47: =(F9+F13+F18+F25+F35+F39+F43) -> 2723.3333 | H47: =(H9+H13+H18+H25+H35+H39+H43) -> 161500 | I47: =(I9+I13+I18+I25+I35+I39+I43) -> 201875 | R47: Quality Assurance | S47: T7.3 | T47: 0 | V47: SECTION 5 | X47: =T47*$X$2 -> 0
R48: TOTAL | T48: =SUM(T10+T14+T19+T26+T36+T40+T44) -> 21343.625 | X48: =SUM(T48) -> 21343.625

Sheet BIN
S2: TOTAL COSTS
H3: AMD2 | I3: AMD2 | S3: Dir & Indir (EUR) | U3: Ind. Costs flat rate
H4: For BUDGET | I4: For 75% RULE | S4: ACTUAL | U4: Project manager | W4: Assistant
C5: ORG = | D5: ORG = | H5: Direct monthly rate | I5: Direct monthly rate | Q5: GreenOfshoreTech BIN (Periode1, 09/21-06/22) | R5: Task/ | S5: M1-M9 | U5: hrs | V5: Salery rate | W5: hrs | X5: Salery rate
C6: AMD1 | D6: AMD1 | E6: AMD2 | F6: AMD2 | G6: AMD2 | H6: 8600 | I6: 8600 | K6: Estimated to 60 EURO per hour | R6: WP | V6: 65.35 | X6: 50.11
C7: BUDGET | D7: BUDGET | E7: REVISION | F7: REVISION | H7: REVISION | I7: REVISION | Q7: Otherdirect Cost ( travel, equipment & Other goods and services)(ODC) | R7: ALL | S7: 0
B8: Task/ | E8: TOTAL | F8: TOTAL | G8: COMMENT | H8: Personnel costs (DIRECT only) | I8: Personnel costs (DIRECT & INDIRECT) | Q8: Assessment of potential new value chains and selection of Topics for Call of Proposals | R8: WP1 | S8: =SUM(V8+X8)*1.25 -> 13000.737 | U8: =SUM(U9:U11) -> 146.5 | V8: =U8*V$6*(1+X$3) -> 9573.775 | W8: =SUM(W9:W11) -> 16.5 | X8: =W8*X$6*(1+X$3) -> 826.815
B9: WP | C9: PM | D9: hours | E9: PMs | F9: Hours | H9: EUR | I9: EUR | Q9: Sustainable challenges, needs and trends of four industrial offshore sectors | R9: T1.1 | S9: =V9+X9 -> 2578.095 | U9: 36 | V9: =U9*V$6*(1+X$3) -> 2352.6 | W9: 4.5 | X9: =W9*X$6*(1+X$3) -> 225.495
A10: Assessment of potential new value chains and selection of Topics for Call of Proposals | B10: WP1 | C10: =SUM(C11:C13) -> 3.25 | D10: =SUM(D11:D13) -> 465.83333 | E10: =SUM(E11:E13) -> 1.2 | F10: =E10*(1720/12) -> 172 | G10: Shift 2,05; Shift 2PM to WP7, Shift 0,5 to WP4 | H10: =SUM(H11:H13) -> 10320 | I10: =SUM(I11:I13) -> 12900 | Q10: Assessment of emerging technology trends and solutions | R10: T1.2 | S10: =V10+X10 -> 5960.02 | U10: 82 | V10: =U10*V$6*(1+X$3) -> 5358.7 | W10: 12 | X10: =W10*X$6*(1+X$3) -> 601.32
A11: Sustainable challenges, needs and trends of four industrial offshore sectors | B11: T1.1 | C11: 0.25 | D11: =C11*1720/12 -> 35.833333 | E11: 0.3 | F11: =E11*(1720/12) -> 43 | H11: =E11*$H$6 -> 2580 | I11: =H11*1.25 -> 3225 | Q11: Potential new value chains and selection of Call Topics | R11: T1.3 | S11: =V11+X11 -> 1862.475 | U11: 28.5 | V11: =U11*V$6*(1+X$3) -> 1862.475 | W11: 0 | X11: =W11*X$6*(1+X$3) -> 0
A12: Assessment of emerging technology trends and solutions | B12: T1.2 | C12: 1 | D12: =C12*1720/12 -> 143.33333 | E12: 0.7 | F12: =E12*(1720/12) -> 100.33333 | H12: =E12*$H$6 -> 6020 | I12: =H12*1.25 -> 7525 | Q12: Methodologies and tools for cross-sectoral/-border collaboration and technology transfer | R12: WP2 | S12: =V12*1.25 -> 653.5 | U12: =SUM(U13:U16) -> 8 | V12: =U12*V$6*(1+X$3) -> 522.8 | X12: =W12*X$6*(1+X$3) -> 0
A13: Potential new value chains and selection of Call Topics | B13: T1.3 | C13: 2 | D13: =C13*1720/12 -> 286.66667 | E13: 0.2 | F13: =E13*(1720/12) -> 28.666667 | H13: =E13*$H$6 -> 1720 | I13: =H13*1.25 -> 2150 | Q13: Methologies and tools for cross-sectoral/-border collaboration and technology transfer | R13: T2.1 | S13: =V13 -> 130.7 | U13: 2 | V13: =U13*V$6*(1+X$3) -> 130.7 | W13: 0 | X13: =W13*X$6*(1+X$3) -> 0
A14: Methodologies and tools for cross-sectoral/-border collaboration and technology transfer | B14: WP2 | C14: =SUM(C15:C18) -> 0.5 | D14: =SUM(D15:D18) -> 71.666667 | E14: =SUM( E15:E18) -> 0.5 | F14: =E14*(1720/12) -> 71.666667 | G14: no changes | H14: =SUM(H15:H18) -> 4300 | I14: =SUM(I15:I18) -> 5375 | Q14: Establishment of a Collaborative Virtual Environment | R14: T2.2 | S14: =V14 -> 0 | U14: 0 | V14: =U14*V$6*(1+X$3) -> 0 | W14: 0 | X14: =W14*X$6*(1+X$3) -> 0
A15: Methologies and tools for cross-sectoral/-border collaboration and technology transfer | B15: T2.1 | C15: 0.25 | D15: =C15*1720/12 -> 35.833333 | E15: 0.25 | F15: =E15*(1720/12) -> 35.833333 | H15: =E15*$H$6 -> 2150 | I15: =H15*1.25 -> 2687.5 | Q15: Establishment of a Survey tool | R15: T2.3 | S15: =V15 -> 196.05 | U15: 3 | V15: =U15*V$6*(1+X$3) -> 196.05 | W15: 0 | X15: =W15*X$6*(1+X$3) -> 0
A16: Establishment of a Collaborative Virtual Environment | B16: T2.2 | C16: 0 | D16: =C16*1720/12 -> 0 | E16: 0 | F16: =E16*(1720/12) -> 0 | H16: =E16*$H$6 -> 0 | I16: =H16*1.25 -> 0 | Q16: Establishment of the GreenOffshoreTech Cluster Collaboration Platform | R16: T2.4 | S16: =V16 -> 196.05 | U16: 3 | V16: =U16*V$6*(1+X$3) -> 196.05 | W16: 0 | X16: =W16*X$6*(1+X$3) -> 0
A17: Establishment of a Survey tool | B17: T2.3 | C17: 0 | D17: =C17*1720/12 -> 0 | E17: 0 | F17: =E17*(1720/12) -> 0 | H17: =E17*$H$6 -> 0 | I17: =H17*1.25 -> 0 | Q17: Direct financial support to SMEs through a competitive Call for Proposals | R17: WP3 | S17: =V17+X17*1.25 -> 1364.2125 | U17: =SUM(U18:U23) -> 18 | V17: =U17*V$6*(1+X$3) -> 1176.3 | W17: =SUM(W18:W23) -> 3 | X17: =W17*X$6*(1+X$3) -> 150.33
A18: Establishment of the GreenOffshoreTech Cluster Collaboration Platform | B18: T2.4 | C18: 0.25 | D18: =C18*1720/12 -> 35.833333 | E18: 0.25 | F18: =E18*(1720/12) -> 35.833333 | H18: =E18*$H$6 -> 2150 | I18: =H18*1.25 -> 2687.5 | Q18: Preparation of the Call for Proposals | R18: T3.1 | S18: =SUM(V18+X18) -> 653.5 | U18: 10 | V18: =U18*V$6*(1+X$3) -> 653.5 | W18: 0 | X18: =W18*X$6*(1+X$3) -> 0
A19: Direct financial support to SMEs through a competitive Call for Proposals | B19: WP3 | C19: =SUM(C20:C25) -> 3.5 | D19: =SUM(D20:D25) -> 501.66667 | E19: =SUM(E20:E25) -> 3.5 | F19: =E19*(1720/12) -> 501.66667 | G19: no changes (WP is extended as discussed) | H19: =SUM(H20:H25) -> 30100 | I19: =SUM(I20:I25) -> 37625 | Q19: Publication of the Call for Proposals and Proposal reception. | R19: T3.2 | S19: =SUM(V19+X19) -> 673.13 | U19: 8 | V19: =U19*V$6*(1+X$3) -> 522.8 | W19: 3 | X19: =W19*X$6*(1+X$3) -> 150.33
A20: Preparation of the Call for Proposals | B20: T3.1 | C20: 0.5 | D20: =C20*1720/12 -> 71.666667 | E20: 0.5 | F20: =E20*(1720/12) -> 71.666667 | H20: =E20*$H$6 -> 4300 | I20: =H20*1.25 -> 5375 | Q20: Evaluation and Selection of SMEs Proposals | R20: T3.3 | S20: =SUM(V20+X20) -> 0 | U20: 0 | V20: =U20*V$6*(1+X$3) -> 0 | W20: 0 | X20: =W20*X$6*(1+X$3) -> 0
A21: Publication of the Call for Proposals and Proposal reception. | B21: T3.2 | C21: 0 | D21: =C21*1720/12 -> 0 | E21: 0 | F21: =E21*(1720/12) -> 0 | H21: =E21*$H$6 -> 0 | I21: =H21*1.25 -> 0 | Q21: Contracting with winner SMEs Projects | R21: T3.4 | S21: =SUM(V21+X21) -> 0 | U21: 0 | V21: =U21*V$6*(1+X$3) -> 0 | W21: 0 | X21: =W21*X$6*(1+X$3) -> 0
A22: Evaluation and Selection of SMEs Proposals | B22: T3.3 | C22: 1 | D22: =C22*1720/12 -> 143.33333 | E22: 1 | F22: =E22*(1720/12) -> 143.33333 | H22: =E22*$H$6 -> 8600 | I22: =H22*1.25 -> 10750 | Q22: Payments and financial monitoring of winner SMEs Projects | R22: T3.5 | S22: =SUM(V22+X22) -> 0 | U22: 0 | V22: =U22*V$6*(1+X$3) -> 0 | W22: 0 | X22: =W22*X$6*(1+X$3) -> 0
A23: Contracting with winner SMEs Projects | B23: T3.4 | C23: 0 | D23: =C23*1720/12 -> 0 | E23: 0 | F23: =E23*(1720/12) -> 0 | H23: =E23*$H$6 -> 0 | I23: =H23*1.25 -> 0 | Q23: Technical monitoring of winner SMEs Projects | R23: T3.6 | S23: =SUM(V23+X23) -> 0 | U23: 0 | V23: =U23*V$6*(1+X$3) -> 0 | W23: 0 | X23: =W23*X$6*(1+X$3) -> 0
A24: Payments and financial monitoring of winner SMEs Projects | B24: T3.5 | C24: 0 | D24: =C24*1720/12 -> 0 | E24: 0 | F24: =E24*(1720/12) -> 0 | H24: =E24*$H$6 -> 0 | I24: =H24*1.25 -> 0 | Q24: Business Support Services to winner SMEs (preparation) | R24: WP4 | S24: =SUM(V24+X24)*1.25 -> 653.5 | U24: =SUM(U25:U33) -> 8 | V24: =U24*V$6*(1+X$3) -> 522.8 | X24: =W24*X$6*(1+X$3) -> 0
A25: Technical monitoring of winner SMEs Projects | B25: T3.6 | C25: 2 | D25: =C25*1720/12 -> 286.66667 | E25: 2 | F25: =E25*(1720/12) -> 286.66667 | H25: =E25*$H$6 -> 17200 | I25: =H25*1.25 -> 21500 | Q25: Programme of Business Support Services to winner SMEs (prep) | R25: T4.1 | S25: =SUM(V25+X25) -> 65.35 | U25: 1 | V25: =U25*V$6*(1+X$3) -> 65.35 | W25: 0 | X25: =W25*X$6*(1+X$3) -> 0
A26: Business Support Services to winner SMEs | B26: WP4 | C26: =SUM(C27:C35) -> 9 | D26: =SUM(D27:D35) -> 1290 | E26: =SUM(E27:E35) -> 9.05 | F26: =E26*(1720/12) -> 1297.1667 | G26: plus 0,05 from WP 1 | H26: =SUM(H27:H35) -> 77830 | I26: =SUM(I27:I35) -> 97287.5 | Q26: Business Support Service #1 Business & Tech Academy | R26: T4.2 | S26: =SUM(V26+X26) -> 196.05 | U26: 3 | V26: =U26*V$6*(1+X$3) -> 196.05 | W26: 0 | X26: =W26*X$6*(1+X$3) -> 0
A27: Programme of Business Support Services to winner SMEs | B27: T4.1 | C27: 0 | D27: =C27*1720/12 -> 0 | E27: 0 | F27: =E27*(1720/12) -> 0 | H27: =E27*$H$6 -> 0 | I27: =H27*1.25 -> 0 | Q27: Business Support Service #2 Brokerage & B2B matchmaking events | R27: T4.3 | S27: =SUM(V27+X27) -> 261.4 | U27: 4 | V27: =U27*V$6*(1+X$3) -> 261.4 | W27: 0 | X27: =W27*X$6*(1+X$3) -> 0
A28: Business Support Service #1 Business & Tech Academy | B28: T4.2 | C28: 3.5 | D28: =C28*1720/12 -> 501.66667 | E28: 3.5 | F28: =E28*(1720/12) -> 501.66667 | H28: =E28*$H$6 -> 30100 | I28: =H28*1.25 -> 37625 | Q28: Business Support Service #3 Access to Finance | R28: T4.4 | S28: =SUM(V28+X28) -> 0 | U28: 0 | V28: =U28*V$6*(1+X$3) -> 0 | W28: 0 | X28: =W28*X$6*(1+X$3) -> 0
A29: Business Support Service #2 Brokerage & B2B matchmaking events | B29: T4.3 | C29: 4 | D29: =C29*1720/12 -> 573.33333 | E29: 4.05 | F29: =E29*(1720/12) -> 580.5 | G29: plus 0,05 from WP 1 | H29: =E29*$H$6 -> 34830 | I29: =H29*1.25 -> 43537.5 | Q29: Business Support Service #4 One-to-One Mentoring and Coaching (prep) | R29: T4.5 | S29: =SUM(V29+X29) -> 0 | U29: 0 | V29: =U29*V$6*(1+X$3) -> 0 | W29: 0 | X29: =W29*X$6*(1+X$3) -> 0
A30: Business Support Service #3 Access to Finance | B30: T4.4 | C30: 0.5 | D30: =C30*1720/12 -> 71.666667 | E30: 0.5 | F30: =E30*(1720/12) -> 71.666667 | H30: =E30*$H$6 -> 4300 | I30: =H30*1.25 -> 5375 | Q30: Business Support Service #5 Branding | R30: T4.6 | S30: =SUM(V30+X30) -> 0 | U30: 0 | V30: =U30*V$6*(1+X$3) -> 0 | W30: 0 | X30: =W30*X$6*(1+X$3) -> 0
A31: Business Support Service #4 One-to-One Mentoring and Coaching (prep + service) | B31: T4.5 | C31: 0 | D31: =C31*1720/12 -> 0 | E31: 0 | F31: =E31*(1720/12) -> 0 | H31: =E31*$H$6 -> 0 | I31: =H31*1.25 -> 0 | Q31: Business Support Service #6 Internationalisation | R31: T4.7 | S31: =SUM(V31+X31) -> 0 | U31: 0 | V31: =U31*V$6*(1+X$3) -> 0 | W31: 0 | X31: =W31*X$6*(1+X$3) -> 0
A32: Business Support Service #5 Branding | B32: T4.6 | C32: 0 | D32: =C32*1720/12 -> 0 | E32: 0 | F32: =E32*(1720/12) -> 0 | H32: =E32*$H$6 -> 0 | I32: =H32*1.25 -> 0 | Q32: Business Support Service #7 Investor pitching | R32: T4.8 | S32: =SUM(V32+X32) -> 0 | U32: 0 | V32: =U32*V$6*(1+X$3) -> 0 | W32: 0 | X32: =W32*X$6*(1+X$3) -> 0
A33: Business Support Service #6 Internationalisation | B33: T4.7 | C33: 0.5 | D33: =C33*1720/12 -> 71.666667 | E33: 0.5 | F33: =E33*(1720/12) -> 71.666667 | H33: =E33*$H$6 -> 4300 | I33: =H33*1.25 -> 5375 | Q33: Business Support Service #8 Investor rounds | R33: T4.9 | S33: =SUM(V33+X33) -> 0 | U33: 0 | V33: =U33*V$6*(1+X$3) -> 0 | W33: 0 | X33: =W33*X$6*(1+X$3) -> 0
A34: Business Support Service #7 Investor pitching | B34: T4.8 | C34: 0 | D34: =C34*1720/12 -> 0 | E34: 0 | F34: =E34*(1720/12) -> 0 | H34: =E34*$H$6 -> 0 | I34: =H34*1.25 -> 0 | Q34: Large-scale Demonstrator (LSD) setup, validation, and impact assessment | R34: WP5 | S34: 0 | U34: =SUM(U35:U37) -> 0 | V34: =U34*V$6*(1+X$3) -> 0 | X34: =W34*X$6*(1+X$3) -> 0
A35: Business Support Service #8 Investor rounds | B35: T4.9 | C35: 0.5 | D35: =C35*1720/12 -> 71.666667 | E35: 0.5 | F35: =E35*(1720/12) -> 71.666667 | H35: =E35*$H$6 -> 4300 | I35: =H35*1.25 -> 5375 | Q35: Set-up of the GreenOffshoreTech LSD in GreenOffshoreTech regions | R35: T5.1 | S35: 0 | U35: 0 | V35: =U35*V$6*(1+X$3) -> 0 | W35: 0 | X35: =W35*X$6*(1+X$3) -> 0
A36: Large-scale Demonstrator (LSD) setup, validation, and impact assessment | B36: WP5 | C36: =SUM(C37:C39) -> 0.75 | D36: =SUM(D37:D39) -> 107.5 | E36: =SUM(E37:E39) -> 0.75 | F36: =E36*(1720/12) -> 107.5 | G36: no changes | H36: =SUM(H37:H39) -> 6450 | I36: =SUM(I37:I39) -> 8062.5 | Q36: Validation & Impact assessment of GreenOffshoreTech LSD (data collection) | R36: T5.2 | S36: 0 | U36: 0 | V36: =U36*V$6*(1+X$3) -> 0 | W36: 0 | X36: =W36*X$6*(1+X$3) -> 0
A37: Set-up of the GreenOffshoreTech LSD in GreenOffshoreTech regions | B37: T5.1 | C37: 0.25 | D37: =C37*1720/12 -> 35.833333 | E37: 0.25 | F37: =E37*(1720/12) -> 35.833333 | H37: =E37*$H$6 -> 2150 | I37: =H37*1.25 -> 2687.5 | Q37: Guidelines of Best Practice to foster cross-sector/-border collaboration and technology transfer through Clusters | R37: T5.3 | S37: 0 | U37: 0 | V37: =U37*V$6*(1+X$3) -> 0 | W37: 0 | X37: =W37*X$6*(1+X$3) -> 0
A38: Validation & Impact assessment of GreenOffshoreTech LSD (data collection & analysis) | B38: T5.2 | C38: 0.25 | D38: =C38*1720/12 -> 35.833333 | E38: 0.25 | F38: =E38*(1720/12) -> 35.833333 | H38: =E38*$H$6 -> 2150 | I38: =H38*1.25 -> 2687.5 | Q38: Communication, Dissemination, Exploitation & Sustainability | R38: WP6 | S38: =SUM(V38+X38)*1.25 -> 408.4375 | U38: =SUM(U39:U41) -> 5 | V38: =U38*V$6*(1+X$3) -> 326.75 | X38: =W38*X$6*(1+X$3) -> 0
A39: Guidelines of Best Practice to foster cross-sector/-border collaboration and technology transfer through Clusters | B39: T5.3 | C39: 0.25 | D39: =C39*1720/12 -> 35.833333 | E39: 0.25 | F39: =E39*(1720/12) -> 35.833333 | H39: =E39*$H$6 -> 2150 | I39: =H39*1.25 -> 2687.5 | Q39: Communication plan and Communication activities | R39: T6.1 | S39: =SUM(V39+X39) -> 326.75 | U39: 5 | V39: =U39*V$6*(1+X$3) -> 326.75 | W39: 0 | X39: =W39*X$6*(1+X$3) -> 0
A40: Communication, Dissemination, Exploitation & Sustainability | B40: WP6 | C40: =SUM(C41:C43) -> 2 | D40: =SUM(D41:D43) -> 286.66667 | E40: =SUM(E41:E43) -> 2 | F40: =E40*(1720/12) -> 286.66667 | G40: no changes | H40: =SUM(H41:H43) -> 17200 | I40: =SUM(I41:I43) -> 21500 | Q40: Dissemination strategy and Dissemination activities | R40: T6.2 | S40: 0 | U40: 0 | V40: =U40*V$6*(1+X$3) -> 0 | W40: 0 | X40: =W40*X$6*(1+X$3) -> 0
A41: Communication plan and Communication activities | B41: T6.1 | C41: 0.5 | D41: =C41*1720/12 -> 71.666667 | E41: 0.5 | F41: =E41*(1720/12) -> 71.666667 | H41: =E41*$H$6 -> 4300 | I41: =H41*1.25 -> 5375 | Q41: Exploitation strategy, IPR and Sustainability | R41: T6.3 | S41: 0 | U41: 0 | V41: =U41*V$6*(1+X$3) -> 0 | W41: 0 | X41: =W41*X$6*(1+X$3) -> 0
A42: Dissemination strategy and Dissemination activities | B42: T6.2 | C42: 1 | D42: =C42*1720/12 -> 143.33333 | E42: 1 | F42: =E42*(1720/12) -> 143.33333 | H42: =E42*$H$6 -> 8600 | I42: =H42*1.25 -> 10750 | Q42: Project Management and Coordination | R42: WP7 | S42: =SUM(V42+X42)*1.25 -> 367.59375 | U42: =SUM(U43:U45) -> 4.5 | V42: =U42*V$6*(1+X$3) -> 294.075 | X42: =W42*X$6*(1+X$3) -> 0
A43: Exploitation strategy, IPR and Sustainability | B43: T6.3 | C43: 0.5 | D43: =C43*1720/12 -> 71.666667 | E43: 0.5 | F43: =E43*(1720/12) -> 71.666667 | H43: =E43*$H$6 -> 4300 | I43: =H43*1.25 -> 5375 | Q43: Project coordination | R43: T7.1 | S43: =SUM(V43+X43) -> 0 | U43: 0 | V43: =U43*V$6*(1+X$3) -> 0 | W43: 0 | X43: =W43*X$6*(1+X$3) -> 0
A44: Project Management and Coordination | B44: WP7 | C44: =SUM(C45:C47) -> 0 | D44: =SUM(D45:D47) -> 0 | E44: =SUM(E45:E47) -> 2 | F44: =E44*(1720/12) -> 286.66667 | G44: plus 2 PM from WP 1 | H44: =SUM(H45:H47) -> 17200 | I44: =SUM(I45:I47) -> 21500 | Q44: Project administration & Financial Management | R44: T7.2 | S44: =SUM(V44+X44) -> 0 | U44: 0 | V44: =U44*V$6*(1+X$3) -> 0 | W44: 0 | X44: =W44*X$6*(1+X$3) -> 0
A45: Project coordination | B45: T7.1 | C45: 0 | D45: =C45*1720/12 -> 0 | E45: 0 | F45: =E45*(1720/12) -> 0 | H45: =E45*$H$6 -> 0 | I45: =H45*1.25 -> 0 | Q45: Quality Assurance | R45: T7.3 | S45: =SUM(V45+X45) -> 294.075 | U45: 4.5 | V45: =U45*V$6*(1+X$3) -> 294.075 | W45: 0 | X45: =W45*X$6*(1+X$3) -> 0
A46: Project administration & Financial Management | B46: T7.2 | C46: 0 | D46: =C46*1720/12 -> 0 | E46: 1.5 | F46: =E46*(1720/12) -> 215 | G46: the shifted 2PM are split between 7.2 and 7.3 | H46: =E46*$H$6 -> 12900 | I46: =H46*1.25 -> 16125 | Q46: TOTAL | S46: =SUM(S8+S12+S17+S24+S34+S38+S42) -> 16447.981 | U46: =U8+U12+U17+U24+U34+U38+U42 -> 190 | V46: =U46*V$6*(1+X$3) -> 12416.5 | W46: =W8+W12+W17+W24+W34+W38+W42 -> 19.5 | X46: =W46*X$6*(1+X$3) -> 977.145
A47: Quality Assurance | B47: T7.3 | C47: 0 | D47: =C47*1720/12 -> 0 | E47: 0.5 | F47: =E47*(1720/12) -> 71.666667 | G47: the shifted 2PM are split between 7.2 and 7.4 | H47: =E47*$H$6 -> 4300 | I47: =H47*1.25 -> 5375
A48: NOTE: Key Tasks are marked light green | C48: =C10+C14+C19+C26+C36+C40+C44 -> 19 | D48: =D10+D14+D19+D26+D36+D40+D44 -> 2723.3333 | E48: =(E10+E14+E19+E26+E36+E40+E44) -> 19 | F48: =(F10+F14+F19+F26+F36+F40+F44) -> 2723.3333 | H48: =(H10+H14+H19+H26+H36+H40+H44) -> 163400 | I48: =(I10+I14+I19+I26+I36+I40+I44) -> 204250

Sheet IOC
G3: (to May) | K3: (to May)
G4: TOTAL COSTS | K4: TOTAL COSTS
G5: Dir & Indir (EUR) | K5: Dir & Indir (EUR)
G6: ACTUAL | K6: ACTUAL
E7: GreenOfshoreTech Iceland Ocean Cluster | F7: Task/ | G7: M1-M9 | K7: M1-M9
F8: WP | I8: Hours/task
E9: Otherdirect Cost ( travel, equipment & Other goods and services)(ODC) | K9: 0
E10: Assessment of potential new value chains and selection of Topics for Call of Proposals | F10: WP1 | G10: =SUM(G11:G13)*1.25 -> 2402.5312 | I10: =SUM(I11:I13) -> 36.75 | K10: =SUM(K11:K13) -> 2402.5312
E11: Sustainable challenges, needs and trends of four industrial offshore sectors | F11: T1.1 | G11: =I11*52.3 -> 248.425 | I11: =4.75 -> 4.75 | K11: =SUM(G11*1.25) -> 310.53125
E12: Assessment of emerging technology trends and solutions | F12: T1.2 | G12: =I12*52.3 -> 1176.75 | I12: =16.25+6.25 -> 22.5 | K12: =SUM(G12*1.25) -> 1470.9375
E13: Potential new value chains and selection of Call Topics | F13: T1.3 | G13: =I13*52.3 -> 496.85 | I13: =9.5 -> 9.5 | K13: =SUM(G13*1.25) -> 621.0625
E14: Methodologies and tools for cross-sectoral/-border collaboration and technology transfer | F14: WP2 | G14: =SUM(G15:G18)*1.25 -> 555.6875 | I14: =SUM(I15:I18) -> 8.5 | K14: =SUM(K15:K18) -> 555.6875
E15: Methologies and tools for cross-sectoral/-border collaboration and technology transfer | F15: T2.1 | G15: =I15*52.3 -> 0 | I15: 0 | K15: =SUM(G15*1.25) -> 0
E16: Establishment of a Collaborative Virtual Environment | F16: T2.2 | G16: =I16*52.3 -> 0 | I16: 0 | K16: =SUM(G16*1.25) -> 0
E17: Establishment of a Survey tool | F17: T2.3 | G17: =I17*52.3 -> 0 | I17: 0 | K17: =SUM(G17*1.25) -> 0
E18: Establishment of the GreenOffshoreTech Cluster Collaboration Platform | F18: T2.4 | G18: =I18*52.3 -> 444.55 | I18: =3.5+5 -> 8.5 | K18: =SUM(G18*1.25) -> 555.6875
E19: Direct financial support to SMEs through a competitive Call for Proposals | F19: WP3 | G19: =SUM(G20:G25)*1.25 -> 1307.5 | I19: =SUM(I20:I25) -> 20 | K19: =SUM(K20:K25) -> 1307.5
E20: Preparation of the Call for Proposals | F20: T3.1 | G20: =I20*52.3 -> 836.8 | I20: =2.5+9.5+4 -> 16 | K20: =SUM(G20*1.25) -> 1046
E21: Publication of the Call for Proposals and Proposal reception. | F21: T3.2 | G21: =I21*52.3 -> 209.2 | I21: =4 -> 4 | K21: =SUM(G21*1.25) -> 261.5
E22: Evaluation and Selection of SMEs Proposals | F22: T3.3 | G22: =I22*52.3 -> 0 | I22: 0 | K22: =SUM(G22*1.25) -> 0
E23: Contracting with winner SMEs Projects | F23: T3.4 | G23: =I23*52.3 -> 0 | I23: 0 | K23: =SUM(G23*1.25) -> 0
E24: Payments and financial monitoring of winner SMEs Projects | F24: T3.5 | G24: =I24*52.3 -> 0 | I24: 0 | K24: =SUM(G24*1.25) -> 0
E25: Technical monitoring of winner SMEs Projects | F25: T3.6 | G25: =I25*52.3 -> 0 | I25: 0 | K25: =SUM(G25*1.25) -> 0
E26: Business Support Services to winner SMEs (preparation) | F26: WP4 | G26: 0 | I26: 0 | K26: =SUM(K27:K35) -> 0
E27: Programme of Business Support Services to winner SMEs (prep) | F27: T4.1 | G27: 0 | I27: 0 | K27: =SUM(G27*1.25) -> 0
E28: Business Support Service #1 Business & Tech Academy | F28: T4.2 | G28: 0 | I28: 0 | K28: =SUM(G28*1.25) -> 0
E29: Business Support Service #2 Brokerage & B2B matchmaking events | F29: T4.3 | G29: 0 | I29: 0 | K29: =SUM(G29*1.25) -> 0
E30: Business Support Service #3 Access to Finance | F30: T4.4 | G30: 0 | I30: 0 | K30: =SUM(G30*1.25) -> 0
E31: Business Support Service #4 One-to-One Mentoring and Coaching (prep) | F31: T4.5 | G31: 0 | I31: 0 | K31: =SUM(G31*1.25) -> 0
E32: Business Support Service #5 Branding | F32: T4.6 | G32: 0 | I32: 0 | K32: =SUM(G32*1.25) -> 0
E33: Business Support Service #6 Internationalisation | F33: T4.7 | G33: 0 | I33: 0 | K33: =SUM(G33*1.25) -> 0
E34: Business Support Service #7 Investor pitching | F34: T4.8 | G34: 0 | I34: 0 | K34: =SUM(G34*1.25) -> 0
E35: Business Support Service #8 Investor rounds | F35: T4.9 | G35: 0 | I35: 0 | K35: =SUM(G35*1.25) -> 0
E36: Large-scale Demonstrator (LSD) setup, validation, and impact assessment | F36: WP5 | G36: =SUM(G37:G39)*1.25 -> 359.5625 | I36: =SUM(I37:I39) -> 5.5 | K36: =SUM(K37:K39) -> 359.5625
E37: Set-up of the GreenOffshoreTech LSD in GreenOffshoreTech regions | F37: T5.1 | G37: =I37*52.3 -> 287.65 | I37: =3.5+2 -> 5.5 | K37: =SUM(G37*1.25) -> 359.5625
E38: Validation & Impact assessment of GreenOffshoreTech LSD (data collection) | F38: T5.2 | G38: =I38*52.3 -> 0 | I38: 0 | K38: =SUM(G38*1.25) -> 0
E39: Guidelines of Best Practice to foster cross-sector/-border collaboration and technology transfer through Clusters | F39: T5.3 | G39: =I39*52.3 -> 0 | I39: 0 | K39: =SUM(G39*1.25) -> 0
E40: Communication, Dissemination, Exploitation & Sustainability | F40: WP6 | G40: =SUM(G41:G43)*1.25 -> 4821.4062 | I40: =SUM(I41:I43) -> 73.75 | K40: =SUM(K41:K43) -> 4821.4062
E41: Communication plan and Communication activities | F41: T6.1 | G41: =I41*52.3 -> 3857.125 | I41: =2.5+32.25+4+2.5+1+2+2.5+2+2+15+8 -> 73.75 | K41: =SUM(G41*1.25) -> 4821.4062
E42: Dissemination strategy and Dissemination activities | F42: T6.2 | G42: =I42*52.3 -> 0 | I42: 0 | K42: =SUM(G42*1.25) -> 0
E43: Exploitation strategy, IPR and Sustainability | F43: T6.3 | G43: =I43*52.3 -> 0 | I43: 0 | K43: =SUM(G43*1.25) -> 0
E44: Project Management and Coordination | F44: WP7 | G44: 0 | I44: 0 | K44: =SUM(K45:K47) -> 0
E45: Project coordination | F45: T7.1 | G45: 0 | I45: 0 | K45: =SUM(G45*1.25) -> 0
E46: Project administration & Financial Management | F46: T7.2 | G46: 0 | I46: 0 | K46: =SUM(G46*1.25) -> 0
E47: Quality Assurance | F47: T7.3 | G47: 0 | I47: 0 | K47: =SUM(G47*1.25) -> 0
E48: TOTAL | G48: =SUM(G10+G14+G19+G26+G36+G40+G44) -> 9446.6875 | I48: =I10+I14+I19+I26+I36+I40+I44 -> 144.5 | K48: =SUM(K10+K14+K19+K26+K36+K40+K44) -> 9446.6875

Sheet HIE
E2: HIE
K3: INCLDING IND COST
G4: TOTAL COSTS | I4: TOTAL COSTS | L4: TOTAL COSTS
G5: Dir & Indir (EUR) | I5: Dir (EUR) | L5: Dir & Indir (EUR)
G6: ACTUAL | I6: ACTUAL | L6: ACTUAL
E7: GreenOfshoreTech PARTNER NAME | F7: Task/ | G7: M1-M9 | I7: M1-M9 | L7: M1-M9
F8: WP
E9: Otherdirect Cost ( travel, equipment & Other goods and services)(ODC) | F9: All | G9: 4611 | I9: 4611 | L9: =SUM(G9*1.25) -> 5763.75
E10: Assessment of potential new value chains and selection of Topics for Call of Proposals | F10: WP1 | G10: =SUM(G11:G13)*1.25 -> 15319.057 | I10: =SUM(I11:I13) -> 15319.057 | L10: =SUM(L11:L13) -> 12255.246
E11: Sustainable challenges, needs and trends of four industrial offshore sectors | F11: T1.1 | G11: 11586.268 | I11: =SUM(G11*1.25) -> 14482.835 | L11: 11586.268
E12: Assessment of emerging technology trends and solutions | F12: T1.2 | G12: 411.67883 | I12: =SUM(G12*1.25) -> 514.59853 | L12: 411.67883
E13: Potential new value chains and selection of Call Topics | F13: T1.3 | G13: 257.29927 | I13: =SUM(G13*1.25) -> 321.62408 | L13: 257.29927
E14: Methodologies and tools for cross-sectoral/-border collaboration and technology transfer | F14: WP2 | G14: =SUM(G15:G18)*1.25 -> 15281.059 | I14: =SUM(I15:I19) -> 21820.31 | L14: =SUM(L15:L18) -> 15281.059
E15: Methologies and tools for cross-sectoral/-border collaboration and technology transfer | F15: T2.1 | G15: 11710.249 | I15: =SUM(G15*1.25) -> 14637.811 | L15: =SUM(G15*1.25) -> 14637.811
E16: Establishment of a Collaborative Virtual Environment | F16: T2.2 | G16: 514.59853 | I16: =SUM(G16*1.25) -> 643.24817 | L16: =SUM(G16*1.25) -> 643.24817
E17: Establishment of a Survey tool | F17: T2.3 | G17: 0 | I17: =SUM(G17*1.25) -> 0 | L17: =SUM(G17*1.25) -> 0
E18: Establishment of the GreenOffshoreTech Cluster Collaboration Platform | F18: T2.4 | G18: 0 | I18: =SUM(G18*1.25) -> 0 | L18: =SUM(G18*1.25) -> 0
E19: Direct financial support to SMEs through a competitive Call for Proposals | F19: WP3 | G19: =SUM(G20:G25)*1.25 -> 6539.2514 | I19: =SUM(I20:I25) -> 6539.2514 | L19: =SUM(L20:L25) -> 6539.2514
E20: Preparation of the Call for Proposals | F20: T3.1 | G20: 1302.4411 | I20: =SUM(G20*1.25) -> 1628.0514 | L20: =SUM(G20*1.25) -> 1628.0514
E21: Publication of the Call for Proposals and Proposal reception. | F21: T3.2 | G21: 3928.96 | I21: =SUM(G21*1.25) -> 4911.2 | J21: Travel costs 4611 euro added to T3.2 | K21: 0 | L21: =SUM(G21*1.25) -> 4911.2
E22: Evaluation and Selection of SMEs Proposals | F22: T3.3 | G22: 0 | I22: =SUM(G22*1.25) -> 0 | L22: =SUM(G22*1.25) -> 0
E23: Contracting with winner SMEs Projects | F23: T3.4 | G23: 0 | I23: =SUM(G23*1.25) -> 0 | L23: =SUM(G23*1.25) -> 0 | O23: WP1 | P23: =SUM(G10) -> 15319.057
E24: Payments and financial monitoring of winner SMEs Projects | F24: T3.5 | G24: 0 | I24: =SUM(G24*1.25) -> 0 | L24: =SUM(G24*1.25) -> 0 | O24: WP2 | P24: =SUM(G14) -> 15281.059
E25: Technical monitoring of winner SMEs Projects | F25: T3.6 | G25: 0 | I25: =SUM(G25*1.25) -> 0 | L25: =SUM(G25*1.25) -> 0 | O25: WP3 | P25: =SUM(G19) -> 6539.2514
E26: Business Support Services to winner SMEs (preparation) | F26: WP4 | G26: =SUM(G27:G35)*1.25 -> 0 | I26: =SUM(I27:I35) -> 0 | L26: =SUM(L27:L35) -> 0 | O26: WP4 | P26: =SUM(G26) -> 0
E27: Programme of Business Support Services to winner SMEs (prep) | F27: T4.1 | G27: 0 | I27: =SUM(G27*1.25) -> 0 | L27: =SUM(G27*1.25) -> 0 | O27: WP5 | P27: =SUM(G36) -> 0
E28: Business Support Service #1 Business & Tech Academy | F28: T4.2 | G28: 0 | I28: =SUM(G28*1.25) -> 0 | L28: =SUM(G28*1.25) -> 0 | O28: WP6 | P28: =SUM(G40) -> 2261.1825
E29: Business Support Service #2 Brokerage & B2B matchmaking events | F29: T4.3 | G29: 0 | I29: =SUM(G29*1.25) -> 0 | L29: =SUM(G29*1.25) -> 0 | O29: WP7 | P29: =SUM(G44) -> 5531.9342
E30: Business Support Service #3 Access to Finance | F30: T4.4 | G30: 0 | I30: =SUM(G30*1.25) -> 0 | L30: =SUM(G30*1.25) -> 0
E31: Business Support Service #4 One-to-One Mentoring and Coaching (prep) | F31: T4.5 | G31: 0 | I31: =SUM(G31*1.25) -> 0 | L31: =SUM(G31*1.25) -> 0
E32: Business Support Service #5 Branding | F32: T4.6 | G32: 0 | I32: =SUM(G32*1.25) -> 0 | L32: =SUM(G32*1.25) -> 0
E33: Business Support Service #6 Internationalisation | F33: T4.7 | G33: 0 | I33: =SUM(G33*1.25) -> 0 | L33: =SUM(G33*1.25) -> 0
E34: Business Support Service #7 Investor pitching | F34: T4.8 | G34: 0 | I34: =SUM(G34*1.25) -> 0 | L34: =SUM(G34*1.25) -> 0
E35: Business Support Service #8 Investor rounds | F35: T4.9 | G35: 0 | I35: =SUM(G35*1.25) -> 0 | L35: =SUM(G35*1.25) -> 0
E36: Large-scale Demonstrator (LSD) setup, validation, and impact assessment | F36: WP5 | G36: =SUM(G37:G39)*1.25 -> 0 | I36: =SUM(I37:I39) -> 0 | L36: =SUM(L37:L39) -> 0
E37: Set-up of the GreenOffshoreTech LSD in GreenOffshoreTech regions | F37: T5.1 | G37: 0 | I37: =SUM(G37*1.25) -> 0 | L37: =SUM(G37*1.25) -> 0
E38: Validation & Impact assessment of GreenOffshoreTech LSD (data collection) | F38: T5.2 | G38: 0 | I38: =SUM(G38*1.25) -> 0 | L38: =SUM(G38*1.25) -> 0
E39: Guidelines of Best Practice to foster cross-sector/-border collaboration and technology transfer through Clusters | F39: T5.3 | G39: 0 | I39: =SUM(G39*1.25) -> 0 | L39: =SUM(G39*1.25) -> 0
E40: Communication, Dissemination, Exploitation & Sustainability | F40: WP6 | G40: =SUM(G41:G43)*1.25 -> 2261.1825 | I40: =SUM(I41:I43) -> 2261.1825 | L40: =SUM(L41:L43) -> 2261.1825
E41: Communication plan and Communication activities | F41: T6.1 | G41: 0 | I41: =SUM(G41*1.25) -> 0 | L41: =SUM(G41*1.25) -> 0
E42: Dissemination strategy and Dissemination activities | F42: T6.2 | G42: 1808.946 | I42: =SUM(G42*1.25) -> 2261.1825 | L42: =SUM(G42*1.25) -> 2261.1825
E43: Exploitation strategy, IPR and Sustainability | F43: T6.3 | G43: 0 | I43: =SUM(G43*1.25) -> 0 | L43: =SUM(G43*1.25) -> 0
E44: Project Management and Coordination | F44: WP7 | G44: =SUM(G45:G47)*1.25 -> 5531.9342 | I44: =SUM(I45:I47) -> 5531.9342 | L44: =SUM(L45:L47) -> 5531.9342
E45: Project coordination | F45: T7.1 | G45: 3808.0292 | I45: =SUM(G45*1.25) -> 4760.0364 | L45: =SUM(G45*1.25) -> 4760.0364
E46: Project administration & Financial Management | F46: T7.2 | G46: 617.51824 | I46: =SUM(G46*1.25) -> 771.8978 | L46: =SUM(G46*1.25) -> 771.8978
E47: Quality Assurance | F47: T7.3 | G47: 0 | I47: =SUM(G47*1.25) -> 0 | L47: =SUM(G47*1.25) -> 0
E48: TOTAL | G48: =SUM(G9+G10+G14+G19+G26+G36+G40+G44) -> 49543.485 | I48: =SUM(I9+I10+I14+I19+I26+I36+I40+I44) -> 56082.736 | L48: =SUM(L9+L10+L14+L19+L26+L36+L40+L44) -> 47632.423

Sheet BAL
AC1: =AF2*1.25 -> 12375 | AF1: 16600 | AH1: 1.25
H2: AMD2 | I2: AMD2 | AC2: =AF3*1.25 -> 6187.5 | AF2: =SUM(AF3:AF5) -> 9900
H3: For BUDGET | I3: For 75% RULE | AC3: =AF4*1.25 -> 3093.75 | AF3: 4950
C4: ORG = | D4: ORG = | H4: Direct monthly rate | I4: Direct monthly rate | V4: TOTAL COSTS | Y4: Hourly cost | Z4: 83.952 | AC4: =AF5*1.25 -> 3093.75 | AF4: 2475
C5: AMD1 | D5: AMD1 | E5: AMD2 | F5: AMD2 | G5: AMD2 | H5: 9900 | I5: 9900 | V5: Dir & Indir (EUR) | AC5: =AF6*1.25 -> 47406.25 | AF5: 2475
C6: BUDGET | D6: BUDGET | E6: REVISION | F6: REVISION | H6: REVISION | I6: REVISION | V6: ACTUAL | AC6: =AF7*1.25 -> 0 | AF6: =SUM(AF7:AF10) -> 37925
B7: Task/ | E7: TOTAL | F7: TOTAL | G7: COMMENT | H7: Personnel costs (DIRECT only) | I7: Personnel costs (DIRECT & INDIRECT) | T7: GreenOfshoreTech PARTNER NAME | U7: Task/ | V7: M1-M9 | AC7: =AF8*1.25 -> 0 | AF7: 0
B8: WP | C8: PM | D8: hours | E8: PMs | F8: Hours | H8: EUR | I8: EUR | U8: WP | AC8: =AF9*1.25 -> 0 | AF8: 0
