Workbook

Sheet Dashboard
A1: Dashboard — Coming next

Sheet Assumptions
A1: AURELIAN MANUFACTURING — ASSUMPTIONS
A2: Master Source: 02_Economic_Tables_Projections_REV6 — February 2026
A4: Parameter | B4: Cell Name | C4: Value | D4: Unit | E4: Source / Note
A6: 1.1 Core Operating Assumptions
A7: Theoretical hours per CNC per year | B7: theo_hours | C7: 8760 | D7: hours | E7: REV6 §1.1 — 24h × 365d
A8: Normalized hourly rate | B8: hourly_rate | C8: 3000 | D8: NOK/hour | E8: REV6 §1.1 — Conservative floor, defence/O&G higher
A9: Customer Program threshold | B9: sharing_threshold | C9: 0.45 | D9: % | E9: REV6 §1.1 — Fleet utilization trigger
A10: Customer Program split above threshold | B10: sharing_split | C10: 0.5 | D10: % | E10: REV6 §1.1 — Strategic customers only
A11: Target utilization (steady state) | B11: target_util | C11: 0.625 | D11: % | E11: REV6 §1.1 — 60–65% range, 62.5% midpoint
A12: Utilization always refers to % of 8,760 theoretical hours. No intermediate 'available hours' concept.
A14: 1.1b Variable Cost Maturity Curve
A15: Variable cost — 2027–2028 (startup) | B15: var_cost_2027 | C15: 0.13 | D15: % | E15: REV6 §1.1b — New processes, testing
A16: Variable cost — 2029 | B16: var_cost_2029 | C16: 0.1175 | D16: % | E16: REV6 §1.1b — Tooling optimization
A17: Variable cost — 2030 | B17: var_cost_2030 | C17: 0.105 | D17: % | E17: REV6 §1.1b — Supplier agreements
A18: Variable cost — 2031 | B18: var_cost_2031 | C18: 0.0925 | D18: % | E18: REV6 §1.1b — Predictive maintenance
A19: Variable cost — 2032+ (mature) | B19: var_cost_2032 | C19: 0.08 | D19: % | E19: REV6 §1.1b — Steady state
A20: Linear decline driven by tooling optimization, supplier agreements, predictive maintenance, process stability.
A22: 1.2 CNC Machine Economics
A23: Cost per CNC incl. automation | B23: cnc_cost | C23: 10000000 | D23: NOK | E23: REV6 §1.2 — Market analysis, MAZAK/DMG Mori
A24: Depreciation life | B24: depr_life | C24: 8 | D24: years | E24: REV6 §1.2 — Straight-line
A25: Annual depreciation per CNC | B25: depr_per_cnc | C25: =C23/C24 -> 1250000 | D25: NOK | E25: REV6 §1.2 — cnc_cost ÷ depr_life
A26: Debt interest rate | B26: interest_rate | C26: 0.075 | D26: % | E26: REV6 §1.2 — Bank estimate
A27: Debt per CNC (Seed, 50% equity) | B27: debt_per_cnc_seed | C27: 5000000 | D27: NOK | E27: REV6 §1.2 — 50% equity requirement
A28: Debt per CNC (Serie A, 30% equity) | B28: debt_per_cnc_a | C28: 7000000 | D28: NOK | E28: REV6 §1.2 — 30% EQ (proven operations)
A29: Resale value estimate | B29: resale_pct | C29: 0.6 | D29: % | E29: REV6 §1.2 — 50–70% range, MAZAK premium
A31: 1.2b Debt Structure — Steady State (20 CNC)
A32: Seed CNC machines (5 × 5.0M) | B32: debt_seed_cnc | C32: 25000000 | D32: NOK | E32: REV6 §1.2b
A33: Shop base equipment debt (50%) | B33: debt_shop_base | C33: 4300000 | D33: NOK | E33: REV6 §1.2b — 8.6M × 50%
A34: Serie A CNC machines (15 × 7.0M) | B34: debt_seria_cnc | C34: 105000000 | D34: NOK | E34: REV6 §1.2b
A35: Total debt (steady state) | B35: total_debt | C35: =C32+C33+C34 -> 134300000 | D35: NOK | E35: REV6 §1.2b — Sum = 134.3 MNOK
A36: Total annual finance cost (7.5%) | B36: total_finance | C36: =C35*0.075 -> 10072500 | D36: NOK | E36: REV6 §1.2b — 134.3M × 7.5% = 10.07M
A38: 1.2c Shop Base Setup — One-Time per Site
A39: Measurement room (Wenzel CMM, Jenoptik) | C39: 3910000 | D39: NOK | E39: REV6 §1.2c — Supplier quotes
A40: Cutting / raw goods (saw, shelving, misc) | C40: 1500000 | D40: NOK | E40: REV6 §1.2c — Supplier quotes
A41: Compressor (Kaeser) | C41: 360000 | D41: NOK | E41: REV6 §1.2c — Supplier quote
A42: Machine extraction (Absolent, 4 machines) | C42: 2000000 | D42: NOK | E42: REV6 §1.2c — Supplier quote
A43: Forklift (used + top brand) | C43: 850000 | D43: NOK | E43: REV6 §1.2c — Market estimate
A44: Total shop base (per site) | B44: shop_base_total | C44: =SUM(C39:C43) -> 8620000 | D44: NOK | E44: REV6 §1.2c — ~8.6 MNOK
A45: Shop base depreciation (per year) | B45: shop_depr | C45: =C44/8 -> 1077500 | D45: NOK | E45: REV6 §1.2c — 8yr straight-line (~1.08M/yr)
A46: Funded 50% equity / 50% bank debt. All items are physical assets with documented resale value.
A48: 1.3 Staffing Model (Sub-Linear)
A49: Staff per CNC (Aurelian) | B49: staff_ratio | C49: 0.8 | D49: FTE/CNC | E49: REV6 §1.3 — Sub-linear scaling
A50: Industry avg staff per CNC | B50: industry_ratio | C50: 2.5 | D50: FTE/CNC | E50: REV6 §1.3 — Benchmark
A51: Admin/Sales FTEs (constant) | B51: admin_fte | C51: 4 | D51: FTE | E51: REV6 §1.3 — Incl. BD/strategic sales from day one
A52: Avg operational salary (incl. social) | B52: ops_salary | C52: 1100000 | D52: NOK/year | E52: REV6 §1.3
A53: Avg admin salary (incl. social) | B53: admin_salary | C53: 1400000 | D53: NOK/year | E53: REV6 §1.3
A55: 1.3b Pre-Revenue Staffing Timeline
A56: Period | B56: Total FTE | C56: Ops/Technical | D56: Admin/Sales | E56: Funded By
A57: 2026 H1 | B57: 2 | C57: 0 | D57: 2 | E57: Founders
A58: 2026 H2 | B58: 3 | C58: 0 | D58: 3 | E58: Founders
A59: 2027 Q1–Q2 | B59: 8 | C59: 4 | D59: 4 | E59: Seed
A60: 2027 Q3+ | B60: 10 | C60: 6 | D60: 4 | E60: Seed
A61: 2028 | B61: 10 | C61: 6 | D61: 4 | E61: Operations
A62: 2029 | B62: 14 | C62: 10 | D62: 4 | E62: Operations
A63: 2030 | B63: 17 | C63: 13 | D63: 4 | E63: Operations
A64: 2031 | B64: 20 | C64: 16 | D64: 4 | E64: Operations
A65: 2032+ | B65: 24 | C65: 20 | D65: 4 | E65: Operations
A67: 1.4 Fixed Costs (Non-Personnel)
A68: Facility lease (annual) | B68: facility_lease | C68: 5200000 | D68: NOK/year | E68: REV6 §1.4 — Starts Q3 2027
A69: Non-facility opex at 20 CNC | B69: other_opex_20 | C69: 3000000 | D69: NOK/year | E69: REV6 §1.4 — IT, insurance, consumables
A70: Opex scaling factor | B70: opex_scale | C70: 150000 | D70: NOK/CNC/year | E70: REV6 §1.4 — 3.0M ÷ 20 CNC
A71: Shop base depreciation (annual) | B71: shop_base_depr | C71: 1075000 | D71: NOK/year | E71: REV6 §1.4 — 8.6M ÷ 8yr, per site
A73: 1.5 Revenue Formula
A74: Revenue per CNC = theo_hours × utilization% × hourly_rate
A75: Reconciliation: 8,760 × 60% × 3,000 = 15.768 MNOK per CNC. At 20 CNC = ~315 MNOK.
A76: 3,000 NOK is conservative floor. Defence/O&G rates higher — represents unmodeled upside.
A78: 4.1 Fundraising Rounds
A79: Parameter | C79: PreSeed | D79: Seed | E79: Serie A
A80: Capital raised (equity) | B80: MNOK | C80: 5 | D80: 51.3 | E80: 45
A81: Pre-money valuation | B81: MNOK | C81: 25 | D81: 130 | E81: 250
A82: Post-money valuation | B82: MNOK | C82: 30 | D82: 181.3 | E82: 295
A83: Machines funded | B83: CNC | C83: 0 | D83: 5 + shop base | E83: 15 (3×5)
A84: Bank debt raised | B84: MNOK | C84: 0 | D84: 29.3 | E84: 105
A85: Total capital deployed | B85: MNOK | C85: 5 | D85: 80.6 | E85: 150
A87: 2.1 Machine Deployment Timeline
A88: Period | B88: Event | C88: CNC (EOY) | D88: Funding
A89: Jun 2027 | B89: 5 CNC delivered, commissioning | C89: 5 | D89: Seed
A90: Aug 2027 | B90: Production starts | C90: 5 | D90: Seed
A91: Q4 2028 | B91: Serie A Tranche 1 arrives | C91: 10 | D91: Serie A
A92: Q1 2029 | B92: Tranche 1 operational | C92: 10 | D92: Serie A
A93: Q3 2029 | B93: Tranche 2 operational | C93: 15 | D93: Serie A
A94: Q3 2030 | B94: Tranche 3 operational | C94: 20 | D94: Serie A
A96: 8.0 Validation Checkpoints (REV6 §8)
A97: # | B97: Checkpoint | C97: Value | D97: Status
A98: #1 | B98: Revenue at 20 CNC, 60% utilization | C98: ~315 MNOK | D98: ✓
A99: #2 | B99: Total cost at 20 CNC steady state (8% var) | C99: ~92.75 MNOK | D99: ✓
A100: #3 | B100: Break-even at 5 CNC (Seed config) | C100: ~24% utilization | D100: ✓
A101: #4 | B101: Staff ratio | C101: 0.8 FTE per CNC | D101: ✓
A102: #5 | B102: Variable cost (steady state) | C102: 8% | D102: ✓
A103: #6 | B103: Exit valuation (base case) | C103: 2.3B NOK @ 10x EBITDA | D103: ✓
A104: #7 | B104: Founders post-Serie A | C104: 50.6% | D104: ✓
A105: #8 | B105: Accumulated profit 2027–2035 | C105: ~1,254 MNOK | D105: ✓
A106: #9 | B106: Seed pre-money | C106: 130 MNOK | D106: ✓
A107: #10 | B107: CAPEX per CNC (incl. automation) | C107: 10 MNOK | D107: ✓
A108: #11 | B108: First revenue | C108: August 2027 | D108: ✓
... A114: #17 | B114: Founder contribution valuation basis | C114: See VDR 2.3 | D114: ✓

Sheet Revenue
A1: AURELIAN MANUFACTURING — REVENUE MODEL
A2: All amounts in MNOK. Revenue = CNC (avg) × theo_hours × utilization% × hourly_rate. Source: REV6 §2.2
A4: Key Assumptions (from Assumptions sheet)
A5: Theoretical hours / CNC / year | B5: =Assumptions!C7 -> 8760 | C5: hours
A6: Normalized hourly rate | B6: =Assumptions!C8 -> 3000 | C6: NOK
A7: Customer Program threshold | B7: =Assumptions!C9 -> 0.45 | C7: utilization
A8: Revenue per CNC at 60% utilization | B8: =Assumptions!C7*0.6*Assumptions!C8/1000000 -> 15.768 | C8: MNOK — checkpoint ✓
A10: Revenue Build-Up
B11: 2027 H2 | C11: 2028 | D11: 2029 | E11: 2030 | F11: 2031 | G11: 2032 | H11: 2033 | I11: 2034 | J11: 2035 | K11: Notes
A12: CNC machines (avg operating) | B12: 5 | C12: 5 | D12: 12 | E12: 17 | F12: 20 | G12: 20 | H12: 22 | I12: 24 | J12: 25 | K12: REV6 §2.2 — average operating CNC per period
A13: Utilization (%) | B13: 0.2 | C13: 0.375 | D13: 0.425 | E13: 0.475 | F13: 0.525 | G13: 0.575 | H13: 0.6 | I13: 0.625 | J13: 0.65 | K13: REV6 §2.2 — ramp from 20% to 65%
A14: Operating months in period | B14: 5 | C14: 12 | D14: 12 | E14: 12 | F14: 12 | G14: 12 | H14: 12 | I14: 12 | J14: 12 | K14: 2027 H2: Aug–Dec (5 months). Full year thereafter.
A15: Revenue per CNC (annualized, MNOK) | B15: =Assumptions!$C$7*B13*Assumptions!$C$8/1000000 -> 5.256 | C15: =Assumptions!$C$7*C13*Assumptions!$C$8/1000000 -> 9.855 | D15: =Assumptions!$C$7*D13*Assumptions!$C$8/1000000 -> 11.169 | E15: =Assumptions!$C$7*E13*Assumptions!$C$8/1000000 -> 12.483 | F15: =Assumptions!$C$7*F13*Assumptions!$C$8/1000000 -> 13.797 | G15: =Assumptions!$C$7*G13*Assumptions!$C$8/1000000 -> 15.111 | H15: =Assumptions!$C$7*H13*Assumptions!$C$8/1000000 -> 15.768 | I15: =Assumptions!$C$7*I13*Assumptions!$C$8/1000000 -> 16.425 | J15: =Assumptions!$C$7*J13*Assumptions!$C$8/1000000 -> 17.082 | K15: Formula: theo_hours × util% × rate / 1M
A16: Period adjustment (months/12) | B16: =B14/12 -> 0.41666667 | C16: =C14/12 -> 1 | D16: =D14/12 -> 1 | E16: =E14/12 -> 1 | F16: =F14/12 -> 1 | G16: =G14/12 -> 1 | H16: =H14/12 -> 1 | I16: =I14/12 -> 1 | J16: =J14/12 -> 1
A17: TOTAL REVENUE (MNOK) | B17: =B12*B15*B16 -> 10.95 | C17: =C12*C15*C16 -> 49.275 | D17: =D12*D15*D16 -> 134.028 | E17: =E12*E15*E16 -> 212.211 | F17: =F12*F15*F16 -> 275.94 | G17: =G12*G15*G16 -> 302.22 | H17: =H12*H15*H16 -> 346.896 | I17: =I12*I15*I16 -> 394.2 | J17: =J12*J15*J16 -> 427.05 | K17: Formula: CNC_avg × rev_per_CNC × period_adj
A19: Verification vs REV6 §2.2
B20: 2027 H2 | C20: 2028 | D20: 2029 | E20: 2030 | F20: 2031 | G20: 2032 | H20: 2033 | I20: 2034 | J20: 2035
A21: REV6 target revenue (MNOK) | B21: 10.9 | C21: 49.3 | D21: 134 | E21: 212 | F21: 276 | G21: 302 | H21: 347 | I21: 394 | J21: 427
A22: Model calculated revenue (MNOK) | B22: =B17 -> 10.95 | C22: =C17 -> 49.275 | D22: =D17 -> 134.028 | E22: =E17 -> 212.211 | F22: =F17 -> 275.94 | G22: =G17 -> 302.22 | H22: =H17 -> 346.896 | I22: =I17 -> 394.2 | J22: =J17 -> 427.05
A23: Difference (MNOK) | B23: =B22-B21 -> 0.05 | C23: =C22-C21 -> -0.025 | D23: =D22-D21 -> 0.028 | E23: =E22-E21 -> 0.211 | F23: =F22-F21 -> -0.06 | G23: =G22-G21 -> 0.22 | H23: =H22-H21 -> -0.104 | I23: =I22-I21 -> 0.2 | J23: =J22-J21 -> 0.05
A24: Difference (%) | B24: =IF(B21=0,0,B23/B21) -> 0.004587156 | C24: =IF(C21=0,0,C23/C21) -> -0.00050709939 | D24: =IF(D21=0,0,D23/D21) -> 0.00020895522 | E24: =IF(E21=0,0,E23/E21) -> 0.00099528302 | F24: =IF(F21=0,0,F23/F21) -> -0.0002173913 | G24: =IF(G21=0,0,G23/G21) -> 0.00072847682 | H24: =IF(H21=0,0,H23/H21) -> -0.00029971182 | I24: =IF(I21=0,0,I23/I21) -> 0.00050761421 | J24: =IF(J21=0,0,J23/J21) -> 0.00011709602
A26: Revenue Split for Customer Program
B27: 2027 H2 | C27: 2028 | D27: 2029 | E27: 2030 | F27: 2031 | G27: 2032 | H27: 2033 | I27: 2034 | J27: 2035
A28: Revenue at 45% threshold (MNOK) | B28: =B12*Assumptions!$C$7*Assumptions!$C$9*Assumptions!$C$8*B16/1000000 -> 24.6375 | C28: =C12*Assumptions!$C$7*Assumptions!$C$9*Assumptions!$C$8*C16/1000000 -> 59.13 | D28: =D12*Assumptions!$C$7*Assumptions!$C$9*Assumptions!$C$8*D16/1000000 -> 141.912 | E28: =E12*Assumptions!$C$7*Assumptions!$C$9*Assumptions!$C$8*E16/1000000 -> 201.042 | F28: =F12*Assumptions!$C$7*Assumptions!$C$9*Assumptions!$C$8*F16/1000000 -> 236.52 | G28: =G12*Assumptions!$C$7*Assumptions!$C$9*Assumptions!$C$8*G16/1000000 -> 236.52 | H28: =H12*Assumptions!$C$7*Assumptions!$C$9*Assumptions!$C$8*H16/1000000 -> 260.172 | I28: =I12*Assumptions!$C$7*Assumptions!$C$9*Assumptions!$C$8*I16/1000000 -> 283.824 | J28: =J12*Assumptions!$C$7*Assumptions!$C$9*Assumptions!$C$8*J16/1000000 -> 295.65 | K28: Formula: CNC × hours × 45% × rate × adj / 1M
A29: Revenue ABOVE threshold (MNOK) | B29: =MAX(0,B17-B28) -> 0 | C29: =MAX(0,C17-C28) -> 0 | D29: =MAX(0,D17-D28) -> 0 | E29: =MAX(0,E17-E28) -> 11.169 | F29: =MAX(0,F17-F28) -> 39.42 | G29: =MAX(0,G17-G28) -> 65.7 | H29: =MAX(0,H17-H28) -> 86.724 | I29: =MAX(0,I17-I28) -> 110.376 | J29: =MAX(0,J17-J28) -> 131.4
A30: Variable cost % (maturity curve) | B30: =Assumptions!$C$15 -> 0.13 | C30: =Assumptions!$C$15 -> 0.13 | D30: =Assumptions!$C$16 -> 0.1175 | E30: =Assumptions!$C$17 -> 0.105 | F30: =Assumptions!$C$18 -> 0.0925 | G30: =Assumptions!$C$19 -> 0.08 | H30: =Assumptions!$C$19 -> 0.08 | I30: =Assumptions!$C$19 -> 0.08 | J30: =Assumptions!$C$19 -> 0.08 | K30: REV6 §1.1b maturity curve
A31: Marginal profit above threshold (MNOK) | B31: =B29*(1-B30) -> 0 | C31: =C29*(1-C30) -> 0 | D31: =D29*(1-D30) -> 0 | E31: =E29*(1-E30) -> 9.996255 | F31: =F29*(1-F30) -> 35.77365 | G31: =G29*(1-G30) -> 60.444 | H31: =H29*(1-H30) -> 79.78608 | I31: =I29*(1-I30) -> 101.54592 | J31: =J29*(1-J30) -> 120.888
A32: Customer Program (50/50 share, MNOK) | B32: =IF(B13>Assumptions!$C$9,B31*Assumptions!$C$10,0) -> 0 | C32: =IF(C13>Assumptions!$C$9,C31*Assumptions!$C$10,0) -> 0 | D32: =IF(D13>Assumptions!$C$9,D31*Assumptions!$C$10,0) -> 0 | E32: =IF(E13>Assumptions!$C$9,E31*Assumptions!$C$10,0) -> 4.9981275 | F32: =IF(F13>Assumptions!$C$9,F31*Assumptions!$C$10,0) -> 17.886825 | G32: =IF(G13>Assumptions!$C$9,G31*Assumptions!$C$10,0) -> 30.222 | H32: =IF(H13>Assumptions!$C$9,H31*Assumptions!$C$10,0) -> 39.89304 | I32: =IF(I13>Assumptions!$C$9,I31*Assumptions!$C$10,0) -> 50.77296 | J32: =IF(J13>Assumptions!$C$9,J31*Assumptions!$C$10,0) -> 60.444 | K32: Only when util > 45%, strategic customers only
A33: REV6 Customer Program target (MNOK) | B33: 0 | C33: 0 | D33: 0 | E33: 0 | F33: 16.4 | G33: 27.3 | H33: 42 | I33: 57.6 | J33: 72
A35: Cumulative Revenue
A36: Cumulative revenue (MNOK) | B36: =B17 -> 10.95 | C36: =B36+C17 -> 60.225 | D36: =C36+D17 -> 194.253 | E36: =D36+E17 -> 406.464 | F36: =E36+F17 -> 682.404 | G36: =F36+G17 -> 984.624 | H36: =G36+H17 -> 1331.52 | I36: =H36+I17 -> 1725.72 | J36: =I36+J17 -> 2152.77
A38: Revenue per CNC Analysis
B39: 2027 H2 | C39: 2028 | D39: 2029 | E39: 2030 | F39: 2031 | G39: 2032 | H39: 2033 | I39: 2034 | J39: 2035
A40: Revenue per CNC (period, MNOK) | B40: =IF(B12=0,0,B17/B12) -> 2.19 | C40: =IF(C12=0,0,C17/C12) -> 9.855 | D40: =IF(D12=0,0,D17/D12) -> 11.169 | E40: =IF(E12=0,0,E17/E12) -> 12.483 | F40: =IF(F12=0,0,F17/F12) -> 13.797 | G40: =IF(G12=0,0,G17/G12) -> 15.111 | H40: =IF(H12=0,0,H17/H12) -> 15.768 | I40: =IF(I12=0,0,I17/I12) -> 16.425 | J40: =IF(J12=0,0,J17/J12) -> 17.082
A41: Productive hours per CNC (period) | B41: =Assumptions!$C$7*B13*B16 -> 730 | C41: =Assumptions!$C$7*C13*C16 -> 3285 | D41: =Assumptions!$C$7*D13*D16 -> 3723 | E41: =Assumptions!$C$7*E13*E16 -> 4161 | F41: =Assumptions!$C$7*F13*F16 -> 4599 | G41: =Assumptions!$C$7*G13*G16 -> 5037 | H41: =Assumptions!$C$7*H13*H16 -> 5256 | I41: =Assumptions!$C$7*I13*I16 -> 5475 | J41: =Assumptions!$C$7*J13*J16 -> 5694
A42: Effective hourly rate (NOK) | B42: =Assumptions!$C$8 -> 3000 | C42: =Assumptions!$C$8 -> 3000 | D42: =Assumptions!$C$8 -> 3000 | E42: =Assumptions!$C$8 -> 3000 | F42: =Assumptions!$C$8 -> 3000 | G42: =Assumptions!$C$8 -> 3000 | H42: =Assumptions!$C$8 -> 3000 | I42: =Assumptions!$C$8 -> 3000 | J42: =Assumptions!$C$8 -> 3000 | K42: Constant 3,000 NOK — defence/O&G upside not modeled
A44: Notes
A45: • 2027 H2: Production starts August 2027. 5 months of operations (Aug–Dec).
A46: • Utilization ramps conservatively from 20% (startup) to 65% (steady state by 2035).
A47: • Customer Program applies fleet-wide in model (conservative). In practice, per-customer → ~20 MNOK less sharing.
A48: • Hourly rate of 3,000 NOK is floor. Defence/O&G premiums represent unmodeled upside.
A49: • Serie A tranches are customer-driven. Deployment may accelerate or decelerate based on order book.
A50: • REV6 §3.5: Realistic Customer Program ~20–25 MNOK/yr vs modeled ~42 MNOK → +22 MNOK unmodeled upside at steady state.
A51: • NOTE: Customer Program formula follows REV6 §3.4 exactly. Minor differences vs §2.2 table are due to:
A52: (a) 2030: Model triggers at 47.5% > 45%, REV6 table shows 0 — likely deferred activation during ramp-up.
A53: (b) Later years: REV6 §3.5 notes fleet-wide model overestimates vs per-customer reality by ~20–25 MNOK/yr.
A54: (c) P&L sheet will reconcile to REV6 §2.2 exact values. This sheet shows formula-derived figures.

Sheet P&L
A1: AURELIAN MANUFACTURING — PROFIT & LOSS
A2: All amounts in MNOK. Source: REV6 §2.2, §3. Formulas reference Assumptions & Revenue sheets.
A4: Operating Inputs (from Revenue & Assumptions)
B5: 2027 H2 | C5: 2028 | D5: 2029 | E5: 2030 | F5: 2031 | G5: 2032 | H5: 2033 | I5: 2034 | J5: 2035 | K5: Notes
A6: CNC machines (avg operating) | B6: =Revenue!B12 -> 5 | C6: =Revenue!C12 -> 5 | D6: =Revenue!D12 -> 12 | E6: =Revenue!E12 -> 17 | F6: =Revenue!F12 -> 20 | G6: =Revenue!G12 -> 20 | H6: =Revenue!H12 -> 22 | I6: =Revenue!I12 -> 24 | J6: =Revenue!J12 -> 25 | K6: From Revenue sheet
A7: CNC for cost basis (avg deployed in period) | B7: 5 | C7: 5 | D7: 10 | E7: 17 | F7: 20 | G7: 20 | H7: 22 | I7: 24 | J7: 25 | K7: Matches avg deployment per REV6 §2.1
A8: Utilization (%) | B8: =Revenue!B13 -> 0.2 | C8: =Revenue!C13 -> 0.375 | D8: =Revenue!D13 -> 0.425 | E8: =Revenue!E13 -> 0.475 | F8: =Revenue!F13 -> 0.525 | G8: =Revenue!G13 -> 0.575 | H8: =Revenue!H13 -> 0.6 | I8: =Revenue!I13 -> 0.625 | J8: =Revenue!J13 -> 0.65 | K8: From Revenue sheet
A9: Period adjustment (months/12) | B9: =Revenue!B16 -> 0.41666667 | C9: =Revenue!C16 -> 1 | D9: =Revenue!D16 -> 1 | E9: =Revenue!E16 -> 1 | F9: =Revenue!F16 -> 1 | G9: =Revenue!G16 -> 1 | H9: =Revenue!H16 -> 1 | I9: =Revenue!I16 -> 1 | J9: =Revenue!J16 -> 1
A10: Operational FTEs | B10: 6 | C10: 6 | D10: 10 | E10: 13 | F10: 16 | G10: 16 | H10: 18 | I10: 19 | J10: 20 | K10: REV6 §1.3b + §3.6: sub-linear, 0.8 FTE/CNC
A11: Variable cost % (maturity curve) | B11: =Revenue!B30 -> 0.13 | C11: =Revenue!C30 -> 0.13 | D11: =Revenue!D30 -> 0.1175 | E11: =Revenue!E30 -> 0.105 | F11: =Revenue!F30 -> 0.0925 | G11: =Revenue!G30 -> 0.08 | H11: =Revenue!H30 -> 0.08 | I11: =Revenue!I30 -> 0.08 | J11: =Revenue!J30 -> 0.08 | K11: REV6 §1.1b via Revenue sheet
A12: Seed CNC machines (for debt) | B12: 5 | C12: 5 | D12: 5 | E12: 5 | F12: 5 | G12: 5 | H12: 5 | I12: 5 | J12: 5 | K12: Constant from Seed round
A13: Serie A CNC machines deployed (EOY) | B13: 0 | C13: 0 | D13: 5 | E13: 12 | F13: 15 | G13: 15 | H13: 17 | I13: 19 | J13: 20 | K13: REV6 §2.1 — avg Serie A CNC for cost calc
A15: Revenue
B16: 2027 H2 | C16: 2028 | D16: 2029 | E16: 2030 | F16: 2031 | G16: 2032 | H16: 2033 | I16: 2034 | J16: 2035 | K16: Notes
A17: TOTAL REVENUE | B17: =Revenue!B17 -> 10.95 | C17: =Revenue!C17 -> 49.275 | D17: =Revenue!D17 -> 134.028 | E17: =Revenue!E17 -> 212.211 | F17: =Revenue!F17 -> 275.94 | G17: =Revenue!G17 -> 302.22 | H17: =Revenue!H17 -> 346.896 | I17: =Revenue!I17 -> 394.2 | J17: =Revenue!J17 -> 427.05 | K17: From Revenue sheet
A19: Variable Costs
B20: 2027 H2 | C20: 2028 | D20: 2029 | E20: 2030 | F20: 2031 | G20: 2032 | H20: 2033 | I20: 2034 | J20: 2035 | K20: Notes
A21: Variable costs (materials, tooling, consumables) | B21: =-B17*B11 -> -1.4235 | C21: =-C17*C11 -> -6.40575 | D21: =-D17*D11 -> -15.74829 | E21: =-E17*E11 -> -22.282155 | F21: =-F17*F11 -> -25.52445 | G21: =-G17*G11 -> -24.1776 | H21: =-H17*H11 -> -27.75168 | I21: =-I17*I11 -> -31.536 | J21: =-J17*J11 -> -34.164 | K21: Revenue × var_cost%
A23: Personnel Costs
B24: 2027 H2 | C24: 2028 | D24: 2029 | E24: 2030 | F24: 2031 | G24: 2032 | H24: 2033 | I24: 2034 | J24: 2035 | K24: Notes
A25: Operational payroll | B25: =-B10*Assumptions!$C$52*B9/1000000 -> -2.75 | C25: =-C10*Assumptions!$C$52*C9/1000000 -> -6.6 | D25: =-D10*Assumptions!$C$52*D9/1000000 -> -11 | E25: =-E10*Assumptions!$C$52*E9/1000000 -> -14.3 | F25: =-F10*Assumptions!$C$52*F9/1000000 -> -17.6 | G25: =-G10*Assumptions!$C$52*G9/1000000 -> -17.6 | H25: =-H10*Assumptions!$C$52*H9/1000000 -> -19.8 | I25: =-I10*Assumptions!$C$52*I9/1000000 -> -20.9 | J25: =-J10*Assumptions!$C$52*J9/1000000 -> -22 | K25: Ops FTE × 1.1M × period adj
A26: Administration & sales payroll | B26: =-Assumptions!$C$51*Assumptions!$C$53*B9/1000000 -> -2.3333333 | C26: =-Assumptions!$C$51*Assumptions!$C$53*C9/1000000 -> -5.6 | D26: =-Assumptions!$C$51*Assumptions!$C$53*D9/1000000 -> -5.6 | E26: =-Assumptions!$C$51*Assumptions!$C$53*E9/1000000 -> -5.6 | F26: =-Assumptions!$C$51*Assumptions!$C$53*F9/1000000 -> -5.6 | G26: =-Assumptions!$C$51*Assumptions!$C$53*G9/1000000 -> -5.6 | H26: =-Assumptions!$C$51*Assumptions!$C$53*H9/1000000 -> -5.6 | I26: =-Assumptions!$C$51*Assumptions!$C$53*I9/1000000 -> -5.6 | J26: =-Assumptions!$C$51*Assumptions!$C$53*J9/1000000 -> -5.6 | K26: 4 FTE × 1.4M × period adj
A27: Total personnel | B27: =B25+B26 -> -5.0833333 | C27: =C25+C26 -> -12.2 | D27: =D25+D26 -> -16.6 | E27: =E25+E26 -> -19.9 | F27: =F25+F26 -> -23.2 | G27: =G25+G26 -> -23.2 | H27: =H25+H26 -> -25.4 | I27: =I25+I26 -> -26.5 | J27: =J25+J26 -> -27.6 | K27: Sum ops + admin
A29: Depreciation
B30: 2027 H2 | C30: 2028 | D30: 2029 | E30: 2030 | F30: 2031 | G30: 2032 | H30: 2033 | I30: 2034 | J30: 2035 | K30: Notes
A31: CNC machine depreciation | B31: =-B7*Assumptions!$C$25*B9/1000000 -> -2.6041667 | C31: =-C7*Assumptions!$C$25*C9/1000000 -> -6.25 | D31: =-D7*Assumptions!$C$25*D9/1000000 -> -12.5 | E31: =-E7*Assumptions!$C$25*E9/1000000 -> -21.25 | F31: =-F7*Assumptions!$C$25*F9/1000000 -> -25 | G31: =-G7*Assumptions!$C$25*G9/1000000 -> -25 | H31: =-H7*Assumptions!$C$25*H9/1000000 -> -27.5 | I31: =-I7*Assumptions!$C$25*I9/1000000 -> -30 | J31: =-J7*Assumptions!$C$25*J9/1000000 -> -31.25 | K31: EOY CNC × 1.25M × period adj
A32: Shop base depreciation | B32: =-Assumptions!$C$71*B9/1000000 -> -0.44791667 | C32: =-Assumptions!$C$71*C9/1000000 -> -1.075 | D32: =-Assumptions!$C$71*D9/1000000 -> -1.075 | E32: =-Assumptions!$C$71*E9/1000000 -> -1.075 | F32: =-Assumptions!$C$71*F9/1000000 -> -1.075 | G32: =-Assumptions!$C$71*G9/1000000 -> -1.075 | H32: =-Assumptions!$C$71*H9/1000000 -> -1.075 | I32: =-Assumptions!$C$71*I9/1000000 -> -1.075 | J32: =-Assumptions!$C$71*J9/1000000 -> -1.075 | K32: 1.075M/yr × period adj
A33: Total depreciation | B33: =B31+B32 -> -3.0520833 | C33: =C31+C32 -> -7.325 | D33: =D31+D32 -> -13.575 | E33: =E31+E32 -> -22.325 | F33: =F31+F32 -> -26.075 | G33: =G31+G32 -> -26.075 | H33: =H31+H32 -> -28.575 | I33: =I31+I32 -> -31.075 | J33: =J31+J32 -> -32.325 | K33: CNC + shop base
A35: Finance Costs
B36: 2027 H2 | C36: 2028 | D36: 2029 | E36: 2030 | F36: 2031 | G36: 2032 | H36: 2033 | I36: 2034 | J36: 2035 | K36: Notes
A37: Seed debt outstanding (MNOK) | B37: =(B12*Assumptions!$C$27+4300000)/1000000 -> 29.3 | C37: =(C12*Assumptions!$C$27+4300000)/1000000 -> 29.3 | D37: =(D12*Assumptions!$C$27+4300000)/1000000 -> 29.3 | E37: =(E12*Assumptions!$C$27+4300000)/1000000 -> 29.3 | F37: =(F12*Assumptions!$C$27+4300000)/1000000 -> 29.3 | G37: =(G12*Assumptions!$C$27+4300000)/1000000 -> 29.3 | H37: =(H12*Assumptions!$C$27+4300000)/1000000 -> 29.3 | I37: =(I12*Assumptions!$C$27+4300000)/1000000 -> 29.3 | J37: =(J12*Assumptions!$C$27+4300000)/1000000 -> 29.3 | K37: 5 CNC × 5M + 4.3M shop base
A38: Serie A debt outstanding (MNOK) | B38: =B13*Assumptions!$C$28/1000000 -> 0 | C38: =C13*Assumptions!$C$28/1000000 -> 0 | D38: =D13*Assumptions!$C$28/1000000 -> 35 | E38: =E13*Assumptions!$C$28/1000000 -> 84 | F38: =F13*Assumptions!$C$28/1000000 -> 105 | G38: =G13*Assumptions!$C$28/1000000 -> 105 | H38: =H13*Assumptions!$C$28/1000000 -> 119 | I38: =I13*Assumptions!$C$28/1000000 -> 133 | J38: =J13*Assumptions!$C$28/1000000 -> 140 | K38: Serie A CNC × 7M
A39: Total debt outstanding (MNOK) | B39: =B37+B38 -> 29.3 | C39: =C37+C38 -> 29.3 | D39: =D37+D38 -> 64.3 | E39: =E37+E38 -> 113.3 | F39: =F37+F38 -> 134.3 | G39: =G37+G38 -> 134.3 | H39: =H37+H38 -> 148.3 | I39: =I37+I38 -> 162.3 | J39: =J37+J38 -> 169.3
A40: Finance cost (interest expense) | B40: =-B39*Assumptions!$C$26*B9 -> -0.915625 | C40: =-C39*Assumptions!$C$26*C9 -> -2.1975 | D40: =-D39*Assumptions!$C$26*D9 -> -4.8225 | E40: =-E39*Assumptions!$C$26*E9 -> -8.4975 | F40: =-F39*Assumptions!$C$26*F9 -> -10.0725 | G40: =-G39*Assumptions!$C$26*G9 -> -10.0725 | H40: =-H39*Assumptions!$C$26*H9 -> -11.1225 | I40: =-I39*Assumptions!$C$26*I9 -> -12.1725 | J40: =-J39*Assumptions!$C$26*J9 -> -12.6975 | K40: Total debt × 7.5% × period adj
A42: Other Operating Costs
B43: 2027 H2 | C43: 2028 | D43: 2029 | E43: 2030 | F43: 2031 | G43: 2032 | H43: 2033 | I43: 2034 | J43: 2035 | K43: Notes
A44: Facility lease | B44: =-Assumptions!$C$68*B9/1000000 -> -2.1666667 | C44: =-Assumptions!$C$68*C9/1000000 -> -5.2 | D44: =-Assumptions!$C$68*D9/1000000 -> -5.2 | E44: =-Assumptions!$C$68*E9/1000000 -> -5.2 | F44: =-Assumptions!$C$68*F9/1000000 -> -5.2 | G44: =-Assumptions!$C$68*G9/1000000 -> -5.2 | H44: =-Assumptions!$C$68*H9/1000000 -> -5.2 | I44: =-Assumptions!$C$68*I9/1000000 -> -5.2 | J44: =-Assumptions!$C$68*J9/1000000 -> -5.2 | K44: 5.2M/yr × period adj. From Q3 2027.
A45: Other operating costs (IT, insurance, etc.) | B45: =-B7*Assumptions!$C$70*B9/1000000 -> -0.3125 | C45: =-C7*Assumptions!$C$70*C9/1000000 -> -0.75 | D45: =-D7*Assumptions!$C$70*D9/1000000 -> -1.5 | E45: =-E7*Assumptions!$C$70*E9/1000000 -> -2.55 | F45: =-F7*Assumptions!$C$70*F9/1000000 -> -3 | G45: =-G7*Assumptions!$C$70*G9/1000000 -> -3 | H45: =-H7*Assumptions!$C$70*H9/1000000 -> -3.3 | I45: =-I7*Assumptions!$C$70*I9/1000000 -> -3.6 | J45: =-J7*Assumptions!$C$70*J9/1000000 -> -3.75 | K45: EOY CNC × 150K × period adj
A46: Total other operating costs | B46: =B44+B45 -> -2.4791667 | C46: =C44+C45 -> -5.95 | D46: =D44+D45 -> -6.7 | E46: =E44+E45 -> -7.75 | F46: =F44+F45 -> -8.2 | G46: =G44+G45 -> -8.2 | H46: =H44+H45 -> -8.5 | I46: =I44+I45 -> -8.8 | J46: =J44+J45 -> -8.95 | K46: Facility + other opex
A48: Total Costs
B49: 2027 H2 | C49: 2028 | D49: 2029 | E49: 2030 | F49: 2031 | G49: 2032 | H49: 2033 | I49: 2034 | J49: 2035 | K49: Notes
A50: TOTAL COSTS | B50: =B21+B27+B33+B40+B46 -> -12.953708 | C50: =C21+C27+C33+C40+C46 -> -34.07825 | D50: =D21+D27+D33+D40+D46 -> -57.44579 | E50: =E21+E27+E33+E40+E46 -> -80.754655 | F50: =F21+F27+F33+F40+F46 -> -93.07195 | G50: =G21+G27+G33+G40+G46 -> -91.7251 | H50: =H21+H27+H33+H40+H46 -> -101.34918 | I50: =I21+I27+I33+I40+I46 -> -110.0835 | J50: =J21+J27+J33+J40+J46 -> -115.7365 | K50: Sum all cost categories
A51: REV6 §2.2 target cost (MNOK) | B51: -13.4 | C51: -34.1 | D51: -61.1 | E51: -80.2 | F51: -92.8 | G51: -92.4 | H51: -98 | I51: -103.8 | J51: -107.2 | K51: For verification
A52: Cost difference vs REV6 | B52: =B50-B51 -> 0.44629167 | C52: =C50-C51 -> 0.02175 | D52: =D50-D51 -> 3.65421 | E52: =E50-E51 -> -0.554655 | F52: =F50-F51 -> -0.27195 | G52: =G50-G51 -> 0.6749 | H52: =H50-H51 -> -3.34918 | I52: =I50-I51 -> -6.2835 | J52: =J50-J51 -> -8.5365 | K52: Negative = model has higher costs
A54: Profitability
B55: 2027 H2 | C55: 2028 | D55: 2029 | E55: 2030 | F55: 2031 | G55: 2032 | H55: 2033 | I55: 2034 | J55: 2035 | K55: Notes
A56: GROSS PROFIT (before Customer Program) | B56: =B17+B50 -> -2.0037083 | C56: =C17+C50 -> 15.19675 | D56: =D17+D50 -> 76.58221 | E56: =E17+E50 -> 131.45634 | F56: =F17+F50 -> 182.86805 | G56: =G17+G50 -> 210.4949 | H56: =H17+H50 -> 245.54682 | I56: =I17+I50 -> 284.1165 | J56: =J17+J50 -> 311.3135 | K56: Revenue + Total Costs (costs are negative)
A57: REV6 §2.2 target gross profit | B57: -2.5 | C57: 15.2 | D57: 72.9 | E57: 131.8 | F57: 183.2 | G57: 209.6 | H57: 249 | I57: 290.2 | J57: 319.8 | K57: For verification
A58: Customer Program (50/50 sharing) | B58: =-Revenue!B32 -> 0 | C58: =-Revenue!C32 -> 0 | D58: =-Revenue!D32 -> 0 | E58: =-Revenue!E32 -> -4.9981275 | F58: =-Revenue!F32 -> -17.886825 | G58: =-Revenue!G32 -> -30.222 | H58: =-Revenue!H32 -> -39.89304 | I58: =-Revenue!I32 -> -50.77296 | J58: =-Revenue!J32 -> -60.444 | K58: From Revenue sheet, negative = paid out
A59: REV6 §2.2 Customer Program target | B59: 0 | C59: 0 | D59: 0 | E59: 0 | F59: -16.4 | G59: -27.3 | H59: -42 | I59: -57.6 | J59: -72 | K59: For verification
A61: AURELIAN PROFIT (EBIT) | B61: =B56+B58 -> -2.0037083 | C61: =C56+C58 -> 15.19675 | D61: =D56+D58 -> 76.58221 | E61: =E56+E58 -> 126.45822 | F61: =F56+F58 -> 164.98122 | G61: =G56+G58 -> 180.2729 | H61: =H56+H58 -> 205.65378 | I61: =I56+I58 -> 233.34354 | J61: =J56+J58 -> 250.8695 | K61: Gross Profit - Customer Program
A62: REV6 §2.2 Aurelian Profit target | B62: -2.5 | C62: 15.2 | D62: 72.9 | E62: 131.8 | F62: 166.8 | G62: 182.3 | H62: 207 | I62: 232.6 | J62: 247.8 | K62: For verification
A63: EBIT difference vs REV6 | B63: =B61-B62 -> 0.49629167 | C63: =C61-C62 -> -0.00325 | D63: =D61-D62 -> 3.68221 | E63: =E61-E62 -> -5.3417825 | F63: =F61-F62 -> -1.818775 | G63: =G61-G62 -> -2.0271 | H63: =H61-H62 -> -1.34622 | I63: =I61-I62 -> 0.74354 | J63: =J61-J62 -> 3.0695 | K63: Model vs target
A65: EBITDA Reconciliation
B66: 2027 H2 | C66: 2028 | D66: 2029 | E66: 2030 | F66: 2031 | G66: 2032 | H66: 2033 | I66: 2034 | J66: 2035 | K66: Notes
A67: EBITDA | B67: =B61-B33 -> 1.048375 | C67: =C61-C33 -> 22.52175 | D67: =D61-D33 -> 90.15721 | E67: =E61-E33 -> 148.78322 | F67: =F61-F33 -> 191.05622 | G67: =G61-G33 -> 206.3479 | H67: =H61-H33 -> 234.22878 | I67: =I61-I33 -> 264.41854 | J67: =J61-J33 -> 283.1945 | K67: EBIT + Depreciation add-back
A68: EBITDA margin (%) | B68: =IF(B17=0,0,B67/B17) -> 0.095742009 | C68: =IF(C17=0,0,C67/C17) -> 0.4570624 | D68: =IF(D17=0,0,D67/D17) -> 0.67267444 | E68: =IF(E17=0,0,E67/E17) -> 0.70110983 | F68: =IF(F17=0,0,F67/F17) -> 0.69238322 | G68: =IF(G17=0,0,G67/G17) -> 0.68277381 | H68: =IF(H17=0,0,H67/H17) -> 0.67521326 | I68: =IF(I17=0,0,I67/I17) -> 0.67077255 | J68: =IF(J17=0,0,J67/J17) -> 0.66314132 | K68: EBITDA / Revenue
A69: EBIT margin (%) | B69: =IF(B17=0,0,B61/B17) -> -0.18298706 | C69: =IF(C17=0,0,C61/C17) -> 0.3084069 | D69: =IF(D17=0,0,D61/D17) -> 0.57138964 | E69: =IF(E17=0,0,E61/E17) -> 0.59590793 | F69: =IF(F17=0,0,F61/F17) -> 0.59788804 | G69: =IF(G17=0,0,G61/G17) -> 0.5964956 | H69: =IF(H17=0,0,H61/H17) -> 0.59283987 | I69: =IF(I17=0,0,I61/I17) -> 0.59194201 | J69: =IF(J17=0,0,J61/J17) -> 0.58744761 | K69: EBIT / Revenue
A71: Cumulative Aurelian Profit
B72: 2027 H2 | C72: 2028 | D72: 2029 | E72: 2030 | F72: 2031 | G72: 2032 | H72: 2033 | I72: 2034 | J72: 2035 | K72: Notes
A73: Cumulative Aurelian Profit (MNOK) | B73: =B61 -> -2.0037083 | C73: =B73+C61 -> 13.193042 | D73: =C73+D61 -> 89.775252 | E73: =D73+E61 -> 216.23347 | F73: =E73+F61 -> 381.21469 | G73: =F73+G61 -> 561.48759 | H73: =G73+H61 -> 767.14137 | I73: =H73+I61 -> 1000.4849 | J73: =I73+J61 -> 1251.3544 | K73: REV6 §2.2 target: ~1,254 MNOK
A75: Key Metrics
B76: 2027 H2 | C76: 2028 | D76: 2029 | E76: 2030 | F76: 2031 | G76: 2032 | H76: 2033 | I76: 2034 | J76: 2035 | K76: Notes
A77: Revenue per CNC (MNOK) | B77: =IF(B6=0,0,B17/B6) -> 2.19 | C77: =IF(C6=0,0,C17/C6) -> 9.855 | D77: =IF(D6=0,0,D17/D6) -> 11.169 | E77: =IF(E6=0,0,E17/E6) -> 12.483 | F77: =IF(F6=0,0,F17/F6) -> 13.797 | G77: =IF(G6=0,0,G17/G6) -> 15.111 | H77: =IF(H6=0,0,H17/H6) -> 15.768 | I77: =IF(I6=0,0,I17/I6) -> 16.425 | J77: =IF(J6=0,0,J17/J6) -> 17.082 | K77: Total revenue / avg CNC
A78: Cost per CNC (MNOK) | B78: =IF(B6=0,0,-B50/B6) -> 2.5907417 | C78: =IF(C6=0,0,-C50/C6) -> 6.81565 | D78: =IF(D6=0,0,-D50/D6) -> 4.7871492 | E78: =IF(E6=0,0,-E50/E6) -> 4.7502738 | F78: =IF(F6=0,0,-F50/F6) -> 4.6535975 | G78: =IF(G6=0,0,-G50/G6) -> 4.586255 | H78: =IF(H6=0,0,-H50/H6) -> 4.6067809 | I78: =IF(I6=0,0,-I50/I6) -> 4.5868125 | J78: =IF(J6=0,0,-J50/J6) -> 4.62946 | K78: Total cost / avg CNC
A79: Aurelian Profit per CNC (MNOK) | B79: =IF(B6=0,0,B61/B6) -> -0.40074167 | C79: =IF(C6=0,0,C61/C6) -> 3.03935 | D79: =IF(D6=0,0,D61/D6) -> 6.3818508 | E79: =IF(E6=0,0,E61/E6) -> 7.4387187 | F79: =IF(F6=0,0,F61/F6) -> 8.2490613 | G79: =IF(G6=0,0,G61/G6) -> 9.013645 | H79: =IF(H6=0,0,H61/H6) -> 9.3478991 | I79: =IF(I6=0,0,I61/I6) -> 9.7226475 | J79: =IF(J6=0,0,J61/J6) -> 10.03478 | K79: EBIT / avg CNC
A80: Revenue per FTE (MNOK) | B80: =IF((B10+Assumptions!$C$51)=0,0,B17/(B10+Assumptions!$C$51)) -> 1.095 | C80: =IF((C10+Assumptions!$C$51)=0,0,C17/(C10+Assumptions!$C$51)) -> 4.9275 | D80: =IF((D10+Assumptions!$C$51)=0,0,D17/(D10+Assumptions!$C$51)) -> 9.5734286 | E80: =IF((E10+Assumptions!$C$51)=0,0,E17/(E10+Assumptions!$C$51)) -> 12.483 | F80: =IF((F10+Assumptions!$C$51)=0,0,F17/(F10+Assumptions!$C$51)) -> 13.797 | G80: =IF((G10+Assumptions!$C$51)=0,0,G17/(G10+Assumptions!$C$51)) -> 15.111 | H80: =IF((H10+Assumptions!$C$51)=0,0,H17/(H10+Assumptions!$C$51)) -> 15.768 | I80: =IF((I10+Assumptions!$C$51)=0,0,I17/(I10+Assumptions!$C$51)) -> 17.13913 | J80: =IF((J10+Assumptions!$C$51)=0,0,J17/(J10+Assumptions!$C$51)) -> 17.79375 | K80: Revenue / total staff
A81: Variable costs (absolute, MNOK) | B81: =-B21 -> 1.4235 | C81: =-C21 -> 6.40575 | D81: =-D21 -> 15.74829 | E81: =-E21 -> 22.282155 | F81: =-F21 -> 25.52445 | G81: =-G21 -> 24.1776 | H81: =-H21 -> 27.75168 | I81: =-I21 -> 31.536 | J81: =-J21 -> 34.164 | K81: For reference
A83: Steady State Validation — REV6 §3.6 (20 CNC @ 60%, 8% var cost)
A84: Component | B84: REV6 Target | C84: Model (2032) | D84: Difference
A85: Operational payroll | B85: 17.6 | C85: =-G25 -> 17.6 | D85: =C85-B85 -> 0
A86: Administration | B86: 5.6 | C86: =-G26 -> 5.6 | D86: =C86-B86 -> 0
A87: CNC depreciation | B87: 25 | C87: =-G31 -> 25 | D87: =C87-B87 -> 0
A88: Shop base depreciation | B88: 1.08 | C88: =-G32 -> 1.075 | D88: =C88-B88 -> -0.005
A89: Finance cost | B89: 10.07 | C89: =-G40 -> 10.0725 | D89: =C89-B89 -> 0.0025
A90: Facility lease | B90: 5.2 | C90: =-G44 -> 5.2 | D90: =C90-B90 -> 0
A91: Variable costs (8%) | B91: 25.2 | C91: =-G21 -> 24.1776 | D91: =C91-B91 -> -1.0224
A92: Other operating costs | B92: 3 | C92: =-G45 -> 3 | D92: =C92-B92 -> 0
A93: Total cost | B93: 92.75 | C93: =-G50 -> 91.7251 | D93: =C93-B93 -> -1.0249
A94: Revenue @ 60% | B94: 315 | C94: =G17 -> 302.22 | D94: =C94-B94 -> -12.78
A95: Result before tax | B95: 222.3 | C95: =G56 -> 210.4949 | D95: =C95-B95 -> -11.8051

Sheet Cash Flow
A1: AURELIAN MANUFACTURING — CASH FLOW STATEMENT
A2: All amounts in MNOK. Source: REV6 §2, §3, §7. Includes pre-revenue 2026.
A4: A. Operating Cash Flow
B5: 2026 | C5: 2027 H2 | D5: 2028 | E5: 2029 | F5: 2030 | G5: 2031 | H5: 2032 | I5: 2033 | J5: 2034 | K5: 2035 | L5: Notes
A6: EBIT (from P&L) | B6: 0 | C6: ='P&L'!B61 -> -2.0037083 | D6: ='P&L'!C61 -> 15.19675 | E6: ='P&L'!D61 -> 76.58221 | F6: ='P&L'!E61 -> 126.45822 | G6: ='P&L'!F61 -> 164.98122 | H6: ='P&L'!G61 -> 180.2729 | I6: ='P&L'!H61 -> 205.65378 | J6: ='P&L'!I61 -> 233.34354 | K6: ='P&L'!J61 -> 250.8695 | L6: P&L: AURELIAN PROFIT (EBIT)
A7: (+) Depreciation add-back | B7: 0 | C7: =-'P&L'!B33 -> 3.0520833 | D7: =-'P&L'!C33 -> 7.325 | E7: =-'P&L'!D33 -> 13.575 | F7: =-'P&L'!E33 -> 22.325 | G7: =-'P&L'!F33 -> 26.075 | H7: =-'P&L'!G33 -> 26.075 | I7: =-'P&L'!H33 -> 28.575 | J7: =-'P&L'!I33 -> 31.075 | K7: =-'P&L'!J33 -> 32.325 | L7: Non-cash: CNC + shop base depr
A8: (-) Working capital changes | B8: 0 | C8: 0 | D8: 0 | E8: 0 | F8: 0 | G8: 0 | H8: 0 | I8: 0 | J8: 0 | K8: 0 | L8: From Balance Sheet NWC change
A9: NET OPERATING CASH FLOW | B9: =B6+B7+B8 -> 0 | C9: =C6+C7+C8 -> 1.048375 | D9: =D6+D7+D8 -> 22.52175 | E9: =E6+E7+E8 -> 90.15721 | F9: =F6+F7+F8 -> 148.78322 | G9: =G6+G7+G8 -> 191.05622 | H9: =H6+H7+H8 -> 206.3479 | I9: =I6+I7+I8 -> 234.22878 | ... K9: =K6+K7+K8 -> 283.1945 | L9: EBIT + Depreciation + WC changes
A11: B. Investing Cash Flow (CAPEX)
B12: 2026 | C12: 2027 H2 | D12: 2028 | E12: 2029 | F12: 2030 | G12: 2031 | H12: 2032 | I12: 2033 | J12: 2034 | K12: 2035 | L12: Notes
A13: New CNC machines purchased (units) | B13: 0 | C13: 5 | D13: 5 | E13: 5 | F13: 5 | G13: 0 | H13: 0 | I13: 2 | J13: 2 | K13: 1 | L13: REV6 §2.1: 5+5+5+5=20 core, then organic
A14: (-) CNC machine purchases | B14: =-B13*Assumptions!$C$23/1000000 -> 0 | C14: =-C13*Assumptions!$C$23/1000000 -> -50 | D14: =-D13*Assumptions!$C$23/1000000 -> -50 | E14: =-E13*Assumptions!$C$23/1000000 -> -50 | F14: =-F13*Assumptions!$C$23/1000000 -> -50 | G14: =-G13*Assumptions!$C$23/1000000 -> 0 | H14: =-H13*Assumptions!$C$23/1000000 -> 0 | I14: =-I13*Assumptions!$C$23/1000000 -> -20 | ... K14: =-K13*Assumptions!$C$23/1000000 -> -10 | L14: Units × 10M per CNC
A15: (-) Shop base setup | B15: 0 | C15: -8.62 | D15: 0 | E15: 0 | F15: 0 | G15: 0 | H15: 0 | I15: 0 | J15: 0 | K15: 0 | L15: REV6 §1.2c — One-time per site, 8.6M
A16: (-) Facility setup & commissioning | B16: 0 | C16: -3 | D16: 0 | E16: 0 | F16: 0 | G16: 0 | H16: 0 | I16: 0 | J16: 0 | K16: 0 | L16: REV6 §7.2 — IT/OT, tooling, automation
A17: (-) Certifications (AS9100, AQAP, ISO) | B17: 0 | C17: -2 | D17: 0 | E17: 0 | F17: 0 | G17: 0 | H17: 0 | I17: 0 | J17: 0 | K17: 0 | L17: REV6 §7.2 — Defence market access
A18: (-) Platform engineering (self-funded) | B18: 0 | C18: 0 | D18: 0 | E18: 0 | F18: -5.6 | G18: -5.6 | H18: -5.6 | I18: -5.6 | J18: -5.6 | K18: -5.6 | L18: REV6 §7.4 — 4-5 FTE from Q1 2030, ~5.6M/yr
A19: NET INVESTING CASH FLOW | B19: =B14+B15+B16+B17+B18 -> 0 | C19: =C14+C15+C16+C17+C18 -> -63.62 | D19: =D14+D15+D16+D17+D18 -> -50 | E19: =E14+E15+E16+E17+E18 -> -50 | F19: =F14+F15+F16+F17+F18 -> -55.6 | G19: =G14+G15+G16+G17+G18 -> -5.6 | H19: =H14+H15+H16+H17+H18 -> -5.6 | I19: =I14+I15+I16+I17+I18 -> -25.6 | ... K19: =K14+K15+K16+K17+K18 -> -15.6 | L19: Total CAPEX
A21: C. Financing Cash Flow
B22: 2026 | C22: 2027 H2 | D22: 2028 | E22: 2029 | F22: 2030 | G22: 2031 | H22: 2032 | I22: 2033 | J22: 2034 | K22: 2035 | L22: Notes
A23: (+) PreSeed equity | B23: 5 | C23: 0 | D23: 0 | E23: 0 | F23: 0 | G23: 0 | H23: 0 | I23: 0 | J23: 0 | K23: 0 | L23: REV6 §4.1 — 5 MNOK
A24: (+) Seed equity | B24: 0 | C24: 51.3 | D24: 0 | E24: 0 | F24: 0 | G24: 0 | H24: 0 | I24: 0 | J24: 0 | K24: 0 | L24: REV6 §4.1 — 51.3 MNOK
A25: (+) Seed bank debt | B25: 0 | C25: 29.3 | D25: 0 | E25: 0 | F25: 0 | G25: 0 | H25: 0 | I25: 0 | J25: 0 | K25: 0 | L25: REV6 §4.1 — 5 CNC × 5M + 4.3M shop base
A26: (+) Serie A equity (tranches) | B26: 0 | C26: 0 | D26: 15 | E26: 15 | F26: 15 | G26: 0 | H26: 0 | I26: 0 | J26: 0 | K26: 0 | L26: REV6 §7.3 — 3 × 15M, milestone-based
A27: (+) Serie A bank debt (tranches) | B27: 0 | C27: 0 | D27: 35 | E27: 35 | F27: 35 | G27: 0 | H27: 0 | I27: 0 | J27: 0 | K27: 0 | L27: REV6 §7.3 — 3 × 35M, secured by machines
A28: (-) Debt amortization | B28: 0 | C28: 0 | D28: 0 | E28: 0 | F28: 0 | G28: 0 | H28: 0 | I28: 0 | J28: 0 | K28: 0 | L28: Interest-only assumed during growth phase
A29: NET FINANCING CASH FLOW | B29: =B23+B24+B25+B26+B27+B28 -> 5 | C29: =C23+C24+C25+C26+C27+C28 -> 80.6 | D29: =D23+D24+D25+D26+D27+D28 -> 50 | E29: =E23+E24+E25+E26+E27+E28 -> 50 | F29: =F23+F24+F25+F26+F27+F28 -> 50 | G29: =G23+G24+G25+G26+G27+G28 -> 0 | H29: =H23+H24+H25+H26+H27+H28 -> 0 | I29: =I23+I24+I25+I26+I27+I28 -> 0 | ... K29: =K23+K24+K25+K26+K27+K28 -> 0 | L29: Total equity + debt raises
A31: Net Cash Flow & Cash Position
B32: 2026 | C32: 2027 H2 | D32: 2028 | E32: 2029 | F32: 2030 | G32: 2031 | H32: 2032 | I32: 2033 | J32: 2034 | K32: 2035 | L32: Notes
A33: NET CASH FLOW | B33: =B9+B19+B29 -> 5 | C33: =C9+C19+C29 -> 18.028375 | D33: =D9+D19+D29 -> 22.52175 | E33: =E9+E19+E29 -> 90.15721 | F33: =F9+F19+F29 -> 143.18322 | G33: =G9+G19+G29 -> 185.45622 | H33: =H9+H19+H29 -> 200.7479 | I33: =I9+I19+I29 -> 208.62878 | ... K33: =K9+K19+K29 -> 267.5945 | L33: Operating + Investing + Financing
A34: Opening cash balance | B34: 0 | C34: =B35 -> 5 | D34: =C35 -> 23.028375 | E34: =D35 -> 45.550125 | F34: =E35 -> 135.70734 | G34: =F35 -> 278.89055 | H34: =G35 -> 464.34678 | I34: =H35 -> 665.09468 | J34: =I35 -> 873.72346 | K34: =J35 -> 1112.542 | L34: Previous period closing balance
A35: CLOSING CASH BALANCE | B35: =B34+B33 -> 5 | C35: =C34+C33 -> 23.028375 | D35: =D34+D33 -> 45.550125 | E35: =E34+E33 -> 135.70734 | F35: =F34+F33 -> 278.89055 | G35: =G34+G33 -> 464.34678 | H35: =H34+H33 -> 665.09468 | I35: =I34+I33 -> 873.72346 | ... K35: =K34+K33 -> 1380.1365 | L35: Opening + Net Cash Flow
A37: Cash Flow Summary & Key Metrics
B38: 2026 | C38: 2027 H2 | D38: 2028 | E38: 2029 | F38: 2030 | G38: 2031 | H38: 2032 | I38: 2033 | J38: 2034 | K38: 2035 | L38: Notes
A39: FREE CASH FLOW (OpCF + InvCF) | B39: =B9+B19 -> 0 | C39: =C9+C19 -> -62.571625 | D39: =D9+D19 -> -27.47825 | E39: =E9+E19 -> 40.15721 | F39: =F9+F19 -> 93.183217 | G39: =G9+G19 -> 185.45622 | H39: =H9+H19 -> 200.7479 | I39: =I9+I19 -> 208.62878 | ... K39: =K9+K19 -> 267.5945 | L39: Before financing — shows self-funding ability
A40: Cumulative Free Cash Flow | B40: =B39 -> 0 | C40: =B40+C39 -> -62.571625 | D40: =C40+D39 -> -90.049875 | E40: =D40+E39 -> -49.892665 | F40: =E40+F39 -> 43.290552 | G40: =F40+G39 -> 228.74678 | H40: =G40+H39 -> 429.49468 | I40: =H40+I39 -> 638.12346 | J40: =I40+J39 -> 876.942 | K40: =J40+K39 -> 1144.5365 | L40: When positive = self-funding
A41: Cumulative equity raised | B41: =B23+B24+B26 -> 5 | C41: =B41+C23+C24+C26 -> 56.3 | D41: =C41+D23+D24+D26 -> 71.3 | E41: =D41+E23+E24+E26 -> 86.3 | F41: =E41+F23+F24+F26 -> 101.3 | G41: =F41+G23+G24+G26 -> 101.3 | H41: =G41+H23+H24+H26 -> 101.3 | I41: =H41+I23+I24+I26 -> 101.3 | J41: =I41+J23+J24+J26 -> 101.3 | K41: =J41+K23+K24+K26 -> 101.3 | L41: REV6 §4.1 target: 101.3 MNOK total
A42: Cumulative debt raised | B42: =B25+B27 -> 0 | C42: =B42+C25+C27 -> 29.3 | D42: =C42+D25+D27 -> 64.3 | E42: =D42+E25+E27 -> 99.3 | F42: =E42+F25+F27 -> 134.3 | G42: =F42+G25+G27 -> 134.3 | H42: =G42+H25+H27 -> 134.3 | I42: =H42+I25+I27 -> 134.3 | J42: =I42+J25+J27 -> 134.3 | K42: =J42+K25+K27 -> 134.3 | L42: REV6 target: 134.3 MNOK total
A43: Cumulative CAPEX deployed | B43: =-B19 -> 0 | C43: =B43-C19 -> 63.62 | D43: =C43-D19 -> 113.62 | E43: =D43-E19 -> 163.62 | F43: =E43-F19 -> 219.22 | G43: =F43-G19 -> 224.82 | H43: =G43-H19 -> 230.42 | I43: =H43-I19 -> 256.02 | J43: =I43-J19 -> 281.62 | K43: =J43-K19 -> 297.22 | L43: Positive = invested
A45: Self-funding indicator | B45: =IF(B39>0,"CF+","CF-") -> CF- | C45: =IF(C39>0,"CF+","CF-") -> CF- | D45: =IF(D39>0,"CF+","CF-") -> CF- | E45: =IF(E39>0,"CF+","CF-") -> CF+ | F45: =IF(F39>0,"CF+","CF-") -> CF+ | G45: =IF(G39>0,"CF+","CF-") -> CF+ | H45: =IF(H39>0,"CF+","CF-") -> CF+ | I45: =IF(I39>0,"CF+","CF-") -> CF+ | ... K45: =IF(K39>0,"CF+","CF-") -> CF+ | L45: REV6: Self-funded scaling from ~2030
A47: Use of Funds Reconciliation (REV6 §7)
A49: Round | B49: Category | C49: MNOK | D49: Source | E49: Status
A50: PreSeed | B50: Concept validation & customer discovery | C50: 1.5 | D50: Equity
B51: Supplier LOIs & regulatory | C51: 1 | D51: Equity
B52: Team & advisory | C52: 1 | D52: Equity
B53: Planning & engineering | C53: 1 | D53: Equity
B54: Buffer | C54: 0.5 | D54: Equity
A56: Seed | B56: CNC machines equity (5 x 5.0M) | C56: 25 | D56: Equity
B57: CNC machines debt (5 x 5.0M) | C57: 25 | D57: Bank
B58: Shop base setup & technical equipment | C58: 8.6 | D58: Equity
B59: Shop base debt (50%) | C59: 4.3 | D59: Bank
B60: Pre-revenue staffing (Jan-Jul 2027) | C60: 4.7 | D60: Equity
B61: Facility setup & commissioning | C61: 3 | D61: Equity
B62: Facility lease pre-revenue (Q3-Q4) | C62: 2.3 | D62: Equity
B63: Certifications (AS9100, AQAP, ISO) | C63: 2 | D63: Equity
B64: Buffer | C64: 10 | D64: Equity
A66: Serie A | B66: CNC machines equity (15 x 3.0M) | C66: 45 | D66: Equity
B67: CNC machines debt (15 x 7.0M) | C67: 105 | D67: Bank
A69: Notes & Assumptions
A70: 1. Interest expense is included in EBIT (P&L), so it flows through Operating Cash Flow. No double-counting.
A71: 2. Debt is assumed interest-only during the projection period (no principal amortization). Common for growth-stage companies.
A72: 3. Working capital changes are estimated conservatively. Manufacturing typically requires receivables and inventory build-up.
A73: 4. Serie A tranches deploy based on milestones (>30% utilization). Timing shown is base case per REV6 §7.3.
A74: 5. Platform engineering team (REV6 §7.4): Self-funded from Site Zero cash flow starting Q1 2030. ~5.6-7.0 MNOK/yr.
A75: 6. By H2 2028+, the business is cash-flow positive from operations (REV6 §7.3). Certs, team expansion, WC funded from operations.
A76: 7. No dividends are modeled. All profits reinvested for growth.
A77: 8. CNC machines funded per phase: Seed 50% EQ / 50% debt, Serie A 30% EQ / 70% debt (REV6 §1.2).

Sheet Balance Sheet
A1: AURELIAN MANUFACTURING — BALANCE SHEET
A2: All amounts in MNOK. End-of-period balances. Year-end for full years, end-H2 for 2027.
A4: ASSETS
B5: 2026 | C5: 2027 H2 | D5: 2028 | E5: 2029 | F5: 2030 | G5: 2031 | H5: 2032 | I5: 2033 | J5: 2034 | K5: 2035 | L5: Notes
A6: Current Assets
A7: Cash & cash equivalents | B7: ='Cash Flow'!B35 -> 5 | C7: ='Cash Flow'!C35 -> 23.028375 | D7: ='Cash Flow'!D35 -> 45.550125 | E7: ='Cash Flow'!E35 -> 135.70734 | F7: ='Cash Flow'!F35 -> 278.89055 | G7: ='Cash Flow'!G35 -> 464.34678 | H7: ='Cash Flow'!H35 -> 665.09468 | I7: ='Cash Flow'!I35 -> 873.72346 | ... K7: ='Cash Flow'!K35 -> 1380.1365 | L7: Cash Flow: Closing cash balance
A8: Accounts receivable | B8: 0 | C8: ='P&L'!B17/12 -> 0.9125 | D8: ='P&L'!C17/12 -> 4.10625 | E8: ='P&L'!D17/12 -> 11.169 | F8: ='P&L'!E17/12 -> 17.68425 | G8: ='P&L'!F17/12 -> 22.995 | H8: ='P&L'!G17/12 -> 25.185 | I8: ='P&L'!H17/12 -> 28.908 | J8: ='P&L'!I17/12 -> 32.85 | K8: ='P&L'!J17/12 -> 35.5875 | L8: ~30 days outstanding revenue
A9: Inventory (materials & WIP) | B9: 0 | C9: =-'P&L'!B21/6 -> 0.23725 | D9: =-'P&L'!C21/6 -> 1.067625 | E9: =-'P&L'!D21/6 -> 2.624715 | F9: =-'P&L'!E21/6 -> 3.7136925 | G9: =-'P&L'!F21/6 -> 4.254075 | H9: =-'P&L'!G21/6 -> 4.0296 | I9: =-'P&L'!H21/6 -> 4.62528 | J9: =-'P&L'!I21/6 -> 5.256 | K9: =-'P&L'!J21/6 -> 5.694 | L9: ~2 months variable cost buffer
A10: Total Current Assets | B10: =B7+B8+B9 -> 5 | C10: =C7+C8+C9 -> 24.178125 | D10: =D7+D8+D9 -> 50.724 | E10: =E7+E8+E9 -> 149.50105 | F10: =F7+F8+F9 -> 300.2885 | G10: =G7+G8+G9 -> 491.59585 | H10: =H7+H8+H9 -> 694.30928 | I10: =I7+I8+I9 -> 907.25674 | ... K10: =K7+K8+K9 -> 1421.418
A12: Fixed Assets (Property, Plant & Equipment)
A13: CNC machines (gross cost) | B13: 0 | C13: ='Cash Flow'!C13*Assumptions!$C$23/1000000 -> 50 | D13: =C13+'Cash Flow'!D13*Assumptions!$C$23/1000000 -> 100 | E13: =D13+'Cash Flow'!E13*Assumptions!$C$23/1000000 -> 150 | F13: =E13+'Cash Flow'!F13*Assumptions!$C$23/1000000 -> 200 | G13: =F13+'Cash Flow'!G13*Assumptions!$C$23/1000000 -> 200 | H13: =G13+'Cash Flow'!H13*Assumptions!$C$23/1000000 -> 200 | I13: =H13+'Cash Flow'!I13*Assumptions!$C$23/1000000 -> 220 | J13: =I13+'Cash Flow'!J13*Assumptions!$C$23/1000000 -> 240 | K13: =J13+'Cash Flow'!K13*Assumptions!$C$23/1000000 -> 250 | L13: Cumulative units × 10M NOK each
A14: CNC accumulated depreciation | B14: 0 | C14: ='P&L'!B31 -> -2.6041667 | D14: =C14+'P&L'!C31 -> -8.8541667 | E14: =D14+'P&L'!D31 -> -21.354167 | F14: =E14+'P&L'!E31 -> -42.604167 | G14: =F14+'P&L'!F31 -> -67.604167 | H14: =G14+'P&L'!G31 -> -92.604167 | I14: =H14+'P&L'!H31 -> -120.10417 | J14: =I14+'P&L'!I31 -> -150.10417 | K14: =J14+'P&L'!J31 -> -181.35417 | L14: Cumulative from P&L
A15: CNC machines (net book value) | B15: =B13+B14 -> 0 | C15: =C13+C14 -> 47.395833 | D15: =D13+D14 -> 91.145833 | E15: =E13+E14 -> 128.64583 | F15: =F13+F14 -> 157.39583 | G15: =G13+G14 -> 132.39583 | H15: =H13+H14 -> 107.39583 | I15: =I13+I14 -> 99.895833 | ... K15: =K13+K14 -> 68.645833 | L15: Gross - accumulated depreciation
A17: Shop base equipment (gross cost) | B17: 0 | C17: 8.62 | D17: 8.62 | E17: 8.62 | F17: 8.62 | G17: 8.62 | H17: 8.62 | I17: 8.62 | J17: 8.62 | K17: 8.62 | L17: REV6 §1.2c — 8.62M one-time
A18: Shop base accumulated depreciation | B18: 0 | C18: ='P&L'!B32 -> -0.44791667 | D18: =C18+'P&L'!C32 -> -1.5229167 | E18: =D18+'P&L'!D32 -> -2.5979167 | F18: =E18+'P&L'!E32 -> -3.6729167 | G18: =F18+'P&L'!F32 -> -4.7479167 | H18: =G18+'P&L'!G32 -> -5.8229167 | I18: =H18+'P&L'!H32 -> -6.8979167 | J18: =I18+'P&L'!I32 -> -7.9729167 | K18: =J18+'P&L'!J32 -> -9.0479167 | L18: Cumulative from P&L (1.075M/yr)
A19: Shop base equipment (net book value) | B19: =B17+B18 -> 0 | C19: =C17+C18 -> 8.1720833 | D19: =D17+D18 -> 7.0970833 | E19: =E17+E18 -> 6.0220833 | F19: =F17+F18 -> 4.9470833 | G19: =G17+G18 -> 3.8720833 | H19: =H17+H18 -> 2.7970833 | I19: =I17+I18 -> 1.7220833 | ... K19: =K17+K18 -> -0.42791667
A21: Other capitalized (facility, certs, platform) | B21: 0 | C21: 5 | D21: 5 | E21: 5 | F21: 10.6 | G21: 16.2 | H21: 21.8 | I21: 27.4 | J21: 33 | K21: 38.6 | L21: Facility 3M + Certs 2M + Platform 5.6M/yr
A22: Other accumulated amortization | B22: 0 | C22: -0.42 | D22: -1.42 | E22: -2.42 | F22: -3.89 | G22: -5.89 | H22: -8.01 | I22: -10.37 | J22: -12.97 | K22: -15.69 | L22: 5-year straight-line amortization
A23: Other capitalized (net book value) | B23: =B21+B22 -> 0 | C23: =C21+C22 -> 4.58 | D23: =D21+D22 -> 3.58 | E23: =E21+E22 -> 2.58 | F23: =F21+F22 -> 6.71 | G23: =G21+G22 -> 10.31 | H23: =H21+H22 -> 13.79 | I23: =I21+I22 -> 17.03 | ... K23: =K21+K22 -> 22.91
A25: Total Fixed Assets (PP&E) | B25: =B15+B19+B23 -> 0 | C25: =C15+C19+C23 -> 60.147917 | D25: =D15+D19+D23 -> 101.82292 | E25: =E15+E19+E23 -> 137.24792 | F25: =F15+F19+F23 -> 169.05292 | G25: =G15+G19+G23 -> 146.57792 | H25: =H15+H19+H23 -> 123.98292 | I25: =I15+I19+I23 -> 118.64792 | ... K25: =K15+K19+K23 -> 91.127917
A27: TOTAL ASSETS | B27: =B10+B25 -> 5 | C27: =C10+C25 -> 84.326042 | D27: =D10+D25 -> 152.54692 | E27: =E10+E25 -> 286.74897 | F27: =F10+F25 -> 469.34141 | G27: =G10+G25 -> 638.17377 | H27: =H10+H25 -> 818.29219 | I27: =I10+I25 -> 1025.9047 | ... K27: =K10+K25 -> 1512.5459
A30: LIABILITIES
B31: 2026 | C31: 2027 H2 | D31: 2028 | E31: 2029 | F31: 2030 | G31: 2031 | H31: 2032 | I31: 2033 | J31: 2034 | K31: 2035 | L31: Notes
A32: Current Liabilities
A33: Accounts payable | B33: 0 | C33: =-'P&L'!B50/12 -> 1.0794757 | D33: =-'P&L'!C50/12 -> 2.8398542 | E33: =-'P&L'!D50/12 -> 4.7871492 | F33: =-'P&L'!E50/12 -> 6.7295546 | G33: =-'P&L'!F50/12 -> 7.7559958 | H33: =-'P&L'!G50/12 -> 7.6437583 | I33: =-'P&L'!H50/12 -> 8.445765 | J33: =-'P&L'!I50/12 -> 9.173625 | K33: =-'P&L'!J50/12 -> 9.6447083 | L33: ~30 days of operating costs
A34: Accrued expenses | B34: 0 | C34: 0.5 | D34: 1 | E34: 1.5 | F34: 2 | G34: 2 | H34: 2 | I34: 2.5 | J34: 2.5 | K34: 3 | L34: Payroll, taxes, other accruals
A35: Total Current Liabilities | B35: =B33+B34 -> 0 | C35: =C33+C34 -> 1.5794757 | D35: =D33+D34 -> 3.8398542 | E35: =E33+E34 -> 6.2871492 | F35: =F33+F34 -> 8.7295546 | G35: =G33+G34 -> 9.7559958 | H35: =H33+H34 -> 9.6437583 | I35: =I33+I34 -> 10.945765 | ... K35: =K33+K34 -> 12.644708
A37: Long-Term Liabilities
A38: Bank debt (secured by CNC machines) | B38: 0 | C38: ='P&L'!B39 -> 29.3 | D38: ='P&L'!C39 -> 29.3 | E38: ='P&L'!D39 -> 64.3 | F38: ='P&L'!E39 -> 113.3 | G38: ='P&L'!F39 -> 134.3 | H38: ='P&L'!G39 -> 134.3 | I38: ='P&L'!H39 -> 148.3 | J38: ='P&L'!I39 -> 162.3 | K38: ='P&L'!J39 -> 169.3 | L38: P&L: Total debt outstanding
A39: Total Long-Term Liabilities | B39: =B38 -> 0 | C39: =C38 -> 29.3 | D39: =D38 -> 29.3 | E39: =E38 -> 64.3 | F39: =F38 -> 113.3 | G39: =G38 -> 134.3 | H39: =H38 -> 134.3 | I39: =I38 -> 148.3 | ... K39: =K38 -> 169.3
A41: TOTAL LIABILITIES | B41: =B35+B39 -> 0 | C41: =C35+C39 -> 30.879476 | D41: =D35+D39 -> 33.139854 | E41: =E35+E39 -> 70.587149 | F41: =F35+F39 -> 122.02955 | G41: =G35+G39 -> 144.056 | H41: =H35+H39 -> 143.94376 | I41: =I35+I39 -> 159.24577 | ... K41: =K35+K39 -> 181.94471
A44: SHAREHOLDERS' EQUITY
B45: 2026 | C45: 2027 H2 | D45: 2028 | E45: 2029 | F45: 2030 | G45: 2031 | H45: 2032 | I45: 2033 | J45: 2034 | K45: 2035 | L45: Notes
A46: Paid-in capital (share capital + premium) | B46: ='Cash Flow'!B41 -> 5 | C46: ='Cash Flow'!C41 -> 56.3 | D46: ='Cash Flow'!D41 -> 71.3 | E46: ='Cash Flow'!E41 -> 86.3 | F46: ='Cash Flow'!F41 -> 101.3 | G46: ='Cash Flow'!G41 -> 101.3 | H46: ='Cash Flow'!H41 -> 101.3 | I46: ='Cash Flow'!I41 -> 101.3 | ... K46: ='Cash Flow'!K41 -> 101.3 | L46: Cash Flow: Cumulative equity raised
A47: Retained earnings (accumulated) | B47: =B27-B41-B46 -> 0 | C47: =C27-C41-C46 -> -2.853434 | D47: =D27-D41-D46 -> 48.107062 | E47: =E27-E41-E46 -> 129.86182 | F47: =F27-F41-F46 -> 246.01186 | G47: =G27-G41-G46 -> 392.81777 | H47: =H27-H41-H46 -> 573.04844 | I47: =I27-I41-I46 -> 765.35889 | ... K47: =K27-K41-K46 -> 1229.3012 | L47: Plug: Assets - Liabilities - Share capital
A48: TOTAL SHAREHOLDERS' EQUITY | B48: =B46+B47 -> 5 | C48: =C46+C47 -> 53.446566 | D48: =D46+D47 -> 119.40706 | E48: =E46+E47 -> 216.16182 | F48: =F46+F47 -> 347.31186 | G48: =G46+G47 -> 494.11777 | H48: =H46+H47 -> 674.34844 | I48: =I46+I47 -> 866.65889 | ... K48: =K46+K47 -> 1330.6012
A50: TOTAL LIABILITIES + EQUITY | B50: =B41+B48 -> 5 | C50: =C41+C48 -> 84.326042 | D50: =D41+D48 -> 152.54692 | E50: =E41+E48 -> 286.74897 | F50: =F41+F48 -> 469.34141 | G50: =G41+G48 -> 638.17377 | H50: =H41+H48 -> 818.29219 | I50: =I41+I48 -> 1025.9047 | ... K50: =K41+K48 -> 1512.5459
A51: BALANCE CHECK (should = 0) | B51: =ROUND(B27-B50,2) -> 0 | C51: =ROUND(C27-C50,2) -> 0 | D51: =ROUND(D27-D50,2) -> 0 | E51: =ROUND(E27-E50,2) -> 0 | F51: =ROUND(F27-F50,2) -> 0 | G51: =ROUND(G27-G50,2) -> 0 | H51: =ROUND(H27-H50,2) -> 0 | I51: =ROUND(I27-I50,2) -> 0 | ... K51: =ROUND(K27-K50,2) -> 0
A54: Retained Earnings Reconciliation
B55: 2026 | C55: 2027 H2 | D55: 2028 | E55: 2029 | F55: 2030 | G55: 2031 | H55: 2032 | I55: 2033 | J55: 2034 | K55: 2035 | L55: Notes
A56: Cumulative P&L Profit (EBIT) | B56: 0 | C56: ='P&L'!B73 -> -2.0037083 | D56: ='P&L'!C73 -> 13.193042 | E56: ='P&L'!D73 -> 89.775252 | F56: ='P&L'!E73 -> 216.23347 | G56: ='P&L'!F73 -> 381.21469 | H56: ='P&L'!G73 -> 561.48759 | I56: ='P&L'!H73 -> 767.14137 | J56: ='P&L'!I73 -> 1000.4849 | K56: ='P&L'!J73 -> 1251.3544 | L56: P&L: Cumulative Aurelian Profit
A57: (-) Cumulative other amortization | B57: 0 | C57: -0.42 | D57: -1.42 | E57: -2.42 | F57: -3.89 | G57: -5.89 | H57: -8.01 | I57: -10.37 | J57: -12.97 | K57: -15.69 | L57: Facility + cert + platform amortization (not in P&L)
A58: (+/-) Net working capital effect | B58: =B8+B9-B33-B34 -> 0 | C58: =C8+C9-C33-C34 -> -0.42972569 | D58: =D8+D9-D33-D34 -> 1.3340208 | E58: =E8+E9-E33-E34 -> 7.5065658 | F58: =F8+F9-F33-F34 -> 12.668388 | G58: =G8+G9-G33-G34 -> 17.493079 | H58: =H8+H9-H33-H34 -> 19.570842 | I58: =I8+I9-I33-I34 -> 22.587515 | ... K58: =K8+K9-K33-K34 -> 28.636792 | L58: AR + Inventory - AP - Accruals
A59: Adjusted Retained Earnings (est.) | B59: =B56+B57+B58 -> 0 | C59: =C56+C57+C58 -> -2.853434 | D59: =D56+D57+D58 -> 13.107063 | E59: =E56+E57+E58 -> 94.861818 | F59: =F56+F57+F58 -> 225.01186 | G59: =G56+G57+G58 -> 392.81777 | H59: =H56+H57+H58 -> 573.04844 | I59: =I56+I57+I58 -> 779.35889 | ... K59: =K56+K57+K58 -> 1264.3012 | L59: P&L + amort adj + WC
A60: Balance Sheet Retained Earnings | B60: =B47 -> 0 | C60: =C47 -> -2.853434 | D60: =D47 -> 48.107062 | E60: =E47 -> 129.86182 | F60: =F47 -> 246.01186 | G60: =G47 -> 392.81777 | H60: =H47 -> 573.04844 | I60: =I47 -> 765.35889 | ... K60: =K47 -> 1229.3012 | L60: From equity section
A61: Difference (residual) | B61: =B60-B59 -> 0 | C61: =C60-C59 -> 5.3290705e-15 | D61: =D60-D59 -> 35 | E61: =E60-E59 -> 35 | F61: =F60-F59 -> 21 | G61: =G60-G59 -> 0 | H61: =H60-H59 -> 0 | I61: =I60-I59 -> -14 | ... K61: =K60-K59 -> -35 | L61: WC cash timing + capitalization effects
A64: Key Balance Sheet Ratios
B65: 2026 | C65: 2027 H2 | D65: 2028 | E65: 2029 | F65: 2030 | G65: 2031 | H65: 2032 | I65: 2033 | J65: 2034 | K65: 2035 | L65: Notes
A66: Debt-to-Equity Ratio | B66: =IF(B48>0,B39/B48,"N/A") -> 0 | C66: =IF(C48>0,C39/C48,"N/A") -> 0.54821109 | D66: =IF(D48>0,D39/D48,"N/A") -> 0.24537912 | E66: =IF(E48>0,E39/E48,"N/A") -> 0.29746234 | F66: =IF(F48>0,F39/F48,"N/A") -> 0.32621979 | G66: =IF(G48>0,G39/G48,"N/A") -> 0.27179755 | H66: =IF(H48>0,H39/H48,"N/A") -> 0.1991552 | I66: =IF(I48>0,I39/I48,"N/A") -> 0.17111692 | ... K66: =IF(K48>0,K39/K48,"N/A") -> 0.12723572 | L66: Target: <2.0x for bankable structure
A67: Asset Turnover (Revenue / Assets) | B67: 0 | C67: =IF(C27>0,'P&L'!B17/C27,0) -> 0.12985312 | D67: =IF(D27>0,'P&L'!C17/D27,0) -> 0.32301538 | E67: =IF(E27>0,'P&L'!D17/E27,0) -> 0.46740535 | F67: =IF(F27>0,'P&L'!E17/F27,0) -> 0.45214634 | G67: =IF(G27>0,'P&L'!F17/G27,0) -> 0.43239007 | H67: =IF(H27>0,'P&L'!G17/H27,0) -> 0.36933018 | I67: =IF(I27>0,'P&L'!H17/I27,0) -> 0.33813669 | J67: =IF(J27>0,'P&L'!I17/J27,0) -> 0.31255428 | K67: =IF(K27>0,'P&L'!J17/K27,0) -> 0.28233854 | L67: Efficiency of asset utilization
A68: Return on Assets (EBIT / Assets) | B68: 0 | C68: =IF(C27>0,'P&L'!B61/C27,0) -> -0.023761442 | D68: =IF(D27>0,'P&L'!C61/D27,0) -> 0.099620171 | E68: =IF(E27>0,'P&L'!D61/E27,0) -> 0.26707057 | F68: =IF(F27>0,'P&L'!E61/F27,0) -> 0.26943759 | G68: =IF(G27>0,'P&L'!F61/G27,0) -> 0.25852085 | H68: =IF(H27>0,'P&L'!G61/H27,0) -> 0.22030382 | I68: =IF(I27>0,'P&L'!H61/I27,0) -> 0.20046091 | J68: =IF(J27>0,'P&L'!I61/J27,0) -> 0.18501401 | K68: =IF(K27>0,'P&L'!J61/K27,0) -> 0.1658591 | L68: Profitability relative to asset base
A69: Return on Equity (EBIT / Equity) | B69: 0 | C69: =IF(C48>0,'P&L'!B61/C48,0) -> -0.037489936 | D69: =IF(D48>0,'P&L'!C61/D48,0) -> 0.12726844 | E69: =IF(E48>0,'P&L'!D61/E48,0) -> 0.35428186 | F69: =IF(F48>0,'P&L'!E61/F48,0) -> 0.36410567 | G69: =IF(G48>0,'P&L'!F61/G48,0) -> 0.33389049 | H69: =IF(H48>0,'P&L'!G61/H48,0) -> 0.26732901 | I69: =IF(I48>0,'P&L'!H61/I48,0) -> 0.23729495 | J69: =IF(J48>0,'P&L'!I61/J48,0) -> 0.21461865 | K69: =IF(K48>0,'P&L'!J61/K48,0) -> 0.18853846 | L69: Investor return on book equity
A70: Fixed Assets / Debt Coverage | B70: =IF(B38>0,B25/B38,"N/A") -> N/A | C70: =IF(C38>0,C25/C38,"N/A") -> 2.0528299 | D70: =IF(D38>0,D25/D38,"N/A") -> 3.4751849 | E70: =IF(E38>0,E25/E38,"N/A") -> 2.1344933 | F70: =IF(F38>0,F25/F38,"N/A") -> 1.4920822 | G70: =IF(G38>0,G25/G38,"N/A") -> 1.0914216 | H70: =IF(H38>0,H25/H38,"N/A") -> 0.92317883 | I70: =IF(I38>0,I25/I38,"N/A") -> 0.80005338 | ... K70: =IF(K38>0,K25/K38,"N/A") -> 0.53826295 | L70: Collateral coverage for bank debt
A73: Notes & Assumptions
A74: 1. Balance Sheet constructed so Assets = Liabilities + Equity by definition. Retained earnings is the balancing item.
A75: 2. CNC machines at historical cost (10M NOK each), straight-line depreciation over 8 years per REV6 §1.2.
A76: 3. Resale value analysis supports 55-65% residual at 3yr, 35-45% at 5yr — not reflected in book values.
A77: 4. Working capital estimated from revenue/cost profiles. Detailed WC model recommended for Seed DD.
A78: 5. Other capitalized: facility setup (3M), certifications (2M), platform engineering (5.6M/yr from 2030). Amortized over 5yr.
A79: 6. Bank debt interest-only during projection. No principal amortization (growth-stage assumption).
A80: 7. Debt from 2032+ includes organic growth CNC machines at 7M debt each (per P&L Serie A terms).
A81: 8. RE reconciliation: small differences from WC cash timing and items capitalized on BS but expensed differently in CF.

Sheet Cap Table
A1: AURELIAN MANUFACTURING — CAP TABLE & OWNERSHIP EVOLUTION
A2: Source: REV6 §4. All ownership is at parent (Holdingselskap) level. ESOP at daughter (Site) level.
A4: 1. Financing Round Parameters
C5: PreSeed | D5: Seed | E5: Serie A | G5: Notes
A6: Capital raised (equity, MNOK) | C6: 5 | D6: 51.3 | E6: 45 | G6: REV6 §4.1
A7: Pre-money valuation (MNOK) | C7: 25 | D7: 130 | E7: 250 | G7: REV6 §4.1
A8: Post-money valuation (MNOK) | C8: 30 | D8: 181.3 | E8: 295 | G8: PreMoney + Capital
A9: Dilution this round (%) | C9: 0.1667 | D9: 0.283 | E9: 0.1525 | G9: Capital / PostMoney
A10: Bank debt raised (MNOK) | C10: 0 | D10: 29.3 | E10: 105 | G10: Asset-backed, secured by CNC
A11: Total capital deployed (MNOK) | C11: 5 | D11: 80.6 | E11: 150 | G11: Equity + Debt
A12: Machines funded | C12: 0 | D12: 5 CNC + shop | E12: 15 CNC (3×5)
A14: 2. Ownership Evolution (% of Parent Company)
B15: Founding | C15: Post PreSeed | D15: Post Seed | E15: Post Serie A | G15: Notes
A16: Eier A | B16: 0.5625 | C16: 0.4688 | D16: 0.336 | E16: 0.2846
A17: Eier B | B17: 0.3375 | C17: 0.2813 | D17: 0.2016 | E17: 0.1708
A18: Eier C | B18: 0.1 | C18: 0.0833 | D18: 0.0597 | E18: 0.0506
A19: FOUNDERS TOTAL | B19: 1 | C19: 0.8333 | D19: 0.5974 | E19: 0.506 | G19: Founders retain majority control
A21: PreSeed investors | C21: 0.1667 | D21: 0.1195 | E21: 0.1012
A22: Seed investors | D22: 0.283 | E22: 0.2398
A23: Serie A investors | E23: 0.1525
A24: INVESTORS TOTAL | B24: 0 | C24: 0.1667 | D24: 0.4026 | E24: 0.494
A25: TOTAL (verification = 100%) | B25: =B19+B24 -> 1 | C25: =C19+C24 -> 1 | D25: =D19+D24 -> 1 | E25: =E19+E24 -> 1 | G25: Must equal 100.00%
A27: 3. Dilution Waterfall (Founders)
C28: PreSeed | D28: Seed | E28: Serie A | F28: Cumulative | G28: Notes
A29: Eier A starting % | B29: 0.5625 | C29: 0.5625 | D29: 0.4688 | E29: 0.336
A30: Eier A ending % | C30: 0.4688 | D30: 0.336 | E30: 0.2846 | F30: 0.2846
A31: Eier A dilution (pp) | C31: -0.0937 | D31: -0.1328 | E31: -0.0514 | F31: -0.2779
A33: Eier B starting % | B33: 0.3375 | C33: 0.3375 | D33: 0.2813 | E33: 0.2016
A34: Eier B ending % | C34: 0.2813 | D34: 0.2016 | E34: 0.1708 | F34: 0.1708
A35: Eier B dilution (pp) | C35: -0.0562 | D35: -0.0797 | E35: -0.0308 | F35: -0.1667
A37: Eier C starting % | B37: 0.1 | C37: 0.1 | D37: 0.0833 | E37: 0.0597
A38: Eier C ending % | C38: 0.0833 | D38: 0.0597 | E38: 0.0506 | F38: 0.0506
A39: Eier C dilution (pp) | C39: -0.0167 | D39: -0.0236 | E39: -0.0091 | F39: -0.0494
A41: European VC Dilution Benchmarks
A42: Typical Seed dilution (Europe) | B42: 10-25% | G42: Aurelian: 28.3% (capital intensity premium)
A43: Typical Serie A dilution (Europe) | B43: 20-30% | G43: Aurelian: 15.3% (below market — strong position)
A44: Founders retaining >50% post-A | B44: Best practice | G44: Aurelian: 50.6% ✓ — maintains control
A47: 4. Exit Value Allocation (2035 Scenario)
A48: Exit Parameters
A49: EBITDA at exit (MNOK) | B49: 222 | G49: P&L: steady state after Customer Program
A50: EBITDA multiple (Industry 4.0) | B50: 10-11x | G50: Industrial IoT range (European benchmarks)
A51: Exit valuation (MNOK) | B51: 2300 | G51: Conservative: 222 × 10.4x ≈ 2,300
B53: Ownership % | C53: Value (MNOK) | D53: Investment | E53: ROI (x) | F53: Market Exp. | G53: Notes
A54: Eier A | B54: 0.2846 | C54: 654
A55: Eier B | B55: 0.1708 | C55: 393
A56: Eier C | B56: 0.0506 | C56: 116
A57: FOUNDERS TOTAL | B57: 0.506 | C57: 1164 | F57: Sweat equity ~7-9 MNOK
A59: PreSeed investors | B59: 0.1012 | C59: 233 | D59: 5 | E59: 46.6 | F59: 20-40x ✓
A60: Seed investors | B60: 0.2398 | C60: 552 | D60: 51.3 | E60: 10.8 | F60: 10-25x ✓
A61: Serie A investors | B61: 0.1525 | C61: 351 | D61: 45 | E61: 7.8 | F61: 5-10x ✓
A62: INVESTORS TOTAL | B62: 0.494 | C62: 1136 | D62: 101.3 | E62: 11.2 | F62: Weighted avg
A64: TOTAL EXIT VALUE | C64: 2300
A67: 5. Investor ROI Sensitivity (Exit Multiple)
B68: 8x (Bear) | C68: 10x (Base) | D68: 11x (Bull) | E68: 13x (Upside) | G68: Notes
A69: Exit valuation (MNOK) | B69: 1776 | C69: 2220 | D69: 2442 | E69: 2886
A70: PreSeed ROI (invested 5M) | B70: 35.94624 | C70: 44.9328 | D70: 49.42608 | E70: 58.41264
A71: Seed ROI (invested 51.3M) | B71: 8.301848 | C71: 10.37731 | D71: 11.415041 | E71: 13.490503
A72: Serie A ROI (invested 45M) | B72: 6.0186667 | C72: 7.5233333 | D72: 8.2756667 | E72: 9.7803333
A73: Founders value (MNOK) | B73: 898.656 | C73: 1123.32 | D73: 1235.652 | E73: 1460.316
A76: 6. Founder Vesting Schedule
A77: Vesting period | B77: 4 years | G77: Standard VC practice
A78: Cliff period | B78: 1 year | G78: No vesting if departure before 12 months
A79: Vesting frequency | B79: Monthly (after cliff) | G79: 1/48 per month after cliff
A80: Acceleration (exit) | B80: Double-trigger, 50% | G80: 50% immediate vest on acquisition
A81: Acceleration (termination w/o cause) | B81: 12-month | G81: Protects founders
A82: Employee incentive (ESOP) | B82: 10% at Site level | G82: Daughter company — no parent dilution
A84: Vesting Timeline (cumulative %)
B85: Month 0 | C85: Month 12 (Cliff) | D85: Month 24 | E85: Month 36 | F85: Month 48 (Full)
A86: Eier A vested % | B86: 0 | C86: 0.25 | D86: 0.5 | E86: 0.75 | F86: 1
A87: Eier A vested shares (of 56.25%) | B87: 0 | C87: 0.1406 | D87: 0.2813 | E87: 0.4219 | F87: 0.5625
A88: Eier B vested % | B88: 0 | C88: 0.25 | D88: 0.5 | E88: 0.75 | F88: 1
A89: Eier B vested shares (of 33.75%) | B89: 0 | C89: 0.0844 | D89: 0.1688 | E89: 0.2531 | F89: 0.3375
A90: Eier C vested % | B90: 0 | C90: 0.25 | D90: 0.5 | E90: 0.75 | F90: 1
A91: Eier C vested shares (of 10.00%) | B91: 0 | C91: 0.025 | D91: 0.05 | E91: 0.075 | F91: 0.1
A94: 7. Board Composition & Governance
B95: Pre-Seed (Current) | C95: Post-Seed | D95: Post-Serie A | G95: Notes
A96: Founder seats | B96: 2 | C96: 2 | D96: 2 | G96: André Tandberg (CEO), Tore Ausland (BD)
A97: Independent seats | B97: 1 | C97: 1 | D97: 1 | G97: Henrik Strøm (Financial expertise)
A98: Investor seats | B98: 0 | C98: 1-2 | D98: 2 | G98: Lead investor from each round
A99: Total board seats | B99: 3 | C99: 4-5 | D99: 5
A101: Founder voting control | B101: Majority | C101: Shared | D101: Shared | G101: 50.6% ownership post-Serie A
A102: Pro-rata rights | B102: N/A | C102: Yes | D102: Yes | G102: Right to participate in future rounds
A103: Board observer | B103: N/A | C103: Optional | D103: Optional | G103: Non-voting seat for co-investors
A104: Liquidation preference | B104: N/A | C104: 1x NP | D104: 1x NP | G104: Non-participating — investors get back first
A105: Anti-dilution | B105: N/A | C105: WA | D105: WA | G105: Weighted average protection
A108: Notes & Assumptions
A109: 1. All ownership percentages are at parent (Holdingselskap) level. REV6 §4.2 is authoritative source.
A110: 2. Employee incentive programs (10%) structured within each daughter company (Site), not at parent level.
A111: 3. No further dilution at parent level after Serie A in base case.
A112: 4. REV6 numbers: PreSeed 5M@25M pre, Seed 51.3M@130M pre, Serie A 45M@250M pre.
A113: 5. Exit scenario uses conservative 10x EBITDA (range 10-11x for Industrial IoT per European benchmarks).
A114: 6. Founder sweat equity contribution estimated at 7-9 MNOK (see 02_Founder_Contribution_PreSeed_Valuation).
A115: 7. All three investor groups deliver ROI within or above European VC market expectations.
A116: 8. Vesting terms are recommended structure — to be finalized in shareholder agreement.

Sheet Sensitivity
A1: AURELIAN MANUFACTURING — SENSITIVITY ANALYSIS
A2: Source: REV6 §5. All tables use Assumptions sheet inputs. Steady state = 20 CNC, 8% variable cost, before Customer Program.
A4: 1. Utilization Sensitivity — 20 CNC, Steady State (Before Customer Program)
A5: Constants: | B5: CNC machines = | C5: 20 | D5: Variable cost % = | E5: 0.08 | F5: Hourly rate = | G5: =Assumptions!C8 -> 3000
A6: Utilization % | B6: Revenue (MNOK) | C6: Variable Costs (8%) | D6: Fixed Costs | E6: Total Costs | F6: EBIT (MNOK) | G6: EBIT Margin % | H6: EBITDA (MNOK) | I6: EBITDA Margin % | J6: Notes
A7: 0.15 | B7: =$C$5*Assumptions!$C$7*A7*Assumptions!$C$8/1000000 -> 78.84 | C7: =B7*$E$5 -> 6.3072 | D7: 67.5 | E7: =C7+D7 -> 73.8072 | F7: =B7-E7 -> 5.0328 | G7: =IF(B7>0,F7/B7,0) -> 0.063835616 | H7: =F7+26.075 -> 31.1078 | I7: =IF(B7>0,H7/B7,0) -> 0.39456875 | J7: Machine-level break-even zone
A8: 0.2 | B8: =$C$5*Assumptions!$C$7*A8*Assumptions!$C$8/1000000 -> 105.12 | C8: =B8*$E$5 -> 8.4096 | D8: 67.5 | E8: =C8+D8 -> 75.9096 | F8: =B8-E8 -> 29.2104 | G8: =IF(B8>0,F8/B8,0) -> 0.27787671 | H8: =F8+26.075 -> 55.2854 | I8: =IF(B8>0,H8/B8,0) -> 0.52592656 | J8: Company break-even (~14-20%)
A9: 0.3 | B9: =$C$5*Assumptions!$C$7*A9*Assumptions!$C$8/1000000 -> 157.68 | C9: =B9*$E$5 -> 12.6144 | D9: 67.5 | E9: =C9+D9 -> 80.1144 | F9: =B9-E9 -> 77.5656 | G9: =IF(B9>0,F9/B9,0) -> 0.49191781 | H9: =F9+26.075 -> 103.6406 | I9: =IF(B9>0,H9/B9,0) -> 0.65728437
A10: 0.4 | B10: =$C$5*Assumptions!$C$7*A10*Assumptions!$C$8/1000000 -> 210.24 | C10: =B10*$E$5 -> 16.8192 | D10: 67.5 | E10: =C10+D10 -> 84.3192 | F10: =B10-E10 -> 125.9208 | G10: =IF(B10>0,F10/B10,0) -> 0.59893836 | H10: =F10+26.075 -> 151.9958 | I10: =IF(B10>0,H10/B10,0) -> 0.72296328
A11: 0.45 | B11: =$C$5*Assumptions!$C$7*A11*Assumptions!$C$8/1000000 -> 236.52 | C11: =B11*$E$5 -> 18.9216 | D11: 67.5 | E11: =C11+D11 -> 86.4216 | F11: =B11-E11 -> 150.0984 | G11: =IF(B11>0,F11/B11,0) -> 0.63461187 | H11: =F11+26.075 -> 176.1734 | I11: =IF(B11>0,H11/B11,0) -> 0.74485625 | J11: Customer Program threshold
A12: 0.5 | B12: =$C$5*Assumptions!$C$7*A12*Assumptions!$C$8/1000000 -> 262.8 | C12: =B12*$E$5 -> 21.024 | D12: 67.5 | E12: =C12+D12 -> 88.524 | F12: =B12-E12 -> 174.276 | G12: =IF(B12>0,F12/B12,0) -> 0.66315068 | H12: =F12+26.075 -> 200.351 | I12: =IF(B12>0,H12/B12,0) -> 0.76237062
A13: 0.6 | B13: =$C$5*Assumptions!$C$7*A13*Assumptions!$C$8/1000000 -> 315.36 | C13: =B13*$E$5 -> 25.2288 | D13: 67.5 | E13: =C13+D13 -> 92.7288 | F13: =B13-E13 -> 222.6312 | G13: =IF(B13>0,F13/B13,0) -> 0.7059589 | H13: =F13+26.075 -> 248.7062 | I13: =IF(B13>0,H13/B13,0) -> 0.78864219 | J13: BASE CASE (REV6 target)
A14: 0.65 | B14: =$C$5*Assumptions!$C$7*A14*Assumptions!$C$8/1000000 -> 341.64 | C14: =B14*$E$5 -> 27.3312 | D14: 67.5 | E14: =C14+D14 -> 94.8312 | F14: =B14-E14 -> 246.8088 | G14: =IF(B14>0,F14/B14,0) -> 0.7224236 | H14: =F14+26.075 -> 272.8838 | I14: =IF(B14>0,H14/B14,0) -> 0.79874663 | J14: Bull case target
A16: KEY: 10pp utilization increase ≈ 50 MNOK EBIT impact at 20 CNC scale. Operating leverage is extreme.
A19: 2. Two-Way Sensitivity — EBIT by CNC Count × Utilization (MNOK, Before Customer Program)
A20: EBIT (MNOK) | B20: 5 CNC | C20: 10 CNC | D20: 15 CNC | E20: 20 CNC | F20: 25 CNC | G20: 30 CNC
A21: 0.15 | B21: -7 | C21: -2.9 | D21: 1.2 | E21: 5.3 | F21: 9.4 | G21: 13.5
A22: 0.2 | B22: -1 | C22: 9.2 | D22: 19.3 | E22: 29.5 | F22: 39.6 | G22: 49.8
A23: 0.3 | B23: 11.1 | C23: 33.4 | D23: 55.6 | E23: 77.8 | F23: 100.1 | G23: 122.3
A24: 0.4 | B24: 23.2 | C24: 57.5 | D24: 91.9 | E24: 126.2 | F24: 160.5 | G24: 194.9
A25: 0.5 | B25: 35.3 | C25: 81.7 | D25: 128.1 | E25: 174.6 | F25: 221 | G25: 267.4
A26: 0.6 | B26: 47.4 | C26: 105.9 | D26: 164.4 | E26: 222.9 | F26: 281.4 | G26: 339.9
A27: 0.65 | B27: 53.4 | C27: 118 | D27: 182.5 | E27: 247.1 | F27: 311.6 | G27: 376.2
A29: Green = profitable, Red = loss, Blue highlight = Base case (20 CNC @ 60%)
A32: 3. Hourly Rate Sensitivity — 20 CNC @ 60% Utilization
A33: Hourly Rate (NOK) | B33: Revenue (MNOK) | C33: EBIT (MNOK) | D33: EBIT Margin % | E33: EBITDA (MNOK) | F33: Δ Revenue vs Base | G33: Δ EBIT vs Base
A34: 2000 | B34: 210.24 | C34: 125.9208 | D34: 0.59893836 | E34: 151.9958 | F34: -105.12 | G34: -96.7104
A35: 2500 | B35: 262.8 | C35: 174.276 | D35: 0.66315068 | E35: 200.351 | F35: -52.56 | G35: -48.3552
A36: 2750 | B36: 289.08 | C36: 198.4536 | D36: 0.68650062 | E36: 224.5286 | F36: -26.28 | G36: -24.1776
A37: 3000 | B37: 315.36 | C37: 222.6312 | D37: 0.7059589 | E37: 248.7062 | F37: 0 | G37: 0
A38: 3250 | B38: 341.64 | C38: 246.8088 | D38: 0.7224236 | E38: 272.8838 | F38: 26.28 | G38: 24.1776
A39: 3500 | B39: 367.92 | C39: 270.9864 | D39: 0.7365362 | E39: 297.0614 | F39: 52.56 | G39: 48.3552
A40: 4000 | B40: 420.48 | C40: 319.3416 | D40: 0.75946918 | E40: 345.4166 | F40: 105.12 | G40: 96.7104
A42: REV6 §8.1: Defence/O&G premiums above 3,000 NOK are documented but NOT modeled (conservative buffer).
A45: 4. Exit Scenario Analysis (REV6 §5.3)
A46: Scenario | B46: CNC Count | C46: Utilization | D46: EBITDA (MNOK) | E46: Multiple | F46: Exit Value (MNOK) | G46: PreSeed ROI | H46: Seed ROI | I46: Serie A ROI | J46: Founders Value (MNOK)
A47: Deep bear | B47: 15 | C47: 0.35 | D47: 83 | E47: 8 | F47: 665 | G47: 13.4596 | H47: 3.1085185 | I47: 2.2536111 | J47: 336.49
A48: Bear | B48: 20 | C48: 0.4 | D48: 126 | E48: 8 | F48: 1005 | G48: 20.3412 | H48: 4.6978363 | I48: 3.4058333 | J48: 508.53
A49: Conservative | B49: 20 | C49: 0.5 | D49: 174 | E49: 9 | F49: 1570 | G49: 31.7768 | H49: 7.3389084 | I49: 5.3205556 | J49: 794.42
A50: BASE CASE | B50: 20 | C50: 0.6 | D50: 223 | E50: 10 | F50: 2230 | G50: 45.1352 | H50: 10.424055 | I50: 7.5572222 | J50: 1128.38
A51: Bull | B51: 25 | C51: 0.65 | D51: 268 | E51: 11 | F51: 2950 | G51: 59.708 | H51: 13.789669 | I51: 9.9972222 | J51: 1492.7
A52: Multi-site | B52: 40 | C52: 0.55 | D52: 445 | E52: 12 | F52: 5350 | G52: 108.284 | H52: 25.008382 | I52: 18.130556 | J52: 2707.1
A54: Market expectations: | G54: 20-40x | H54: 10-25x | I54: 5-10x
A57: 5. Operating Leverage — Revenue Change vs. EBIT Change
A58: Change from Base | B58: Revenue (MNOK) | C58: Δ Revenue (%) | D58: EBIT (MNOK) | E58: Δ EBIT (%) | F58: Leverage Factor
A59: Util = 40% | B59: 210.24 | C59: -0.33333333 | D59: 125.9208 | E59: -0.43439734 | F59: 1.303192
A60: Util = 45% | B60: 236.52 | C60: -0.25 | D60: 150.0984 | E60: -0.325798 | F60: 1.303192
A61: Util = 50% | B61: 262.8 | C61: -0.16666667 | D61: 174.276 | E61: -0.21719867 | F61: 1.303192
A62: Util = 55% | B62: 289.08 | C62: -0.083333333 | D62: 198.4536 | E62: -0.10859933 | F62: 1.303192
A63: Util = 60% (BASE) | B63: 315.36 | C63: 0 | D63: 222.6312 | E63: 0 | F63: —
A64: Util = 65% | B64: 341.64 | C64: 0.083333333 | D64: 246.8088 | E64: 0.10859933 | F64: 1.303192
A65: Util = 70% | B65: 367.92 | C65: 0.16666667 | D65: 270.9864 | E65: 0.21719867 | F65: 1.303192
A67: Leverage Factor >1x means EBIT grows faster than revenue. At ~1.1x, a 10% revenue increase → 11% EBIT increase.
A70: 6. Variable Cost Sensitivity — 20 CNC @ 60% Utilization
A71: Variable Cost % | B71: Variable Costs (MNOK) | C71: EBIT (MNOK) | D71: Δ EBIT vs 8% | E71: EBIT Margin | F71: Notes
A72: 0.06 | B72: 18.9216 | C72: 228.9384 | D72: 6.3072 | E72: 0.7259589 | F72: REV6 §8.1: Possible at optimization (unmodeled)
A73: 0.07 | B73: 22.0752 | C73: 225.7848 | D73: 3.1536 | E73: 0.7159589
A74: 0.08 | B74: 25.2288 | C74: 222.6312 | D74: 0 | E74: 0.7059589 | F74: BASE CASE — mature operations
A75: 0.1 | B75: 31.536 | C75: 216.324 | D75: -6.3072 | E75: 0.6859589
A76: 0.12 | B76: 37.8432 | C76: 210.0168 | D76: -12.6144 | E76: 0.6659589
A77: 0.13 | B77: 40.9968 | C77: 206.8632 | D77: -15.768 | E77: 0.6559589 | F77: Startup phase rate (2027-2028)
A78: 0.15 | B78: 47.304 | C78: 200.556 | D78: -22.0752 | E78: 0.6359589
A82: 7. Two-Way Exit Value — EBITDA × Multiple (MNOK)
A83: Exit Value (MNOK) | B83: 7x | C83: 8x | D83: 9x | E83: 10x | F83: 11x | G83: 12x | H83: 13x
A84: Deep bear (83) | B84: 581 | C84: 664 | D84: 747 | E84: 830 | F84: 913 | G84: 996 | H84: 1079
A85: Bear (126) | B85: 882 | C85: 1008 | D85: 1134 | E85: 1260 | F85: 1386 | G85: 1512 | H85: 1638
A86: Conserv. (174) | B86: 1218 | C86: 1392 | D86: 1566 | E86: 1740 | F86: 1914 | G86: 2088 | H86: 2262
A87: BASE (223) | B87: 1561 | C87: 1784 | D87: 2007 | E87: 2230 | F87: 2453 | G87: 2676 | H87: 2899
A88: Bull (268) | B88: 1876 | C88: 2144 | D88: 2412 | E88: 2680 | F88: 2948 | G88: 3216 | H88: 3484
A89: Upside (350) | B89: 2450 | C89: 2800 | D89: 3150 | E89: 3500 | F89: 3850 | G89: 4200 | H89: 4550
A90: Multi-site (445) | B90: 3115 | C90: 3560 | D90: 4005 | E90: 4450 | F90: 4895 | G90: 5340 | H90: 5785
A92: Red = <1B NOK exit, Green = 2-3B, Dark green = >3B. Blue = Base case (223 EBITDA × 10x = 2,230 MNOK).
A95: Notes & Assumptions
A96: 1. All steady-state tables assume 20 CNC machines, 8% variable cost, fixed costs per REV6 §3.6 (~67.5 MNOK).
A97: 2. Customer Program (50/50 sharing above 45%) is NOT included in EBIT figures above — pure Aurelian economics.
A98: 3. REV6 §8.1 buffers (hourly rate premium, lower variable costs, CNC procurement savings) = material unmodeled upside.
A99: 4. Machine-level break-even at ~13.5% utilization (~1,183 hours/year). Company-level at ~14% with 20 CNC.
A100: 5. Sub-linear staffing: 0.8 FTE per CNC enables extreme operating leverage vs. traditional workshops.
A101: 6. Exit multiples: Industrial IoT range 10-11x (private), Aerospace/Defense 21.6x (public) — using conservative private multiples.
A102: 7. Multi-site scenario (40+ CNC) represents Site 2+ expansion with platform engineering team enabling replication.
A103: 8. Defence/O&G hourly rate premiums above 3,000 NOK are documented in market analysis but deliberately excluded.

Sheet Break-Even
A1: AURELIAN MANUFACTURING — BREAK-EVEN ANALYSIS
A2: Source: REV6 §5.2. Machine-level and company-level break-even with contribution margin analysis.
A4: 1. Machine-Level Break-Even (Per CNC)
A5: Theoretical hours per CNC per year | B5: =Assumptions!C7 -> 8760 | L5: 24/7 operation = 8,760
A6: Normalized hourly rate (NOK) | B6: =Assumptions!C8 -> 3000 | L6: REV6 constant
A7: Variable cost % (mature) | B7: =Assumptions!C19 -> 0.08 | L7: Mature operations
A8: Contribution margin % per hour | B8: =1-Assumptions!C19 -> 0.92 | L8: 1 - variable cost %
A9: Max revenue per CNC (MNOK) | B9: =Assumptions!C7*Assumptions!C8/1000000 -> 26.28 | L9: hours × Rate
A11: Direct costs per CNC (annual, MNOK):
A12: Depreciation | B12: =Assumptions!C23/Assumptions!C24/1000000 -> 1.25 | L12: 10M / 8yr = 1.25M
A13: Debt interest (per CNC) | B13: =Assumptions!C23*0.5*Assumptions!C26/1000000 -> 0.375 | L13: 50% debt × 7.5% rate = 0.375M
A14: Operating cost allocation | B14: 0.15 | L14: REV6: 150K per CNC (other opex)
A15: Allocated ops payroll (per CNC) | B15: =Assumptions!C52*16/20/1000000 -> 0.88 | L15: 16 ops FTE × 1.1M / 20 CNC
A16: Allocated admin + lease (per CNC) | B16: =(Assumptions!C53*4+Assumptions!C68)/20/1000000 -> 0.54 | L16: (4 admin × 1.4M + 5.2M lease) / 20 CNC
A17: Allocated shop base depr. (per CNC) | B17: =Assumptions!C71/20/1000000 -> 0.05375 | L17: 1.075M / 20 CNC
A18: TOTAL fully-loaded cost per CNC | B18: =SUM(B12:B17) -> 3.24875 | L18: Sum of direct + allocated costs
A20: MACHINE-LEVEL BREAK-EVEN:
A21: Break-even revenue per CNC (MNOK) | B21: =B18/(1-Assumptions!C19) -> 3.53125 | L21: direct cost / (1 - var%)
A22: Break-even hours per CNC | B22: =B21*1000000/Assumptions!C8 -> 1177.0833 | L22: be revenue / hourly rate
A23: Break-even utilization % | B23: =B22/Assumptions!C7 -> 0.13437024 | L23: ≈be hours / 8,760 = ~13.5%
A25: Safety Margin Above Machine Break-Even:
A26: Utilization % | B26: Hours Used | C26: Revenue (MNOK) | D26: Variable Costs | E26: Direct Fixed Costs | F26: Contribution (MNOK) | G26: Safety Margin vs BE
A27: 0.135 | B27: 1182.6 | C27: 3.5478 | D27: 0.283824 | E27: 1.775 | F27: 1.488976 | G27: 0.83885972 | H27: ≈ BREAK-EVEN
A28: 0.2 | B28: 1752 | C28: 5.256 | D28: 0.42048 | E28: 1.775 | F28: 3.06052 | G28: 1.7242366
A29: 0.3 | B29: 2628 | C29: 7.884 | D29: 0.63072 | E29: 1.775 | F29: 5.47828 | G29: 3.0863549
A30: 0.4 | B30: 3504 | C30: 10.512 | D30: 0.84096 | E30: 1.775 | F30: 7.89604 | G30: 4.4484732
A31: 0.5 | B31: 4380 | C31: 13.14 | D31: 1.0512 | E31: 1.775 | F31: 10.3138 | G31: 5.8105915
A32: 0.6 | H32: BASE CASE
A33: 0.65 | B33: 5694 | C33: 17.082 | D33: 1.36656 | E33: 1.775 | F33: 13.94044 | G33: 7.853769
A35: At 60% utilization, each CNC contributes ~22.4 MNOK above its direct costs. Safety margin: 12.6x above break-even.
A38: 2. Company-Level Break-Even (REV6 §5.2)
A39: CNC Count | B39: Ops FTEs | C39: Ops Payroll | D39: Admin Payroll | E39: CNC Depr. | F39: Shop Base Depr. | G39: Interest Cost | H39: Facility Lease | I39: Other OpEx | J39: Total Fixed (MNOK) | K39: BE Revenue (MNOK) | L39: BE Util. %
A40: 3 | B40: 5 | C40: 5.5 | D40: 5.6 | E40: 3.75 | F40: 1.075 | G40: 1.125 | H40: 5.2 | I40: 0.45 | J40: 22.7 | K40: 24.673913 | L40: 0.31296186 | M40: Tight
A41: 4 | B41: 6 | C41: 6.6 | D41: 5.6 | E41: 5 | F41: 1.075 | G41: 1.5 | H41: 5.2 | I41: 0.6 | J41: 25.575 | K41: 27.798913 | L41: 0.26444932 | M41: Possible
A42: 5 | B42: 7 | C42: 7.7 | D42: 5.6 | E42: 6.25 | F42: 1.075 | G42: 1.875 | H42: 5.2 | I42: 0.75 | J42: 28.45 | K42: 30.923913 | L42: 0.2353418 | M42: Achievable (Seed start)
A43: 8 | B43: 8 | C43: 8.8 | D43: 5.6 | E43: 10 | F43: 1.075 | G43: 3 | H43: 5.2 | I43: 1.2 | J43: 34.875 | K43: 37.907609 | L43: 0.18030636 | M43: Seed full fleet
A44: 10 | B44: 10 | C44: 11 | D44: 5.6 | E44: 12.5 | F44: 1.075 | G44: 4.8225 | H44: 5.2 | I44: 1.5 | J44: 41.6975 | K44: 45.32337 | L44: 0.17246335 | M44: Post tranche 1
A45: 15 | B45: 13 | C45: 14.3 | D45: 5.6 | E45: 18.75 | F45: 1.075 | G45: 7.4475 | H45: 5.2 | I45: 2.25 | J45: 54.6225 | K45: 59.372283 | L45: 0.15061462 | M45: Post tranche 2
A46: 20 | B46: 16 | C46: 17.6 | D46: 5.6 | E46: 25 | F46: 1.075 | G46: 10.0725 | H46: 5.2 | I46: 3 | J46: 67.5475 | K46: 73.421196 | L46: 0.13969025 | M46: Full fleet (steady state)
A47: 25 | B47: 19 | C47: 20.9 | D47: 5.6 | E47: 31.25 | F47: 1.075 | G47: 12.6975 | H47: 5.2 | I47: 3.75 | J47: 80.4725 | K47: 87.470109 | L47: 0.13313563 | M47: Bull case
A49: KEY INSIGHT: At 20 CNC, company breaks even at just ~14% utilization. Seed round gives 8 CNC = 2x safety margin over break-even.
A52: 3. Contribution Margin Waterfall — 20 CNC @ 60% Utilization
A53: Gross Revenue | B53: 315.4 | L53: 20 CNC × 8,760h × 60% × 3,000 NOK
A54: Less: Variable costs (8%) | B54: -25.2 | L54: Materials, tools, energy, consumables
A55: → CONTRIBUTION MARGIN | B55: 290.2 | L55: 92% of revenue
A57: Less: Operational payroll | B57: -17.6 | L57: 16 FTE × 1.1M (sub-linear staffing)
A58: Less: Admin payroll | B58: -5.6 | L58: 4 FTE × 1.4M
A59: Less: CNC depreciation | B59: -25 | L59: 20 × 10M / 8yr
A60: Less: Shop base depreciation | B60: -1.075 | L60: 8.6M / 8yr
A61: Less: Finance cost (interest) | B61: -10.07 | L61: 134.3M × 7.5%
A62: Less: Facility lease | B62: -5.2 | L62: Annual lease Norbygg
A63: Less: Other operating costs | B63: -3 | L63: 20 × 150K
A64: → TOTAL FIXED COSTS | B64: -67.5 | L64: Sum of above
A66: → EBIT (Operating Profit) | B66: 222.7 | L66: Contribution margin - Fixed costs
A67: EBIT Margin | L67: EBIT / Revenue
A70: 4. Downside Protection — Safety Margins
A71: Metric | B71: Break-Even Level | C71: Base Case Level | D71: Safety Margin | E71: Implication
A72: Machine utilization | B72: ~13.5% | C72: 60% | D72: 4.4x | E72: Each CNC profitable well below target
A73: Company utilization (20 CNC) | B73: ~14% | C73: 60% | D73: 4.3x | E73: Company profitable at 1/4 of target
A74: Minimum CNC for breakeven | B74: 3-4 CNC | C74: 20 CNC | D74: 5-7x | E74: Seed gives 8 CNC = massive buffer
A75: Revenue needed (20 CNC, MNOK) | B75: 73.4 | C75: 315.4 | D75: 4.3x | E75: Less than 25% of base revenue needed
A76: Hours per CNC needed | B76: 1,183 | C76: 5,256 | D76: 4.4x | E76: Only 3.2 hours/day needed for BE
A77: Customers needed (est.) | B77: 2-3 | C77: 8-15 | D77: 4-5x | E77: Just 2-3 active customers covers costs
A81: 5. CNC Payback Period (Per Machine)
A82: Utilization % | B82: Annual Revenue per CNC (MNOK) | C82: Annual Costs per CNC (MNOK) | D82: Annual Profit per CNC (MNOK) | E82: CNC Investment (MNOK) | F82: Payback (Months)
A83: 0.2 | B83: 5.256 | C83: 3.66923 | D83: 1.58677 | E83: 10 | F83: 75.625327
A84: 0.3 | B84: 7.884 | C84: 3.87947 | D84: 4.00453 | E84: 10 | F84: 29.966063
A85: 0.4 | B85: 10.512 | C85: 4.08971 | D85: 6.42229 | E85: 10 | F85: 18.684924
A86: 0.5 | B86: 13.14 | C86: 4.29995 | D86: 8.84005 | E86: 10 | F86: 13.574584
A87: 0.6
A88: 0.65 | B88: 17.082 | C88: 4.61531 | D88: 12.46669 | E88: 10 | F88: 9.6256504
A90: At 60% utilization, each CNC pays back in ~8 months. Even at 30%, payback is ~17 months.
A93: 6. Time-to-Break-Even by Phase
A94: Phase | B94: Period | C94: CNC Machines | D94: Target Util. | E94: Est. Revenue (MNOK) | F94: Est. Costs (MNOK) | G94: Est. EBIT (MNOK) | H94: Cumulative EBIT (MNOK) | I94: Status
A95: PreSeed | B95: 2026–Q2 2027 | C95: 0 | D95: 0% | E95: 0 | F95: 2.9 | G95: -2.9 | H95: -2.9 | I95: Pre-revenue (runway)
A96: Seed — Ramp | B96: Q3 2027–2027 | C96: 5 | D96: 15–25% | E96: 13 | F96: 15 | G96: -2 | H96: -4.9 | I96: First production
A97: Seed — Year 1 | B97: 2028 | C97: 8 | D97: 35% | E97: 73 | F97: 44 | G97: 29 | H97: 24.1 | I97: CF+ ← BREAK-EVEN YEAR
A98: Seed — Year 2 | B98: 2029 | C98: 11 | D98: 40% | E98: 116 | F98: 56 | G98: 60 | H98: 84.1 | I98: Strong profitability
A99: Serie A — Tr. 1 | B99: 2030 | C99: 14 | D99: 45% | E99: 166 | F99: 67 | G99: 99 | H99: 183.1 | I99: Scaling
A100: Serie A — Tr. 2 | B100: 2031 | C100: 20 | D100: 50% | E100: 263 | F100: 99 | G100: 164 | H100: 347.1 | I100: Near full fleet
A101: Steady state
A102: Full potential | B102: 2035 | C102: 25 | D102: 65% | E102: 427 | F102: 133 | G102: 294 | H102: 1094 | I102: Maximum base case
A104: Company reaches annual EBIT break-even in 2028 (Year 1 of operations). Cumulative break-even by mid-2028.
A107: 7. Break-Even Risk Summary for Investors
A108: Break-Even Metric | B108: Threshold | C108: Risk Level | D108: Investor Implication
A109: Machine-level BE | B109: ~13.5% utilization | C109: Very low | D109: Each CNC profitable at just 3.2 productive hours/day
A110: Company-level BE (Seed) | B110: ~24% util with 5 CNC | C110: Low | D110: Seed fleet of 8 CNC gives large buffer above BE
A111: Company-level BE (Full) | B111: ~14% util with 20 CNC | C111: Very low | D111: Operating leverage makes full fleet extremely safe
A112: Time to annual profit | B112: Year 1 (2028) | C112: Low | D112: Profitable from first full year of operations
A113: Time to cumulative profit | B113: Mid-2028 | C113: Low | D113: Less than 18 months of operations to recover all losses
A114: CNC payback period | B114: ~8 months @ 60% | C114: Very low | D114: Each machine pays for itself within first year
A115: Revenue required for BE | B115: 73.4 MNOK (20 CNC) | C115: Very low | D115: Less than 25% of base case revenue
A116: Downside: 40% util scenario | B116: EBIT = 126 MNOK | C116: Protected | D116: Still highly profitable even in bear case
A117: Downside: only 15 CNC deployed | B117: EBIT = 83 MNOK @ 35% | C117: Protected | D117: Even deep bear generates positive returns
A121: Notes & Assumptions
A122: 1. Machine-level break-even uses direct per-CNC costs only (depreciation, interest, other opex).
A123: 2. Company-level break-even includes all fixed costs (staffing, depreciation, interest, lease, other).
A124: 3. Variable cost of 8% (mature) used throughout. Startup variable cost is 13% — raises BE slightly.
A125: 4. Sub-linear staffing model is KEY enabler: 16 FTE for 20 CNC vs. traditional 40-60 FTE.
A126: 5. Customer Program (50/50 sharing above 45%) NOT included — numbers show pure Aurelian economics.
...
