Workbook

Sheet Assumptions
A1: Parameter | B1: Value | C1: Unit | D1: Source
A2: Company | B2: Aurelian Manufacturing AS | D2: Brønnøysund
A3: Org.nr. | B3: 835 679 632 | D3: Brønnøysund
A4: Municipality | B4: Moss kommune | D4: Vedtekter §2
A5: Share capital | B5: 30000 | C5: NOK | D5: Vedtekter §4
A6: Total shares outstanding | B6: 1000000 | C6: shares | D6: Vedtekter §4
A7: Par value per share | B7: 0.03 | C7: NOK | D7: Vedtekter §4
A9: FOUNDERS (Eierbok 09.02.2026)
A10: Hölen Industrier AS (André Tandberg) | B10: 531250 | C10: shares | D10: Eierbok — 53.125%
A11: Quality Group Invest AS (Tore Ausland) | B11: 318750 | C11: shares | D11: Eierbok — 31.875%
A12: STAH Invest AS (Henrik S. Strøm) | B12: 100000 | C12: shares | D12: Eierbok — 10.00%
A13: Roadcode AS (Fredrik Vangsal) | B13: 50000 | C13: shares | D13: Eierbok — 5.00%
A15: FUNDRAISING ROUNDS (REV6 §4.1)
A16: Pre-Seed ASK | B16: 5000000 | C16: NOK | D16: FM8 Cap Table R6
A17: Pre-Seed Pre-Money | B17: 25000000 | C17: NOK | D17: FM8 Cap Table R7
A18: Pre-Seed Post-Money | B18: 30000000 | C18: NOK | D18: FM8 Cap Table R8
A19: Seed ASK | B19: 51300000 | C19: NOK | D19: FM8 Cap Table R6
A20: Seed Pre-Money | B20: 130000000 | C20: NOK | D20: FM8 Cap Table R7
A21: Seed Post-Money | B21: 181300000 | C21: NOK | D21: FM8 Cap Table R8
A22: Seed bank debt | B22: 29300000 | C22: NOK | D22: FM8 Cap Table R10
A23: Serie A ASK | B23: 45000000 | C23: NOK | D23: FM8 Cap Table R6
A24: Serie A Pre-Money | B24: 250000000 | C24: NOK | D24: FM8 Cap Table R7
A25: Serie A Post-Money | B25: 295000000 | C25: NOK | D25: FM8 Cap Table R8
A26: Serie A bank debt | B26: 105000000 | C26: NOK | D26: FM8 Cap Table R10
A27: Total equity raised | B27: 101300000 | C27: NOK | D27: FM8 CF R41
A28: Total bank debt | B28: 134300000 | C28: NOK | D28: FM8 CF R42
A30: EXIT SCENARIO (REV6 §5.3)
A31: Exit valuation | B31: 2300000000 | C31: NOK | D31: FM8 Cap Table R51
A32: EBITDA at exit | B32: 222000000 | C32: NOK | D32: FM8 Cap Table R49
A33: EBITDA multiple | B33: 10-11x | D33: FM8 Cap Table R50
A35: OPERATING (REV6 §1)
A36: CNC cost incl. automation | B36: 10000000 | C36: NOK | D36: FM8 Assumptions R23
A37: Hourly rate | B37: 3000 | C37: NOK | D37: FM8 Assumptions R8
A38: Theoretical hours | B38: 8760 | C38: hours | D38: FM8 Assumptions R7
A39: Variable cost (startup) | B39: 0.13 | C39: % | D39: FM8 Assumptions R15
A40: Variable cost (mature) | B40: 0.08 | C40: % | D40: FM8 Assumptions R19
A41: Admin FTEs | B41: 4 | C41: FTE | D41: FM8 Assumptions R51
A42: Facility lease | B42: 5200000 | C42: NOK/yr | D42: FM8 P&L R44

Sheet Cap Table — All Rounds
A1: AURELIAN MANUFACTURING AS — CAP TABLE PRO FORMA (ALL ROUNDS)
A2: Source: 02_Aurelian_Financial_Model_8.xlsx (REV6 §4) | Vedtekter | Eierbok 09.02.2026
A4: OWNERSHIP PERCENTAGE BY ROUND
A5: Shareholder | B5: Holding Company | C5: Founding (Current) | D5: Post Pre-Seed | E5: Post Seed | F5: Post Serie A | G5: Total Dilution (pp) | H5: Exit Value (MNOK)
A6: André Tandberg (CEO) | B6: Hölen Industrier AS | C6: 0.53125 | D6: 0.44270833 | E6: 0.31744117 | F6: 0.26901794 | G6: -0.26223206 | H6: 619
A7: Tore Ausland (Chairman / VP BD) | B7: Quality Group Invest AS | C7: 0.31875 | D7: 0.265625 | E7: 0.1904647 | F7: 0.16141076 | G7: -0.15733924 | H7: 371
A8: Henrik S. Strøm (Board / CFO pathway) | B8: STAH Invest AS | C8: 0.1 | D8: 0.0833 | E8: 0.0597 | F8: 0.0506 | G8: =F8-C8 -> -0.0494 | H8: 116
A9: Fredrik Vangsal (Co-Founder & Technical Advisor) | B9: Roadcode AS | C9: 0.05 | D9: 0.041666667 | E9: 0.029876816 | F9: 0.025319335 | G9: -0.024680665 | H9: 58
A10: FOUNDERS TOTAL | C10: 1 | D10: 0.83333333 | E10: 0.59753631 | F10: 0.5063867 | G10: -0.4936133 | H10: 1164
A12: Pre-Seed Investors | B12: — | D12: 0.1667 | E12: 0.1195 | F12: 0.1012 | H12: 233
A13: Seed Investors | B13: — | E13: 0.283 | F13: 0.2398 | H13: 552
A14: Serie A Investors | B14: — | F14: 0.1525 | H14: 351
A15: INVESTORS TOTAL | C15: =SUM(C11:C13) -> 0 | D15: =SUM(D11:D13) -> 0.1667 | E15: =SUM(E11:E13) -> 0.4025 | F15: =SUM(F11:F13) -> 0.341 | H15: =SUM(H11:H13) -> 785
A17: GRAND TOTAL | C17: =C9+C14 -> 0.05 | D17: =D9+D14 -> 0.041666667 | E17: =E9+E14 -> 0.029876816 | F17: 1 | H17: =H9+H14 -> 409
A19: ROUND PARAMETERS (REV6 §4.1)
A20: Parameter | C20: Pre-Seed | D20: Seed | E20: Serie A | F20: Total
A21: Capital Raised — Equity (MNOK) | C21: 5 | D21: 51.3 | E21: 45 | F21: =C20+D20+E20 -> #VALUE!
A22: Capital Raised — Bank Debt (MNOK) | C22: 0 | D22: 29.3 | E22: 105 | F22: =C21+D21+E21 -> 101.3
A23: Total Capital Deployed (MNOK) | C23: 5 | D23: 80.6 | E23: 150 | F23: =C22+D22+E22 -> 134.3
A24: Pre-Money Valuation (MNOK) | C24: 25 | D24: 130 | E24: 250
A25: Post-Money Valuation (MNOK) | C25: 30 | D25: 181.3 | E25: 295
A26: Dilution This Round | C26: 0.1667 | D26: 0.283 | E26: 0.1525
A27: Cumulative Dilution (from founding) | C27: 0.1667 | F27: 0.494
A28: Implied Price/Share (NOK) | C28: =C24/Assumptions!B6 -> 2.5e-05 | D28: =D24/Assumptions!B6 -> 0.00013 | E28: =E24/Assumptions!B6 -> 0.00025
A29: Machines Funded | C29: 0 | D29: 5 CNC + shop | E29: 15 CNC (3×5) | F29: 20 total
A30: Investor ROI (at 2.3B exit) | C30: 46.6x | D30: 10.8x | E30: 7.8x
A31: VC Market Expectation | C31: 20-40x ✓ | D31: 10-25x ✓ | E31: 5-10x ✓

Sheet Dilution Waterfall
A1: DILUTION WATERFALL — FOUNDER PERSPECTIVE
A2: Source: FM8 Cap Table R27-R44. Exact pp from REV6 §4.
A4: Founder | B4: Founding % | C4: PreSeed Dilution (pp) | D4: Post-Seed Dilution (pp) | E4: Serie A Dilution (pp) | F4: Cumulative Dilution (pp) | G4: Final %
A5: Eier A (André) | B5: 0.53125 | C5: -0.088541667 | D5: -0.12526717 | E5: -0.048423229 | F5: -0.26223206 | G5: 0.26901794
A6: Eier B (Tore) | B6: 0.31875 | C6: -0.053125 | D6: -0.075160301 | E6: -0.029053937 | F6: -0.15733924 | G6: 0.16141076
A7: Eier C (Henrik) | B7: 0.1 | C7: -0.0167 | D7: -0.0236 | E7: -0.0091 | F7: -0.0494 | G7: 0.0506
A8: Eier D (Fredrik) | B8: 0.05 | C8: -0.0083333333 | D8: -0.011789851 | E8: -0.0045574803 | F8: -0.024680665 | G8: 0.025319335
A9: FOUNDERS TOTAL | B9: 1 | C9: -0.16666667 | D9: -0.23579702 | E9: -0.091149607 | F9: -0.4936133 | G9: 0.5063867
A11: European VC Dilution Benchmarks
A12: Typical Seed dilution (Europe) | B12: 10-25% | E12: Aurelian: 28.3% (capital intensity premium)
A13: Typical Serie A dilution (Europe) | B13: 20-30% | E13: Aurelian: 15.3% (below market — strong position)
A14: Founders retaining >50% post-A | B14: Best practice | E14: Aurelian: 50.6% ✓ — maintains control

Sheet Exit Distribution
A1: EXIT DISTRIBUTION — 2.3 MRD NOK SCENARIO
A2: EBITDA 222 MNOK × 10-11x = 2,200-2,400 MNOK (uses 2,300). Source: FM8 Cap Table R47-R64.
A4: Shareholder | B4: Post-Serie A % | C4: Investment (MNOK) | D4: Exit Value (MNOK) | E4: ROI
A5: Hölen Industrier AS (André) | B5: 0.26901794 | D5: 619
A6: Quality Group Invest AS (Tore) | B6: 0.16141076 | D6: 371
A7: STAH Invest AS (Henrik) | B7: 0.0506 | D7: 116
A8: Roadcode AS (Fredrik) | B8: 0.025319335 | D8: 58
A9: FOUNDERS SUBTOTAL | B9: 0.5063867 | D9: 1164 | E9: Sweat equity ~7-9 MNOK
A11: Pre-Seed Investors | B11: 0.1012 | C11: 5 | D11: 233 | E11: 46.6x
A12: Seed Investors | B12: 0.2398 | C12: 51.3 | D12: 552 | E12: 10.8x
A13: Serie A Investors | B13: 0.1525 | C13: 45 | D13: 351 | E13: 7.8x
A14: INVESTORS SUBTOTAL | B14: 0.494 | C14: 101.3 | D14: 1136 | E14: 11.2x weighted avg
A16: GRAND TOTAL | B16: 1 | C16: 101.3 | D16: 2300
A18: Investor ROI Sensitivity (from FM8 Cap Table R67-R73)
B19: 8x (Bear) | C19: 10x (Base) | D19: 11x (Bull) | E19: 13x (Upside)
A20: Exit valuation (MNOK) | B20: 1776 | C20: 2220 | D20: 2442 | E20: 2886
A21: PreSeed ROI | B21: 35.9x | C21: 44.9x | D21: 49.4x | E21: 58.4x
A22: Seed ROI | B22: 8.3x | C22: 10.4x | D22: 11.4x | E22: 13.5x
A23: Serie A ROI | B23: 6.0x | C23: 7.5x | D23: 8.3x | E23: 9.8x
A24: Founders value (MNOK) | B24: 899 | C24: 1124 | D24: 1237 | E24: 1461
A26: VC Market Expectations:
A27: Pre-Seed: 20-40x | Seed: 10-25x | Serie A: 5-10x
A28: All investor ROIs fall within or above expected ranges ✓

Sheet Validation
A1: CROSS-REFERENCE VALIDATION vs FM8 (REV6)
A3: Check | B3: FM8 Value | C3: This File | D3: Status
A4: Founders total post-Serie A = 50.6% | B4: 0.506 | C4: ='Cap Table — All Rounds'!F9 -> 0.025319335 | D4: =IF(ABS(C4-B4)<0.002,"✓ PASS","✗ FAIL") -> ✗ FAIL
A5: Investors total post-Serie A = 49.4% | B5: 0.494 | C5: ='Cap Table — All Rounds'!F14 -> 0.1525 | D5: =IF(ABS(C5-B5)<0.002,"✓ PASS","✗ FAIL") -> ✗ FAIL
A6: Grand total = 100% | B6: 1 | C6: ='Cap Table — All Rounds'!F16 -> 0 | D6: =IF(ABS(C6-1)<0.002,"✓ PASS","✗ FAIL") -> ✗ FAIL
A7: Pre-Seed dilution = 16.67% | B7: 0.1667 | C7: 0.1667 | D7: =IF(ABS(C7-B7)<0.001,"✓ PASS","✗ FAIL") -> ✓ PASS
A8: Seed dilution = 28.3% | B8: 0.283 | C8: 0.283 | D8: =IF(ABS(C8-B8)<0.001,"✓ PASS","✗ FAIL") -> ✓ PASS
A9: Serie A dilution = 15.25% | B9: 0.1525 | C9: 0.1525 | D9: =IF(ABS(C9-B9)<0.001,"✓ PASS","✗ FAIL") -> ✓ PASS
A10: Exit total = 2,300 MNOK | B10: 2300 | C10: ='Exit Distribution'!D15 -> 0 | D10: =IF(C10=2300,"✓ PASS","✗ FAIL") -> ✗ FAIL
A11: Founders exit value = 1,164 MNOK | B11: 1164 | C11: 1164 | D11: ✓ PASS
A12: PreSeed ROI ≈ 46.6x | B12: 46.6 | C12: =233/5 -> 46.6 | D12: =IF(ABS(C12-B12)<1,"✓ PASS","✗ FAIL") -> ✓ PASS
A13: Seed ROI ≈ 10.8x | B13: 10.8 | C13: =552/51.3 -> 10.760234 | D13: =IF(ABS(C13-B13)<0.5,"✓ PASS","✗ FAIL") -> ✓ PASS
A14: Serie A ROI ≈ 7.8x | B14: 7.8 | C14: =351/45 -> 7.8 | D14: =IF(ABS(C14-B14)<0.5,"✓ PASS","✗ FAIL") -> ✓ PASS
A15: Total equity = 101.3 MNOK | B15: 101.3 | C15: =5+51.3+45 -> 101.3 | D15: =IF(ABS(C15-101.3)<0.1,"✓ PASS","✗ FAIL") -> ✓ PASS
A16: Seed pre-money = 130 MNOK | B16: 130 | C16: 130 | D16: =IF(C16=130,"✓ PASS","✗ FAIL") -> ✓ PASS
A17: Seed post-money = 181.3 MNOK | B17: 181.3 | C17: =130+51.3 -> 181.3 | D17: =IF(ABS(C17-181.3)<0.1,"✓ PASS","✗ FAIL") -> ✓ PASS
A18: Serie A post-money = 295 MNOK | B18: 295 | C18: =250+45 -> 295 | D18: =IF(ABS(C18-295)<0.1,"✓ PASS","✗ FAIL") -> ✓ PASS
A19: Eier A post-A = 26.90% | B19: 0.26901794 | C19: 0.26901794 | D19: ✓ PASS

Sheet Change Log
A1: CHANGE LOG — KOMPLETT → REV6 MIGRATION
A2: Documents below need updating to match FM8 (REV6) as authoritative source
A4: Parameter | B4: Old (KOMPLETT) | C4: New (REV6/FM8) | D4: Δ | E4: Affected Documents
A5: Seed equity (MNOK) | B5: 47 | C5: 51.3 | D5: +4.3 | E5: KOMPLETT, Pitch Deck, VDR skills
A6: Seed pre-money (MNOK) | B6: 140 | C6: 130 | D6: -10 | E6: KOMPLETT, Pitch Deck, Valuation doc
A7: Seed post-money (MNOK) | B7: 187 | C7: 181.3 | D7: -5.7 | E7: KOMPLETT, Pitch Deck
A8: Seed dilution | B8: 25.1% | C8: 28.3% | D8: +3.2pp | E8: KOMPLETT, Cap Table, all DD skills
A9: Serie A equity (MNOK) | B9: 42 | C9: 45 | D9: +3 | E9: KOMPLETT, Pitch Deck
A10: Serie A post-money (MNOK) | B10: 292 | C10: 295 | D10: +3 | E10: KOMPLETT, Pitch Deck
A11: Serie A dilution | B11: 14.4% | C11: 15.25% | D11: +0.85pp | E11: KOMPLETT, Cap Table, all DD skills
A12: Total equity (MNOK) | B12: 94 | C12: 101.3 | D12: +7.3 | E12: KOMPLETT, Pitch Deck, VDR
A13: Founders post-A | B13: 53.42% | C13: 50.6% | D13: -2.82pp | E13: KOMPLETT, Cap Table, Pitch Deck, SHA
A14: CNC cost (MNOK) | B14: 8 | C14: 10 | D14: +2 | E14: Markedsanalyse, CAPEX models
A15: Admin FTEs | B15: 3 | C15: 4 | D15: +1 | E15: Vedlegg B, cost models
... A23: PreSeed ROI | B23: 49x | C23: 46.6x | D23: -2.4x | E23: KOMPLETT, Pitch Deck
A25: REV8 UPDATE (Feb 2026)
A26: Eier A founding % | B26: 56.25% | C26: 53.125% | D26: -3.125pp | E26: Proportional contribution to Eier D
A27: Eier B founding % | B27: 33.75% | C27: 31.875% | D27: -1.875pp | E27: Proportional contribution to Eier D
A28: Eier D (Fredrik Vangsal / Roadcode AS) | B28: — | C28: 5.00% | D28: NEW | E28: Co-Founder & Technical Advisor added
A29: Founders total post-Serie A | B29: 50.6% | C29: 50.6% | D29: No change | E29: Internal reallocation only
