Workbook

Sheet Cash Flows
A1: Years | B1: 0 | C1: 1 | D1: 2 | E1: 3 | F1: 4 | G1: 5 | H1: 6 | I1: 7 | J1: 8 | K1: 9 | L1: 10 | M1: 11 | N1: 12 | O1: 13 | P1: 14 | Q1: 15 | R1: 16
A2: Quantities sold (MWH) | D2: 88000 | E2: 88000 | F2: 88000 | G2: 88000 | H2: 88000 | I2: 88000 | J2: 88000 | K2: 88000 | L2: 88000 | M2: 88000 | N2: 88000 | O2: 88000 | P2: 88000 | Q2: 88000 | R2: 88000
A3: x Price | D3: 30 | E3: =D3*1.015 -> 30.45 | F3: =E3*1.015 -> 30.90675 | G3: =F3*1.015 -> 31.370351 | H3: =G3*1.015 -> 31.840907 | I3: =H3*1.015 -> 32.31852 | J3: =I3*1.015 -> 32.803298 | K3: =J3*1.015 -> 33.295347 | L3: =K3*1.015 -> 33.794778 | ... R3: =Q3*1.015 -> 36.952672
A4: = Sales | D4: =D2*D3 -> 2640000 | E4: =E2*E3 -> 2679600 | F4: =F2*F3 -> 2719794 | G4: =G2*G3 -> 2760590.9 | H4: =H2*H3 -> 2801999.8 | I4: =I2*I3 -> 2844029.8 | J4: =J2*J3 -> 2886690.2 | K4: =K2*K3 -> 2929990.6 | ... R4: =R2*R3 -> 3251835.1
A5: = EBITDA | D5: =D4*0.82 -> 2164800 | E5: =E4*0.82 -> 2197272 | F5: =F4*0.82 -> 2230231.1 | G5: =G4*0.82 -> 2263684.5 | H5: =H4*0.82 -> 2297639.8 | I5: =I4*0.82 -> 2332104.4 | J5: =J4*0.82 -> 2367086 | K5: =K4*0.82 -> 2402592.3 | ... R5: =R4*0.82 -> 2666504.8
A6: - Depreciation | D6: =20000000/15 -> 1333333.3 | E6: =20000000/15 -> 1333333.3 | F6: =20000000/15 -> 1333333.3 | G6: =20000000/15 -> 1333333.3 | H6: =20000000/15 -> 1333333.3 | I6: =20000000/15 -> 1333333.3 | J6: =20000000/15 -> 1333333.3 | K6: =20000000/15 -> 1333333.3 | ... R6: =20000000/15 -> 1333333.3
A7: = EBIT | D7: =D5-D6 -> 831466.67 | E7: =E5-E6 -> 863938.67 | F7: =F5-F6 -> 896897.75 | G7: =G5-G6 -> 930351.21 | H7: =H5-H6 -> 964306.48 | I7: =I5-I6 -> 998771.08 | J7: =J5-J6 -> 1033752.6 | K7: =K5-K6 -> 1069258.9 | ... R7: =R5-R6 -> 1333171.5
A8: - Taxes | D8: =D7*0.25 -> 207866.67 | E8: =E7*0.25 -> 215984.67 | F8: =F7*0.25 -> 224224.44 | G8: =G7*0.25 -> 232587.8 | H8: =H7*0.25 -> 241076.62 | I8: =I7*0.25 -> 249692.77 | J8: =J7*0.25 -> 258438.16 | K8: =K7*0.25 -> 267314.73 | ... R8: =R7*0.25 -> 333292.87
A9: = NOPAT | D9: =D7-D8 -> 623600 | E9: =E7-E8 -> 647954 | F9: =F7-F8 -> 672673.31 | G9: =G7-G8 -> 697763.41 | H9: =H7-H8 -> 723229.86 | I9: =I7-I8 -> 749078.31 | J9: =J7-J8 -> 775314.48 | K9: =K7-K8 -> 801944.2 | ... R9: =R7-R8 -> 999878.6
A10: + Depreciation | D10: =D6 -> 1333333.3 | E10: =E6 -> 1333333.3 | F10: =F6 -> 1333333.3 | G10: =G6 -> 1333333.3 | H10: =H6 -> 1333333.3 | I10: =I6 -> 1333333.3 | J10: =J6 -> 1333333.3 | K10: =K6 -> 1333333.3 | ... R10: =R6 -> 1333333.3
A11: Working Capital | B11: 0 | C11: 0 | D11: =D4*20/365 -> 144657.53 | E11: =E4*20/365 -> 146827.4 | F11: =F4*20/365 -> 149029.81 | G11: =G4*20/365 -> 151265.26 | H11: =H4*20/365 -> 153534.23 | I11: =I4*20/365 -> 155837.25 | J11: =J4*20/365 -> 158174.81 | K11: =K4*20/365 -> 160547.43 | ... R11: =R4*20/365 -> 178182.75
A12: - Change in WC | C12: 0 | D12: =D11-C11 -> 144657.53 | E12: =E11-D11 -> 2169.863 | F12: =F11-E11 -> 2202.411 | G12: =G11-F11 -> 2235.4471 | H12: =H11-G11 -> 2268.9788 | I12: =I11-H11 -> 2303.0135 | J12: =J11-I11 -> 2337.5587 | K12: =K11-J11 -> 2372.6221 | ... R12: =R11-Q11 -> 2633.2426
A13: = Operating CF | D13: =D9+D10-D12 -> 1812275.8 | E13: =E9+E10-E12 -> 1979117.5 | F13: =F9+F10-F12 -> 2003804.2 | G13: =G9+G10-G12 -> 2028861.3 | H13: =H9+H10-H12 -> 2054294.2 | I13: =I9+I10-I12 -> 2080108.6 | J13: =J9+J10-J12 -> 2106310.3 | K13: =K9+K10-K12 -> 2132904.9 | ... R13: =R9+R10-R12 -> 2330578.7
A14: Emission rights | D14: =D2*0.8*5 -> 352000 | E14: =E2*0.8*5 -> 352000 | F14: =F2*0.8*5 -> 352000 | G14: =G2*0.8*5 -> 352000 | H14: =H2*0.8*5 -> 352000 | I14: =I2*0.8*5 -> 352000 | J14: =J2*0.8*5 -> 352000 | K14: =K2*0.8*5 -> 352000 | ... R14: =R2*0.8*5 -> 352000
A15: - Investment expenditures | B15: 6000000 | C15: 14000000 | D15: 0 | E15: 0 | F15: 0 | G15: 0 | H15: 0 | I15: 0 | J15: 0 | K15: 0 | L15: 0 | M15: 0 | N15: 0 | O15: 0 | P15: 0 | Q15: 0 | R15: 0
A16: = CF Available for Debt Service | B16: =B13+B14-B15 -> -6000000 | C16: =C13+C14-C15 -> -14000000 | D16: =D13+D14-D15 -> 2164275.8 | E16: =E13+E14-E15 -> 2331117.5 | F16: =F13+F14-F15 -> 2355804.2 | G16: =G13+G14-G15 -> 2380861.3 | H16: =H13+H14-H15 -> 2406294.2 | I16: =I13+I14-I15 -> 2432108.6 | ... R16: =R13+R14-R15 -> 2682578.7

Sheet Capital Structure
A1: Years | B1: 0 | C1: 1 | D1: 2 | E1: 3 | F1: 4 | G1: 5 | H1: 6 | I1: 7 | J1: 8 | K1: 9 | L1: 10 | M1: 11 | N1: 12 | O1: 13 | P1: 14 | Q1: 15 | R1: 16
A2: Debt Tranche 1 | B2: 0 | C2: 14000000 | D2: =C2*1.1 -> 15400000 | E2: =D2*1.1 -> 16940000 | F2: 0 | G2: 0 | H2: 0 | I2: 0 | J2: 0 | K2: 0 | L2: 0 | M2: 0 | N2: 0 | O2: 0 | P2: 0 | Q2: 0 | R2: 0
A3: Interest Payment | B3: 0 | C3: 0 | D3: 0 | E3: 0 | F3: =C2*0.1+D2*0.1+E2*0.1 -> 4634000 | G3: 0 | H3: 0 | I3: 0 | J3: 0 | K3: 0 | L3: 0 | M3: 0 | N3: 0 | O3: 0 | P3: 0 | Q3: 0 | R3: 0
A4: Principal Repayment | B4: 0 | C4: 0 | D4: 0 | E4: 0 | F4: 14000000 | G4: 0 | H4: 0 | I4: 0 | J4: 0 | K4: 0 | L4: 0 | M4: 0 | N4: 0 | O4: 0 | P4: 0 | Q4: 0 | R4: 0
A5: Debt Tranche 2 | B5: 0 | C5: 0 | D5: 0 | E5: 0 | F5: =F3+F4 -> 18634000 | G5: =F5-G6 -> 17081167 | H5: =G5-H6 -> 15528333 | I5: =H5-I6 -> 13975500 | J5: =I5-J6 -> 12422667 | K5: =J5-K6 -> 10869833 | L5: =K5-L6 -> 9317000 | M5: =L5-M6 -> 7764166.7 | N5: =M5-N6 -> 6211333.3 | ... R5: =Q5-R6 -> 0
A6: Principal Repayment | B6: 0 | C6: 0 | D6: 0 | E6: 0 | F6: 0 | G6: =$F$5/12 -> 1552833.3 | H6: =$F$5/12 -> 1552833.3 | I6: =$F$5/12 -> 1552833.3 | J6: =$F$5/12 -> 1552833.3 | K6: =$F$5/12 -> 1552833.3 | L6: =$F$5/12 -> 1552833.3 | M6: =$F$5/12 -> 1552833.3 | N6: =$F$5/12 -> 1552833.3 | ... R6: =$F$5/12 -> 1552833.3
A7: Interest Payment | B7: 0 | C7: 0 | D7: 0 | E7: 0 | F7: 0 | G7: =F5*0.05 -> 931700 | H7: =G5*0.05 -> 854058.33 | I7: =H5*0.05 -> 776416.67 | J7: =I5*0.05 -> 698775 | K7: =J5*0.05 -> 621133.33 | L7: =K5*0.05 -> 543491.67 | M7: =L5*0.05 -> 465850 | N7: =M5*0.05 -> 388208.33 | ... R7: =Q5*0.05 -> 77641.667
A8: Total Debt | B8: 0 | C8: =C2 -> 14000000 | D8: =D2 -> 15400000 | E8: =E2 -> 16940000 | F8: =F5 -> 18634000 | G8: =G5 -> 17081167 | H8: =H5 -> 15528333 | I8: =I5 -> 13975500 | J8: =J5 -> 12422667 | K8: =K5 -> 10869833 | L8: =L5 -> 9317000 | M8: =M5 -> 7764166.7 | ... R8: =R5 -> 0
A10: Initial Equity | B10: 6000000 | C10: 6000000 | D10: 6000000 | E10: 6000000 | F10: 6000000 | G10: 6000000 | H10: 6000000 | I10: 6000000 | J10: 6000000 | K10: 6000000 | L10: 6000000 | M10: 6000000 | N10: 6000000 | O10: 6000000 | P10: 6000000 | Q10: 6000000 | R10: 6000000
A11: Cumulative Retained Earnings | B11: =SUM(B28) -> 0 | C11: =SUM(B28:C28) -> 0 | D11: =SUM(B28:D28) -> -568533.33 | E11: =SUM(B28:E28) -> -1244594.7 | F11: =SUM(B28:F28) -> -2041696.9 | G11: =SUM(B28:G28) -> -2043045.7 | H11: =SUM(B28:H28) -> -1932797.6 | I11: =SUM(B28:I28) -> -1743517.6 | J11: =SUM(B28:J28) -> -1558653.5 | K11: =SUM(B28:K28) -> -1298030.4 | L11: =SUM(B28:L28) -> -977504.06 | M11: =SUM(B28:M28) -> -596889.98 | N11: =SUM(B28:N28) -> -308004.43 | O11: =SUM(B28:O28) -> 15729.769 | P11: =SUM(B28:P28) -> 374485.95 | Q11: =SUM(B28:Q28) -> 768440.05 | R11: =SUM(B28:R28) -> 1197770.7
A12: Total Equity | B12: =B10+B11 -> 6000000 | C12: =C10+C11 -> 6000000 | D12: =D10+D11 -> 5431466.7 | E12: =E10+E11 -> 4755405.3 | F12: =F10+F11 -> 3958303.1 | G12: =G10+G11 -> 3956954.3 | H12: =H10+H11 -> 4067202.4 | I12: =I10+I11 -> 4256482.4 | ... R12: =R10+R11 -> 7197770.7
A14: Capital Invested | B14: =B8+B12 -> 6000000 | C14: =C8+C12 -> 20000000 | D14: =D8+D12 -> 20831467 | E14: =E8+E12 -> 21695405 | F14: =F8+F12 -> 22592303 | G14: =G8+G12 -> 21038121 | H14: =H8+H12 -> 19595536 | I14: =I8+I12 -> 18231982 | ... R14: =R8+R12 -> 7197770.7
A16: Gearing | B16: =B8/B12 -> 0 | C16: =C8/C12 -> 2.3333333 | D16: =D8/D12 -> 2.8353299 | E16: =E8/E12 -> 3.5622621 | F16: =F8/F12 -> 4.7075728 | G16: =G8/G12 -> 4.316746 | H16: =H8/H12 -> 3.8179396 | I16: =I8/I12 -> 3.2833449 | ... R16: =R8/R12 -> 0
A19: Years | B19: 0 | C19: 1 | D19: 2 | E19: 3 | F19: 4 | G19: 5 | H19: 6 | I19: 7 | J19: 8 | K19: 9 | L19: 10 | M19: 11 | N19: 12 | O19: 13 | P19: 14 | Q19: 15 | R19: 16
A20: EBIT | B20: 0 | C20: 0 | D20: 831466.67 | E20: 863938.67 | F20: 896897.75 | G20: 930351.21 | H20: 964306.48 | I20: 998771.08 | J20: 1033752.6 | K20: 1069258.9 | L20: 1105297.8 | M20: 1141877.3 | N20: 1179005.4 | O20: 1216690.5 | P20: 1254940.9 | Q20: 1293765 | R20: 1333171.5
A21: Interest Expenses | B21: 0 | C21: 0 | D21: =C8*0.1 -> 1400000 | E21: =D8*0.1 -> 1540000 | F21: =E8*0.1 -> 1694000 | G21: =G7 -> 931700 | H21: =H7 -> 854058.33 | I21: =I7 -> 776416.67 | J21: =J7 -> 698775 | K21: =K7 -> 621133.33 | L21: =L7 -> 543491.67 | M21: =M7 -> 465850 | N21: =N7 -> 388208.33 | ... R21: =R7 -> 77641.667
A22: Income Before Tax | B22: =B20-B21 -> 0 | C22: =C20-C21 -> 0 | D22: =D20-D21 -> -568533.33 | E22: =E20-E21 -> -676061.33 | F22: =F20-F21 -> -797102.25 | G22: =G20-G21 -> -1348.7871 | H22: =H20-H21 -> 110248.15 | I22: =I20-I21 -> 222354.41 | ... R22: =R20-R21 -> 1255529.8
A23: Losses Carried Forward (3 years max) | B23: 0 | C23: 0 | D23: 0 | E23: =D22 -> -568533.33 | F23: =D22+E22 -> -1244594.7 | G23: =D22+E22+F22 -> -2041696.9 | H23: =E22+F22 -> -1473163.6 | I23: =F22 -> -797102.25 | J23: =G22 -> -1348.7871 | K23: 0 | L23: 0 | M23: 0 | N23: 0 | O23: 0 | P23: 0 | Q23: 0 | R23: 0
A24: Taxable Income | B24: =B22+B23 -> 0 | C24: =C22+C23 -> 0 | D24: =D22+D23 -> -568533.33 | E24: =E22+E23 -> -1244594.7 | F24: =F22+F23 -> -2041696.9 | G24: =G22+G23 -> -2043045.7 | H24: =H22+H23 -> -1362915.4 | I24: =I22+I23 -> -574747.84 | ... R24: =R22+R23 -> 1255529.8
A25: Tax | B25: 0 | C25: 0 | D25: 0 | E25: 0 | F25: 0 | G25: 0 | H25: 0 | I25: 0 | J25: =J24*0.25 -> 83407.214 | K25: =K24*0.25 -> 112031.4 | L25: =L24*0.25 -> 140451.54 | M25: =M24*0.25 -> 169006.82 | N25: =N24*0.25 -> 197699.28 | O25: =O24*0.25 -> 226530.96 | P25: =P24*0.25 -> 255503.97 | Q25: =Q24*0.25 -> 284620.42 | R25: =R24*0.25 -> 313882.45
A26: Net Income | B26: 0 | C26: 0 | D26: =D22 -> -568533.33 | E26: =E22 -> -676061.33 | F26: =F22 -> -797102.25 | G26: =G22 -> -1348.7871 | H26: =H22 -> 110248.15 | I26: =I22 -> 222354.41 | J26: =J22-J25 -> 251570.43 | K26: =K22-K25 -> 336094.2 | L26: =L22-L25 -> 421354.61 | M26: =M22-M25 -> 507020.46 | N26: =N22-N25 -> 593097.83 | O26: =O22-O25 -> 679592.89 | P26: =P22-P25 -> 766511.91 | Q26: =Q22-Q25 -> 853861.25 | R26: =R22-R25 -> 941647.35
A27: Dividends | B27: 0 | C27: 0 | D27: 0 | E27: 0 | F27: 0 | G27: 0 | H27: 0 | I27: =H26*0.3 -> 33074.444 | J27: =I26*0.3 -> 66706.323 | K27: =J26*0.3 -> 75471.129 | L27: =K26*0.3 -> 100828.26 | M27: =L26*0.3 -> 126406.38 | N27: =M26*0.6 -> 304212.28 | O27: =N26*0.6 -> 355858.7 | P27: =O26*0.6 -> 407755.74 | Q27: =P26*0.6 -> 459907.15 | R27: =Q26*0.6 -> 512316.75
A28: Retained Earnings Each Year | B28: =B26-B27 -> 0 | C28: =C26-C27 -> 0 | D28: =D26-D27 -> -568533.33 | E28: =E26-E27 -> -676061.33 | F28: =F26-F27 -> -797102.25 | G28: =G26-G27 -> -1348.7871 | H28: =H26-H27 -> 110248.15 | I28: =I26-I27 -> 189279.97 | ... R28: =R26-R27 -> 429330.61

Sheet APV
A1: Years | B1: 0 | C1: 1 | D1: 2 | E1: 3 | F1: 4 | G1: 5 | H1: 6 | I1: 7 | J1: 8 | K1: 9 | L1: 10 | M1: 11 | N1: 12 | O1: 13 | P1: 14 | Q1: 15 | R1: 16
A2: CF Available for Debt Service | B2: ='Cash Flows'!B16 -> -6000000 | C2: ='Cash Flows'!C16 -> -14000000 | D2: ='Cash Flows'!D16 -> 2164275.8 | E2: ='Cash Flows'!E16 -> 2331117.5 | F2: ='Cash Flows'!F16 -> 2355804.2 | G2: ='Cash Flows'!G16 -> 2380861.3 | H2: ='Cash Flows'!H16 -> 2406294.2 | I2: ='Cash Flows'!I16 -> 2432108.6 | ... R2: ='Cash Flows'!R16 -> 2682578.7
A3: PV of CFADS | B3: =B2/(1+$B19)^B1 -> -6000000 | C3: =C2/(1+$B19)^C1 -> -12750455 | D3: =D2/(1+$B19)^D1 -> 1795179.7 | E3: =E2/(1+$B19)^E1 -> 1760991 | F3: =F2/(1+$B19)^F1 -> 1620801.5 | G3: =G2/(1+$B19)^G1 -> 1491840.5 | H3: =H2/(1+$B19)^H1 -> 1373202.8 | I3: =I2/(1+$B19)^I1 -> 1264056.8 | ... R3: =R2/(1+$B19)^R1 -> 601056.13
A4: NPV Base Case | B4: =SUM(B3:R3) -> -1746911.9
A5: IRR | B5: =IRR(B2:R2) -> 0.082706732
A8: Years | B8: 0 | C8: 1 | D8: 2 | E8: 3 | F8: 4 | G8: 5 | H8: 6 | I8: 7 | J8: 8 | K8: 9 | L8: 10 | M8: 11 | N8: 12 | O8: 13 | P8: 14 | Q8: 15 | R8: 16
A9: Interest Expenses | B9: ='Capital Structure'!B21 -> 0 | C9: ='Capital Structure'!C21 -> 0 | D9: ='Capital Structure'!D21 -> 1400000 | E9: ='Capital Structure'!E21 -> 1540000 | F9: ='Capital Structure'!F21 -> 1694000 | G9: ='Capital Structure'!G21 -> 931700 | H9: ='Capital Structure'!H21 -> 854058.33 | I9: ='Capital Structure'!I21 -> 776416.67 | ... R9: ='Capital Structure'!R21 -> 77641.667
A10: Tax Shield | B10: 0 | C10: 0 | D10: =D9*0.25 -> 350000 | E10: =E9*0.25 -> 385000 | F10: =F9*0.25 -> 423500 | G10: =G9*0.25 -> 232925 | H10: =H9*0.25 -> 213514.58 | I10: =I9*0.25 -> 194104.17 | J10: =J9*0.25 -> 174693.75 | K10: =K9*0.25 -> 155283.33 | ... R10: =R9*0.25 -> 19410.417
A11: PV of Tax Shield | B11: 0 | C11: 0 | D11: =D10/(1+$B20)^D8 -> 289256.2 | E11: =E10/(1+$B20)^E8 -> 289256.2 | F11: =F10/(1+$B20)^F8 -> 289256.2 | G11: =G10/(1+$B21)^G8 -> 182502.83 | H11: =H10/(1+$B21)^H8 -> 159327.87 | I11: =I10/(1+$B21)^I8 -> 137946.21 | J11: =J10/(1+$B21)^J8 -> 118239.61 | K11: =K10/(1+$B21)^K8 -> 100097.02 | L11: =L10/(1+$B21)^L8 -> 83414.184 | M11: =M10/(1+$B21)^M8 -> 68093.212 | N11: =N10/(1+$B21)^N8 -> 54042.232 | ... R11: =R10/(1+$B21)^R8 -> 8892.1355
A12: Sum of PV TS | B12: =SUM(B11:R11) -> 1869583.2
A15: APV [NPV Base Case + Sum of PV TS] | B15: =B4+B12 -> 122671.21
A18: Ba | B18: 0.8
A19: Ra | B19: =0.05+B18*0.06 -> 0.098
A20: Rd Tranche 1 | B20: 0.1
A21: Rd Tranche 2 | B21: 0.05

Sheet Chart
